Workbook
Name _1NOTES_FIELDS: #REF!
Name _1NOTES_FIELDS: #REF!
Name \0: #REF!
Name \0: #REF!
Name \P: '[1]2010 bud'!#REF!
Name \P: '[1]2010 bud'!#REF!
Name \P: '[1]2010 bud'!#REF!
Name \P: '[2]2011 bud'!#REF!
Name \P: '[3]2011 bud'!#REF!
Name \P: ' bud'!#REF!
Name \P: ' bud'!#REF!
Name a: '[4]Cash Flow-IBS'!#REF!
Name a: '[4]Cash Flow-IBS'!#REF!
Name aa: #REF!
Name aa: #REF!
Name ab: #REF!
Name ac: #REF!
Name ADMIN: #REF!
Name ADMIN: #REF!
Name ADMIN: #REF!
Name ADMIN: #REF!
Name ADMIN: #REF!
Name ADMIN: #REF!
Name ADMIN: #REF!
Name AIRCONDITIONER: '[5]REQUIRED AND BASE INFO'!$C$32
Name AMORT: '[6]2Assumption'!#REF!
Name AmortizationTermYears: #REF!
Name AmortizationTermYears: #REF!
Name AmortizedLoanCosts: #REF!
Name AmortizedLoanCosts: #REF!
Name ANS_INFOPRT: #REF!
Name ANS_INFOPRT: #REF!
Name ANS_KEEPDATA: #REF!
Name ANS_MACROPRT1: #REF!
Name ANS_MACROPRT2: #REF!
Name ANS_MACROPRT3: #REF!
Name ANS_SWAPDATA: #REF!
Name ANS_UPDDATA: #REF!
Name ASSESSMENT: '[5]REQUIRED AND BASE INFO'!$C$33
Name BACKGRND: #REF!
Name BACKGRND: #REF!
Name BalanceOutstanding: #REF!
Name BalanceOutstanding: #REF!
Name BASE: [7]Budget!#REF!
Name BASE: [7]Budget!#REF!
Name BCK_COL: #REF!
Name BCK_COL: #REF!
Name BCK_LOOP: #REF!
Name BCK_LOOP: #REF!
Name Beginning_Balance: -FV(Interest_Rate/12,'Pie Chart for Annual'!Payment_Number-1,-'Pie Chart for Annual'!Monthly_Payment,Loan_Amount)
Name Beginning_Balance: -FV(Interest_Rate/12,Payment_Number-1,-Monthly_Payment,Loan_Amount)
Name BIKE: '[5]REQUIRED AND BASE INFO'!$C$34
Name Body: #REF!
Name Body: #REF!
Name BONUS: '[5]Payroll Data'!$S$34:$S$64
Name Brorrower: #REF!
Name Brorrower: #REF!
Name BUDGET: ' bud'!$A$1:$G$54
Name Ca: #REF!
Name Ca: #REF!

Sheet VLookup Data
A1: 0000-9994 | B1: ASSETS | C1: =SUMIF('yardi_data (2)'!$A:$A,$A1,'yardi_data (2)'!C:C) -> 0 | D1: =SUMIF('yardi_data (2)'!$A:$A,$A1,'yardi_data (2)'!$D:$D) -> 0 | E1: =SUMIF('yardi_data (2)'!$A:$A,$A1,'yardi_data (2)'!$E:$E) -> 0 | F1: =SUMIF('yardi_data (2)'!$A:$A,$A1,'yardi_data (2)'!$F:$F) -> 0 | G1: =SUMIF('yardi_data (2)'!$A:$A,$A1,'yardi_data (2)'!$G:$G) -> 0
A2: 0000-9995 | B2: CASH AND CASH EQUIVALENTS | C2: =SUMIF('yardi_data (2)'!$A:$A,$A2,'yardi_data (2)'!C:C) -> 0 | D2: =SUMIF('yardi_data (2)'!$A:$A,$A2,'yardi_data (2)'!$D:$D) -> 0 | E2: =SUMIF('yardi_data (2)'!$A:$A,$A2,'yardi_data (2)'!$E:$E) -> 0 | F2: =SUMIF('yardi_data (2)'!$A:$A,$A2,'yardi_data (2)'!$F:$F) -> 0 | G2: =SUMIF('yardi_data (2)'!$A:$A,$A2,'yardi_data (2)'!$G:$G) -> 0
A3: 0010-0000 | B3: Operating Account | C3: =SUMIF('yardi_data (2)'!$A:$A,$A3,'yardi_data (2)'!C:C) -> 0 | D3: =SUMIF('yardi_data (2)'!$A:$A,$A3,'yardi_data (2)'!$D:$D) -> 0 | E3: =SUMIF('yardi_data (2)'!$A:$A,$A3,'yardi_data (2)'!$E:$E) -> 0 | F3: =SUMIF('yardi_data (2)'!$A:$A,$A3,'yardi_data (2)'!$F:$F) -> 0 | G3: =SUMIF('yardi_data (2)'!$A:$A,$A3,'yardi_data (2)'!$G:$G) -> 0
A4: 0010-0002 | B4: Operating Account 2 | C4: =SUMIF('yardi_data (2)'!$A:$A,$A4,'yardi_data (2)'!C:C) -> 0 | D4: =SUMIF('yardi_data (2)'!$A:$A,$A4,'yardi_data (2)'!$D:$D) -> 0 | E4: =SUMIF('yardi_data (2)'!$A:$A,$A4,'yardi_data (2)'!$E:$E) -> 0 | F4: =SUMIF('yardi_data (2)'!$A:$A,$A4,'yardi_data (2)'!$F:$F) -> 0 | G4: =SUMIF('yardi_data (2)'!$A:$A,$A4,'yardi_data (2)'!$G:$G) -> 0
A5: 0010-0003 | B5: Payroll Account | C5: =SUMIF('yardi_data (2)'!$A:$A,$A5,'yardi_data (2)'!C:C) -> 0 | D5: =SUMIF('yardi_data (2)'!$A:$A,$A5,'yardi_data (2)'!$D:$D) -> 0 | E5: =SUMIF('yardi_data (2)'!$A:$A,$A5,'yardi_data (2)'!$E:$E) -> 0 | F5: =SUMIF('yardi_data (2)'!$A:$A,$A5,'yardi_data (2)'!$F:$F) -> 0 | G5: =SUMIF('yardi_data (2)'!$A:$A,$A5,'yardi_data (2)'!$G:$G) -> 0
A6: 0010-0004 | B6: Void Exchange | C6: =SUMIF('yardi_data (2)'!$A:$A,$A6,'yardi_data (2)'!C:C) -> 0 | D6: =SUMIF('yardi_data (2)'!$A:$A,$A6,'yardi_data (2)'!$D:$D) -> 0 | E6: =SUMIF('yardi_data (2)'!$A:$A,$A6,'yardi_data (2)'!$E:$E) -> 0 | F6: =SUMIF('yardi_data (2)'!$A:$A,$A6,'yardi_data (2)'!$F:$F) -> 0 | G6: =SUMIF('yardi_data (2)'!$A:$A,$A6,'yardi_data (2)'!$G:$G) -> 0
A7: 0010-0005 | B7: Operating Account 5 | C7: =SUMIF('yardi_data (2)'!$A:$A,$A7,'yardi_data (2)'!C:C) -> 0 | D7: =SUMIF('yardi_data (2)'!$A:$A,$A7,'yardi_data (2)'!$D:$D) -> 0 | E7: =SUMIF('yardi_data (2)'!$A:$A,$A7,'yardi_data (2)'!$E:$E) -> 0 | F7: =SUMIF('yardi_data (2)'!$A:$A,$A7,'yardi_data (2)'!$F:$F) -> 0 | G7: =SUMIF('yardi_data (2)'!$A:$A,$A7,'yardi_data (2)'!$G:$G) -> 0
A8: 0010-0006 | B8: OEF-Checking | C8: =SUMIF('yardi_data (2)'!$A:$A,$A8,'yardi_data (2)'!C:C) -> 0 | D8: =SUMIF('yardi_data (2)'!$A:$A,$A8,'yardi_data (2)'!$D:$D) -> 0 | E8: =SUMIF('yardi_data (2)'!$A:$A,$A8,'yardi_data (2)'!$E:$E) -> 0 | F8: =SUMIF('yardi_data (2)'!$A:$A,$A8,'yardi_data (2)'!$F:$F) -> 0 | G8: =SUMIF('yardi_data (2)'!$A:$A,$A8,'yardi_data (2)'!$G:$G) -> 0
A9: 0010-0099 | B9: Old Operating Accounts | C9: =SUMIF('yardi_data (2)'!$A:$A,$A9,'yardi_data (2)'!C:C) -> 0 | D9: =SUMIF('yardi_data (2)'!$A:$A,$A9,'yardi_data (2)'!$D:$D) -> 0 | E9: =SUMIF('yardi_data (2)'!$A:$A,$A9,'yardi_data (2)'!$E:$E) -> 0 | F9: =SUMIF('yardi_data (2)'!$A:$A,$A9,'yardi_data (2)'!$F:$F) -> 0 | G9: =SUMIF('yardi_data (2)'!$A:$A,$A9,'yardi_data (2)'!$G:$G) -> 0
A10: 0020-0000 | B10: Money Market Account | C10: =SUMIF('yardi_data (2)'!$A:$A,$A10,'yardi_data (2)'!C:C) -> 0 | D10: =SUMIF('yardi_data (2)'!$A:$A,$A10,'yardi_data (2)'!$D:$D) -> 0 | E10: =SUMIF('yardi_data (2)'!$A:$A,$A10,'yardi_data (2)'!$E:$E) -> 0 | F10: =SUMIF('yardi_data (2)'!$A:$A,$A10,'yardi_data (2)'!$F:$F) -> 0 | G10: =SUMIF('yardi_data (2)'!$A:$A,$A10,'yardi_data (2)'!$G:$G) -> 0
A11: 0020-0002 | B11: Money Market Account 2 | C11: =SUMIF('yardi_data (2)'!$A:$A,$A11,'yardi_data (2)'!C:C) -> 0 | D11: =SUMIF('yardi_data (2)'!$A:$A,$A11,'yardi_data (2)'!$D:$D) -> 0 | E11: =SUMIF('yardi_data (2)'!$A:$A,$A11,'yardi_data (2)'!$E:$E) -> 0 | F11: =SUMIF('yardi_data (2)'!$A:$A,$A11,'yardi_data (2)'!$F:$F) -> 0 | G11: =SUMIF('yardi_data (2)'!$A:$A,$A11,'yardi_data (2)'!$G:$G) -> 0
A12: 0020-0003 | B12: Money Market Account 3 | C12: =SUMIF('yardi_data (2)'!$A:$A,$A12,'yardi_data (2)'!C:C) -> 0 | D12: =SUMIF('yardi_data (2)'!$A:$A,$A12,'yardi_data (2)'!$D:$D) -> 0 | E12: =SUMIF('yardi_data (2)'!$A:$A,$A12,'yardi_data (2)'!$E:$E) -> 0 | F12: =SUMIF('yardi_data (2)'!$A:$A,$A12,'yardi_data (2)'!$F:$F) -> 0 | G12: =SUMIF('yardi_data (2)'!$A:$A,$A12,'yardi_data (2)'!$G:$G) -> 0
... A753: 9999-9998 | B753: Total of All | C753: =SUMIF('yardi_data (2)'!$A:$A,$A753,'yardi_data (2)'!C:C) -> 0 | D753: =SUMIF('yardi_data (2)'!$A:$A,$A753,'yardi_data (2)'!$D:$D) -> 0 | E753: =SUMIF('yardi_data (2)'!$A:$A,$A753,'yardi_data (2)'!$E:$E) -> 0 | F753: =SUMIF('yardi_data (2)'!$A:$A,$A753,'yardi_data (2)'!$F:$F) -> 0 | G753: =SUMIF('yardi_data (2)'!$A:$A,$A753,'yardi_data (2)'!$G:$G) -> 0

Sheet yardi_data (2)
C1: 9/1/2015 | D1: 12/1/2015 | F1: tempcen_cf
A2: Cash | B2: Cash
A3: 148 | B3: 148
A4: Oracle
A5: Sql Server | C5: =TEXT(MONTHADD($C$1,-MOD(MONTH($C$1)-1,3)),"mm/dd/yyyy") -> #NAME? | D5: =TEXT(MONTHADD($D$1,-MOD(MONTH($D$1)-1,3)),"mm/dd/yyyy") -> #NAME?
I6: Filter
I7: 1
I8: 1
I9: 1
I10: 1
B11: 444 East 86th Owners Corp | E11: Y-T-D | F11: Y-T-D | G11: 2025 | I11: 1
C12: 2023 | D12: 2024 | E12: 08/2025 | F12: 08/2025 | G12: Budget | I12: 1
A13: GL# | B13: ="Budget "&TEXT($H$12,"0000") -> Budget 0000 | C13: Actual | D13: Actual | E13: Actual | F13: BUDGET | G13: APPROVED | I13: 1
A16: 0000-0000 | B16: CASH FLOW | I16: 1 | J16: 1133606
A18: 0000-0000 | B18: (Header) | I18: 1 | J18: 1133607
A20: 4000-9994 | B20: INCOME | I20: 1 | J20: 1133608
A22: 4000-9995 | B22: RECURRING INCOME | I22: 1 | J22: 1133609
A23: 4010-0000 | B23: Maintenance | C23: 8599731.2 | D23: 8693546.6 | E23: 6012298.2 | F23: 6044653.4 | G23: 9066980 | I23: =C23+D23+E23+F23+G23 -> 38417209 | J23: 1133610
A24: 4011-0000 | B24: Maintenance Sponsors | C24: 0 | D24: 0 | E24: 0 | F24: 0 | G24: 0 | I24: =C24+D24+E24+F24+G24 -> 0 | J24: 1133611
A25: 4020-0000 | B25: Common Charges | C25: 0 | D25: 0 | E25: 0 | F25: 0 | G25: 0 | I25: =C25+D25+E25+F25+G25 -> 0 | J25: 1133612
A26: 4030-0005 | B26: Commercial Common Charges | C26: 0 | D26: 0 | E26: 0 | F26: 0 | G26: 0 | I26: =C26+D26+E26+F26+G26 -> 0 | J26: 1133613
A27: 4021-0000 | B27: Common Charges Sponsors | C27: 0 | D27: 0 | E27: 0 | F27: 0 | G27: 0 | I27: =C27+D27+E27+F27+G27 -> 0 | J27: 1133614
A28: 4025-0000 | B28: Homeowner Association Dues | C28: 0 | D28: 0 | E28: 0 | F28: 0 | G28: 0 | I28: =C28+D28+E28+F28+G28 -> 0 | J28: 1133615
A29: 4030-0000 | B29: Rental Income | C29: 0 | D29: 0 | E29: 0 | F29: 0 | G29: 0 | I29: =C29+D29+E29+F29+G29 -> 0 | J29: 1133616
A30: 4080-0000 | B30: Rents- Residential Below Market | C30: 0 | D30: 0 | E30: 0 | F30: 0 | G30: 0 | I30: =C30+D30+E30+F30+G30 -> 0 | J30: 1133617
A31: 4030-0010 | B31: Vacancy Loss | C31: 0 | D31: 0 | E31: 0 | F31: 0 | G31: 0 | I31: =C31+D31+E31+F31+G31 -> 0 | J31: 1133618
A32: 4040-0000 | B32: Commercial Rent | C32: 52258.06 | D32: 54000 | E32: 36000 | F32: 36000 | G32: 54000 | I32: =C32+D32+E32+F32+G32 -> 232258.06 | J32: 1133619
A33: 4080-0002 | B33: Rents- Commercial Straight Line | C33: 0 | D33: 0 | E33: 0 | F33: 0 | G33: 0 | I33: =C33+D33+E33+F33+G33 -> 0 | J33: 1133620
A34: 4080-0004 | B34: Rents-Commercial Above Market | C34: 0 | D34: 0 | E34: 0 | F34: 0 | G34: 0 | I34: =C34+D34+E34+F34+G34 -> 0 | J34: 1133621
... A91: 4515-0015 | B91: Straight Line Adjustment | C91: 0 | D91: 0 | E91: 0 | F91: 0 | G91: 0 | I91: =C91+D91+E91+F91+G91 -> 0 | J91: 1133678
A92: 4520-0000 | B92: Commercial Real Estate Tax | C92: 0 | D92: 0 | E92: 0 | F92: 0 | G92: 0
A93: 4525-0000 | B93: Porter Wage | C93: 0 | D93: 0 | E93: 0 | F93: 0 | G93: 0 | I93: 1 | J93: 1133679
A94: 4530-0000 | B94: Garage - Operator | C94: 0 | D94: 0 | E94: 0 | F94: 0 | G94: 0 | I94: =C94+D94+E94+F94+G94 -> 0 | J94: 1133680
A95: 4580-0000 | B95: Sales Tax | C95: 0 | D95: 0 | E95: 0 | F95: 0 | G95: 0 | I95: =C95+D95+E95+F95+G95 -> 0 | J95: 1133681
A96: 4600-0000 | B96: Management Fees | C96: 0 | D96: 0 | E96: 0 | F96: 0 | G96: 0 | I96: =C96+D96+E96+F96+G96 -> 0 | J96: 1133682
A97: 4600-0010 | B97: Management Fees-Staff | C97: 0 | D97: 0 | E97: 0 | F97: 0 | G97: 0 | I97: =C97+D97+E97+F97+G97 -> 0 | J97: 1133683
A98: 4605-0000 | B98: Conference Room | C98: 0 | D98: 0 | E98: 0 | F98: 0 | G98: 0 | I98: =C98+D98+E98+F98+G98 -> 0 | J98: 1133684
A99: 4606-0000 | B99: Amenity Rental | C99: 0 | D99: 0 | E99: 0 | F99: 0 | G99: 0 | I99: =C99+D99+E99+F99+G99 -> 0 | J99: 1133685
A100: 4650-0000 | B100: Bad Debt | C100: 0 | D100: 0 | E100: 0 | F100: 0 | G100: 0 | I100: =C100+D100+E100+F100+G100 -> 0 | J100: 1133686
A101: 4655-0000 | B101: N.Y.C. Grant | C101: 0 | D101: 0 | E101: 0 | F101: 0 | G101: 0 | I101: =C101+D101+E101+F101+G101 -> 0 | J101: 1133687
A102: 4660-0000 | B102: Roof Income | C102: 0 | D102: 0 | E102: 0 | F102: 0 | G102: 0 | I102: =C102+D102+E102+F102+G102 -> 0 | J102: 1133688
A103: 4690-0000 | B103: Other Recurring Income | C103: 0 | D103: 0 | E103: 0 | F103: 0 | G103: 0 | I103: =C103+D103+E103+F103+G103 -> 0 | J103: 1133689
A104: 4699-9997 | B104: TOTAL RECURRING INCOME | C104: 9263904.6 | D104: 9372345.5 | E104: 6536585.7 | F104: 5854647.7 | G104: 9083861 | I104: =C104+D104+E104+F104+G104 -> 40111345 | J104: 1133690
I105: =C105+D105+E105+F105+G105 -> 0 | J105: 1133691
A106: 4700-9994 | B106: NON-RECURRING INCOME | I106: =C106+D106+E106+F106+G106 -> #VALUE! | J106: 1133692
A107: 4705-0000 | B107: Late Charges | C107: 3024.12 | D107: 2345.14 | E107: 450 | F107: 1000 | G107: 1500 | I107: =C107+D107+E107+F107+G107 -> 8319.26 | J107: 1133693
A108: 4710-0000 | B108: Legal Fees | C108: 3895.04 | D108: 0 | E108: 0 | F108: 0 | G108: 0 | I108: =C108+D108+E108+F108+G108 -> 3895.04 | J108: 1133694
A109: 4715-0000 | B109: Bounce Check Fee | C109: 650 | D109: 300 | E109: 650 | F109: 0 | G109: 0 | I109: =C109+D109+E109+F109+G109 -> 1600 | J109: 1133695
A110: 4720-0000 | B110: Apartment Repair Income | C110: 2768.64 | D110: 0 | E110: -4566.04 | F110: 0 | G110: 0 | I110: =C110+D110+E110+F110+G110 -> -1797.4 | J110: 1133696
A111: 4720-0010 | B111: Architectural/Enginerring Fees | C111: 4875 | D111: 2300 | E111: 900 | F111: 0 | G111: 0 | I111: =C111+D111+E111+F111+G111 -> 8075 | J111: 1133697
A112: 4720-0020 | B112: Paint & Plaster | C112: 0 | D112: 0 | E112: 0 | F112: 0 | G112: 0 | I112: =C112+D112+E112+F112+G112 -> 0 | J112: 1133698
A113: 4720-0025 | B113: Bathroom Repair | C113: 0 | D113: 0 | E113: 0 | F113: 0 | G113: 0 | I113: =C113+D113+E113+F113+G113 -> 0 | J113: 1133699
A114: 4720-0030 | B114: Plumbing Repair | C114: 8401.54 | D114: 15844.69 | E114: 6848.55 | F114: 0 | G114: 0 | I114: =C114+D114+E114+F114+G114 -> 31094.78 | J114: 1133700
A115: 4720-0035 | B115: A/C Repair | C115: 0 | D115: 0 | E115: 0 | F115: 0 | G115: 0 | I115: =C115+D115+E115+F115+G115 -> 0 | J115: 1133701
A116: 4720-0040 | B116: HVAC Repair | C116: 0 | D116: 0 | E116: 0 | F116: 0 | G116: 0 | I116: =C116+D116+E116+F116+G116 -> 0 | J116: 1133702
A117: 4720-0045 | B117: Refrigerator | C117: 0 | D117: 0 | E117: 0 | F117: 0 | G117: 0 | I117: =C117+D117+E117+F117+G117 -> 0 | J117: 1133703
A118: 4720-0046 | B118: Range & Oven | C118: 0 | D118: 0 | E118: 0 | F118: 0 | G118: 0 | I118: =C118+D118+E118+F118+G118 -> 0 | J118: 1133704
... A170: 4954-0000 | B170: Accounting Fees | C170: 0 | D170: 0 | E170: 0 | F170: 0 | G170: 0 | I170: =C170+D170+E170+F170+G170 -> 0 | J170: 1133756
A171: 4955-0000 | B171: Tax Abatement Program | C171: 0 | D171: 0 | E171: 0 | F171: 0 | G171: 0
A172: 4956-0000 | B172: Security Account Admin. | C172: 0 | D172: 0 | E172: 0 | F172: 0 | G172: 0 | I172: 1 | J172: 1133757
A173: 4959-0000 | B173: Leasing Commissions | C173: 0 | D173: 0 | E173: 0 | F173: 0 | G173: 0
A174: 4970-0000 | B174: Sales Commissions | C174: 0 | D174: 0 | E174: 0 | F174: 0 | G174: 0 | I174: 1 | J174: 1133758
A175: 4972-0000 | B175: Insurance Commissions | C175: 0 | D175: 0 | E175: 0 | F175: 0 | G175: 0
A176: 4974-0000 | B176: Mortgage Brokerage Commissions | C176: 0 | D176: 0 | E176: 0 | F176: 0 | G176: 0 | I176: 1 | J176: 1133759
A177: 4975-0000 | B177: Co-Broker | C177: 0 | D177: 0 | E177: 0 | F177: 0 | G177: 0 | I177: =C177+D177+E177+F177+G177 -> 0 | J177: 1133760 | L177: =+F177-E177 -> 0
A178: 4975-0010 | B178: Closing Costs Reimbursement | C178: 0 | D178: 0 | E178: 0 | F178: 0 | G178: 0 | I178: =C178+D178+E178+F178+G178 -> 0 | J178: 1133761
A179: 4975-0015 | B179: Gain on Debt | C179: 0 | D179: 0 | E179: 0 | F179: 0 | G179: 0 | I179: =C179+D179+E179+F179+G179 -> 0 | J179: 1133762
A180: 4975-0020 | B180: Apartment Sales | C180: 0 | D180: 0 | E180: 0 | F180: 0 | G180: 0 | I180: =C180+D180+E180+F180+G180 -> 0 | J180: 1133763
A181: 4975-0025 | B181: Cost of Sales | C181: 0 | D181: 0 | E181: 0 | F181: 0 | G181: 0 | I181: =C181+D181+E181+F181+G181 -> 0 | J181: 1133764
A182: 4990-0000 | B182: Other Non Recurring Income | C182: 0 | D182: 57727.6 | E182: 34221.28 | F182: 0 | G182: 0 | I182: =C182+D182+E182+F182+G182 -> 91948.88 | J182: 1133765
A183: 4998-9997 | B183: TOTAL NON-RECURRING INCOME | C183: 139660.61 | D183: 186000.47 | E183: 112724.92 | F183: 24000 | G183: 32500 | I183: =C183+D183+E183+F183+G183 -> 494886 | J183: 1133766
A184: 4999-9998 | B184: TOTAL INCOME | C184: 9403565.2 | D184: 9558346 | E184: 6649310.6 | F184: 5878647.7 | G184: 9116361 | I184: =C184+D184+E184+F184+G184 -> 40606231 | J184: 1133767
I185: =C185+D185+E185+F185+G185 -> 0 | J185: 1133768
A186: 5000-9994 | B186: EXPENSES | I186: =C186+D186+E186+F186+G186 -> #VALUE! | J186: 1133769
I187: =C187+D187+E187+F187+G187 -> 0 | J187: 1133770
A188: 5000-9995 | B188: OPERATING EXPENSES | I188: =C188+D188+E188+F188+G188 -> #VALUE! | J188: 1133771
I189: =C189+D189+E189+F189+G189 -> 0 | J189: 1133772
A190: 5100-9994 | B190: PAYROLL EXPENSES | I190: =C190+D190+E190+F190+G190 -> #VALUE! | J190: 1133773
A191: 5105-0000 | B191: Gross Payroll | C191: 697497.87 | D191: 709484.74 | E191: 464474.23 | F191: 539851 | G191: 802063 | I191: =C191+D191+E191+F191+G191 -> 3213370.8 | J191: 1133774
A192: 5105-0010 | B192: Overtime Pay | C192: 44679.92 | D192: 45711.62 | E192: 38888.88 | F192: 21614 | G192: 26138 | I192: =C192+D192+E192+F192+G192 -> 177032.42 | J192: 1133775
A193: 5105-0015 | B193: Vacation Pay | C193: 52201.42 | D193: 57738.99 | E193: 55459.56 | F193: 33016 | G193: 33016 | I193: =C193+D193+E193+F193+G193 -> 231431.97 | J193: 1133776
A194: 5105-0020 | B194: Holiday Pay | C194: 24204.87 | D194: 25440.57 | E194: 15234.04 | F194: 7274 | G194: 14547 | I194: =C194+D194+E194+F194+G194 -> 86700.48 | J194: 1133777
A195: 5105-0021 | B195: Holiday Premium Pay | C195: 26677.79 | D195: 24263.82 | E195: 15065.04 | F195: 6938 | G195: 13874 | I195: =C195+D195+E195+F195+G195 -> 86818.65 | J195: 1133778
A196: 5105-0025 | B196: Sick Pay | C196: 30871.45 | D196: 35606.01 | E196: 30446.68 | F196: 18140 | G196: 20360 | I196: =C196+D196+E196+F196+G196 -> 135424.14 | J196: 1133779
A197: 5105-0027 | B197: Meal Reimbursement - Payroll | C197: 0 | D197: 60 | E197: 390 | F197: 22.64 | G197: 34 | I197: =C197+D197+E197+F197+G197 -> 506.64 | J197: 1133780
A198: 5105-0029 | B198: Tool Reimbursement | C198: 0 | D198: 0 | E198: 0 | F198: 0 | G198: 0 | I198: =C198+D198+E198+F198+G198 -> 0 | J198: 1133781
A199: 5105-0030 | B199: Miscellaneous Pay | C199: 1258.48 | D199: 0 | E199: 2302.4 | F199: 0 | G199: 0 | I199: =C199+D199+E199+F199+G199 -> 3560.88 | J199: 1133782
A200: 5105-0035 | B200: Bonus | C200: 37300 | D200: 45600 | E200: 1000 | F200: 0 | G200: 34500 | I200: =C200+D200+E200+F200+G200 -> 118400 | J200: 1133783
A201: 5140-0000 | B201: Employee Payroll Taxes | C201: 0 | D201: 0 | E201: 0 | F201: 0 | G201: 0 | I201: =C201+D201+E201+F201+G201 -> 0 | J201: 1133784
A202: 5140-0010 | B202: Medicare | C202: 0 | D202: 0 | E202: 0 | F202: 0 | G202: 0 | I202: =C202+D202+E202+F202+G202 -> 0 | J202: 1133785
... A219: 5160-0010 | B219: Pension Fund | C219: 73959.25 | D219: 71736.5 | E219: 51415 | F219: 52077.36 | G219: 78116 | I219: =C219+D219+E219+F219+G219 -> 327304.11 | J219: 1133802
A220: 5160-0015 | B220: Health Fund | C220: 251635.41 | D220: 256270.08 | E220: 179828 | F220: 180488 | G220: 270732
A221: 5160-0020 | B221: Annuity Fund | C221: 6890 | D221: 6900 | E221: 4550 | F221: 4840 | G221: 7190 | I221: 1 | J221: 1133803
A222: 5160-0025 | B222: Legal Fund | C222: 541.9 | D222: 384.2 | E222: 1313.51 | F222: 264 | G222: 396 | I222: =C222+D222+E222+F222+G222 -> 2899.61 | J222: 1133804
A223: 5160-0030 | B223: Training Fund | C223: 1846.18 | D223: 1809.57 | E223: 1243.44 | F223: 1243.36 | G223: 1865 | I223: =C223+D223+E223+F223+G223 -> 8007.55 | J223: 1133805
A224: 5160-0035 | B224: Welfare Fund | C224: 0 | D224: 0 | E224: 0 | F224: 0 | G224: 0 | I224: =C224+D224+E224+F224+G224 -> 0 | J224: 1133806
A225: 5160-0040 | B225: Garnishments | C225: 0 | D225: 0 | E225: 0 | F225: 0 | G225: 0 | I225: =C225+D225+E225+F225+G225 -> 0 | J225: 1133807
A226: 5165-0000 | B226: Workers Compensation Insurance | C226: 28055.93 | D226: 50121.96 | E226: 35572.36 | F226: 31483 | G226: 47227 | I226: =C226+D226+E226+F226+G226 -> 192460.25 | J226: 1133808
A227: 5165-0050 | B227: Workers Comp Audit / Dividend | C227: -7425.9 | D227: -9481.22 | E227: -8644.9 | F227: 0 | G227: 0 | I227: =C227+D227+E227+F227+G227 -> -25552.02 | J227: 1133809
A228: 5166-0000 | B228: Disability Insurance | C228: 326.2 | D228: -156.76 | E228: 1326.2 | F228: 4838 | G228: 4838 | I228: =C228+D228+E228+F228+G228 -> 11171.64 | J228: 1133810
...

Sheet COV
A2: .
C22: For the Board of Directors of
C23: 444 East 86th Street Owners Corp.
C24: =contents!C2 -> Operating Budget
C25: =contents!C3 -> For Year Ending 12/31/2026
E26: Building # | F26: 204
F30: =+' bud'!G5 -> Approved
F31: Prepared By: KP
F32: Reviewd By: MC
F33: =TODAY() -> 46105
C35: 2026 Proposed Increase: | F35: =' bud'!E38 -> -8.7366373e-09

Sheet contents
C1: =+COV!C23 -> 444 East 86th Street Owners Corp.
C2: Operating Budget
C3: =yrlycomp!H3 -> For Year Ending 12/31/2026
B5: TABLE OF CONTENTS
B7: CATEGORY | D7: SCHEDULE | F7: PAGE #
B9: OPERATING BUDGET SUMMARY | D9: - | F9: 1
B11: YEARLY COMPARISON | D11: - | F11: 2
B13: INCOME ANALYSIS | D13: A | F13: 3
B14: COMMERCIAL RENT & ESCALATIONS | D14: A-1 | F14: 4
B16: EXPENSE PIE CHART | D16: - | F16: 5
B18: PAYROLL | D18: B | F18: 6
B20: ELECTRIC | D20: C | F20: 7 & 8
B22: GAS-COOKING | D22: D | F22: 9
B24: GAS -HEATING | D24: E | F24: 10
B26: SUPPLIES, REPAIRS, & MAINTENANCE | D26: F | F26: 11
B28: GENERAL & ADMINISTRATIVE | D28: F-1 | F28: 12
B29: PROFESSIONAL FEES
B30: ADMINISTRATIVE
B31: INSURANCE
B32: CORPORATE TAX
B33: FINANCIAL EXPENSES
B35: WATER & SEWER | D35: G | F35: 13
B37: REAL ESTATE TAXES | D37: H | F37: 14
B39: CAPITAL EXPENSES | D39: I | F39: 15
B41: MANAGEMENT FEE LETTER | D41: - | F41: 16-17
B43: ENERGY SCORE | D43: - | F43: 17-18
F79: =+F77+1 -> 1

Sheet  bud
C1: =+COV!C23 -> 444 East 86th Street Owners Corp.
C2: Operating Budget Summary
C3: =yrlycomp!H3 -> For Year Ending 12/31/2026
G5: Approved
B7: Operating Income
B8: =yrlycomp!B10 -> Maintenance | D8: =yrlycomp!L10 -> 9384324.6
B9: =yrlycomp!B12 -> Commercial | D9: =yrlycomp!L12 -> 54000
B10: Gaarage | D10: =yrlycomp!L13 -> 460000
B11: =yrlycomp!B11 -> Tax Benefit Credits (Abatement, Star,etc) | D11: =yrlycomp!L11 -> -830104.75
B12: =+yrlycomp!B15 -> Storage Income | D12: =+yrlycomp!L15 -> 61380
B13: =yrlycomp!B16 -> Bicycle Charge | D13: =yrlycomp!L16 -> 7380
B14: =yrlycomp!B17 -> Laundry | D14: =yrlycomp!L17 -> 52999.92
B15: =yrlycomp!B18 -> Assessment - Operating | D15: =yrlycomp!L18 -> 200448
B16: =yrlycomp!B14 -> Commercial Real Estate Tax | D16: =yrlycomp!L14 -> 0
B17: =yrlycomp!B19 -> Other Income | D17: =yrlycomp!L19 -> 44000
B18: Total Income | D18: =SUM(D8:D17) -> 9434427.8
B20: Operating Expenses
B21: =+yrlycomp!B23 -> Payroll | D21: =+yrlycomp!L23 -> 1540644.7
B22: =+yrlycomp!B24 -> Electric | D22: =+yrlycomp!L24 -> 251140.76
B23: =+yrlycomp!B25 -> Gas Cooking / Heating | D23: =+yrlycomp!L25 -> 569699.59
B24: =+yrlycomp!B27 -> Water & Sewer | D24: =+yrlycomp!L27 -> 216507.32
B25: =+yrlycomp!B28 -> Supplies | D25: =+yrlycomp!L28 -> 90000
B26: =+yrlycomp!B29 -> Repairs & Maintenance | D26: =+yrlycomp!L29 -> 675000.26
B27: =+yrlycomp!B30 -> Insurance | D27: =+yrlycomp!L30 -> 641578.18
B28: =+yrlycomp!B31 -> Real Estate Taxes | D28: =+yrlycomp!L31 -> 5106995
B29: =+yrlycomp!B32 -> Real Estate Tax Benefit Credits | D29: =+yrlycomp!L32 -> -838405.79
B30: =+yrlycomp!B33 -> Corporate Taxes | D30: =+yrlycomp!L33 -> 24500
B31: =+yrlycomp!B34 -> Professional Fees | D31: =+yrlycomp!L34 -> 178772.6
B32: =+yrlycomp!B35 -> Administrative & Other | D32: =+yrlycomp!L35 -> 87575
B33: =+yrlycomp!B36 -> Financial Expenses | D33: =+yrlycomp!L36 -> 890420.12
B34: Total Expenses | D34: =SUM(D21:D33) -> 9434427.7
B36: Operating Surplus < Deficit> | D36: =D18-D34 -> 0.081987441
B38: Maintenance Increase Needed to Cover <Deficit> | E38: =+D36/D8*-1 -> -8.7366373e-09
B41: Cash & Cash Equivalents
F42: G/L
C43: Webster Bank Operating Account | F43: 0010-0000 | G43: 311669.03
C44: Webster Bank Reserve | F44: 0020-0000 | G44: 1606538.7
C45: NCB | F45: 0035-0002 | G45: 529378.86
C46: Webster Bank Tax Escrow | F46: 0055-0007 | G46: 769146.39
C47: Bank United Escrow Deposit | F47: 0055-0000 | G47: 48295.42
C48: Bank United Security Deposit | F48: 0055-0002 | G48: 18401.72
B50: Total Cash & Cash Equivalents @ 08/31/2025 | G50: =SUM(G43:G49) -> 3283430.1
B53: Page 1
B58: Pie Chart Data
B60: =+B8 -> Maintenance | C60: =+D8 -> 9384324.6
B61: =+B9 -> Commercial | C61: =+D9 -> 54000
B62: Garage | C62: =+D10 -> 460000
B63: =+B11 -> Tax Benefit Credits (Abatement, Star,etc) | C63: =+D11 -> -830104.75
B64: =+B14 -> Laundry | C64: =+D14 -> 52999.92
B65: =+B18 -> Total Income | C65: =SUM(C60:C64) -> 9121219.8
B67: =+B20 -> Operating Expenses
B68: =+B21 -> Payroll | C68: =+D21 -> 1540644.7
B69: =+B22 -> Electric | C69: =+D22 -> 251140.76
B70: =+B23 -> Gas Cooking / Heating | C70: =+D23 -> 569699.59
B71: =+B24 -> Water & Sewer | C71: =+D24 -> 216507.32
B72: =+B25 -> Supplies | C72: =+D25 -> 90000
B73: =+B26 -> Repairs & Maintenance | C73: =+D26 -> 675000.26
B74: =+B27 -> Insurance | C74: =+D27 -> 641578.18
B75: Real Estate Tax (Net of Credits) | C75: =+D28+D29 -> 4268589.2
B76: =+B30 -> Corporate Taxes | C76: =+D30 -> 24500
B77: =+B31 -> Professional Fees | C77: =+D31 -> 178772.6
B78: =+B32 -> Administrative & Other | C78: =+D32 -> 87575
B79: =+B33 -> Financial Expenses | C79: =+D33 -> 890420.12
B80: =+B34 -> Total Expenses | C80: =SUM(C68:C79) -> 9434427.7

Sheet yrlycomp
H1: =+' bud'!C1 -> 444 East 86th Street Owners Corp.
H2: Yearly Comparison | N2: Income - Operating assessment amount is used to help balance the budget and control the amount of the increase.
H3: For Year Ending 12/31/2026 | N3: Leave the same amount used in prevoius years budget until the Board advises to change it
N5: update years column M
D7: 2021 | E7: 2022 | F7: 2023 | G7: 2024 | H7: 2025 | I7: =H7 -> 2025 | J7: =I7 -> 2025 | K7: =J7 -> 2025 | L7: =K7+1 -> 2026 | M7: 2026 Budget
D8: Actual * | E8: Actual * | F8: Actual * | G8: Actual * | H8: 8 Mo. Actual | I8: 4 Mo. Est** | J8: 12 Mo. Forecast | K8: Budget | L8: Budget | M8: V. 2025 Forecast
B9: Income
B10: Maintenance | D10: 7922916 | E10: 8140848 | F10: 8588595 | G10: 8760380 | H10: =SUMIF('VLookup Data'!$A:$A,'VLookup Data'!A235,'VLookup Data'!$E:$E)+SUMIF('VLookup Data'!$A:$A,'VLookup Data'!A247,'VLookup Data'!$E:$E)++SUMIF('VLookup Data'!$A:$A,'VLookup Data'!A245,'VLookup Data'!$E:$E) -> 6032067.9 | I10: =+J10-H10 -> 3034912.4 | J10: =+Income!H16 -> 9066980.3 | K10: 9066980.3 | L10: =+Income!H18 -> 9384324.6 | M10: =+(L10-J10)/J10 -> 0.035
B11: Tax Benefit Credits (Abatement, Star,etc) | D11: -814837 | E11: -772263 | F11: -778849 | G11: -750999 | H11: =SUMIF('VLookup Data'!$A:$A,'VLookup Data'!A248,'VLookup Data'!$E:$E)+SUMIF('VLookup Data'!$A:$A,'VLookup Data'!A249,'VLookup Data'!$E:$E)+SUMIF('VLookup Data'!$A:$A,'VLookup Data'!A250,'VLookup Data'!$E:$E)+SUMIF('VLookup Data'!$A:$A,'VLookup Data'!A251,'VLookup Data'!$E:$E)+SUMIF('VLookup Data'!$A:$A,'VLookup Data'!A252,'VLookup Data'!$E:$E) -> -807394.18 | I11: =J11-H11 -> -650 | J11: =-'RE Taxes'!F29 -> -808044.18 | K11: -825636.71 | L11: =-'RE Taxes'!G29 -> -830104.75 | M11: =+(L11-J11)/J11 -> 0.027301189 | N11: =+H11/9 -> -89710.464 | P11: =4+3+3 -> 10
B12: Commercial | C12: (A) | D12: 24000 | E12: 54000 | F12: 54000 | G12: 54000 | H12: =+'Comm Rent & Escalations'!C38 -> 36000 | I12: 1500 | J12: ='Comm Rent & Escalations'!E38 -> 54000 | K12: 54000 | L12: ='Comm Rent & Escalations'!G38 -> 54000 | M12: =+(L12-J12)/J12 -> 0 | P12: =2.5+2.5+2.5 -> 7.5
B13: Garage | C13: (A) | D13: 62945 | E13: 385818 | F13: 463643 | G13: 450963 | H13: ='Comm Rent & Escalations'!C39 -> 344059.74 | I13: ='Comm Rent & Escalations'!D39 -> 114686.58 | J13: ='Comm Rent & Escalations'!E39 -> 458746.32 | K13: 456000 | L13: ='Comm Rent & Escalations'!G39 -> 460000 | M13: =+(L13-J13)/J13 -> 0.0027328394
B14: Commercial Real Estate Tax | D14: 0 | E14: 0 | F14: 0 | H14: =SUMIF('VLookup Data'!$A:$A,'VLookup Data'!A293,'VLookup Data'!$E:$E) -> 0 | I14: 0 | J14: =+'Comm Rent & Escalations'!E40 -> 0 | K14: 0 | L14: =+'Comm Rent & Escalations'!G40 -> 0 | M14: =+(L14-J14)/J14 -> #DIV/0!
B15: Storage Income | D15: 0 | E15: 26830 | F15: 43216 | G15: 57860 | H15: =+'VLookup Data'!E257 -> 36115.75 | I15: =+J15-H15 -> 25264.25 | J15: =Income!I34 -> 61380 | K15: 52980 | L15: =+Income!I37 -> 61380 | M15: =+(L15-J15)/J15 -> 0
B16: Bicycle Charge | D16: 0 | E16: 0 | F16: 0 | G16: 0 | H16: =SUMIF('VLookup Data'!$A:$A,'VLookup Data'!A258,'VLookup Data'!$E:$E) -> 2959.95 | I16: =+J16-H16 -> 4420.05 | J16: =+Income!H43 -> 7380 | K16: 4680 | L16: =+Income!H45 -> 7380 | M16: =+(L16-J16)/J16 -> 0
B17: Laundry | D17: 60000 | E17: 60000 | F17: 60000 | G17: 58250 | H17: =SUMIF('VLookup Data'!$A:$A,'VLookup Data'!A263,'VLookup Data'!$E:$E) -> 49699.94 | I17: =+J17-H17 -> 3299.98 | J17: =+Income!F51 -> 52999.92 | K17: 52999.92 | L17: =+Income!F53 -> 52999.92 | M17: =+(L17-J17)/J17 -> 0 | S17: =+H18+H43 -> 843076.65
B18: Assessment - Operating | C18: (B) | D18: 145000 | E18: 150000 | F18: 238000 | G18: 230000 | H18: ='VLookup Data'!E274 -> 843076.65 | I18: =+J18-H18 -> -621218.65 | J18: =K18 -> 221858 | K18: 221858 | L18: 200448 | M18: =+(L18-J18)/J18 -> -0.096503169 | N18: =+L18/709000 -> 0.28271932 | S18: =-H53 -> -339591.93
B19: Other Income | D19: =823+22500+24629 -> 47952 | E19: =23500+18492+1254 -> 43246 | F19: =23000+38763+3024 -> 64787 | G19: =81112+12500+12573 -> 106185 | H19: =+Income!D78 -> 77494.5 | I19: =+J19-H19 -> 22228.155 | J19: =+Income!F78 -> 99722.655 | K19: 32500 | L19: =+Income!H78 -> 44000 | M19: =+(L19-J19)/J19 -> -0.55877629 | S19: =-H18 -> -843076.65
B20: Total Income | D20: =SUM(D10:D19) -> 7447976 | E20: =SUM(E10:E19) -> 8088479 | F20: =SUM(F10:F19) -> 8733392 | G20: =SUM(G10:G19) -> 8966639 | H20: =SUM(H10:H19) -> 6614080.2 | I20: =SUM(I10:I19) -> 2584442.8 | J20: =SUM(J10:J19) -> 9215023 | K20: =SUM(K10:K19) -> 9116361.5 | L20: =SUM(L10:L19) -> 9434427.8 | M20: =+(L20-J20)/J20 -> 0.023809465 | S20: =SUM(S17:S19) -> -339591.93
N21: Do Not Print(Use these review Projections)
B22: Expenses | N22: Projected Variance Over 2016 Results
B23: Payroll | D23: =1269052+4529 -> 1273581 | E23: =921032+341913+58722 -> 1321667 | F23: =917786+376231+74535 -> 1368552 | G23: =949984+380390+76798 -> 1407172 | H23: =+Payroll!H77 -> 974031.24 | I23: =+J23-H23 -> 509266.31 | J23: =+Payroll!J77 -> 1483297.5 | K23: 1488209.5 | L23: =+Payroll!L77 -> 1540644.7 | M23: =+(L23-J23)/J23 -> 0.038661935 | N23: =(L23-J23)/J23 -> 0.038661935 | P23: =+J23-E23 -> 161630.55 | Q23: =+E23-D23 -> 48086 | R23: =+J23-E23 -> 161630.55
B24: Electric | D24: 224415 | E24: 303451 | F24: 317329 | G24: 206874 | H24: =SUMIF('VLookup Data'!$A:$A,'VLookup Data'!A432,'VLookup Data'!$E:$E) -> 144894.89 | I24: =+J24-H24 -> 108288.92 | J24: =Electric!F37+'Electric 2'!D37 -> 253183.81 | K24: 321913.7 | L24: =Electric!F53+'Electric 2'!D53 -> 251140.76 | M24: =+(L24-J24)/J24 -> -0.0080694374 | N24: =(L24-J24)/J24 -> -0.0080694374 | P24: =+P23/E23 -> 0.12229294 | Q24: =+Q23/D23 -> 0.037756531 | R24: =+R23/E23 -> 0.12229294
B25: Gas Cooking / Heating | D25: 395473 | E25: 466316 | F25: 524865 | G25: 468018 | H25: =SUMIF('VLookup Data'!$A:$A,'VLookup Data'!A429,'VLookup Data'!$E:$E)+SUMIF('VLookup Data'!$A:$A,'VLookup Data'!A431,'VLookup Data'!$E:$E) -> 376764.45 | I25: =+J25-H25 -> 194777.08 | J25: =+'Gas Cooking'!F37+'Gas-Heat'!F37 -> 571541.53 | K25: 535361.39 | L25: =+'Gas Cooking'!F53+'Gas-Heat'!F53 -> 569699.59 | M25: =+(L25-J25)/J25 -> -0.0032227603 | N25: =(L25-J25)/J25 -> -0.0032227603
B26: Fuel | D26: 0 | E26: 0 | F26: 0 | G26: 0 | H26: =SUMIF('VLookup Data'!$A:$A,'VLookup Data'!A433,'VLookup Data'!$E:$E) -> 0 | I26: 0 | J26: 0 | K26: 0 | L26: 0
B27: Water & Sewer | D27: 209320 | E27: 214222 | F27: 211315 | G27: 265390 | H27: =+Water!D39 -> 136280.9 | I27: =+J27-H27 -> 72501.47 | J27: =+Water!G39 -> 208782.37 | K27: 217796.61 | L27: =+Water!I39 -> 216507.32 | M27: =+(L27-J27)/J27 -> 0.037 | N27: =(L27-J27)/J27 -> 0.037
B28: Supplies | D28: =18540+69215 -> 87755 | E28: =17603+61201 -> 78804 | F28: =25923+75818 -> 101741 | G28: =30860+77598 -> 108458 | H28: =+'Repairs & Supplies'!D9 -> 45896.47 | I28: =+J28-H28 -> 20504.12 | J28: =+'Repairs & Supplies'!H9 -> 66400.59 | K28: 90000 | L28: =+'Repairs & Supplies'!J9 -> 90000 | M28: =+(L28-J28)/J28 -> 0.35540964 | N28: =(L28-J28)/J28 -> 0.35540964
B29: Repairs & Maintenance | D29: =596659-69215 -> 527444 | E29: =555982-61201 -> 494781 | F29: =748274-75818 -> 672456 | G29: =768962-77598 -> 691364 | H29: =+'Repairs & Supplies'!D57 -> 519828.15 | I29: =+J29-H29 -> 123363.53 | J29: =+'Repairs & Supplies'!H57 -> 643191.68 | K29: 550000.09 | L29: =+'Repairs & Supplies'!J57 -> 675000.26 | M29: =+(L29-J29)/J29 -> 0.049454274 | N29: =(L29-J29)/J29 -> 0.049454274 | O29: =154580+90267 -> 244847
B30: Insurance | D30: 249055 | E30: 277481 | F30: 336029 | G30: 393544 | H30: =+'Gen & Admin'!D57 -> 557894.07 | I30: =+J30-H30 -> 0 | J30: =+'Gen & Admin'!H57 -> 557894.07 | K30: 501226.29 | L30: =+'Gen & Admin'!J57 -> 641578.18 | M30: =+(L30-J30)/J30 -> 0.15 | N30: =(L30-J30)/J30 -> 0.15 | Q30: 2014 | R30: 2013
B31: Real Estate Taxes | D31: =3777699+814837 -> 4592536 | E31: =3929982+772263+3 -> 4702248 | F31: =3985240+778849 -> 4764089 | G31: =4167342+750999 -> 4918341 | H31: =+'RE Taxes'!D41 -> 3724147.8 | I31: =+J31-H31 -> 1249363.4 | J31: =+'RE Taxes'!F41 -> 4973511.1 | K31: 5087406.1 | L31: =+'RE Taxes'!H41 -> 5106995 | M31: =+(L31-J31)/J31 -> 0.026838956 | N31: =(L31-J31)/J31 -> 0.026838956 | P31: E | Q31: 294056.38 | R31: 277601
B32: Real Estate Tax Benefit Credits | D32: =D11 -> -814837 | E32: =E11 -> -772263 | F32: -778849 | G32: -750999 | H32: =+'RE Taxes'!D46-'RE Taxes'!D41 -> -608282.85 | I32: =+J32-H32 -> -204260.75 | J32: =+'RE Taxes'!F46-'RE Taxes'!F41 -> -812543.6 | K32: -845992.58 | L32: =+'RE Taxes'!H46-'RE Taxes'!H41 -> -838405.79 | M32: =+(L32-J32)/J32 -> 0.031828686 | N32: =(L32-J32)/J32 -> 0.031828686 | P32: G | Q32: 351520 | R32: 121107
B33: Corporate Taxes | D33: =25778+34483 -> 60261 | E33: 49803 | F33: 17268 | G33: 32746 | H33: =+'Gen & Admin'!D60 -> 19550 | I33: =+J33-H33 -> 5664 | J33: =+'Gen & Admin'!H60 -> 25214 | K33: 27300 | L33: ='Gen & Admin'!J61 -> 24500 | M33: =+(L33-J33)/J33 -> -0.028317601 | N33: =(L33-J33)/J33 -> -0.028317601 | Q33: =SUM(Q31:Q32) -> 645576.38 | R33: =SUM(R31:R32) -> 398708 | T33: =+E31-D31 -> 109712 | U33: =+J31+J32 -> 4160967.5
B34: Professional Fees | D34: =55899+672+15750+125667+10267 -> 208255 | E34: =27995+63009+129122 -> 220126 | F34: =20722+33460+132673 -> 186855 | G34: =22715+13186+136322 -> 172223 | H34: =+'Gen & Admin'!D18 -> 116223.15 | I34: =+J34-H34 -> 48844.075 | J34: =+'Gen & Admin'!H18 -> 165067.22 | K34: 175820.63 | L34: =+'Gen & Admin'!J18 -> 178772.6 | M34: =+(L34-J34)/J34 -> 0.083029051 | N34: =(L34-J34)/J34 -> 0.083029051 | P34: =+L34-139000 -> 39772.6 | T34: =+T33/D31 -> 0.023889198 | U34: =+U33-E31 -> -541280.47
B35: Administrative & Other | D35: =15328+31775+26561 -> 73664 | E35: =63175+600+8751 -> 72526 | F35: =61569+350+6724 -> 68643 | G35: =85714+600+7208 -> 93522 | H35: =+'Gen & Admin'!D47 -> 61257.55 | I35: =+J35-H35 -> 13804.55 | J35: =+'Gen & Admin'!H47 -> 75062.1 | K35: 76900 | L35: =+'Gen & Admin'!J47 -> 87575 | M35: =+(L35-J35)/J35 -> 0.16670064 | N35: =(L35-J35)/J35 -> 0.16670064 | U35: =+U34/E31 -> -0.115111
B36: Financial Expenses | D36: =581421+174131 -> 755552 | E36: =618553+181161 -> 799714 | F36: =611214+188474 -> 799688 | G36: =605232+194437 -> 799669 | H36: =+'Gen & Admin'!D68 -> 594030.08 | I36: =+J36-H36 -> 297015.04 | J36: =+'Gen & Admin'!H68 -> 891045.12 | K36: 890420.12 | L36: =+'Gen & Admin'!J68 -> 890420.12 | M36: =+(L36-J36)/J36 -> -0.00070142351 | N36: =(L36-J36)/J36 -> -0.00070142351
B37: Total Expenses | D37: =SUM(D23:D36) -> 7842474 | E37: =SUM(E23:E36) -> 8228876 | F37: =SUM(F23:F36) -> 8589981 | G37: =SUM(G23:G36) -> 8806322 | H37: =SUM(H23:H36) -> 6662515.9 | I37: =SUM(I23:I36) -> 2439131.7 | J37: =SUM(J23:J36) -> 9101647.6 | K37: =SUM(K23:K36) -> 9116361.8 | L37: =SUM(L23:L36) -> 9434427.7 | M37: =+(L37-J37)/J37 -> 0.036562626
B39: Net Operating Surplus <Deficit> | D39: =D20-D37 -> -394498 | E39: =E20-E37 -> -140397 | F39: =F20-F37 -> 143411 | G39: =G20-G37 -> 160317 | H39: =H20-H37 -> -48435.63 | I39: =I20-I37 -> 145311.08 | J39: =J20-J37 -> 113375.45 | K39: -0.33465522 | L39: =L20-L37 -> 0.081987441 | M39: =+(L39-J39)/J39 -> -0.99999928 | N39: =+L39/L10 -> 8.7366373e-09
B41: Non-Operating Income
B42: Capital Assessment | D42: 0 | E42: 0 | H42: 0 | I42: 0 | J42: 0 | K42: 0 | L42: 0 | M42: 0
B43: Special Assessment | C43: (B) | D43: 658816 | E43: 583354 | F43: 843349 | G43: 836993 | H43: 0 | I43: =+J43-H43 -> 644430.14 | J43: =+Income!G24-K18 -> 644430.14 | K43: 644432.69 | L43: =Income!G26-L18 -> 665570.54 | M43: =+(L43-J43)/J43 -> 0.032804788 | N43: Make sure the assessment 12 mo Forecast is equal to the budgeted amount for the current year
B44: Interest Income | D44: 1995 | E44: 58368 | F44: 85128 | G44: 84807 | H44: =SUMIF('VLookup Data'!$A:$A,'VLookup Data'!A334,'VLookup Data'!$E:$E) -> 35230.42 | I44: =+H44/8*4 -> 17615.21 | J44: =SUM(H44:I44) -> 52845.63 | K44: 0 | L44: 0 | M44: =+(L44-J44)/J44 -> -1 | O44: change the interest income formula
B45: Insurance Proceeds | D45: 0 | E45: 0 | G45: 0 | H45: =SUMIF('VLookup Data'!$A:$A,'VLookup Data'!A677,'VLookup Data'!$E:$E)*-1 -> 22958.17 | I45: 0 | J45: =SUM(H45:I45) -> 22958.17 | K45: 0 | L45: 0
B46: Real Estate Tax refund | D46: 64873 | E46: 65786 | F46: 0 | G46: 0 | H46: 0 | I46: 0 | J46: 0 | K46: 0 | L46: 0
B47: Capital Assessment | C47: (C) | D47: 1000659 | E47: 1000000 | F47: 0 | G47: 0 | H47: =SUMIF('VLookup Data'!$A:$A,'VLookup Data'!A218,'VLookup Data'!$E:$E) -> 659559.49 | I47: =J47-H47 -> 345119.15 | J47: =2.52*Income!E18 -> 1004678.6 | K47: 0 | L47: 0
B48: ICON Settlement Proceeds | C48: (E) | D48: 0 | E48: 0 | H48: 0 | I48: 0 | J48: =SUM(H48:I48) -> 0 | K48: 0 | L48: 0
B49: SBA - PPP Loan Proceeds | C49: (E) | D49: 208076 | E49: 0 | F49: 0 | H49: =SUMIF('VLookup Data'!$A:$A,'VLookup Data'!A166,'VLookup Data'!$E:$E) -> 0 | I49: 0 | J49: =SUM(H49:I49) -> 0 | K49: 0 | L49: 0
B50: Total Non- Operating Income | D50: =SUM(D42:D49) -> 1934419 | E50: =SUM(E42:E49) -> 1707508 | F50: =SUM(F42:F49) -> 928477 | G50: =SUM(G42:G49) -> 921800 | H50: =SUM(H42:H49) -> 717748.08 | I50: =SUM(I42:I49) -> 1007164.5 | J50: =SUM(J42:J49) -> 1724912.6 | K50: =SUM(K42:K49) -> 644432.69 | L50: =SUM(L42:L49) -> 665570.54 | M50: =+(L50-J50)/J50 -> -0.61414245
B52: Non-Operating Expense
B53: Capital Expenses | D53: 0 | E53: 0 | F53: 0 | G53: 0 | H53: =+CAP!D31 -> 339591.93 | I53: 0 | J53: =+CAP!H31 -> 251988.65 | K53: 0 | L53: =+CAP!J31 -> 0 | M53: =+(L53-J53)/J53 -> -1
B54: Cert Fee for Tax Reduction | D54: 0 | E54: 0 | H54: 0 | I54: 0 | J54: 0 | K54: 0 | L54: 0
B55: Total Non-Operating Expenses | D55: =SUM(D53:D54) -> 0 | E55: =SUM(E53:E54) -> 0 | F55: =SUM(F53:F54) -> 0 | H55: =SUM(H53:H54) -> 339591.93 | I55: =SUM(I53:I54) -> 0 | J55: =SUM(J53:J54) -> 251988.65 | K55: 0 | L55: =SUM(L53:L54) -> 0 | M55: =+(L55-J55)/J55 -> -1
B57: Total Surplus <Deficit> | D57: =+D39+D50-D55 -> 1539921 | E57: =+E39+E50-E55 -> 1567111 | F57: =+F39+F50-F55 -> 1071888 | G57: =+G39+G50-G55 -> 1082117 | H57: =+H39+H50-H55 -> 329720.52 | I57: =+I39+I50-I55 -> 1152475.6 | J57: =+J39+J50-J55 -> 1586299.4 | K57: =+K39+K50-K55 -> 644432.35 | L57: =+L39+L50-L55 -> 665570.62 | M57: =+(L57-J57)/J57 -> -0.58042559
O58: (B) Fuel - Purchased fuel to perform oil tank tightness test in 2017
B60: * Per Audited Financial Statements.
B61: ** Includes Accrual Adjustments
B63: (A) Garage - 444 East 86th Street owns the Garage. Contract with 1623 York Avenue Parking Corp. They pay a management fee of monthly proceeds
B64: based on revenue collected less expenses. 2024 new commercial lease with Corrie Horshinski, D.C. at $4,500.00/mo. from 1/13/2023-1/12/2027.
B65: (B) In June 2024 and 2023, a special assessment was charged to tenant-stockholders in the amount of $836,990.00 and $842,826.00 respectively. The assessments were based | N65: CHANGE NOTE WHEN BOARD DECIDES WHAT THE AMOUNT TO KEEP IN OPERATING FROM THE ASSESSMENT
B66: on the per share amount credited to tenant-stockholders who use their unit as their primary residence and are eligible to the NYC RE Tax Abatement credit. For Y/E 12/31/24 and
B67: 12/31/23, the BOD allocated $111,371.00 and $238,300.00 of the special assessment to fund operating expenses. 2025 Budget assumed $221,858.00 of operating funding with
B68: $644,433.00 to Special Assessment. See Schedule A - 2026 Budget total is $866,019.00 with $200,448.00 allocated to operating income and $665,571.00 to Special Assessment.
B69: (C) Capital Assessment - Board approved a Capital Assessment at $2.52/share from 01/01/25-12/31/25 to replenish reserves due to HVAC system upgrades and repairs.
B70: (E) ICON Settlement Proceeds - $600,000.00 received from ICON. Negotiations are still ongoing and the funds will be applied once completed.
O71: (D) Other Source Of Funds - Mortgage Refinance funds received of $15,942,865.34 which paid off John Hancock for $12,429,783.97, opened new reserve at NCB which was a
O72: mortgage requirement of $500,000.00, closing costs of $173,462,23. Net proceeds went to operating in the amount of $2,839,619.14.
O74: (E) SBA PPP Loan Proceeds - forgiven
O81: 2025 notes
O82: (A) Garage - 444 East 86th Street owns the Garage. Contract with 1623 York Avenue Parking Corp. They pay a management fee of monthly proceeds
O83: based on revenue collected less expenses. 2024 new commercial lease with Corrie Horshinski, D.C. at $4,500.00/mo. from 1/13/2023-1/12/2027.
I84: Page 2 | O84: (B) In June 2023 and 2022, a special assessment was charged to tenant-stockholders in the amount of $842,826.00 and $821,654.00 respectively. The assessments were based
O85: on the per share amount credited to tenant-stockholders who use their unit as their primary residence and are eligible to the NYC RE Tax Abatement credit. For Y/E 12/31/23 and
O86: 12/31/22, the BOD allocated $238,000.00 and $150,00.00 of the special assessment to fund operating expenses. 2024 Budget assumed $111,371.00 of operating funding with
O87: $725,619.00 to Special Assessment. See Schedule A - 2025 Budget total is $866,291.00 with $221,858.00 allocated to operating income and $644,433.00 to Special Assessment.
O88: (C) Real Estate Tax Refund - Tax Commission Settlement refund for overpayment of third and fourth quarters of 2021/2022 after corrected tax bills issued.
O89: (D) Capital Assessment - $2,000,000.00 Capital Assessment at $0.209/share from 01/21/21-12/31/22

Sheet Income
E1: =yrlycomp!H1 -> 444 East 86th Street Owners Corp.
E2: Income
B3: Schedule A | E3: =yrlycomp!H3 -> For Year Ending 12/31/2026
A5: G/L
E6: Shares | F6: Mthly $/per sh | G6: Monthly | H6: Annual | I6: Increase | K6: 315 Units
A7: 4010-0000 | B7: Maintenance
D8: 2017 | E8: 398682 | F8: 1.4650472 | G8: =E8*F8 -> 584087.95 | H8: =G8*12 -> 7009055.4 | I8: 0.025
D9: 2018 | E9: 398682 | F9: =+F8*I9+F8 -> 1.5177889 | G9: =E9*F9 -> 605115.11 | H9: =G9*12 -> 7261381.4 | I9: 0.036
D10: 2019 | E10: 398682 | F10: =+F9*I10+F9 -> 1.5709115 | G10: =+E10*F10 -> 626294.14 | H10: =+G10*12 -> 7515529.7 | I10: 0.035
D11: 2020 | E11: 398682 | F11: =+F10*I11+F10 -> 1.614897 | G11: =+E11*F11 -> 643830.38 | H11: =+G11*12 -> 7725964.5 | I11: 0.028
D12: 2021 | E12: 398682 | F12: =+F11*I12+F11 -> 1.6552695 | G12: =+E12*F12 -> 659926.14 | H12: =+G12*12 -> 7919113.7 | I12: 0.025
D13: 2022 | E13: 398682 | F13: =F12*I13+F12 -> 1.701617 | G13: =+E13*F13 -> 678404.07 | H13: =+G13*12 -> 8140848.8 | I13: 0.028
D14: 2023 | E14: 398682 | F14: =F13*I14+F13 -> 1.7952059 | G14: =+E14*F14 -> 715716.29 | H14: =+G14*12 -> 8588595.5 | I14: 0.055
D15: 2024 | E15: 398682 | F15: 1.8311101 | G15: 730030.62 | H15: 8760367.4 | I15: 0.02
D16: 2025 | E16: 398682 | F16: 1.8951989 | G16: 755581.69 | H16: 9066980.3 | I16: 0.035
D18: 2026 Budget | E18: =E16 -> 398682 | F18: =F16*I18+F16 -> 1.9615309 | G18: =+E18*F18 -> 782027.05 | H18: =+G18*12 -> 9384324.6 | I18: 0.035 | K18: =E18*2.52 -> 1004678.6
A20: 4200-0000 | B20: Special Assessment | E20: Shares | F20: $/per Share | G20: Total | H20: Month Billed
D21: 2022 | E21: 398682 | F21: 2.06142 | G21: =+F21*E21 -> 821851.05 | H21: June
D22: 2023 | E22: 398682 | F22: 2.11403 | G22: =+E22*F22 -> 842825.71 | H22: June
B23: (Assessment/Abatement) | D23: 2024 | E23: 398682 | F23: 2.0993937 | G23: =E23*F23 -> 836990.46 | H23: May | J23: Operating Assessment is based on 17.5% of Gross Real Estate Taxes for 2015/2016
D24: 2025 | E24: 398682 | F24: 2.17288 | G24: =E24*F24 -> 866288.14 | H24: May
D26: =D18 -> 2026 Budget | E26: =E24 -> 398682 | F26: =+(('RE Taxes'!I11*2)*17.5%)/Income!E26 -> 2.1722038 | G26: =+E26*F26 -> 866018.54 | H26: May | J26: DO NOT REMOVE FORMULA IN F26
A28: 4130-0010 | B28: Storage Room | C28: (A) | E28: Total Units | F28: Units Occupied | G28: Monthly $/Per Unit | H28: Monthly Fee | I28: Annual Fee
D29: 2025 | N29: 2023 | O29: Storage Fees were reduced after budget approved for 2023
D30: Size A | E30: 18 | F30: 17 | G30: 75 | H30: =F30*G30 -> 1275 | I30: =H30*12 -> 15300 | K30: =E30*G30 -> 1350 | L30: 28-32 cubic feet | N30: 7 vacant
D31: Size B | E31: 14 | F31: 13 | G31: 100 | H31: =G31*F31 -> 1300 | I31: =H31*12 -> 15600 | K31: =E31*G31 -> 1400 | L31: 36 cubic feet | O31: Size A - $75.00
D32: Size C | E32: 16 | F32: 16 | G32: 125 | H32: =G32*F32 -> 2000 | I32: =H32*12 -> 24000 | K32: =E32*G32 -> 2000 | L32: 48 cubic Feet | O32: Size B - $100.00
D33: Size D | E33: 3 | F33: 3 | G33: 180 | H33: =G33*F33 -> 540 | I33: =H33*12 -> 6480 | K33: =E33*G33 -> 540 | O33: Size C - $125.00
D34: Total | E34: =SUM(E30:E33) -> 51 | F34: =SUM(F30:F33) -> 49 | G34: =SUM(G30:G33) -> 480 | H34: =SUM(H30:H33) -> 5115 | I34: =SUM(I30:I33) -> 61380 | K34: =SUM(K30:K33) -> 5290 | L34: monthly at full capacity | O34: Size D - $180.00
D37: =D26 -> 2026 Budget | E37: 51 | F37: =F34 -> 49 | G37: 0 | H37: =H34 -> 5115 | I37: =H37*12 -> 61380
A39: 4130-0015 | B39: Bicycle Storage | C39: (B) | E39: Total Units | F39: Units Occupied | G39: Annual fee | H39: Total | L39: 42 Bike Racks Total
D40: 2022 | F40: 28 | G40: 180 | H40: =F40*G40 -> 5040 | L40: per Jacob - increase for 2022 # of spots
D41: 2023 | F41: 28 | G41: 180 | H41: =F41*G41 -> 5040
D42: 2024 | E42: 43 | F42: 26 | G42: 180 | H42: =F42*G42 -> 4680 | L42: Bicycle Billed monthly $15.00/mo.
D43: 2025 | E43: 43 | F43: 41 | G43: 180 | H43: =F43*G43 -> 7380 | M43: Jan 30 spots
M44: Feb-March-April-Aug-Sept 27 spots
D45: =D37 -> 2026 Budget | E45: 43 | F45: =F43 -> 41 | G45: =G43 -> 180 | H45: =F45*G45 -> 7380
M46: May-June-July-Oct 28 spots
A47: 4130-0030 | B47: Laundry | C47: (C) | E47: Monthly | F47: Annual
C48: (C) | D48: 2022 | E48: 5000 | F48: =+E48*12 -> 60000
D49: 2023 | E49: 5000 | F49: =+E49*12 -> 60000
B50: SEBCO Laundry Systems | D50: 2024 | E50: 5000 | F50: 60000
D51: 2025 | E51: 4416.66 | F51: 52999.92
J52: Sebco new contract from commencement date 12/24-11/32
D53: =D45 -> 2026 Budget | E53: =E51 -> 4416.66 | F53: =+E53*12 -> 52999.92 | J53: New Laundry Contract with Sebco for 2024
J54: 8 year term
B57: Other Income | D57: =+yrlycomp!H7 -> 2025 | E57: =D57 -> 2025 | F57: =E57 -> 2025 | G57: =F57 -> 2025 | H57: =+G57+1 -> 2026
D58: Jan - Aug | E58: Sep - Dec | F58: 12 Month | G58: Budget | H58: Budget
B59: Category | D59: Actual | E59: Est | F59: Forecast
A60: 4250-0025 | B60: Electric | D60: =SUMIF('VLookup Data'!$A:$A,A60,'VLookup Data'!$E:$E) -> 0 | E60: =D60/8*4 -> 0 | F60: =SUM(D60:E60) -> 0 | G60: 0 | H60: 0
A61: 4705-0000 | B61: Late Charges | D61: =SUMIF('VLookup Data'!$A:$A,A61,'VLookup Data'!$E:$E) -> 450 | E61: =D61/8*4 -> 225 | F61: =SUM(D61:E61) -> 675 | G61: 1500 | H61: 1000
A62: 4710-0000 | B62: Legal Fees | D62: =SUMIF('VLookup Data'!$A:$A,A62,'VLookup Data'!$E:$E) -> 0 | E62: =D62/8*4 -> 0 | F62: =SUM(D62:E62) -> 0 | G62: 0 | H62: 0
A63: 4715-0000 | B63: Bounce Check Fee | D63: =SUMIF('VLookup Data'!$A:$A,A63,'VLookup Data'!$E:$E) -> 650 | E63: =D63/8*4 -> 325 | F63: =SUM(D63:E63) -> 975 | G63: 0 | H63: 0
A64: 4720-0000 | B64: Apartment Repair Income | D64: =SUMIF('VLookup Data'!$A:$A,A64,'VLookup Data'!$E:$E) -> -4566.04 | E64: 0 | F64: =SUM(D64:E64) -> -4566.04 | G64: 0 | H64: 0
A65: 4720-0010 | B65: Architectural/Engineering Fees | D65: =SUMIF('VLookup Data'!$A:$A,A65,'VLookup Data'!$E:$E) -> 900 | E65: =D65/8*4 -> 450 | F65: =SUM(D65:E65) -> 1350 | G65: 0 | H65: 0 | J65: credit for damage from the roof
A66: 4720-0030 | B66: Plumbing Repair | D66: =SUMIF('VLookup Data'!$A:$A,A66,'VLookup Data'!$E:$E) -> 6848.55 | E66: =D66/8*4 -> 3424.275 | F66: =SUM(D66:E66) -> 10272.825 | G66: 0 | H66: 0
A67: 4725-0000 | B67: Other Apartment Charges | D67: =SUMIF('VLookup Data'!$A:$A,A67,'VLookup Data'!$E:$E) -> 0 | E67: =D67/8*4 -> 0 | F67: =SUM(D67:E67) -> 0 | G67: 0 | H67: 0
A68: 4725-0025 | B68: Move-In Out Fees | D68: =SUMIF('VLookup Data'!$A:$A,A68,'VLookup Data'!$E:$E) -> 16000 | E68: =D68/8*4 -> 8000 | F68: =SUM(D68:E68) -> 24000 | G68: 15000 | H68: 15000
A69: 4725-0030 | B69: Locks & Keys | D69: =SUMIF('VLookup Data'!$A:$A,A69,'VLookup Data'!$E:$E) -> 0 | E69: =D69/8*4 -> 0 | F69: =SUM(D69:E69) -> 0 | G69: 0 | H69: 0
A70: 4725-0035 | B70: Sublet Fees | D70: =SUMIF('VLookup Data'!$A:$A,A70,'VLookup Data'!$E:$E) -> 7679.01 | E70: =1450.97*4 -> 5803.88 | F70: =SUM(D70:E70) -> 13482.89 | G70: 6000 | H70: 10000
A71: 4803-0000 | B71: Dividend Income | D71: =SUMIF('VLookup Data'!$A:$A,A71,'VLookup Data'!$E:$E) -> 7311.7 | E71: 0 | F71: =SUM(D71:E71) -> 7311.7 | G71: 7000 | H71: 7000
A72: 4809-0000 | B72: Real Estate Tax Refunds | D72: =SUMIF('VLookup Data'!$A:$A,A72,'VLookup Data'!$E:$E) -> 0 | E72: =D72/8*4 -> 0 | F72: =SUM(D72:E72) -> 0 | G72: 0 | H72: 0
A73: 4812-0000 | B73: Corporation Tax Refunds | D73: =SUMIF('VLookup Data'!$A:$A,A73,'VLookup Data'!$E:$E) -> 0 | E73: =D73/8*4 -> 0 | F73: =SUM(D73:E73) -> 0 | G73: 0 | H73: 0
A74: 4815-0000 | B74: Payroll Tax Refunds | D74: =SUMIF('VLookup Data'!$A:$A,A74,'VLookup Data'!$E:$E) -> 0 | E74: =D74/8*4 -> 0 | F74: =SUM(D74:E74) -> 0 | G74: 0 | H74: 0
A75: 4922-0000 | B75: Alteration Agreement Fee | D75: =SUMIF('VLookup Data'!$A:$A,A75,'VLookup Data'!$E:$E) -> 7500 | E75: =D75/8*4 -> 3750 | F75: =SUM(D75:E75) -> 11250 | G75: 3000 | H75: 3000
A76: 4932-0000 | B76: Application Fees | D76: =SUMIF('VLookup Data'!$A:$A,A76,'VLookup Data'!$E:$E) -> 500 | E76: =D76/8*4 -> 250 | F76: =SUM(D76:E76) -> 750 | G76: 0 | H76: 500
A77: 4990-0000 | B77: Other Non Recurring Income | C77: (D) | D77: =SUMIF('VLookup Data'!$A:$A,A77,'VLookup Data'!$E:$E) -> 34221.28 | E77: 0 | F77: =SUM(D77:E77) -> 34221.28 | G77: 0 | H77: 7500
D78: =SUM(D60:D77) -> 77494.5 | E78: =SUM(E60:E77) -> 22228.155 | F78: =SUM(F60:F77) -> 99722.655 | G78: =SUM(G60:G77) -> 32500 | H78: =SUM(H60:H77) -> 44000
J79: update notes
A81: (A) Storage Room - Currently there are 2 vacant units. 2026 Budget is based on average $/Unit. | M81: (A) Real Estate Tax Refund - Refund due to 2017/2018 Assessed Value Reduction of $54,301.80 received by Tuchman, Korngold
A82: (B) Bicycle Storage - 2026 Budgets assumes 2 vacant spots. 2026 Budget is the same as the 2025 Forecast. | M82: Refund received from request of overpayments on the Real Estate Tax account of $46,179.76.
A83: (C) Laundry contract - SEBCO Laundry Systems 12/2024-11/2032 | M83: (A) Bad Debt - Settlement with Apt. 24D and Apt. 33J
A84: (D) Other Non-Recurring Income - 2025 Actual consists of Spectrum Marketing Agreement $25,925.00, and 2024 refund from vendor.
A85: 2026 Budget is for apartment repair charges that are billed back to shareholders and bounced check fees.
M90: (C) Real Estate Tax Refund - Tax Commission Settlement refund for overpayment of third and fourth quarters of 2021/2022 after corrected
A91: Page 3 | M91: tax bills issued.

Sheet Comm Rent & Escalations
D1: =yrlycomp!H1 -> 444 East 86th Street Owners Corp.
D2: Commercial Rent & Escalations
B3: Schedule A-1 | D3: =yrlycomp!H3 -> For Year Ending 12/31/2026
H5: 1/23 new lease Horshinski
C6: COMMERCIAL RENT | H6: 1/13/23-1/12/24 $54,000
B7: Tenant | C7: Period | D7: Rent | E7: Annualized | H7: 1/13/24-1/12/25 $54,000
C9: 2023
C10: Jan - Dec | D10: 4500 | E10: =+D10*12 -> 54000
C11: 2024
C12: Jan - Dec | D12: 4500 | E12: 54000
B13: Corrie Horshinski, D.C. | C13: 2025
C14: Jan - Dec | D14: 4500 | E14: 54000
C15: 2026 | H15: 1/13/25-1/12/26 $54,000
C16: Jan - Dec | D16: 4500 | E16: =+D16*12 -> 54000 | H16: 1/13/26-1/12/27 $54,000
C18: 2025 Payments | D18: Receipt Month | E18: Payments Received
B19: East 86th Street Garage | C19: Nov 2024 | D19: 45664 | E19: 36961.02
C20: Dec 2024 | D20: 45686 | E20: 39945.44
C21: Jan 2025 | D21: 45719 | E21: 44777.36
C22: Feb 2025 | D22: 45743 | E22: 28651.89
C23: March 2025 | D23: 45769 | E23: 34168
C24: April 2025 | D24: 45817 | E24: 46381.33
C25: May 2025 | D25: 45831 | E25: 38783.93
C26: June 2025 | D26: 45862 | E26: 33696.36
C27: July 2025 | D27: 45888 | E27: 40694.41
C28: Aug 2024 | D28: 45561 | E28: 0
C29: Jan-August Totals | E29: =SUM(E19:E28) -> 344059.74
C30: Sept-Dec Estimated | E30: =E29/9*3 -> 114686.58
C32: 2025 Estimated Total | E32: =SUM(E29:E30) -> 458746.32 | H32: =E32/12 -> 38228.86
C34: =+yrlycomp!H7 -> 2025 | D34: =C34 -> 2025 | E34: =D34 -> 2025 | F34: =E34 -> 2025 | G34: =+F34+1 -> 2026
C35: Jan - Aug | D35: Sep - Dec | E35: 12 Month | F35: Budget | G35: Budget
B36: Category | C36: Actual | D36: Est | E36: Forecast
A38: 4040-0000 | B38: Commercial Rent | C38: ='VLookup Data'!E242 -> 36000 | D38: =E38-C38 -> 18000 | E38: =E14 -> 54000 | F38: 54000 | G38: =E16 -> 54000 | I38: fix formula cells in all columns next year
A39: 4135-0010 | B39: Garage | C39: ='VLookup Data'!E268 -> 344059.74 | D39: =E39-C39 -> 114686.58 | E39: =E32 -> 458746.32 | F39: 456000 | G39: 460000
A40: 4520-0000 | B40: Commercial R/E Tax Escalation | C40: =SUMIF('VLookup Data'!$A:$A,A40,'VLookup Data'!$E:$E) -> 0 | D40: =C40*8/4 -> 0 | E40: 0 | F40: 0 | G40: 0
C41: =SUM(C38:C40) -> 380059.74 | D41: =SUM(D38:D40) -> 132686.58 | E41: =SUM(E38:E40) -> 512746.32 | F41: =SUM(F38:F40) -> 510000 | G41: =SUM(G38:G40) -> 514000
A43: *Commercial Lease with Corrie Horshinski, D.C. 01/13/2023-1/12/2027.
A44: *Garage - 444 East 86th Street owns the Garage. Contract with 1623 York Avenue Parking Corp. They pay a management fee of monthly proceeds
A45: based on revenue collected less expenses. 2025 Budget assumes monthly collections of $38,000.00
I46: For 2022 Commercial Rent and Garage Income totals are combined. 2023 Budget will separate and code to separate line items
D62: Page 4

Sheet pyrl
D1: =COV!C23 -> 444 East 86th Street Owners Corp.
D2: Labor & Related
A3: Schedule B | D3: =yrlycomp!H3 -> For Year Ending 12/31/2026
H4: Resident | J4: Ptr/Drmn | K4: Porter
A5: Union: 32 BJ | H5: Manager | I5: Handyman | J5: Concierge | K5: Man (80%) | L5: Total
H6: 1 | I6: 2 | J6: 10 | K6: 3 | L6: =SUM(H6:K6) -> 16
A7: Wages:
A8: Resident Manager | B8: =41.7865*40 -> 1671.46 | C8: /wk | D8: * | E8: 0 | F8: Wks | H8: =B8*E8*H$6 -> 0 | L8: =SUM(H8:K8) -> 0
A9: =+A8 -> Resident Manager | B9: =+B8+25 -> 1696.46 | C9: =+C8 -> /wk | D9: =+D8 -> * | E9: =52-E8 -> 52 | F9: =+F8 -> Wks | H9: =B9*E9*H$6 -> 88215.92 | L9: =SUM(H9:K9) -> 88215.92
A10: =+A8 -> Resident Manager | B10: 0 | C10: /Qtr | D10: =+D9 -> * | E10: 4 | F10: Qtrs | H10: =B10*E10*H$6 -> 0 | L10: =SUM(H10:K10) -> 0
A11: Handyman | B11: =22.3408*40 -> 893.632 | C11: /wk | D11: * | E11: 16 | F11: Wks | I11: =+B11*E11*I6 -> 28596.224 | L11: =SUM(H11:K11) -> 28596.224
A12: =+A11 -> Handyman | B12: =+B11+24 -> 917.632 | C12: =+C11 -> /wk | D12: =+D11 -> * | E12: =52-E11 -> 36 | F12: =+F11 -> Wks | I12: =+B12*E12*I6 -> 66069.504 | L12: =SUM(H12:K12) -> 66069.504
A13: Ptr/Drmn/Concierge | B13: =20.2128*40 -> 808.512 | C13: /wk | D13: * | E13: 16 | F13: Wks | J13: =+B13*E13*J6 -> 129361.92 | L13: =SUM(H13:K13) -> 129361.92
A14: =+A13 -> Ptr/Drmn/Concierge | B14: =+B13+22 -> 830.512 | C14: =+C13 -> /wk | D14: =+D13 -> * | E14: =52-E13 -> 36 | F14: =+F13 -> Wks | J14: =+B14*E14*J6 -> 298984.32 | L14: =SUM(H14:K14) -> 298984.32
A15: Porter | B15: =+B13*80% -> 646.8096 | C15: /wk | D15: * | E15: 16 | F15: Wks | K15: =+B15*E15*K6 -> 31046.861 | L15: =SUM(H15:K15) -> 31046.861
A16: =+A15 -> Porter | B16: =+B14*80% -> 664.4096 | C16: =+C15 -> /wk | D16: =+D15 -> * | E16: =52-E15 -> 36 | F16: =+F15 -> Wks | K16: =+B16*E16*K6 -> 71756.237 | L16: =SUM(H16:K16) -> 71756.237
C17: Total: | H17: =SUM(H8:H16) -> 88215.92 | I17: =SUM(I8:I16) -> 94665.728 | J17: =SUM(J8:J16) -> 428346.24 | K17: =SUM(K8:K16) -> 102803.1 | L17: =SUM(L8:L16) -> 714030.99
B19: Overtime: % of wages @ | E19: 0.002 | H19: =+H17*$E$19 -> 176.43184 | I19: =+I17*$E$19 -> 189.33146 | J19: =+J17*$E$19 -> 856.69248 | K19: =+K17*$E$19 -> 205.6062 | L19: =SUM(H19:K19) -> 1428.062
L20: =SUM(H20:K20) -> 0
A21: Vacation, Sick ,Personal | D21: Union | F21: Coverage | L21: =SUM(H21:K21) -> 0
A22: =+A10 -> Resident Manager | B22: =+B9 -> 1696.46 | C22: * | D22: 4 | E22: WKS.* | F22: 0 | H22: =+B22*F22 -> 0 | L22: =SUM(H22:K22) -> 0
A23: =+A11 -> Handyman | B23: =+B12 -> 917.632 | C23: * | D23: 7 | E23: WKS.* | F23: 4 | I23: =+B23*F23 -> 3670.528 | L23: =SUM(H23:K23) -> 3670.528
A24: =+A13 -> Ptr/Drmn/Concierge | B24: =+B14 -> 830.512 | C24: * | D24: 53.1 | E24: WKS.* | F24: 10 | J24: =+B24*F24 -> 8305.12 | L24: =SUM(H24:K24) -> 8305.12
A25: =+A16 -> Porter | B25: =+B16 -> 664.4096 | C25: * | D25: 3 | E25: WKS.* | F25: 0 | K25: =+B25*F25 -> 0 | L25: =SUM(H25:K25) -> 0
A26: Summer Relief | B26: =+B24*80% -> 664.4096 | D26: 3 | E26: Employees | F26: 18.67 | K26: =+D26*B26*F26 -> 37213.582 | L26: =SUM(H26:K26) -> 37213.582
A27: Subtotal | H27: =SUM(H22:H26) -> 0 | I27: =SUM(I22:I26) -> 3670.528 | J27: =SUM(J22:J26) -> 8305.12 | K27: =SUM(K22:K26) -> 37213.582 | L27: =SUM(L22:L26) -> 49189.23
A28: Unused Sick Time | D28: Union | F28: Coverage
A29: Unused Sick Time -Res Mgr | B29: =+B22/5 -> 339.292 | C29: * | D29: 13 | E29: days | F29: 10 | H29: =+B29*F29*H6 -> 3392.92 | L29: =SUM(H29:K29) -> 3392.92
A30: Unused Sick Time -Handyman | B30: =+B23/5 -> 183.5264 | C30: * | D30: 13 | E30: days | F30: 10 | I30: =+B30*F30*I6 -> 3670.528 | L30: =SUM(H30:K30) -> 3670.528
A31: Unused Sick Time -P/D/C | B31: =+B24/5 -> 166.1024 | C31: * | D31: 13 | E31: days | F31: 10 | J31: =+B31*F31*J6 -> 16610.24 | L31: =SUM(H31:K31) -> 16610.24
A32: Unused Sick Time-Porter | B32: =+B25/5 -> 132.88192 | C32: * | D32: 13 | E32: days | F32: 10 | J32: =+B32*F32*J7 -> 0 | K32: =+B32*F32*K6 -> 3986.4576 | L32: =SUM(H32:K32) -> 3986.4576
A33: Subtotal | H33: =SUM(H29:H32) -> 3392.92 | I33: =SUM(I29:I32) -> 3670.528 | J33: =SUM(J29:J32) -> 16610.24 | K33: =SUM(K29:K32) -> 3986.4576 | L33: =SUM(L29:L32) -> 27660.146
A34: * Coverage is for vacation time & Union unused sick time is paid even though not taken
A35: Total Vacation / Sick /Personal | F35: Total: | H35: =+H27+H33 -> 3392.92 | I35: =+I27+I33 -> 7341.056 | J35: =+J27+J33 -> 24915.36 | K35: =+K27+K33 -> 41200.039 | L35: =+L27+L33 -> 76849.375
A37: Holiday, Bonus: | D37: Union | G37: Coverage
A38: Super | B38: =+B29 -> 339.292 | C38: * | D38: 11 | E38: DAYS * | F38: 1.5 | G38: 0 | H38: =+B38*D38*F38*G38 -> 0 | L38: =SUM(H38:K38) -> 0
A39: =+A23 -> Handyman | B39: =+B30 -> 183.5264 | C39: * | D39: 11 | E39: DAYS * | F39: 1.5 | G39: 1 | I39: =+B39*D39*F39*G39 -> 3028.1856 | L39: =SUM(H39:K39) -> 3028.1856
A40: =+A24 -> Ptr/Drmn/Concierge | B40: =+B31 -> 166.1024 | C40: * | D40: 11 | E40: DAYS * | F40: 1.5 | G40: 4 | J40: =+B40*D40*F40*G40 -> 10962.758 | L40: =SUM(H40:K40) -> 10962.758
A41: Ptr/Drmn/Concierge -80% | B41: =+B32 -> 132.88192 | C41: * | D41: 11 | E41: DAYS * | F41: 1.5 | G41: 0 | K41: =+B41*D41*F41*G41 -> 0 | L41: =SUM(H41:K41) -> 0
A42: Bonus (Based on prior year merrit) | H42: 15000 | I42: =+B12*I6*2 -> 3670.528 | J42: =+B14*J6 -> 8305.12 | K42: =+B16*K6 -> 1993.2288 | L42: =SUM(H42:K42) -> 28968.877
C43: Total: | H43: =SUM(H38:H42) -> 15000 | I43: =SUM(I38:I42) -> 6698.7136 | J43: =SUM(J38:J42) -> 19267.878 | K43: =SUM(K38:K42) -> 1993.2288 | L43: =SUM(L38:L42) -> 42959.821
B45: Total Gross Wages: | H45: =H17+H35+H43+H19 -> 106785.27 | I45: =I17+I35+I43+I19 -> 108894.83 | J45: =J17+J35+J43+J19 -> 473386.17 | K45: =K17+K35+K43+K19 -> 146201.97 | L45: =L17+L35+L43+L19 -> 835268.24
A47: Payroll Taxes & Payroll Related Expenses:
A48: FICA-Gross Wages * | C48: 0.0765 | H48: =+H45*$C$48 -> 8169.0733 | I48: =+I45*$C$48 -> 8330.4544 | J48: =+J45*$C$48 -> 36214.042 | K48: =+K45*$C$48 -> 11184.451 | L48: =SUM(H48:K48) -> 63898.021
A49: SUI | B49: 0.075 | C49: of 1st | E49: 8500 | H49: =+$E$49*$B$49*H6 -> 637.5 | I49: =+$E$49*$B$49*I6 -> 1275 | J49: =+$E$49*$B$49*J6 -> 6375 | K49: =+$E$49*$B$49*K6 -> 1912.5 | L49: =SUM(H49:K49) -> 10200
A50: FUI | B50: 0.011 | C50: of 1st | E50: 8000 | H50: =+$E$50*$B$50*H6 -> 88 | I50: =+$E$50*$B$50*I6 -> 176 | J50: =+$E$50*$B$50*J6 -> 880 | K50: =+$E$50*$B$50*K6 -> 264 | L50: =SUM(H50:K50) -> 1408
A51: MTA | B51: 0.0034 | C51: of 1st | E51: 2500 | F51: quarterly | G51: 4 | H51: =+$B$51*$E$51*$G$51*H6 -> 34 | I51: =+$B$51*$E$51*$G$51*I6 -> 68 | J51: =+$B$51*$E$51*$G$51*J6 -> 340 | K51: =+$B$51*$E$51*$G$51*K6 -> 102 | L51: =SUM(H51:K51) -> 544
A52: NYS Disability | C52: 45 | D52: per annum per emp | H52: =C52*H6 -> 45 | I52: =C52*I6 -> 90 | J52: =+C52*J6 -> 450 | K52: =+C52*K6 -> 135 | L52: =SUM(H52:K52) -> 720
A53: Worker's Comp. | B53: 0.045 | C53: of total gross wages | H53: =+H45*$B$53 -> 4805.3372 | I53: =+I45*$B$53 -> 4900.2673 | J53: =+J45*$B$53 -> 21302.378 | K53: =+K45*$B$53 -> 6579.0887 | L53: =SUM(H53:K53) -> 37587.071
L54: =SUM(H54:K54) -> 0
A55: Welfare | B55: =3217.66/3 -> 1072.5533 | C55: Per Mo/Man * | E55: 12 | F55: Months | H55: =+$B$55*$E$55*H6 -> 12870.64 | I55: =+$B$55*$E$55*I6 -> 25741.28 | J55: =+$B$55*$E$55*J6 -> 128706.4 | K55: =+$B$55*$E$55*K6 -> 38611.92 | L55: =SUM(H55:K55) -> 205930.24
A56: Pension | B56: 82.75 | C56: Per Wk/Man * | E56: 52 | F56: Wks | H56: =+$B$56*$E$56*H6 -> 4303 | I56: =+$B$56*$E$56*I6 -> 8606 | J56: =+$B$56*$E$56*J6 -> 43030 | K56: 0 | L56: =SUM(H56:K56) -> 55939
A57: Supplemental Retirement | B57: 10 | C57: Per Wk/Man * | E57: 52 | F57: Wks | H57: =+$B$57*$E$57*H6 -> 520 | I57: =+$B$57*$E$57*I6 -> 1040 | J57: =+$B$57*$E$57*J6 -> 5200 | K57: 0 | L57: =SUM(H57:K57) -> 6760
A58: Savings Plan (SRSP) | L58: =SUM(H58:K58) -> 0
A59: Legal Fund | B59: 16.63 | C59: Per Mo/Man * | E59: 12 | F59: =+F55 -> Months | H59: =+$B$59*$E$59*H6 -> 199.56 | I59: =+$B$59*$E$59*I6 -> 399.12 | J59: =+$B$59*$E$59*J6 -> 1995.6 | K59: =+$B$59*$E$59*K6 -> 598.68 | L59: =SUM(H59:K59) -> 3192.96
A60: Training Fund | B60: 14.13 | C60: Per Mo/Man * | E60: 12 | F60: =+F59 -> Months | H60: =+$B$60*$E$60*H6 -> 169.56 | I60: =+$B$60*$E$60*I6 -> 339.12 | J60: =+$B$60*$E$60*J6 -> 1695.6 | K60: =+$B$60*$E$60*K6 -> 508.68 | L60: =SUM(H60:K60) -> 2712.96
A61: Profit Sharing * | B61: 130 | C61: Per Qtr/Man * | E61: 4 | F61: Otrs | H61: =+$B$61*$E$61*H6 -> 520 | I61: =+$B$61*$E$61*I6 -> 1040 | J61: =+$B$61*$E$61*J6 -> 5200 | K61: =+$B$61*$E$61*K6 -> 1560 | L61: =SUM(H61:K61) -> 8320
A62: *Discretionary | B62: Total P/R Taxes & Related Exps: | H62: =SUM(H48:H61) -> 32361.671 | I62: =SUM(I48:I61) -> 52005.242 | J62: =SUM(J48:J61) -> 251389.02 | K62: =SUM(K48:K61) -> 61456.32 | L62: =SUM(L48:L61) -> 397212.25
A64: Other-Bonus | B64: 0 | C64: days @ | D64: 0 | E64: 0 | F64: hrs | H64: 0 | I64: 0 | J64: 0 | K64: 0 | L64: =SUM(H64:K64) -> 0
B65: Total Labor & Related: | H65: =H62+H45+H64 -> 139146.94 | I65: =I62+I45+I64 -> 160900.07 | J65: =J62+J45+J64 -> 724775.19 | K65: =K62+K45+K64 -> 207658.29 | L65: =L62+L45+L64 -> 1232480.5
A66: Cost Per Employee | H66: =H65/H6 -> 139146.94 | I66: =I65/I6 -> 80450.035 | J66: =J65/J6 -> 72477.519 | K66: =K65/K6 -> 69219.43 | L66: =L65/L6 -> 77030.031
E68: Payroll Summary | H68: 2011 | I68: 2011 | J68: 2011 | K68: 2011 | L68: 2012
H69: Jan - Oct | I69: Novt-Dec | J69: 12 Month | K69: Budget | L69: Budget
H70: Actual | I70: Est * | J70: Forecast
H71: =883222-8484 -> 874738 | I71: =+H71/9*3+28900 -> 320479.33 | J71: =SUM(H71:I71) -> 1195217.3 | K71: 1196720 | L71: =+L65 -> 1232480.5
A74: Page 4
A78: Payroll Budget Upload
A79: 2011 Budget # of Weds | B79: 4 | C79: 5 | D79: 4 | E79: 4 | F79: 5 | G79: 4 | H79: 4 | I79: 5 | J79: 4 | K79: 5 | L79: 4 | M79: 4 | N79: =SUM(B79:M79) -> 52
B80: Jan | C80: Feb | D80: Mar | E80: Apr | F80: May | G80: Jun | H80: Jul | I80: Aug | J80: Sep | K80: Oct | L80: Nov | M80: Dec | N80: Amount
A81: Gross Wages | B81: =(+$L$45-$L$33-$L$42)/52*B79 -> 59895.325 | C81: =(+$L$45-$L$33-$L$42)/52*C79 -> 74869.156 | D81: =(+$L$45-$L$33-$L$42)/52*D79 -> 59895.325 | E81: =(+$L$45-$L$33-$L$42)/52*E79 -> 59895.325 | F81: =(+$L$45-$L$33-$L$42)/52*F79 -> 74869.156 | G81: =(+$L$45-$L$33-$L$42)/52*G79 -> 59895.325 | H81: =(+$L$45-$L$33-$L$42)/52*H79 -> 59895.325 | I81: =(+$L$45-$L$33-$L$42)/52*I79 -> 74869.156 | ... M81: =(+$L$45-$L$33-$L$42)/52*M79 -> 59895.325 | N81: =SUM(B81:M81) -> 778639.22
A82: {Excl Unused Sick & Bonus}
A83: Unused Sick Time | C83: =+L33 -> 27660.146 | N83: =SUM(B83:M83) -> 27660.146
A84: Bonus | M84: =+L42 -> 28968.877 | N84: =SUM(B84:M84) -> 28968.877
A85: Total Gross Wages | B85: =SUM(B81:B84) -> 59895.325 | C85: =SUM(C81:C84) -> 102529.3 | D85: =SUM(D81:D84) -> 59895.325 | E85: =SUM(E81:E84) -> 59895.325 | F85: =SUM(F81:F84) -> 74869.156 | G85: =SUM(G81:G84) -> 59895.325 | H85: =SUM(H81:H84) -> 59895.325 | I85: =SUM(I81:I84) -> 74869.156 | ... N85: =SUM(N81:N84) -> 835268.24 | O85: G/L 5101
A87: FICA
A88: =+C48 -> 0.0765 | B88: =+B85*$A$88 -> 4581.9923 | C88: =+C85*$A$88 -> 7843.4916 | D88: =+D85*$A$88 -> 4581.9923 | E88: =+E85*$A$88 -> 4581.9923 | F88: =+F85*$A$88 -> 5727.4904 | G88: =+G85*$A$88 -> 4581.9923 | H88: =+H85*$A$88 -> 4581.9923 | I88: =+I85*$A$88 -> 5727.4904 | ... M88: =+M85*$A$88 -> 6798.1114 | N88: =SUM(B88:M88) -> 63898.021
A89: SUI | C89: =+L49 -> 10200 | N89: =SUM(B89:M89) -> 10200
A90: FUI | C90: =+L50 -> 1408 | N90: =SUM(B90:M90) -> 1408
A91: MTA | D91: =+L51/4 -> 136 | G91: =D91 -> 136 | J91: =D91 -> 136 | L91: =D91 -> 136 | N91: =SUM(B91:M91) -> 544
A92: Total taxes | B92: =SUM(B88:B91) -> 4581.9923 | C92: =SUM(C88:C91) -> 19451.492 | D92: =SUM(D88:D91) -> 4717.9923 | E92: =SUM(E88:E91) -> 4581.9923 | F92: =SUM(F88:F91) -> 5727.4904 | G92: =SUM(G88:G91) -> 4717.9923 | H92: =SUM(H88:H91) -> 4581.9923 | I92: =SUM(I88:I91) -> 5727.4904 | ... M92: =SUM(M88:M91) -> 6798.1114 | N92: =SUM(B92:M92) -> 76050.021 | O92: G/L 5010
A95: Worker's Comp | D95: 3000 | E95: =(+$L$53-$D$95)/9 -> 3843.0079 | F95: =(+$L$53-$D$95)/9 -> 3843.0079 | G95: =(+$L$53-$D$95)/9 -> 3843.0079 | H95: =(+$L$53-$D$95)/9 -> 3843.0079 | I95: =(+$L$53-$D$95)/9 -> 3843.0079 | J95: =(+$L$53-$D$95)/9 -> 3843.0079 | K95: =(+$L$53-$D$95)/9 -> 3843.0079 | L95: =(+$L$53-$D$95)/9 -> 3843.0079 | M95: =(+$L$53-$D$95)/9 -> 3843.0079 | N95: =SUM(B95:M95) -> 37587.071 | O95: G/L 5025
A96: Disability | D96: =+L52 -> 720 | N96: =SUM(B96:M96) -> 720 | O96: G/L 5030
A97: Total W/Comp & Disab. | B97: =SUM(B95:B96) -> 0 | C97: =SUM(C95:C96) -> 0 | D97: =SUM(D95:D96) -> 3720 | E97: =SUM(E95:E96) -> 3843.0079 | F97: =SUM(F95:F96) -> 3843.0079 | G97: =SUM(G95:G96) -> 3843.0079 | H97: =SUM(H95:H96) -> 3843.0079 | I97: =SUM(I95:I96) -> 3843.0079 | ... N97: =SUM(N95:N96) -> 38307.071
A100: Union Benefits | B100: =SUM($L$55:$L$61)/12 -> 23571.263 | C100: =SUM($L$55:$L$61)/12 -> 23571.263 | D100: =SUM($L$55:$L$61)/12 -> 23571.263 | E100: =SUM($L$55:$L$61)/12 -> 23571.263 | F100: =SUM($L$55:$L$61)/12 -> 23571.263 | G100: =SUM($L$55:$L$61)/12 -> 23571.263 | H100: =SUM($L$55:$L$61)/12 -> 23571.263 | I100: =SUM($L$55:$L$61)/12 -> 23571.263 | ... M100: =SUM($L$55:$L$61)/12 -> 23571.263 | N100: =SUM(B100:M100) -> 282855.16 | O100: G/L 5015
A102: Total Payroll | B102: =+B85+B92+B97+B100 -> 88048.58 | C102: =+C85+C92+C97+C100 -> 145552.06 | D102: =+D85+D92+D97+D100 -> 91904.58 | E102: =+E85+E92+E97+E100 -> 91891.588 | F102: =+F85+F92+F97+F100 -> 108010.92 | G102: =+G85+G92+G97+G100 -> 92027.588 | H102: =+H85+H92+H97+H100 -> 91891.588 | I102: =+I85+I92+I97+I100 -> 108010.92 | ... N102: =+N85+N92+N97+N100 -> 1232480.5

Sheet Payroll
F1: =Income!E1 -> 444 East 86th Street Owners Corp. | P1: Super - Michael Stones
F2: Payroll | P2: per JS - 2021 increase pay rate for whole year
A3: Schedule B | F3: =' bud'!C3 -> For Year Ending 12/31/2026 | P3: as of 9/25 - budgets assume a 5% increase at time of union increases
I4: =pyrl!H4 -> Resident
A5: 32 BJ Rates | I5: =pyrl!H5 -> Manager | J5: Handyman | K5: Porter/Doorman | L5: Porter/Doorman | M5: Total | P5: Assistant Super - Mario Espejo(Board increased 9/23 5%)
A6: Base Wages:* | I6: 1 | J6: 3 | K6: 7 | L6: 1 | M6: =SUM(I6:L6) -> 12 | P6: Handymen
A7: Resident Manager | B7: =58.8105*40 -> 2352.42 | C7: /wk | E7: 24 | F7: Wks | I7: =SUM(B7*E7*$I$6) -> 56458.08 | M7: =SUM(I7:K7) -> 56458.08 | P7: David Leoniuk, Nelson Garcia
A8: Resident Manager | B8: =58.8105*1.05*40 -> 2470.041 | C8: /wk | E8: 28 | F8: Wks | I8: =SUM(B8*E8*$I$6) -> 69161.148
A9: Assistant Super | B9: =34.14*40 -> 1365.6 | C9: /wk | E9: 16 | F9: Wks | J9: =(B9*E9)*1 -> 21849.6 | M9: =SUM(I9:K9) -> 21849.6 | P9: Porters | S9: Doormen
A10: =+A9 -> Assistant Super | B10: =B9+42 -> 1407.6 | C10: =+C9 -> /wk | E10: 36 | F10: Wks | J10: =(B10*E10)*1 -> 50673.6 | M10: =SUM(I10:K10) -> 50673.6 | P10: Shiva Balram | Q10: 0.75 | S10: Walter Koch
A11: Handyman | B11: =32.61*40 -> 1304.4 | C11: =+C10 -> /wk | E11: 16 | F11: Wks | J11: =SUM(B11*E11)*2 -> 41740.8 | M11: =SUM(I11:K11) -> 41740.8 | P11: Sinayoko Bakary | S11: Jose Ortega
A12: =+A11 -> Handyman | B12: =+B11+42 -> 1346.4 | C12: =+C11 -> /wk | E12: 36 | F12: Wks | J12: =SUM(B12*E12)*2 -> 96940.8 | M12: =SUM(I12:K12) -> 96940.8 | P12: Nicky Boysie | S12: Rey Quinones
A13: Porter/Doorman | B13: =29.78*40 -> 1191.2 | C13: /wk | E13: 16 | F13: =+F9 -> Wks | K13: =SUM(B13*E13*$K$6) -> 133414.4 | M13: =SUM(I13:K13) -> 133414.4 | P13: Harbajan | S13: Jerry Rivera
A14: Porter/Doorman | B14: =+B13+40 -> 1231.2 | C14: /wk | E14: 36 | F14: Wks | K14: =SUM(B14*E14*$K$6) -> 310262.4 | M14: =SUM(I14:K14) -> 310262.4
A15: Porter/Doorman 75% | B15: =B13*75% -> 893.4 | C15: /wk | E15: 16 | F15: Wks | L15: =SUM(B15*E15*$L$6) -> 14294.4 | M15: =SUM(J15:L15) -> 14294.4
A16: Porter/Doorman 75% | B16: =B14*75% -> 923.4 | C16: /wk | E16: 32 | F16: Wks | L16: =SUM(B16*E16*$L$6) -> 29548.8 | M16: =SUM(J16:L16) -> 29548.8 | P16: Christian Acosta Sevilla replaced by Shiva Balram
A17: Porter/Doorman 85% | B17: =B14*85% -> 1046.52 | C17: /wk | E17: 4 | F17: Wks | L17: =SUM(B17*E17*$L$6) -> 4186.08 | M17: =SUM(J17:L17) -> 4186.08
F18: Gross Payroll: | I18: =SUM(I7:I17) -> 125619.23 | J18: =SUM(J7:J17) -> 211204.8 | K18: =SUM(K7:K17) -> 443676.8 | L18: =SUM(L7:L17) -> 48029.28 | M18: =SUM(M7:M17) -> 759368.96 | P18: Balram -hire 3/04/24 at 75%
P19: 85% 12/04/26 | R19: Pension 03/04/26
A20: Gross Payroll was multiplied by 1.135 to bring the pay year to | O20: factor spread | P20: 100% 08/04/27 | R20: Annuity 03/04/25
A21: 59 weeks to allow for relief, sick days, holidays, vacation pay, and OT: | H21: =59/52 -> 1.1346154 | I21: =+I18*$H$21 -> 142529.51 | J21: =+J18*$H$21 -> 239636.22 | K21: =+K18*$H$21 -> 503402.52 | L21: =+L18*$H$21 -> 54494.76 | M21: =SUM(I21:L21) -> 940063.01 | O21: =M21-M18 -> 180694.05
A22: Bonus | I22: 15000 | J22: =3000*3 -> 9000 | K22: =1800*K6 -> 12600 | L22: =1600*L6 -> 1600 | M22: =SUM(I22:L22) -> 38200
B23: Total Gross Wages: | I23: =SUM(I21:I22) -> 157529.51 | J23: =SUM(J21:J22) -> 248636.22 | K23: =SUM(K21:K22) -> 516002.52 | L23: =SUM(L21:L22) -> 56094.76 | M23: =SUM(M21:M22) -> 978263.01
A24: Payroll Taxes & Payroll Related Expenses:
A25: FICA-Gross Wages * | C25: 0.0765 | D25: (Using maximum estimated $183,600 for 2026) | I25: =+I23*$C$25 -> 12051.007 | J25: =+J23*$C$25 -> 19020.67 | K25: =+K23*$C$25 -> 39474.193 | L25: =+L23*$C$25 -> 4291.2491 | M25: =SUM(I25:L25) -> 74837.12
A26: SUI | B26: 0.02025 | C26: of 1st | E26: 12000 | I26: =+$B$26*$E$26*I6 -> 243 | J26: =+$B$26*$E$26*J6 -> 729 | K26: =+$B$26*$E$26*K6 -> 1701 | L26: =+$B$26*$E$26*L6 -> 243 | M26: =SUM(I26:L26) -> 2916
A27: FUI | B27: 0.006 | C27: of 1st | E27: 7000 | I27: =+$E$27*$B$27*I6 -> 42 | J27: =+$E$27*$B$27*J6 -> 126 | K27: =+$E$27*$B$27*K6 -> 294 | L27: =+$E$27*$B$27*L6 -> 42 | M27: =SUM(I27:L27) -> 504
A28: MTA | B28: 0.0034 | C28: of gross wages | I28: =I23*$B$28 -> 535.60033 | J28: =J23*$B$28 -> 845.36313 | K28: =K23*$B$28 -> 1754.4086 | L28: =L23*$B$28 -> 190.72218 | M28: =SUM(I28:L28) -> 3326.0942
A29: NYS Disability | C29: 45 | D29: per annum per emp | I29: =+C29*I6 -> 45 | J29: =+C29*J6 -> 135 | K29: =+C29*K6 -> 315 | L29: =+C29*L6 -> 45 | M29: =SUM(I29:L29) -> 540
A30: Paid Family Leave | B30: 0.00455 | C30: of gross wages | I30: =I23*$B$30 -> 716.75926 | J30: =J23*$B$30 -> 1131.2948 | K30: =K23*$B$30 -> 2347.8115 | L30: =L23*$B$30 -> 255.23116 | M30: =SUM(I30:L30) -> 4451.0967
A31: Worker's Comp. | B31: 0.05 | C31: of total gross wages | I31: =+$B$31*I23 -> 7876.4754 | J31: =+$B$31*J23 -> 12431.811 | K31: =+$B$31*K23 -> 25800.126 | L31: =+$B$31*L23 -> 2804.738 | M31: =SUM(I31:L31) -> 48913.15
A33: Non-Union Benefits(RM Only)
A34: Health | E34: =(283.85*10%)+283.85 -> 312.235 | F34: /month | I34: =+E34*12 -> 3746.82 | J34: 0 | K34: 0 | L34: 0 | M34: =SUM(I34:K34) -> 3746.82
E35: =(3289.72*10%)+3289.72 -> 3618.692 | F35: /month | I35: =+E35*12 -> 43424.304 | J35: 0 | K35: 0 | L35: 0 | M35: =SUM(I35:K35) -> 43424.304
A36: Union Benefits:
A37: Health | E37: =2113*12 -> 25356 | F37: /year | I37: 0 | J37: =+$E$37*J6 -> 76068 | K37: =+$E$37*K6 -> 177492 | L37: =+$E$37*L6 -> 25356 | M37: =SUM(I37:L37) -> 278916
A38: Pension | E38: =143*52 -> 7436 | F38: /year | I38: 0 | J38: =$E$38*J6 -> 22308 | K38: =$E$38*K6 -> 52052 | L38: =E38*L6 -> 7436 | M38: =SUM(I38:L38) -> 81796
A39: Supplemental Retirement | E39: =10*52 -> 520 | F39: /year | I39: 0 | J39: =$E$39*J6 -> 1560 | K39: =($E$39*7)+(10*43) -> 4070 | L39: =E39*L6 -> 520 | M39: =SUM(I39:L39) -> 6150
A40: Additional Supplemental Retirement | E40: =+E39 -> 520 | F40: /year | I40: 0 | J40: 0 | K40: =+E40*3 -> 1560 | L40: 0 | M40: =SUM(I40:L40) -> 1560
A41: Legal | E41: 199 | F41: /year | I41: 0 | J41: =+$E$41*J6 -> 597 | K41: =+$E$41*K6 -> 1393 | L41: =+$E$41*L6 -> 199 | M41: =SUM(I41:L41) -> 2189
A42: Training | E42: =14.13*12 -> 169.56 | F42: /year | I42: 0 | J42: =+$E$42*J6 -> 508.68 | K42: =+$E$42*K6 -> 1186.92 | L42: =+$E$42*L6 -> 169.56 | M42: =SUM(I42:L42) -> 1865.16
B44: Total P/R Taxes & Related Exps, and Union Benefits: | I44: =SUM(I25:I42) -> 68680.966 | J44: =SUM(J25:J42) -> 135460.82 | K44: =SUM(K25:K42) -> 309440.46 | L44: =SUM(L25:L42) -> 41552.5 | M44: =SUM(M25:M42) -> 555134.75
A46: Other-Bonus | B46: 0 | C46: days @ | D46: 0 | E46: 0 | F46: hrs | I46: 0 | J46: 0 | K46: 0
B47: Total Labor & Related: | I47: =+I23+I44 -> 226210.48 | J47: =+J23+J44 -> 384097.03 | K47: =+K23+K44 -> 825442.98 | L47: =+L23+L44 -> 97647.26 | M47: =+M23+M44 -> 1533397.8
F48: Cost Per Employee: | I48: =I47/I6 -> 226210.48 | J48: =J47/J6 -> 128032.34 | K48: =K47/K6 -> 117920.43 | L48: =L47/L6 -> 97647.26
E50: Payroll Summary | H50: =+yrlycomp!H7 -> 2025 | I50: =H50 -> 2025 | J50: =I50 -> 2025 | K50: =J50 -> 2025 | L50: =+K50+1 -> 2026
H51: Jan - Aug | I51: Sep - Dec | J51: 12 Month | K51: Budget | L51: Budget | O51: DO NOT ERASE - NEEDED TO ENTER BUDGET
E52: G/L | H52: Actual | I52: Est * | J52: Forecast
E53: 5105-0000 | F53: Gross Payroll | H53: =SUMIF('VLookup Data'!$A:$A,E53,'VLookup Data'!$E:$E) -> 464474.23 | I53: =H53/8*4+4256 -> 236493.11 | J53: =SUM(H53:I53) -> 700967.34 | K53: 802061.84 | L53: =M18 -> 759368.96 | O53: 2025 figures | P53: %
E54: 5105-0010 | F54: Overtime Pay | H54: =SUMIF('VLookup Data'!$A:$A,E54,'VLookup Data'!$E:$E) -> 38888.88 | I54: =H54/8*4 -> 19444.44 | J54: =SUM(H54:I54) -> 58333.32 | K54: 26138.391 | L54: =+$O$21*P54 -> 46686.108 | O54: 54984.95 | P54: =O54/SUM($O$54:$O$60) -> 0.25837103 | Q54: ot
E55: 5105-0015 | F55: Vacation Pay | H55: =SUMIF('VLookup Data'!$A:$A,E55,'VLookup Data'!$E:$E) -> 55459.56 | I55: =H55/8*2 -> 13864.89 | J55: =SUM(H55:I55) -> 69324.45 | K55: 33015.769 | L55: =+$O$21*P55 -> 53046.573 | O55: 62476.04 | P55: =O55/SUM($O$54:$O$60) -> 0.29357122 | Q55: vac
E56: 5105-0020 | F56: Holiday Pay | H56: =SUMIF('VLookup Data'!$A:$A,E56,'VLookup Data'!$E:$E) -> 15234.04 | I56: =H56/8*4 -> 7617.02 | J56: =SUM(H56:I56) -> 22851.06 | K56: 14547.189 | L56: =+$O$21*P56 -> 24629.468 | O56: 29007.56 | P56: =O56/SUM($O$54:$O$60) -> 0.13630481 | Q56: hol
E57: 5105-0021 | F57: Holiday Premium Pay | H57: =SUMIF('VLookup Data'!$A:$A,E57,'VLookup Data'!$E:$E) -> 15065.04 | I57: =H57/8*4 -> 7532.52 | J57: =SUM(H57:I57) -> 22597.56 | K57: 13874.311 | L57: =+$O$21*P57 -> 23641.591 | O57: 27844.08 | P57: =O57/SUM($O$54:$O$60) -> 0.13083769 | Q57: hol prem
E58: 5105-0025 | F58: Sick Pay | H58: =SUMIF('VLookup Data'!$A:$A,E58,'VLookup Data'!$E:$E) -> 30446.68 | I58: =(H58-19996.68)/8*4 -> 5225 | J58: =SUM(H58:I58) -> 35671.68 | K58: 20359.895 | L58: =+$O$21*P58 -> 30289.645 | O58: 35673.88 | P58: =O58/SUM($O$54:$O$60) -> 0.16762946 | Q58: sick
E59: 5105-0027 | F59: Meal Reimbursement - Payroll | H59: =SUMIF('VLookup Data'!$A:$A,E59,'VLookup Data'!$E:$E) -> 390 | I59: =H59/8*4 -> 195 | J59: =SUM(H59:I59) -> 585 | K59: 34.308639 | L59: =+$O$21*P59 -> 445.7621 | O59: 525 | P59: =O59/SUM($O$54:$O$60) -> 0.002466944 | Q59: meal
E60: 5105-0030 | F60: Miscellaneous Pay | H60: =SUMIF('VLookup Data'!$A:$A,E60,'VLookup Data'!$E:$E) -> 2302.4 | I60: =H60/8*4 -> 1151.2 | J60: =SUM(H60:I60) -> 3453.6 | K60: 0 | L60: =+$O$21*P60 -> 1954.9003 | O60: 2302.4 | P60: =O60/SUM($O$54:$O$60) -> 0.010818842 | Q60: misc
E61: 5105-0035 | F61: Bonus | H61: =SUMIF('VLookup Data'!$A:$A,E61,'VLookup Data'!$E:$E) -> 1000 | I61: =M22 -> 38200 | J61: =SUM(H61:I61) -> 39200 | K61: 34500 | L61: =M22 -> 38200 | O61: =SUM(O54:O60) -> 212813.91
E62: 5105-0000 | F62: Gross Payroll | H62: =SUM(H53:H61) -> 623260.83 | I62: =SUM(I53:I61) -> 329723.19 | J62: =SUM(J53:J61) -> 952984.02 | K62: 944531.7 | L62: =+M23 -> 978263.01
E63: 5145-0000 | F63: Employer Payroll Taxes | H63: =SUMIF('VLookup Data'!$A:$A,E63,'VLookup Data'!$E:$E)+'VLookup Data'!E402 -> 52227.66 | I63: =H63/8*4 -> 26113.83 | J63: =SUM(H63:I63) -> 78341.49 | K63: 78888.083 | L63: =+M25+M26+M27+M28 -> 81583.214
E64: 5145-0015 | F64: SUI - State Unemployment | H64: 0 | I64: =H64/8*4 -> 0 | J64: =SUM(H64:I64) -> 0 | K64: 0 | L64: 0
E65: 5155-0010 | F65: Union Dues | H65: =SUMIF('VLookup Data'!$A:$A,E65,'VLookup Data'!$E:$E) -> 0 | I65: =H65/8*4 -> 0 | J65: =SUM(H65:I65) -> 0 | K65: 0 | L65: 0
E66: 5150-0000 | F66: 401K | H66: ='VLookup Data'!E404 -> -1340 | I66: 1340 | J66: 0 | K66: 0 | L66: 0
E67: 5155-0015 | F67: Health Insurance | H67: =SUMIF('VLookup Data'!$A:$A,E67,'VLookup Data'!$E:$E) -> 28588.56 | I67: =H67/8*4 -> 14294.28 | J67: =SUM(H67:I67) -> 42882.84 | K67: 49205.418 | L67: =+M34+M35 -> 47171.124
E68: 5160-0010 | F68: Pension Fund | H68: =SUMIF('VLookup Data'!$A:$A,E68,'VLookup Data'!$E:$E) -> 51415 | I68: =H68/8*4 -> 25707.5 | J68: =SUM(H68:I68) -> 77122.5 | K68: 78116.25 | L68: =+M38 -> 81796
E69: 5160-0015 | F69: Health Fund | H69: =SUMIF('VLookup Data'!$A:$A,E69,'VLookup Data'!$E:$E) -> 179828 | I69: =22561*4 -> 90244 | J69: =SUM(H69:I69) -> 270072 | K69: 270732 | L69: =+M37 -> 278916
E70: 5160-0020 | F70: Annuity Fund | H70: =SUMIF('VLookup Data'!$A:$A,E70,'VLookup Data'!$E:$E) -> 4550 | I70: =(520*3)+650 -> 2210 | J70: =SUM(H70:I70) -> 6760 | K70: 7190 | L70: =+M39+M40 -> 7710
E71: 5160-0025 | F71: Legal Fund | H71: =SUMIF('VLookup Data'!$A:$A,E71,'VLookup Data'!$E:$E) -> 1313.51 | I71: =182.93*4 -> 731.72 | J71: =SUM(H71:I71) -> 2045.23 | K71: 396 | L71: =+M41 -> 2189
E72: 5160-0030 | F72: Training Fund | H72: =SUMIF('VLookup Data'!$A:$A,E72,'VLookup Data'!$E:$E) -> 1243.44 | I72: =155.43*4 -> 621.72 | J72: =SUM(H72:I72) -> 1865.16 | K72: 1865.16 | L72: =+M42 -> 1865.16
E73: 5165-0000 | F73: Workers Compensation | H73: =SUMIF('VLookup Data'!$A:$A,E73,'VLookup Data'!$E:$E) -> 35572.36 | I73: =3817.92*4 -> 15271.68 | J73: =SUM(H73:I73) -> 50844.04 | K73: 47226.585 | L73: =+M31 -> 48913.15
E74: 5165-0050 | F74: Workers Comp Dividend | H74: =SUMIF('VLookup Data'!$A:$A,E74,'VLookup Data'!$E:$E) -> -8644.9 | I74: 0 | J74: =SUM(H74:I74) -> -8644.9 | K74: 0 | L74: 0
E75: 5166-0000 | F75: Disability Insurance | H75: =SUMIF('VLookup Data'!$A:$A,E75,'VLookup Data'!$E:$E) -> 1326.2 | I75: =H75/8*4 -> 663.1 | J75: =SUM(H75:I75) -> 1989.3 | K75: 4837.6192 | L75: =+M29+M30 -> 4991.0967
E76: 5172-0000 | F76: Payroll Processing | H76: =SUMIF('VLookup Data'!$A:$A,E76,'VLookup Data'!$E:$E) -> 4690.58 | I76: =H76/8*4 -> 2345.29 | J76: =SUM(H76:I76) -> 7035.87 | K76: 5220.7129 | L76: =+J76*1.03 -> 7246.9461
H77: =SUM(H62:H76) -> 974031.24 | I77: =SUM(I62:I76) -> 509266.3 | J77: =SUM(J62:J76) -> 1483297.5 | K77: =SUM(K62:K76) -> 1488209.5 | L77: =SUM(L62:L76) -> 1540644.7
N80: 2024 Workers Compensation was budgeted at 3.5% of total gross wages, 2025 is being budgeted at 5%.
E82: K. Harbajan was on leave 1/30/23-6/04/23. During this time benefit payments were reduced.
P84: 2025 notes
P85: (A) Porter C. Sevilla replaced by S. Balram at 75% rate 03/04/24. There was a 3 month savings in union benefits as
P86: Balram became eligible for Health , Legal and Training 06/04/24. Annuity will begin 03/04/25.
H93: Page 6

Sheet Gas
F1: =+COV!C23 -> 444 East 86th Street Owners Corp.
F2: =+yrlycomp!B24 -> Electric
B3: Schedule C | F3: =+COV!C25 -> For Year Ending 12/31/2026
L5: Cooking Gas
E6: Hess A/C # 4321095000000102948425 | I6: ConEd A/C # 432109500000010 | M6: ConEd A/C # 4321095100000018 | P6: Total
B7: 2010 | D7: Amount | E7: MMBtu | F7: $ Per MMBtu | H7: Amount | I7: Therm | J7: $ Per therm | L7: Amount | M7: Therm | N7: $ Per therm | P7: Gas
B8: January | D8: 19848.57 | E8: 1819.5 | F8: =+D8/E8 -> 10.908805 | H8: 10491.31 | I8: 18607 | J8: =+H8/I8 -> 0.56383673 | L8: 341.32 | M8: 201 | N8: =+L8/M8 -> 1.6981095 | P8: =+D8+H8+L8 -> 30681.2
B9: February | D9: 12524.61 | E9: 1498.16 | F9: =+D9/E9 -> 8.3599949 | H9: 8652.85 | I9: 15106 | J9: =+H9/I9 -> 0.57280882 | L9: 300.24 | M9: 186 | N9: =+L9/M9 -> 1.6141935 | P9: =+D9+H9+L9 -> 21477.7
B10: March | D10: 7871.4 | E10: 1093.25 | F10: =+D10/E10 -> 7.2 | H10: 6103.59 | I10: 7629 | J10: =+H10/I10 -> 0.80005112 | L10: 225.1 | M10: 141 | N10: =+L10/M10 -> 1.5964539 | P10: =+D10+H10+L10 -> 14200.09
B11: April | D11: 4172 | E11: 673.99 | F11: =+D11/E11 -> 6.1900028 | H11: 4241.9 | I11: 5721 | J11: =+H11/I11 -> 0.74146128 | L11: 215.4 | M11: 139 | N11: =+L11/M11 -> 1.5496403 | P11: =+D11+H11+L11 -> 8629.3
B12: May | D12: 3769.82 | E12: 540.09 | F12: =+D12/E12 -> 6.9799848 | H12: 2932.64 | I12: 5207 | J12: =+H12/I12 -> 0.56321106 | L12: 225.9 | M12: 140 | N12: =+L12/M12 -> 1.6135714 | P12: =+D12+H12+L12 -> 6928.36
B13: June | D13: 3140.24 | E13: 465.22 | F13: =+D13/E13 -> 6.7500107 | H13: 2727.68 | I13: 4492 | J13: =+H13/I13 -> 0.60723063 | L13: 190.34 | M13: 113 | N13: =+L13/M13 -> 1.6844248 | P13: =+D13+H13+L13 -> 6058.26
B14: July | D14: 2898.41 | E14: 385.94 | F14: =+D14/E14 -> 7.5100016 | H14: 2145.86 | I14: 3297 | J14: =+H14/I14 -> 0.65085229 | L14: 171.55 | M14: 95 | N14: =+L14/M14 -> 1.8057895 | P14: =+D14+H14+L14 -> 5215.82
B15: August | D15: 2850.82 | E15: 372.17 | F15: =+D15/E15 -> 7.6599941 | H15: 2448.42 | I15: 3833 | J15: =+H15/I15 -> 0.63877381 | L15: 177.26 | M15: 96 | N15: =+L15/M15 -> 1.8464583 | P15: =+D15+H15+L15 -> 5476.5
B16: September | D16: 2863.71 | E16: 414.43 | F16: =+D16/E16 -> 6.9099969 | H16: 2565.57 | I16: 4105 | J16: =+H16/I16 -> 0.6249866 | L16: 217.26 | M16: 129 | N16: =+L16/M16 -> 1.684186 | P16: =+D16+H16+L16 -> 5646.54
B17: October | D17: 3881.87 | E17: 581.99 | F17: =+D17/E17 -> 6.6699943 | H17: 3863.77 | I17: 5676 | J17: =+H17/I17 -> 0.68072058 | L17: 237.08 | M17: 144 | N17: =+L17/M17 -> 1.6463889 | P17: =+D17+H17+L17 -> 7982.72
B18: November | D18: 5443.06 | E18: 908.69 | F18: =+D18/E18 -> 5.9900076 | H18: 5656.16 | I18: 10701 | J18: =+H18/I18 -> 0.52856369 | L18: 285.46 | M18: 192 | N18: =+L18/M18 -> 1.4867708 | P18: =+D18+H18+L18 -> 11384.68
B19: December | D19: 10286.98 | E19: 1506 | F19: =+D19/E19 -> 6.830664 | H19: 7369.89 | I19: 16098 | J19: =+H19/I19 -> 0.45781401 | L19: 262.32 | M19: 172 | N19: =+L19/M19 -> 1.5251163 | P19: =+D19+H19+L19 -> 17919.19
B20: Total | D20: =SUM(D8:D19) -> 79551.49 | E20: =SUM(E8:E19) -> 10259.43 | F20: =+D20/E20 -> 7.7539873 | H20: =SUM(H8:H19) -> 59199.64 | I20: =SUM(I8:I19) -> 100472 | J20: =+H20/I20 -> 0.5892153 | L20: =SUM(L8:L19) -> 2849.23 | M20: =SUM(M8:M19) -> 1748 | N20: =+L20/M20 -> 1.6299943 | P20: =SUM(P8:P19) -> 141600.36
E22: =E6 -> Hess A/C # 4321095000000102948425 | I22: =I6 -> ConEd A/C # 432109500000010 | M22: =M6 -> ConEd A/C # 4321095100000018 | P22: Total
B23: 2011 | D23: Amount | E23: =+E7 -> MMBtu | F23: =+F7 -> $ Per MMBtu | H23: Amount | I23: =+I7 -> Therm | J23: =+J7 -> $ Per therm | L23: Amount | M23: =+M7 -> Therm | N23: =+N7 -> $ Per therm | P23: Gas
B24: January | D24: 14440.28 | E24: 1895.05 | F24: =+D24/E24 -> 7.6199995 | H24: 8762.21 | I24: 19923 | J24: =+H24/I24 -> 0.43980374 | L24: 308.61 | M24: 204 | N24: =+L24/M24 -> 1.5127941 | P24: =+D24+H24+L24 -> 23511.1
B25: February | D25: 10708.02 | E25: 1392.46 | F25: =+D25/E25 -> 7.6900019 | H25: 6736.64 | I25: 13138 | J25: =+H25/I25 -> 0.51275993 | L25: 260 | M25: 167 | N25: =+L25/M25 -> 1.5568862 | P25: =+D25+H25+L25 -> 17704.66
B26: March | D26: 7627.95 | E26: 1147.06 | F26: =+D26/E26 -> 6.6500009 | H26: 4808.12 | I26: 9582 | J26: =+H26/I26 -> 0.50178668 | L26: 220.11 | M26: 143 | N26: =+L26/M26 -> 1.5392308 | P26: =+D26+H26+L26 -> 12656.18
B27: April | D27: 4698.64 | E27: 717.35 | F27: =+D27/E27 -> 6.5499965 | H27: 3798.46 | I27: 6249 | J27: =+H27/I27 -> 0.60785086 | L27: 217.77 | M27: 140 | N27: =+L27/M27 -> 1.5555 | P27: =+D27+H27+L27 -> 8714.87
B28: May | D28: 3355.02 | E28: 506.8 | F28: =+D28/E28 -> 6.6200079 | H28: 2707.61 | I28: 4345 | J28: =+H28/I28 -> 0.62315535 | L28: 204.5 | M28: 133 | N28: =+L28/M28 -> 1.537594 | P28: =+D28+H28+L28 -> 6267.13
B29: June | D29: 2760.06 | E29: 450.99 | F29: =+D29/E29 -> 6.1200027 | H29: 2624 | I29: 4488 | J29: =+H29/I29 -> 0.58467023 | L29: 177.27 | M29: 113 | N29: =+L29/M29 -> 1.5687611 | P29: =+D29+H29+L29 -> 5561.33
B30: July | D30: 2354.47 | E30: 374.32 | F30: =+D30/E30 -> 6.2899925 | H30: 2101.61 | I30: 3365 | J30: =+H30/I30 -> 0.62454978 | L30: 158.59 | M30: 95 | N30: =+L30/M30 -> 1.6693684 | P30: =+D30+H30+L30 -> 4614.67
B31: August | D31: 2331.28 | E31: 361.44 | F31: =+D31/E31 -> 6.4499779 | H31: 2156.95 | I31: 3519 | J31: =+H31/I31 -> 0.61294402 | L31: 155.05 | M31: 94 | N31: =+L31/M31 -> 1.6494681 | P31: =+D31+H31+L31 -> 4643.28
B32: September | D32: 2523.69 | E32: 413.72 | F32: =+D32/E32 -> 6.0999952 | H32: 1931.42 | I32: 3261 | J32: =+H32/I32 -> 0.59227844 | L32: 202.58 | M32: 141 | N32: =+L32/M32 -> 1.4367376 | P32: =+D32+H32+L32 -> 4657.69
B33: October | C33: Est | D33: =+E33*F33 -> 3897.8969 | E33: 600 | F33: =+J59 -> 6.4964949 | H33: =+I33*J33 -> 3595.4263 | I33: 5700 | J33: =+J60 -> 0.63077654 | L33: =+M33*N33 -> 229.51883 | M33: 150 | N33: =+J61 -> 1.5301255 | P33: =+D33+H33+L33 -> 7722.842
B34: November | C34: Est | D34: =+E34*F34 -> 6496.4949 | E34: 1000 | F34: =+J59 -> 6.4964949 | H34: =+I34*J34 -> 6938.542 | I34: 11000 | J34: =+J60 -> 0.63077654 | L34: =+M34*N34 -> 306.02511 | M34: 200 | N34: =+J61 -> 1.5301255 | P34: =+D34+H34+L34 -> 13741.062
B35: December | C35: Est | D35: =+E35*F35 -> 9907.1546 | E35: 1525 | F35: =+F34 -> 6.4964949 | H35: =+I35*J35 -> 10250.119 | I35: 16250 | J35: =+J34 -> 0.63077654 | L35: =+M35*N35 -> 267.77197 | M35: 175 | N35: =+N34 -> 1.5301255 | P35: =+D35+H35+L35 -> 20425.045
B36: Total | D36: =SUM(D24:D35) -> 71100.956 | E36: =SUM(E24:E35) -> 10384.19 | F36: =+D36/E36 -> 6.8470392 | H36: =SUM(H24:H35) -> 56411.107 | I36: =SUM(I24:I35) -> 100820 | J36: =+H36/I36 -> 0.55952298 | L36: =SUM(L24:L35) -> 2707.7959 | M36: =SUM(M24:M35) -> 1755 | N36: =+L36/M36 -> 1.5429036 | P36: =SUM(P24:P35) -> 130219.86
B38: Actual | E38: =E6 -> Hess A/C # 4321095000000102948425 | I38: =I6 -> ConEd A/C # 432109500000010 | M38: =M6 -> ConEd A/C # 4321095100000018 | P38: Total
B39: 2012 | D39: Amount | E39: =+E23 -> MMBtu | F39: $ Per Therm | H39: Amount | I39: =+I23 -> Therm | J39: $ Per Therm | L39: Amount | M39: =+M23 -> Therm | N39: $ Per Therm | P39: Gas
B40: January | L40: =+M40*N40 -> 331.53995 | M40: =SUM(M8+M24)/2 -> 202.5 | N40: =+L61 -> 1.6372343 | P40: =+D40+H40+L40 -> 331.53995
B41: February | L41: =+M41*N41 -> 288.97186 | M41: =SUM(M9+M25)/2 -> 176.5 | N41: =+N40 -> 1.6372343 | P41: =+D41+H41+L41 -> 288.97186
B42: March | L42: =+M42*N42 -> 232.48727 | M42: =SUM(M10+M26)/2 -> 142 | N42: =+N41 -> 1.6372343 | P42: =+D42+H42+L42 -> 232.48727
B43: April | L43: =+M43*N43 -> 228.39419 | M43: =SUM(M11+M27)/2 -> 139.5 | N43: =+N42 -> 1.6372343 | P43: =+D43+H43+L43 -> 228.39419
B44: May | L44: =+M44*N44 -> 223.48248 | M44: =SUM(M12+M28)/2 -> 136.5 | N44: =+N43 -> 1.6372343 | P44: =+D44+H44+L44 -> 223.48248
B45: June | L45: =+M45*N45 -> 185.00748 | M45: =SUM(M13+M29)/2 -> 113 | N45: =+N44 -> 1.6372343 | P45: =+D45+H45+L45 -> 185.00748
B46: July | L46: =+M46*N46 -> 155.53726 | M46: =SUM(M14+M30)/2 -> 95 | N46: =+N45 -> 1.6372343 | P46: =+D46+H46+L46 -> 155.53726
B47: August | L47: =+M47*N47 -> 155.53726 | M47: =SUM(M15+M31)/2 -> 95 | N47: =+N46 -> 1.6372343 | P47: =+D47+H47+L47 -> 155.53726
B48: September | L48: =+M48*N48 -> 221.02663 | M48: =SUM(M16+M32)/2 -> 135 | N48: =+N47 -> 1.6372343 | P48: =+D48+H48+L48 -> 221.02663
B49: October | L49: =+M49*N49 -> 240.67344 | M49: =SUM(M17+M33)/2 -> 147 | N49: =+N48 -> 1.6372343 | P49: =+D49+H49+L49 -> 240.67344
B50: November | L50: =+M50*N50 -> 320.89793 | M50: =SUM(M18+M34)/2 -> 196 | N50: =+N49 -> 1.6372343 | P50: =+D50+H50+L50 -> 320.89793
B51: December | L51: =+M51*N51 -> 284.06015 | M51: =SUM(M19+M35)/2 -> 173.5 | N51: =+N50 -> 1.6372343 | P51: =+D51+H51+L51 -> 284.06015
B52: Total | D52: =SUM(D40:D51) -> 0 | E52: =SUM(E40:E51) -> 0 | F52: =+D52/E52 -> #DIV/0! | H52: =SUM(H40:H51) -> 0 | I52: =SUM(I40:I51) -> 0 | J52: =+H52/I52 -> #DIV/0! | L52: =SUM(L40:L51) -> 2867.6159 | M52: =SUM(M40:M51) -> 1751.5 | N52: =+L52/M52 -> 1.6372343 | P52: =SUM(P40:P51) -> 2867.6159
D54: 2013 Budget Assumptions:
D55: Budget Electric Usage: Two year average consumption.
D56: Budget Price reflects an increase over prior yr costs @ | J56: 0.07
D57: 2011 three month estimate was calculated based on usage plus | J57: 0.065
J58: 2011 4th Qtr | L58: 2012 Budget
E59: =+E38 -> Hess A/C # 4321095000000102948425 | J59: =+F32*J57+F32 -> 6.4964949 | L59: =+J59*J56+J59 -> 6.9512495
E60: =+I38 -> ConEd A/C # 432109500000010 | J60: =+J32*J57+J32 -> 0.63077654 | L60: =+J60*J56+J60 -> 0.6749309
E61: =+M38 -> ConEd A/C # 4321095100000018 | J61: =+N32*J57+N32 -> 1.5301255 | L61: =+J61*J56+J61 -> 1.6372343
B63: Page 5

Sheet Electric
E1: =+yrlycomp!H1 -> 444 East 86th Street Owners Corp.
E2: Electric
B3: Schedule C | E3: =+yrlycomp!H3 -> For Year Ending 12/31/2026
B5: G/L | N5: New Account Number
B6: 5255-0000 | N6: 50834100005
D7: Con Ed #49-4182-7002-0000-8 new account #50834100005 | U7: 0000-8 General
B8: 2024 | D8: Con Ed | E8: Esco | F8: Total | G8: KWH | H8: Con Ed $/Per KWH | I8: ESCO $/ KWH | K8: $/Per KWH
B9: January | D9: 7382.01 | E9: 7286.49 | F9: =+D9+E9 -> 14668.5 | G9: 73939 | H9: =+D9/G9 -> 0.099839192 | I9: =+E9/G9 -> 0.098547316 | K9: =+H9+I9 -> 0.19838651 | U9: 0002-0
B10: February | D10: 6811.74 | E10: 7046.63 | F10: =+D10+E10 -> 13858.37 | G10: 73452 | H10: =+D10/G10 -> 0.092737298 | I10: =+E10/G10 -> 0.095935169 | K10: =+H10+I10 -> 0.18867247 | R10: =339200/4 -> 84800
B11: March | D11: 6901.65 | E11: 6065.4 | F11: =+D11+E11 -> 12967.05 | G11: 66666 | H11: =+D11/G11 -> 0.10352579 | I11: =+E11/G11 -> 0.09098191 | K11: =+H11+I11 -> 0.1945077
B12: April | D12: 5500.34 | E12: 5159.7 | F12: =+D12+E12 -> 10660.04 | G12: 56446 | H12: =+D12/G12 -> 0.097444283 | I12: =+E12/G12 -> 0.091409489 | K12: =+H12+I12 -> 0.18885377
B13: May | D13: 7805.2 | E13: 4041.69 | F13: =+D13+E13 -> 11846.89 | G13: 44188 | H13: =+D13/G13 -> 0.17663619 | I13: =+E13/G13 -> 0.091465783 | K13: =+H13+I13 -> 0.26810197
B14: June | D14: 10849.36 | E14: 7758.64 | F14: =+D14+E14 -> 18608 | G14: 74572 | H14: =+D14/G14 -> 0.14548839 | I14: =+E14/G14 -> 0.10404227 | K14: =+H14+I14 -> 0.24953065
B15: July | D15: 11785.74 | E15: 12199.59 | F15: =+D15+E15 -> 23985.33 | G15: 111481 | H15: =+D15/G15 -> 0.10571972 | I15: =+E15/G15 -> 0.10943201 | K15: =+H15+I15 -> 0.21515173
B16: August | D16: 10654.93 | E16: 11003.19 | F16: =+D16+E16 -> 21658.12 | G16: 108129 | H16: =+D16/G16 -> 0.09853906 | I16: =+E16/G16 -> 0.10175984 | K16: =+H16+I16 -> 0.2002989
B17: September | D17: 11838.1 | E17: 10736.45 | F17: =+D17+E17 -> 22574.55 | G17: 109438 | H17: =+D17/G17 -> 0.10817175 | I17: =+E17/G17 -> 0.09810532 | K17: =+H17+I17 -> 0.20627707
B18: October | D18: 9245.5 | E18: 7797.58 | F18: =+D18+E18 -> 17043.08 | G18: 78130 | H18: =+D18/G18 -> 0.11833483 | I18: =+E18/G18 -> 0.099802637 | K18: =+H18+I18 -> 0.21813746
B19: November | D19: 5738.9 | E19: 5871.58 | F19: =+D19+E19 -> 11610.48 | G19: 59991 | H19: =+D19/G19 -> 0.095662683 | I19: =+E19/G19 -> 0.097874348 | K19: =+H19+I19 -> 0.19353703
B20: December | D20: 7449.74 | E20: 9610.08 | F20: =+D20+E20 -> 17059.82 | G20: 69126 | H20: =+D20/G20 -> 0.10777045 | I20: =+E20/G20 -> 0.13902265 | K20: =+H20+I20 -> 0.2467931
B21: Total | D21: =SUM(D9:D20) -> 101963.21 | E21: =SUM(E9:E20) -> 94577.02 | F21: =SUM(F9:F20) -> 196540.23 | G21: =SUM(G9:G20) -> 925558 | H21: =+D21/G21 -> 0.11016404 | I21: =+E21/G21 -> 0.10218379 | K21: =F21/G21 -> 0.21234783
D23: =D7 -> Con Ed #49-4182-7002-0000-8 new account #50834100005
B24: =B8+1 -> 2025 | D24: =+D8 -> Con Ed | E24: ESCO | F24: Total | G24: KWH | H24: Con Ed $/KWH | I24: ESCO $/ KWH | K24: $/Per KWH
B25: January | D25: 6848.26 | E25: 13612.08 | F25: =D25+E25 -> 20460.34 | G25: 67982 | H25: =+D25/G25 -> 0.10073637 | I25: =E25/G25 -> 0.20023065 | K25: =+H25+I25 -> 0.30096702
B26: February | D26: 5385.08 | E26: 10461.16 | F26: =D26+E26 -> 15846.24 | G26: 56840 | H26: =D26/G26 -> 0.094741027 | I26: =E26/G26 -> 0.18404574 | K26: =SUM(H26:I26) -> 0.27878677
B27: March | D27: 5090.12 | E27: 6650.44 | F27: =D27+E27 -> 11740.56 | G27: 53836 | H27: =D27/G27 -> 0.094548629 | I27: =E27/G27 -> 0.12353147 | K27: =SUM(H27:I27) -> 0.2180801
B28: April | D28: 5271.22 | E28: 6337.48 | F28: =D28+E28 -> 11608.7 | G28: 54952 | H28: =D28/G28 -> 0.095924079 | I28: =E28/G28 -> 0.11532756 | K28: =SUM(H28:I28) -> 0.21125164
B29: May | D29: 8083.76 | E29: 7250.93 | F29: =D29+E29 -> 15334.69 | G29: 71005 | H29: =D29/G29 -> 0.11384776 | I29: =E29/G29 -> 0.10211858 | K29: =SUM(H29:I29) -> 0.21596634
B30: June | D30: 10959.29 | E30: 10950.23 | F30: =D30+E30 -> 21909.52 | G30: 94615 | H30: =D30/G30 -> 0.11583037 | I30: =E30/G30 -> 0.11573461 | K30: =SUM(H30:I30) -> 0.23156497
B31: July | D31: 14114.42 | E31: 15720.57 | F31: =D31+E31 -> 29834.99 | G31: 114667 | H31: =D31/G31 -> 0.12309051 | I31: =E31/G31 -> 0.1370976 | K31: =SUM(H31:I31) -> 0.26018811
B32: August | C32: Est | D32: =G32*H32 -> 15287.732 | E32: =+G32*I32 -> 18484.71 | F32: =D32+E32 -> 33772.442 | G32: =+(G16+G78)/2 -> 144864.5 | H32: =SUM(H25:H31)/7 -> 0.10553125 | I32: 0.1276 | K32: =K31 -> 0.26018811
B33: September | C33: Est | D33: =G33*H33 -> 15483.439 | E33: =+G33*I33 -> 18721.344 | F33: =D33+E33 -> 34204.784 | G33: =+(G17+G79)/2 -> 146719 | H33: =H32 -> 0.10553125 | I33: =I32 -> 0.1276 | K33: =K32 -> 0.26018811
B34: October | C34: Est | D34: =G34*H34 -> 9544.0879 | E34: =+G34*I34 -> 11539.953 | F34: =D34+E34 -> 21084.04 | G34: =+(G18+G80)/2 -> 90438.5 | H34: =H32 -> 0.10553125 | I34: =I32 -> 0.1276 | K34: =K33 -> 0.26018811
B35: November | C35: Est | D35: =G35*H35 -> 7423.4374 | E35: =+G35*I35 -> 8975.8306 | F35: =D35+E35 -> 16399.268 | G35: =+(G19+G81)/2 -> 70343.5 | H35: =H32 -> 0.10553125 | I35: =I32 -> 0.1276 | K35: =K34 -> 0.26018811
B36: December | C36: Est | D36: =G36*H36 -> 8290.8515 | E36: =+G36*I36 -> 10024.639 | F36: =D36+E36 -> 18315.49 | G36: =+(G20+G82)/2 -> 78563 | H36: =H32 -> 0.10553125 | I36: =I32 -> 0.1276 | K36: =+K35 -> 0.26018811
B37: Total | D37: =SUM(D25:D36) -> 111781.7 | E37: =SUM(E25:E36) -> 138729.37 | F37: =SUM(F25:F36) -> 250511.06 | G37: =SUM(G25:G36) -> 1044825.5 | H37: =D37/G37 -> 0.106986 | I37: =E37/G37 -> 0.13277755 | K37: =+F37/G37 -> 0.23976354
B39: Budget | D39: =D23 -> Con Ed #49-4182-7002-0000-8 new account #50834100005
B40: =B24+1 -> 2026 | D40: =+D24 -> Con Ed | E40: =E24 -> ESCO | F40: Total | G40: =G24 -> KWH | H40: =H24 -> Con Ed $/KWH | I40: ESCO $/KWH | K40: =K24 -> $/Per KWH
B41: January | D41: =G41*H41 -> 7720.1675 | E41: =G41*I41 -> 9657.7241 | F41: =D41+E41 -> 17377.892 | G41: =+(G9+G25)/2 -> 70960.5 | H41: =$H$25*$I$57+H25 -> 0.10879528 | I41: =I64 -> 0.1361 | K41: =+H41+I41 -> 0.24489528
B42: February | D42: =G42*H42 -> 6665.7589 | E42: =G42*I42 -> 8866.3706 | F42: =D42+E42 -> 15532.129 | G42: =+(G10+G26)/2 -> 65146 | H42: =$H$26*$I$57+H26 -> 0.10232031 | I42: =I64 -> 0.1361 | K42: =SUM(H42:I42) -> 0.23842031
B43: March | D43: =G43*H43 -> 6152.3814 | E43: =G43*I43 -> 8200.1611 | F43: =D43+E43 -> 14352.543 | G43: =+(G11+G27)/2 -> 60251 | H43: =H27*I57+H27 -> 0.10211252 | I43: =I64 -> 0.1361 | K43: =SUM(H43:I43) -> 0.23821252
B44: April | D44: =G44*H44 -> 5770.3053 | E44: =G44*I44 -> 7580.6339 | F44: =D44+E44 -> 13350.939 | G44: =+(G12+G28)/2 -> 55699 | H44: =H28*I57+H28 -> 0.10359801 | I44: =I64 -> 0.1361 | K44: =SUM(H44:I44) -> 0.23969801
B45: May | D45: =G45*H45 -> 7081.8109 | E45: =G45*I45 -> 7838.8836 | F45: =D45+E45 -> 14920.695 | G45: =+(G13+G29)/2 -> 57596.5 | H45: =H29*I57+H29 -> 0.12295558 | I45: =I64 -> 0.1361 | K45: =SUM(H45:I45) -> 0.25905558
B46: June | D46: =G46*H46 -> 10582.376 | E46: =G46*I46 -> 11513.175 | F46: =D46+E46 -> 22095.551 | G46: =+(G14+G30)/2 -> 84593.5 | H46: =H30*I57+H30 -> 0.12509679 | I46: =I64 -> 0.1361 | K46: =SUM(H46:I46) -> 0.26119679
B47: July | D47: =G47*H47 -> 15031.804 | E47: =G47*I47 -> 15389.371 | F47: =D47+E47 -> 30421.175 | G47: =+(G15+G31)/2 -> 113074 | H47: =H31*I57+H31 -> 0.13293776 | I47: =I64 -> 0.1361 | K47: =SUM(H47:I47) -> 0.26903776
B48: August | D48: =G48*H48 -> 14417.309 | E48: =G48*I48 -> 17216.208 | F48: =D48+E48 -> 31633.517 | G48: =+(G16+G32)/2 -> 126496.75 | H48: =H32*I57+H32 -> 0.11397375 | I48: =I64 -> 0.1361 | K48: =SUM(H48:I48) -> 0.25007375
B49: September | D49: =G49*H49 -> 14597.587 | E49: =G49*I49 -> 17431.484 | F49: =D49+E49 -> 32029.071 | G49: =+(G17+G33)/2 -> 128078.5 | H49: =H33*I57+H33 -> 0.11397375 | I49: =I64 -> 0.1361 | K49: =SUM(H49:I49) -> 0.25007375
B50: October | D50: =G50*H50 -> 9606.192 | E50: =G50*I50 -> 11471.086 | F50: =D50+E50 -> 21077.278 | G50: =+(G18+G34)/2 -> 84284.25 | H50: =H34*I57+H34 -> 0.11397375 | I50: =I64 -> 0.1361 | K50: =SUM(K41:K49)/9 -> 0.25007375
B51: November | D51: =G51*H51 -> 7427.3558 | E51: =G51*I51 -> 8869.2627 | F51: =D51+E51 -> 16296.619 | G51: =+(G19+G35)/2 -> 65167.25 | H51: =H35*I57+H35 -> 0.11397375 | I51: =I64 -> 0.1361 | K51: =K50 -> 0.25007375
B52: December | D52: =G52*H52 -> 8416.3345 | E52: =G52*I52 -> 10050.236 | F52: =D52+E52 -> 18466.571 | G52: =+(G20+G36)/2 -> 73844.5 | H52: =H36*I57+H36 -> 0.11397375 | I52: =I64 -> 0.1361 | K52: =+K51 -> 0.25007375
B53: Total | D53: =SUM(D41:D52) -> 113469.38 | E53: =SUM(E41:E52) -> 134084.6 | F53: =SUM(F41:F52) -> 247553.98 | G53: =SUM(G41:G52) -> 985191.75 | H53: =D53/G53 -> 0.11517492 | I53: =E53/G53 -> 0.1361 | K53: =+F53/G53 -> 0.25127492
B55: 2026 Budget Assumptions:
B56: 2026 Budget Electric Usage: Prior Two year Average Consumption
B57: 2026 Budget Price reflects an increase over prior year costs @ | I57: 0.08
N59: 2024 October-December Electric Price and Usage: Provided by Aurora Energy Advisors
B60: 2023 October-December Electric Price is at 2023 YTD Average $/KWH
B61: 2025 August - December Electric Usage: Prior Period two year Average
B62: 2025 August - Decembre Electric Pice is at 2025 YTD Average $/KWH
B64: Contract Price for ESCO: 07/01/2023-06/30/2025 | I64: 0.1361
F67: Page 7
D69: Con Ed #49-4182-7002-0000-8
B70: =B8-1 -> 2023 | D70: Con Ed | F70: KWH | H70: $/Per KWH
B71: January | D71: 23080.925 | E71: 0 | F71: 23080.925 | G71: 84800 | H71: 0.27218072 | I71: 0 | K71: 0.27218072
B72: February | D72: 28734.39 | E72: 0 | F72: 28734.39 | G72: 126400 | H72: 0.22732903 | I72: 0 | K72: 0.22732903
B73: March | D73: 17097.02 | E73: 0 | F73: 17097.02 | G73: 87200 | H73: 0.19606674 | I73: 0 | K73: 0.19606674
B74: April | D74: 12474.28 | E74: 0 | F74: 12474.28 | G74: 64800 | H74: 0.19250432 | I74: 0 | K74: 0.19250432
B75: May | D75: 22232.82 | E75: 0 | F75: 22232.82 | G75: 125600 | H75: 0.1770129 | I75: 0 | K75: 0.1770129
B76: June | D76: 34074.83 | E76: 0 | F76: 34074.83 | G76: 173600 | H76: 0.19628358 | I76: 0 | K76: 0.19628358
B77: July | D77: 37282.95 | E77: 0 | F77: 37282.95 | G77: 188000 | H77: 0.19831356 | I77: 0 | K77: 0.19831356
B78: August | D78: 17456.04 | E78: 18038.75 | F78: 35494.79 | G78: 181600 | H78: 0.096123568 | I78: 0.099332324 | K78: 0.19545589
B79: September | D79: 19817.25 | E79: 17490.27 | F79: 37307.52 | G79: 184000 | H79: 0.10770245 | I79: 0.095055815 | K79: 0.20275826
B80: October | D80: 11790.45 | E80: 9746.05 | F80: 27148.45 | G80: 102747 | H80: 0.11475226 | I80: 0.14947395 | K80: 0.26422621
B81: November | D81: 8058.28 | E81: 9876.33 | F81: 24978.81 | G81: 80696 | H81: 0.09985972 | I81: 0.20968239 | K81: 0.30954211
B82: December | D82: 9567.79 | E82: 10580.37 | F82: 18951.85 | G82: 88000 | H82: 0.10872489 | I82: 0.10663705 | K82: 0.21536193
B83: Total | D83: =SUM(D71:D82) -> 241667.03 | F83: =SUM(F71:F82) -> 318858.64 | H83: =+D83/F83 -> 0.75791275

Sheet Electric 2
E1: =+yrlycomp!H1 -> 444 East 86th Street Owners Corp.
E2: Electric
B3: Schedule C | E3: =+yrlycomp!H3 -> For Year Ending 12/31/2026
B5: G/L
B6: 5255-0000
D7: Con Ed #42-2039-0422-3500-0 new account #70788-12000-7
B8: =Electric!B8 -> 2024 | D8: Con Ed | F8: KWH | H8: $/Per KWH | L8: Super
B9: January | D9: 204.22 | F9: 491 | H9: =+D9/F9 -> 0.41592668
B10: February | D10: 151.33 | F10: 374 | H10: =+D10/F10 -> 0.40462567
B11: March | D11: 142.14 | F11: 322 | H11: =+D11/F11 -> 0.44142857 | K11: 70788120007
B12: April | D12: 124.25 | F12: 309 | H12: =+D12/F12 -> 0.40210356
B13: May | D13: 189.94 | F13: 523 | H13: =+D13/F13 -> 0.363174
B14: June | D14: 599.82 | F14: 1649 | H14: =+D14/F14 -> 0.36374773
B15: July | D15: 507.66 | F15: 1355 | H15: =+D15/F15 -> 0.37465683
B16: August | D16: 436.46 | F16: 1152 | H16: =+D16/F16 -> 0.37887153
B17: September | D17: 313.62 | F17: 778 | H17: =+D17/F17 -> 0.40311054
B18: October | D18: 186.68 | F18: 418 | H18: =+D18/F18 -> 0.44660287
B19: November | D19: 178.62 | F19: 415 | H19: =+D19/F19 -> 0.43040964
B20: December | D20: 246.85 | F20: 578 | H20: =+D20/F20 -> 0.42707612
B21: Total | D21: =SUM(D9:D20) -> 3281.59 | F21: =SUM(F9:F20) -> 8364 | H21: =+D21/F21 -> 0.39234696
D23: =D7 -> Con Ed #42-2039-0422-3500-0 new account #70788-12000-7
B24: =B8+1 -> 2025 | D24: =+D8 -> Con Ed | F24: KWH | H24: $/Per KWH
B25: January | D25: 259.51 | F25: 591 | H25: =+D25/F25 -> 0.43910321
B26: February | D26: 192.08 | F26: 404 | H26: =+D26/F26 -> 0.47544554
B27: March | D27: 157.39 | F27: 341 | H27: =+D27/F27 -> 0.46155425
B28: April | D28: 151.62 | F28: 315 | H28: =+D28/F28 -> 0.48133333
B29: May | D29: 158.22 | F29: 325 | H29: =+D29/F29 -> 0.48683077
B30: June | D30: 200.59 | F30: 415 | H30: =+D30/F30 -> 0.4833494
B31: July | D31: 242.31 | F31: 506 | H31: =+D31/F31 -> 0.47887352
B32: August | C32: Est | D32: =+F32*H32 -> 379.774 | F32: =+(F16+F79)/2 -> 804 | H32: =SUM(H25:H31)/7 -> 0.47235572
B33: September | C33: Est | D33: =+F33*H33 -> 305.61415 | F33: =+(F17+F80)/2 -> 647 | H33: =H32 -> 0.47235572
B34: October | C34: Est | D34: =+F34*H34 -> 194.37438 | F34: =+(F18+F81)/2 -> 411.5 | H34: =H32 -> 0.47235572
B35: November | C35: Est | D35: =+F35*H35 -> 177.84193 | F35: =+(F19+F82)/2 -> 376.5 | H35: =H32 -> 0.47235572
B36: December | C36: Est | D36: =+F36*H36 -> 253.41884 | F36: =+(F20+F83)/2 -> 536.5 | H36: =H32 -> 0.47235572
B37: Total | D37: =SUM(D25:D36) -> 2672.7433 | F37: =SUM(F25:F36) -> 5672.5 | H37: =+D37/F37 -> 0.47117555
B39: Budget | D39: =D7 -> Con Ed #42-2039-0422-3500-0 new account #70788-12000-7
B40: =B24+1 -> 2026 | D40: =D8 -> Con Ed | F40: KWH | H40: $/Per KWH | K40: For Budget Entry
B41: January | D41: =+F41*H41 -> 256.55923 | F41: =(F9+F25)/2 -> 541 | H41: =+H25*$H$57+H25 -> 0.47423147 | K41: =Electric!F41+'Electric 2'!D41 -> 17634.451
B42: February | D42: =+F42*H42 -> 199.74418 | F42: =(F10+F26)/2 -> 389 | H42: =+H26*$H$57+H26 -> 0.51348119 | K42: =Electric!F42+'Electric 2'!D42 -> 15731.874
B43: March | D43: =+F43*H43 -> 165.24565 | F43: =(F11+F27)/2 -> 331.5 | H43: =+H27*$H$57+H27 -> 0.49847859 | K43: =Electric!F43+'Electric 2'!D43 -> 14517.788
B44: April | D44: =+F44*H44 -> 162.19008 | F44: =(F12+F28)/2 -> 312 | H44: =+H28*$H$57+H28 -> 0.51984 | K44: =Electric!F44+'Electric 2'!D44 -> 13513.129
B45: May | D45: =+F45*H45 -> 222.92955 | F45: =(F13+F29)/2 -> 424 | H45: =+H29*$H$57+H29 -> 0.52577723 | K45: =Electric!F45+'Electric 2'!D45 -> 15143.624
B46: June | D46: =+F46*H46 -> 538.7219 | F46: =(F14+F30)/2 -> 1032 | H46: =+H30*$H$57+H30 -> 0.52201735 | K46: =Electric!F46+'Electric 2'!D46 -> 22634.273
B47: July | D47: =+F47*H47 -> 481.23915 | F47: =(F15+F31)/2 -> 930.5 | H47: =+H31*$H$57+H31 -> 0.5171834 | K47: =Electric!F47+'Electric 2'!D47 -> 30902.414
B48: August | D48: =+F48*H48 -> 498.921 | F48: =(F16+F32)/2 -> 978 | H48: =+H32*$H$57+H32 -> 0.51014418 | K48: =Electric!F48+'Electric 2'!D48 -> 32132.438
B49: September | D49: =+F49*H49 -> 363.47773 | F49: =(F17+F33)/2 -> 712.5 | H49: =+H33*$H$57+H33 -> 0.51014418 | K49: =Electric!F49+'Electric 2'!D49 -> 32392.548
B50: October | D50: =+F50*H50 -> 211.5823 | F50: =(F18+F34)/2 -> 414.75 | H50: =+H34*$H$57+H34 -> 0.51014418 | K50: =Electric!F50+'Electric 2'!D50 -> 21288.861
B51: November | D51: =+F51*H51 -> 201.88956 | F51: =(F19+F35)/2 -> 395.75 | H51: =+H35*$H$57+H35 -> 0.51014418 | K51: =Electric!F51+'Electric 2'!D51 -> 16498.508
B52: December | D52: =+F52*H52 -> 284.27784 | F52: =(F20+F36)/2 -> 557.25 | H52: =+H36*$H$57+H36 -> 0.51014418 | K52: =Electric!F52+'Electric 2'!D52 -> 18750.849
B53: Total | D53: =SUM(D41:D52) -> 3586.7782 | F53: =SUM(F41:F52) -> 7018.25 | H53: =+D53/F53 -> 0.51106446 | K53: =SUM(K41:K52) -> 251140.76
B55: =Electric!B55 -> 2026 Budget Assumptions:
B56: 2026 Budget Electric Usage: Prior two year average consumption.
B57: 2026 Budget Price reflects an increase over prior year costs @ | H57: 0.08
B59: 2025 August - December Electric Usage: Prior Period Two Year Average
B60: 2025 August - December Electric Price is at 2025 YTD Average $/KWH
E64: Page 8
D70: =D7 -> Con Ed #42-2039-0422-3500-0 new account #70788-12000-7
B71: =Electric!B70 -> 2023 | D71: Con Ed | F71: KWH | H71: $/Per KWH
B72: January | D72: 275.56 | F72: 708 | H72: 0.38920904
B73: February | D73: 236.56 | F73: 624 | H73: 0.37910256
B74: March | D74: 175.59 | F74: 516 | H74: 0.3402907
B75: April | D75: 130.65 | F75: 384 | H75: 0.34023438
B76: May | D76: 133.93 | F76: 384 | H76: 0.34877604
B77: June | D77: 224.37 | F77: 600 | H77: 0.37395
B78: July | D78: 285.09 | F78: 768 | H78: 0.37121094
B79: August | D79: 177.78 | F79: 456 | H79: 0.38986842
B80: September | D80: 210.44 | F80: 516 | H80: 0.40782946
B81: October | D81: 149.64 | F81: 405 | H81: 0.36948148
B82: November | D82: 142.32 | F82: 338 | H82: 0.42106509
B83: December | D83: 187.18 | F83: 495 | H83: 0.37814141
B84: Total | D84: =SUM(D72:D83) -> 2329.11 | F84: =SUM(F72:F83) -> 6194 | H84: =+D84/F84 -> 0.3760268

Sheet elect
F1: Morton Square Condominium
F2: Electric
B3: Schedule D | F3: For Year Ending 12/31/2011
E6: Electric-A/C # 432109500000010 | I6: Electric-A/C # 436207190138003 | L6: Total
B7: 2009 | D7: Amount | E7: KWH | F7: $ Per KWH | H7: Amount | I7: KWH | J7: $ Per KWH | L7: Utility
B8: January | D8: 29549.54 | E8: 173600 | F8: =+D8/E8 -> 0.17021624 | H8: 392.91 | I8: 1632 | J8: =+H8/I8 -> 0.24075368 | L8: =+D8+H8 -> 29942.45
B9: February | D9: 24140.24 | E9: 157600 | F9: =+D9/E9 -> 0.15317411 | H9: 306.42 | I9: 1392 | J9: =+H9/I9 -> 0.22012931 | L9: =+D9+H9 -> 24446.66
B10: March | D10: 27308.89 | E10: 150400 | F10: =+D10/E10 -> 0.18157507 | H10: 221.69 | I10: 876 | J10: =+H10/I10 -> 0.25307078 | L10: =+D10+H10 -> 27530.58
B11: April | D11: 33176.34 | E11: 147200 | F11: =+D11/E11 -> 0.22538274 | H11: 257.98 | I11: 852 | J11: =+H11/I11 -> 0.30279343 | L11: =+D11+H11 -> 33434.32
B12: May | D12: 39252.44 | E12: 176000 | F12: =+D12/E12 -> 0.22302523 | H12: 399.73 | I12: 1248 | J12: =+H12/I12 -> 0.32029647 | L12: =+D12+H12 -> 39652.17
B13: June | D13: 43190.88 | E13: 194400 | F13: =+D13/E13 -> 0.22217531 | H13: 428.41 | I13: 1344 | J13: =+H13/I13 -> 0.31875744 | L13: =+D13+H13 -> 43619.29
B14: July | D14: 42420.13 | E14: 198400 | F14: =+D14/E14 -> 0.21381114 | H14: 661.31 | I14: 2088 | J14: =+H14/I14 -> 0.31671935 | L14: =+D14+H14 -> 43081.44
B15: August | D15: 31903.79 | E15: 200000 | F15: =+D15/E15 -> 0.15951895 | H15: 414.36 | I15: 1560 | J15: =+H15/I15 -> 0.26561538 | L15: =+D15+H15 -> 32318.15
B16: September | D16: 27803.43 | E16: 164800 | F16: =+D16/E16 -> 0.16871013 | H16: 343.18 | I16: 1248 | J16: =+H16/I16 -> 0.27498397 | L16: =+D16+H16 -> 28146.61
B17: October | D17: 23897.19 | E17: 148000 | F17: =+D17/E17 -> 0.1614675 | H17: 169.98 | I17: 612 | J17: =+H17/I17 -> 0.2777451 | L17: =+D17+H17 -> 24067.17
B18: November | D18: 30083.12 | E18: 155200 | F18: =+D18/E18 -> 0.19383454 | H18: 238.85 | I18: 864 | J18: =+H18/I18 -> 0.27644676 | L18: =+D18+H18 -> 30321.97
B19: December | D19: 32147.89 | E19: 164800 | F19: =+D19/E19 -> 0.19507215 | H19: 482.04 | I19: 1812 | J19: =+H19/I19 -> 0.26602649 | L19: =+D19+H19 -> 32629.93
B20: Total | D20: =SUM(D8:D19) -> 384873.88 | E20: =SUM(E8:E19) -> 2030400 | F20: =+D20/E20 -> 0.18955569 | H20: =SUM(H8:H19) -> 4316.86 | I20: =SUM(I8:I19) -> 15528 | J20: =+H20/I20 -> 0.27800489 | L20: =SUM(L8:L19) -> 389190.74
E22: =E6 -> Electric-A/C # 432109500000010 | I22: =I6 -> Electric-A/C # 436207190138003 | L22: Total
B23: 2010 | D23: Amount | E23: KWH | F23: $ Per KWH | H23: Amount | I23: KWH | J23: $ Per KWH | L23: Utility
B24: January | D24: 32335.33 | E24: 179200 | F24: =+D24/E24 -> 0.18044269 | H24: 467.07 | I24: 1872 | J24: =+H24/I24 -> 0.24950321 | L24: =+D24+H24 -> 32802.4
B25: February | D25: 24866.19 | E25: 156800 | F25: =+D25/E25 -> 0.1585854 | H25: 327.29 | I25: 1404 | J25: =+H25/I25 -> 0.23311254 | L25: =+D25+H25 -> 25193.48
B26: March | D26: 27568.89 | E26: 148800 | F26: =+D26/E26 -> 0.1852748 | H26: 243.04 | I26: 924 | J26: =+H26/I26 -> 0.2630303 | L26: =+D26+H26 -> 27811.93
B27: April | D27: 27397.62 | E27: 152000 | F27: =+D27/E27 -> 0.1802475 | H27: 233.52 | I27: 864 | J27: =+H27/I27 -> 0.27027778 | L27: =+D27+H27 -> 27631.14
B28: May | D28: 33117.55 | E28: 168800 | F28: =+D28/E28 -> 0.19619402 | H28: 272.9 | I28: 864 | J28: =+H28/I28 -> 0.31585648 | L28: =+D28+H28 -> 33390.45
B29: June | D29: 36391.02 | E29: 186400 | F29: =+D29/E29 -> 0.19523079 | H29: 506.23 | I29: 1620 | J29: =+H29/I29 -> 0.31248765 | L29: =+D29+H29 -> 36897.25
B30: July | D30: 46565.59 | E30: 217600 | F30: =+D30/E30 -> 0.21399628 | H30: 589.43 | I30: 1776 | J30: =+H30/I30 -> 0.33188626 | L30: =+D30+H30 -> 47155.02
B31: August | D31: 29100.82 | E31: 189600 | F31: =+D31/E31 -> 0.15348534 | H31: 485.33 | I31: 1764 | J31: =+H31/I31 -> 0.27513039 | L31: =+D31+H31 -> 29586.15
B32: September | D32: 30301.53 | E32: 168800 | F32: =+D32/E32 -> 0.17951143 | H32: 355.23 | I32: 1164 | J32: =+H32/I32 -> 0.30518041 | L32: =+D32+H32 -> 30656.76
B33: October | C33: Est | D33: 0 | E33: 0 | F33: =+D33/E33 -> #DIV/0! | H33: 0 | I33: 0 | J33: =+H33/I33 -> #DIV/0! | L33: =+D33+H33 -> 0
B34: November | C34: Est | D34: =+E34*F34 -> 27936 | E34: =+E18 -> 155200 | F34: =+K83 -> 0.18 | H34: =+I34*J34 -> 239.97176 | I34: =+I18 -> 864 | J34: =+K84 -> 0.2777451 | L34: =+D34+H34 -> 28175.972
B35: December | C35: Est | D35: =+E35*F35 -> 29664 | E35: =+E19 -> 164800 | F35: =+F34 -> 0.18 | H35: =+I35*J35 -> 503.27412 | I35: =+I19 -> 1812 | J35: =+J34 -> 0.2777451 | L35: =+D35+H35 -> 30167.274
B36: Total | D36: =SUM(D24:D35) -> 345244.54 | E36: =SUM(E24:E35) -> 1888000 | F36: =+D36/E36 -> 0.18286257 | H36: =SUM(H24:H35) -> 4223.2859 | I36: =SUM(I24:I35) -> 14928 | J36: =+H36/I36 -> 0.28291036 | L36: =SUM(L24:L35) -> 349467.83
E38: =E6 -> Electric-A/C # 432109500000010 | I38: =I6 -> Electric-A/C # 436207190138003 | L38: Total
B39: 2011 | D39: Amount | E39: KWH | F39: $ Per KWH | H39: Amount | I39: KWH | J39: $ Per KWH | L39: Utility
B40: January | D40: 33974.64 | E40: =SUM(E8+E24)/2 -> 176400 | F40: =+L83 -> 0.1926 | L40: =+D40+H40 -> 33974.64
B41: February | D41: 30276.72 | E41: =SUM(E9+E25)/2 -> 157200 | F41: =+F40 -> 0.1926 | L41: =+D41+H41 -> 30276.72
B42: March | D42: 28812.96 | E42: =SUM(E10+E26)/2 -> 149600 | F42: =+F41 -> 0.1926 | L42: =+D42+H42 -> 28812.96
B43: April | D43: 28812.96 | E43: =SUM(E11+E27)/2 -> 149600 | F43: =+F42 -> 0.1926 | L43: =+D43+H43 -> 28812.96
B44: May | D44: 33204.24 | E44: =SUM(E12+E28)/2 -> 172400 | F44: =+F43 -> 0.1926 | L44: =+D44+H44 -> 33204.24
B45: June | D45: 36671.04 | E45: =SUM(E13+E29)/2 -> 190400 | F45: =+F44 -> 0.1926 | L45: =+D45+H45 -> 36671.04
B46: July | D46: 40060.8 | E46: =SUM(E14+E30)/2 -> 208000 | F46: =+F45 -> 0.1926 | L46: =+D46+H46 -> 40060.8
B47: August | D47: 37518.48 | E47: =SUM(E15+E31)/2 -> 194800 | F47: =+F46 -> 0.1926 | L47: =+D47+H47 -> 37518.48
B48: September | D48: 32125.68 | E48: =SUM(E16+E32)/2 -> 166800 | F48: =+F47 -> 0.1926 | L48: =+D48+H48 -> 32125.68
B49: October | D49: 14252.4 | E49: =SUM(E17+E33)/2 -> 74000 | F49: =+F48 -> 0.1926 | L49: =+D49+H49 -> 14252.4
B50: November | D50: 29891.52 | E50: =SUM(E18+E34)/2 -> 155200 | F50: =+F49 -> 0.1926 | L50: =+D50+H50 -> 29891.52
B51: December | D51: 31740.48 | E51: =SUM(E19+E35)/2 -> 164800 | F51: =+F50 -> 0.1926 | H51: 289.86 | I51: 1236 | J51: =+H51/I51 -> 0.23451456 | L51: =+D51+H51 -> 32030.34
B52: Total | D52: =SUM(D40:D51) -> 377341.92 | E52: =SUM(E40:E51) -> 1959200 | F52: =+D52/E52 -> 0.1926 | H52: =SUM(H40:H51) -> 289.86 | I52: =SUM(I40:I51) -> 1236 | J52: =+H52/I52 -> 0.23451456 | L52: =SUM(L40:L51) -> 377631.78
E54: =E22 -> Electric-A/C # 432109500000010 | I54: =I22 -> Electric-A/C # 436207190138003 | L54: Total
B55: 2012 | D55: Amount | E55: KWH | F55: $ Per KWH | H55: Amount | I55: KWH | J55: $ Per KWH | L55: Utility
B56: January | F56: =+L99 -> 0 | J56: =+L100 -> 0 | L56: =+D56+H56 -> 0
B57: February | F57: =+F56 -> 0 | J57: =+J56 -> 0 | L57: =+D57+H57 -> 0
B58: March | F58: =+F57 -> 0 | J58: =+J57 -> 0 | L58: =+D58+H58 -> 0
B59: April | F59: =+F58 -> 0 | J59: =+J58 -> 0 | L59: =+D59+H59 -> 0
B60: May | F60: =+F59 -> 0 | J60: =+J59 -> 0 | L60: =+D60+H60 -> 0
B61: June | F61: =+F60 -> 0 | J61: =+J60 -> 0 | L61: =+D61+H61 -> 0
B62: July | F62: =+F61 -> 0 | J62: =+J61 -> 0 | L62: =+D62+H62 -> 0
B63: August | F63: =+F62 -> 0 | J63: =+J62 -> 0 | L63: =+D63+H63 -> 0
B64: September | F64: =+F63 -> 0 | J64: =+J63 -> 0 | L64: =+D64+H64 -> 0
B65: October | F65: =+F64 -> 0 | J65: =+J64 -> 0 | L65: =+D65+H65 -> 0
B66: November | F66: =+F65 -> 0 | J66: =+J65 -> 0 | L66: =+D66+H66 -> 0
B67: December | F67: =+F66 -> 0 | J67: =+J66 -> 0 | L67: =+D67+H67 -> 0
B68: Total | D68: =SUM(D56:D67) -> 0 | E68: =SUM(E56:E67) -> 0 | F68: =+D68/E68 -> #DIV/0! | H68: =SUM(H56:H67) -> 0 | I68: =SUM(I56:I67) -> 0 | J68: =+H68/I68 -> #DIV/0! | L68: =SUM(L56:L67) -> 0
D78: 2011 Budget Assumptions:
D79: 2011 Budget Electric Usage: Two year average consumption.
D80: 2011 Budget Price reflects an increase over prior yr costs @ | K80: 0.07
D81: 2010 three month estimate was calculated based on cost per KWH as follows:
K82: 2010 4th Qtr | L82: 2011 Budget
F83: =+E38 -> Electric-A/C # 432109500000010 | K83: 0.18 | L83: =+K83*K80+K83 -> 0.1926
F84: =+I38 -> Electric-A/C # 436207190138003 | K84: 0.2777451 | L84: =+K84*K80+K84 -> 0.29718725
B86: Page 6

Sheet Gas Cooking
E1: =+yrlycomp!H1 -> 444 East 86th Street Owners Corp.
E2: Gas - Cooking
B3: Schedule D | E3: =+yrlycomp!H3 -> For Year Ending 12/31/2026
B5: G/L | M5: New Account Number
B6: 5250-0000 | M6: 50834100005
D7: Con Ed #49-4182-7002-0000-8
B8: =Electric!B8 -> 2024 | D8: Con Ed | E8: Esco | F8: Total | G8: Therms | H8: Con Ed Therms | I8: EscoTherms | K8: $/Per Therm
B9: January | D9: 658.91 | E9: =229.55+105.27 -> 334.82 | F9: =+D9+E9 -> 993.73 | G9: 744 | H9: =+D9/G9 -> 0.88563172 | I9: =+E9/G9 -> 0.45002688 | K9: =+H9+I9 -> 1.3356586
B10: February | D10: 706.55 | E10: =233.31+103.09 -> 336.4 | F10: =+D10+E10 -> 1042.95 | G10: 745 | H10: =+D10/G10 -> 0.94838926 | I10: =+E10/G10 -> 0.45154362 | K10: =+H10+I10 -> 1.3999329
B11: March | D11: 596 | E11: =168.17+71.62 -> 239.79 | F11: =+D11+E11 -> 835.79 | G11: 663 | H11: =+D11/G11 -> 0.89894419 | I11: =+E11/G11 -> 0.36167421 | K11: =+H11+I11 -> 1.2606184
B12: April | D12: 624.54 | E12: =169.69+59.25 -> 228.94 | F12: =+D12+E12 -> 853.48 | G12: 678 | H12: =+D12/G12 -> 0.92115044 | I12: =+E12/G12 -> 0.33766962 | K12: =+H12+I12 -> 1.2588201
B13: May | D13: 625 | E13: =161.91+64.75-161.91-64.75+67.18 -> 67.18 | F13: =+D13+E13 -> 692.18 | G13: 694 | H13: =+D13/G13 -> 0.90057637 | I13: =+E13/G13 -> 0.096801153 | K13: =+H13+I13 -> 0.99737752
B14: June | D14: 612.61 | E14: =183.2+85.62 -> 268.82 | F14: =+D14+E14 -> 881.43 | G14: 654 | H14: =+D14/G14 -> 0.93671254 | I14: =+E14/G14 -> 0.41103976 | K14: =+H14+I14 -> 1.3477523
B15: July | D15: 543.68 | E15: =171.2+85.39 -> 256.59 | F15: =+D15+E15 -> 800.27 | G15: 575 | H15: =+D15/G15 -> 0.94553043 | I15: =+E15/G15 -> 0.44624348 | K15: =+H15+I15 -> 1.3917739
B16: August | D16: 552.01 | E16: =152.98+77.29 -> 230.27 | F16: =+D16+E16 -> 782.28 | G16: 590 | H16: =+D16/G16 -> 0.93561017 | I16: =+E16/G16 -> 0.39028814 | K16: =+H16+I16 -> 1.3258983
B17: September | D17: 658.71 | E17: =181.54+88.05 -> 269.59 | F17: =+D17+E17 -> 928.3 | G17: 723 | H17: =+D17/G17 -> 0.91107884 | I17: =+E17/G17 -> 0.3728769 | K17: =+H17+I17 -> 1.2839557
B18: October | D18: 629.56 | E18: =207.33+93.09 -> 300.42 | F18: =+D18+E18 -> 929.98 | G18: 703 | H18: =+D18/G18 -> 0.89553343 | I18: =+E18/G18 -> 0.42733997 | K18: =+H18+I18 -> 1.3228734
B19: November | D19: 634.13 | E19: =216.91+91.19 -> 308.1 | F19: =+D19+E19 -> 942.23 | G19: 702 | H19: =+D19/G19 -> 0.90331909 | I19: =+E19/G19 -> 0.43888889 | K19: =+H19+I19 -> 1.342208
B20: December | D20: 724.26 | E20: =299.65+121.46 -> 421.11 | F20: =+D20+E20 -> 1145.37 | G20: 807 | H20: =+D20/G20 -> 0.89747212 | I20: =+E20/G20 -> 0.52182156 | K20: =+H20+I20 -> 1.4192937
B21: Total | D21: =SUM(D9:D20) -> 7565.96 | E21: =SUM(E9:E20) -> 3262.03 | F21: =SUM(F9:F20) -> 10827.99 | G21: =SUM(G9:G20) -> 8278 | H21: =D21/G21 -> 0.91398405 | I21: =E21/G21 -> 0.39406016 | K21: =+F21/G21 -> 1.3080442
D23: =D7 -> Con Ed #49-4182-7002-0000-8
B24: =B8+1 -> 2025 | D24: =+D8 -> Con Ed | E24: =E8 -> Esco | F24: Total | G24: Therms | H24: Con Ed Therms | I24: =I8 -> EscoTherms | K24: $/Per Therm | M24: Direct Energy Effecive 01/2019 account #686734-61005
B25: January | D25: 836.04 | E25: 356.04 | F25: =D25+E25 -> 1192.08 | G25: 893 | H25: =+D25/G25 -> 0.93621501 | I25: =E25/G25 -> 0.39870101 | K25: =+H25+I25 -> 1.334916 | M25: Includes the Gas cooking now - must break out for both
B26: February | D26: 735.09 | E26: 305.71 | F26: =D26+E26 -> 1040.8 | G26: 759 | H26: =D26/G26 -> 0.96849802 | I26: =E26/G26 -> 0.40277997 | K26: =SUM(H26:I26) -> 1.371278
B27: March | D27: 709.7 | E27: 303.46 | F27: =D27+E27 -> 1013.16 | G27: 728 | H27: =D27/G27 -> 0.97486264 | I27: =E27/G27 -> 0.41684066 | K27: =SUM(H27:I27) -> 1.3917033
B28: April | D28: 706.93 | E28: 293.57 | F28: =D28+E28 -> 1000.5 | G28: 727 | H28: =D28/G28 -> 0.9723934 | I28: =E28/G28 -> 0.40381018 | K28: =SUM(H28:I28) -> 1.3762036
B29: May | D29: 811 | E29: 455.71 | F29: =D29+E29 -> 1266.71 | G29: 837 | H29: =D29/G29 -> 0.96893668 | I29: =E29/G29 -> 0.54445639 | K29: =SUM(H29:I29) -> 1.5133931
B30: June | D30: 731.97 | E30: 396.6 | F30: =D30+E30 -> 1128.57 | G30: 742 | H30: =D30/G30 -> 0.98648248 | I30: =E30/G30 -> 0.53450135 | K30: =SUM(H30:I30) -> 1.5209838
B31: July | D31: 657.38 | E31: 344.2 | F31: =D31+E31 -> 1001.58 | G31: 665 | H31: =D31/G31 -> 0.98854135 | I31: =E31/G31 -> 0.51759398 | K31: =SUM(H31:I31) -> 1.5061353
B32: August | C32: Est | D32: =+G32*H32 -> 525.83505 | E32: =+G32*I32 -> 336.117 | F32: =D32+E32 -> 861.95205 | G32: =+(G16+G79)/2 -> 619 | H32: =SUM(H25:H31)/8 -> 0.8494912 | I32: 0.543 | K32: =SUM(H32:I32) -> 1.3924912
B33: September | C33: Est | D33: =+G33*H33 -> 638.81738 | E33: =+G33*I33 -> 408.336 | F33: =D33+E33 -> 1047.1534 | G33: =+(G17+G80)/2 -> 752 | H33: =H32 -> 0.8494912 | I33: =I32 -> 0.543 | K33: =SUM(H33:I33) -> 1.3924912
B34: October | C34: Est | D34: =+G34*H34 -> 612.05841 | E34: =+G34*I34 -> 391.2315 | F34: =D34+E34 -> 1003.2899 | G34: =+(G18+G81)/2 -> 720.5 | H34: =H32 -> 0.8494912 | I34: =I32 -> 0.543 | K34: =SUM(K25:K33)/9 -> 1.4221773
B35: November | C35: Est | D35: =+G35*H35 -> 607.38621 | E35: =+G35*I35 -> 388.245 | F35: =D35+E35 -> 995.63121 | G35: =+(G19+G82)/2 -> 715 | H35: =H32 -> 0.8494912 | I35: =I32 -> 0.543 | K35: =K34 -> 1.4221773
B36: December | C36: Est | D36: =+G36*H36 -> 701.25498 | E36: =+G36*I36 -> 448.2465 | F36: =D36+E36 -> 1149.5015 | G36: =+(G20+G83)/2 -> 825.5 | H36: =H32 -> 0.8494912 | I36: =I32 -> 0.543 | K36: =+K35 -> 1.4221773
B37: Total | D37: =SUM(D25:D36) -> 8273.462 | E37: =SUM(E25:E36) -> 4427.466 | F37: =SUM(F25:F36) -> 12700.928 | G37: =SUM(G25:G36) -> 8983 | H37: =D37/G37 -> 0.92101325 | I37: =E37/G37 -> 0.49287165 | K37: =+F37/G37 -> 1.4138849
B39: Budget | D39: =D7 -> Con Ed #49-4182-7002-0000-8
B40: =B24+1 -> 2026 | D40: =D8 -> Con Ed | E40: =E24 -> Esco | F40: Total | G40: Therms | H40: Con Ed Therms | I40: =I24 -> EscoTherms | K40: $/Per Therm
B41: January | D41: =+G41*H41 -> 873.57286 | E41: =+G41*I41 -> 492.5733 | F41: =+D41+E41 -> 1366.1462 | G41: =(G9+G25)/2 -> 818.5 | H41: =+H25*$I$57+H25 -> 1.0672851 | I41: =I62 -> 0.6018 | K41: =H41+I41 -> 1.6690851
B42: February | D42: =+G42*H42 -> 830.27399 | E42: =+G42*I42 -> 452.5536 | F42: =+D42+E42 -> 1282.8276 | G42: =(G10+G26)/2 -> 752 | H42: =+H26*$I$57+H26 -> 1.1040877 | I42: =I62 -> 0.6018 | K42: =H42+I42 -> 1.7058877
B43: March | D43: =+G43*H43 -> 772.93934 | E43: =+G43*I43 -> 418.5519 | F43: =+D43+E43 -> 1191.4912 | G43: =(G11+G27)/2 -> 695.5 | H43: =+H27*$I$57+H27 -> 1.1113434 | I43: =I62 -> 0.6018 | K43: =H43+I43 -> 1.7131434
B44: April | D44: =+G44*H44 -> 778.74125 | E44: =+G44*I44 -> 422.7645 | F44: =+D44+E44 -> 1201.5058 | G44: =(G12+G28)/2 -> 702.5 | H44: =+H28*$I$57+H28 -> 1.1085285 | I44: =I62 -> 0.6018 | K44: =H44+I44 -> 1.7103285
B45: May | D45: =+G45*H45 -> 845.56197 | E45: =+G45*I45 -> 460.6779 | F45: =+D45+E45 -> 1306.2399 | G45: =(G13+G29)/2 -> 765.5 | H45: =+H29*$I$57+H29 -> 1.1045878 | I45: =I62 -> 0.6018 | K45: =H45+I45 -> 1.7063878
B46: June | D46: =+G46*H46 -> 784.96384 | E46: =+G46*I46 -> 420.0564 | F46: =+D46+E46 -> 1205.0202 | G46: =(G14+G30)/2 -> 698 | H46: =+H30*$I$57+H30 -> 1.12459 | I46: =I62 -> 0.6018 | K46: =H46+I46 -> 1.72639
B47: July | D47: =+G47*H47 -> 698.70103 | E47: =+G47*I47 -> 373.116 | F47: =+D47+E47 -> 1071.817 | G47: =(G15+G31)/2 -> 620 | H47: =+H31*$I$57+H31 -> 1.1269371 | I47: =I62 -> 0.6018 | K47: =H47+I47 -> 1.7287371
B48: August | D48: =+G48*H48 -> 585.40987 | E48: =+G48*I48 -> 363.7881 | F48: =+D48+E48 -> 949.19797 | G48: =(G16+G32)/2 -> 604.5 | H48: =+H32*$I$57+H32 -> 0.96841996 | I48: =I62 -> 0.6018 | K48: =H48+I48 -> 1.57022
B49: September | D49: =+G49*H49 -> 714.20972 | E49: =+G49*I49 -> 443.8275 | F49: =+D49+E49 -> 1158.0372 | G49: =(G17+G33)/2 -> 737.5 | H49: =+H33*$I$57+H33 -> 0.96841996 | I49: =I62 -> 0.6018 | K49: =H49+I49 -> 1.57022
B50: October | D50: =+G50*H50 -> 689.27291 | E50: =+G50*I50 -> 428.33115 | F50: =+D50+E50 -> 1117.6041 | G50: =(G18+G34)/2 -> 711.75 | H50: =+H34*$I$57+H34 -> 0.96841996 | I50: =I62 -> 0.6018 | K50: =H50+I50 -> 1.57022
B51: November | D51: =+G51*H51 -> 686.12554 | E51: =+G51*I51 -> 426.3753 | F51: =+D51+E51 -> 1112.5008 | G51: =(G19+G35)/2 -> 708.5 | H51: =+H35*$I$57+H35 -> 0.96841996 | I51: =I62 -> 0.6018 | K51: =H51+I51 -> 1.57022
B52: December | D52: =+G52*H52 -> 790.4728 | E52: =+G52*I52 -> 491.21925 | F52: =+D52+E52 -> 1281.692 | G52: =(G20+G36)/2 -> 816.25 | H52: =+H36*$I$57+H36 -> 0.96841996 | I52: =I62 -> 0.6018 | K52: =H52+I52 -> 1.57022
B53: Total | D53: =SUM(D41:D52) -> 9050.2451 | E53: =SUM(E41:E52) -> 5193.8349 | F53: =SUM(F41:F52) -> 14244.08 | G53: =SUM(G41:G52) -> 8630.5 | H53: =D53/G53 -> 1.0486351 | I53: =E53/G53 -> 0.6018 | K53: =+F53/G53 -> 1.6504351
B55: =Electric!B55 -> 2026 Budget Assumptions:
B56: 2026 Budget Gas Usage: Prio two year average consumption
B57: 2026 Con Ed Budget Price relects an increase over prior year costs @ | I57: 0.14
N58: New contract with Direct Energy for 2021 expires December
B59: 2025 August - December Gas Usage: Prior Period Two Year Average
B60: 2025 August - December Gas Price is at 2025 YTD Average $/Therm
B62: Contract Price for ESCO: 07/01/2025-06/30/2027 | I62: 0.6018
E66: Page 9
D70: Con Ed #49-4182-7002-0000-8
B71: ='Electric 2'!B71 -> 2023 | D71: Con Ed | E71: Direct Energy | F71: Total | G71: Therms | H71: Con Ed Therms | I71: Direct Energy Therms | K71: $/Per Therm
B72: January | D72: 678.85 | E72: 700.59 | F72: 1379.44 | G72: 809 | H72: 0.83912237 | I72: 0.86599506 | K72: 1.7051174
B73: February | D73: 658.37 | E73: 700.59 | F73: 1358.96 | G73: 795 | H73: 0.82813836 | I73: 0.88124528 | K73: 1.7093836
B74: March | D74: 559.67 | E74: 400.91 | F74: 960.58 | G74: 672 | H74: 0.83284226 | I74: 0.59659226 | K74: 1.4294345
B75: April | D75: 572.83 | E75: 394.93 | F75: 967.76 | G75: 695 | H75: 0.82421583 | I75: 0.5682446 | K75: 1.3924604
B76: May | D76: 558.12 | E76: 408.41 | F76: 966.53 | G76: 706 | H76: 0.79053824 | I76: 0.57848442 | K76: 1.3690227
B77: June | D77: 620.63 | E77: 473.93 | F77: 1094.56 | G77: 817 | H77: 0.75964504 | I77: 0.58008568 | K77: 1.3397307
B78: July | D78: 524.34 | E78: 314.8 | F78: 839.14 | G78: 679 | H78: 0.77222386 | I78: 0.46362297 | K78: 1.2358468
B79: August | D79: 541.8 | E79: 282.42 | F79: 824.22 | G79: 648 | H79: 0.83611111 | I79: 0.43583333 | K79: 1.2719444
B80: September | D80: 662.91 | E80: 342.96 | F80: 1005.87 | G80: 781 | H80: 0.84879641 | I80: 0.43912932 | K80: 1.2879257
B81: October | D81: 624.63 | E81: 339.36 | F81: 963.99 | G81: 738 | H81: 0.84638211 | I81: 0.4598374 | K81: 1.3062195
B82: November | D82: 614.57 | E82: 362.59 | F82: 977.16 | G82: 728 | H82: 0.84418956 | I82: 0.49806319 | K82: 1.3422527
B83: December | D83: 711.33 | E83: 396.04 | F83: 1107.37 | G83: 844 | H83: 0.84280806 | I83: 0.46924171 | K83: 1.3120498
B84: Total | D84: =SUM(D72:D83) -> 7328.05 | E84: =SUM(E72:E83) -> 5117.53 | F84: =SUM(F72:F83) -> 12445.58 | G84: =SUM(G72:G83) -> 8912 | H84: =D84/G84 -> 0.82226773 | I84: =E84/G84 -> 0.57422913 | K84: =+F84/G84 -> 1.3964969

Sheet Gas-Heat
F1: =+yrlycomp!H1 -> 444 East 86th Street Owners Corp.
F2: Gas - Heating
B3: Schedule D | F3: =+yrlycomp!H3 -> For Year Ending 12/31/2026
B5: G/L
B6: 5252-0000
D7: Con Ed #42-2039-0422-3701-4 new #71914-82000-7
B8: =Electric!B8 -> 2024 | D8: Con Ed | E8: Esco | F8: Total | G8: Therms | H8: Con Ed Therms | I8: Esco Therms | K8: $/Per Therm | M8: 71914820007
B9: January | D9: 41599.47 | E9: 13486.56 | F9: =+D9+E9 -> 55086.03 | G9: 29976 | H9: =+D9/G9 -> 1.3877592 | I9: =+E9/G9 -> 0.44991193 | K9: =+H9+J9 -> 1.3877592
B10: February | D10: 40952.65 | E10: 12511.05 | F10: =+D10+E10 -> 53463.7 | G10: 28535 | H10: =+D10/G10 -> 1.4351726 | I10: =+E10/G10 -> 0.43844577 | K10: =+H10+J10 -> 1.4351726
B11: March | D11: 34714.26 | E11: 7675.04 | F11: =+D11+E11 -> 42389.3 | G11: 21963 | H11: =+D11/G11 -> 1.5805792 | I11: =+E11/G11 -> 0.34945317 | K11: =+H11+J11 -> 1.5805792
B12: April | D12: 23516.64 | E12: 5913.37 | F12: =+D12+E12 -> 29430.01 | G12: 17595 | H12: =+D12/G12 -> 1.3365524 | I12: =+E12/G12 -> 0.33608241 | K12: =+H12+J12 -> 1.3365524
B13: May | D13: 11568.05 | E13: 2912.99 | F13: =+D13+E13 -> 14481.04 | G13: 8277 | H13: =+D13/G13 -> 1.3976139 | I13: =+E13/G13 -> 0.3519379 | K13: =+H13+J13 -> 1.3976139
B14: June | D14: 19171.87 | E14: 6279.55 | F14: =+D14+E14 -> 25451.42 | G14: 15284 | H14: =+D14/G14 -> 1.2543752 | I14: =+E14/G14 -> 0.41085776 | K14: =+H14+J14 -> 1.2543752
B15: July | D15: 37599.95 | E15: 14393.29 | F15: =+D15+E15 -> 51993.24 | G15: 32250 | H15: =+D15/G15 -> 1.1658899 | I15: =+E15/G15 -> 0.44630357 | K15: =+H15+J15 -> 1.1658899
B16: August | D16: 34001.47 | E16: 11368.91 | F16: =+D16+E16 -> 45370.38 | G16: 29146 | H16: =+D16/G16 -> 1.1665913 | I16: =+E16/G16 -> 0.39006759 | K16: =+H16+J16 -> 1.1665913 | M16: Direct Energy Effecive 01/2019 account #686734-61005
B17: September | D17: 30644.37 | E17: 9834.27 | F17: =+D17+E17 -> 40478.64 | G17: 26363 | H17: =+D17/G17 -> 1.1624007 | I17: =+E17/G17 -> 0.37303304 | K17: =+H17+J17 -> 1.1624007 | M17: Includes the Gas cooking now - must break out for both
B18: October | D18: 19435.45 | E18: 6297.12 | F18: =+D18+E18 -> 25732.57 | G18: 14731 | H18: =+D18/G18 -> 1.3193571 | I18: =+E18/G18 -> 0.42747403 | K18: =+H18+J18 -> 1.3193571
B19: November | D19: 17283.31 | E19: 4514.81 | F19: =+D19+E19 -> 21798.12 | G19: 10289 | H19: =+D19/G19 -> 1.6797852 | I19: =+E19/G19 -> 0.43879969 | K19: =+H19+J19 -> 1.6797852
B20: December | D20: 28219 | E20: 13743.8 | F20: =+D20+E20 -> 41962.8 | G20: 26346 | H20: =+D20/G20 -> 1.0710924 | I20: =+E20/G20 -> 0.52166553 | K20: =+H20+J20 -> 1.0710924
B21: Total | D21: =SUM(D9:D20) -> 338706.49 | E21: =SUM(E9:E20) -> 108930.76 | F21: =SUM(F9:F20) -> 447637.25 | G21: =SUM(G9:G20) -> 260755 | H21: =D21/G21 -> 1.2989453 | I21: =E21/G21 -> 0.41775138 | K21: =+F21/G21 -> 1.7166967
D23: =D7 -> Con Ed #42-2039-0422-3701-4 new #71914-82000-7
B24: =B8+1 -> 2025 | D24: =+D8 -> Con Ed | E24: =E8 -> Esco | F24: Total | G24: Therms | H24: Con Ed Therms | I24: =I8 -> Esco Therms | K24: $/Per Therm
B25: January | D25: 38991.59 | E25: 18405.13 | F25: =D25+E25 -> 57396.72 | G25: 32561 | H25: =+D25/G25 -> 1.1974936 | I25: =E25/G25 -> 0.56525076 | K25: =+H25+I25 -> 1.7627444
B26: February | D26: 34773.34 | E26: 15898.09 | F26: =D26+E26 -> 50671.43 | G26: 27628 | H26: =D26/G26 -> 1.2586268 | I26: =E26/G26 -> 0.57543398 | K26: =SUM(H26:I26) -> 1.8340607
B27: March | D27: 28840.02 | E27: 11090.18 | F27: =D27+E27 -> 39930.2 | G27: 17984 | H27: =D27/G27 -> 1.6036488 | I27: =E27/G27 -> 0.61666926 | K27: =SUM(H27:I27) -> 2.2203181
B28: April | D28: 19843.78 | E28: 8857.14 | F28: =D28+E28 -> 28700.92 | G28: 14132 | H28: =D28/G28 -> 1.4041735 | I28: =E28/G28 -> 0.62674356 | K28: =SUM(H28:I28) -> 2.0309171
B29: May | D29: 23441.35 | E29: 7893.65 | F29: =D29+E29 -> 31335 | G29: 14496 | H29: =D29/G29 -> 1.6170909 | I29: =E29/G29 -> 0.54453987 | K29: =SUM(H29:I29) -> 2.1616308
B30: June | D30: 32280.14 | E30: 13333.76 | F30: =D30+E30 -> 45613.9 | G30: 24950 | H30: =D30/G30 -> 1.2937932 | I30: =E30/G30 -> 0.53441924 | K30: =SUM(H30:I30) -> 1.8282124 | L30: NO NRG Bills, values taken from General Ledger
B31: July | D31: 51449.45 | E31: 20915 | F31: =D31+E31 -> 72364.45 | G31: 40465 | H31: =+AVERAGE(H25:H30) -> 1.3958045 | I31: =+AVERAGE(I26:I30) -> 0.57956118 | K31: =SUM(H31:I31) -> 1.9753656
B32: August | C32: Est | D32: =+G32*H32 -> 43162.89 | E32: =+G32*I32 -> 16402.944 | F32: =D32+E32 -> 59565.834 | G32: =(G16+G88)/2 -> 30208 | H32: =+AVERAGE(H26:H31) -> 1.4288563 | I32: 0.543 | K32: =SUM(H32:I32) -> 1.9718563
B33: September | C33: Est | D33: =+G33*H33 -> 42894.959 | E33: =+G33*I33 -> 15983.748 | F33: =D33+E33 -> 58878.707 | G33: =(G17+G89)/2 -> 29436 | H33: =+AVERAGE(H27:H32) -> 1.4572279 | I33: 0.543 | K33: =SUM(H33:I33) -> 2.0002279
B34: October | C34: Est | D34: =+G34*H34 -> 20877.684 | E34: =+G34*I34 -> 7912.053 | F34: =D34+E34 -> 28789.737 | G34: =(G18+G90)/2 -> 14571 | H34: =+AVERAGE(H28:H33) -> 1.4328244 | I34: 0.543 | K34: =SUM(K25:K33)/9 -> 1.9761481
B35: November | C35: Est | D35: =+G35*H35 -> 17605.562 | E35: =+G35*I35 -> 6649.8495 | F35: =D35+E35 -> 24255.412 | G35: =(G19+G91)/2 -> 12246.5 | H35: =+AVERAGE(H29:H34) -> 1.4375995 | I35: 0.543 | K35: =K34 -> 1.9761481
B36: December | C36: Est | D36: =+G36*H36 -> 44263.928 | E36: =+G36*I36 -> 17074.363 | F36: =D36+E36 -> 61338.292 | G36: =(G20+G92)/2 -> 31444.5 | H36: =+AVERAGE(H30:H35) -> 1.4076843 | I36: 0.543 | K36: =+K35 -> 1.9761481
B37: Total | D37: =SUM(D25:D36) -> 398424.69 | E37: =SUM(E25:E36) -> 160415.91 | F37: =SUM(F25:F36) -> 558840.6 | G37: =SUM(G25:G36) -> 290122 | H37: =D37/G37 -> 1.3733005 | I37: =E37/G37 -> 0.55292569 | K37: =+F37/G37 -> 1.9262262
B39: Budget | D39: =D23 -> Con Ed #42-2039-0422-3701-4 new #71914-82000-7
B40: =B24+1 -> 2026 | D40: =D8 -> Con Ed | E40: =E24 -> Esco | F40: Total | G40: Therms | H40: Con Ed Therms | I40: =I24 -> Esco Therms | K40: $/Per Therm
B41: January | D41: 38942 | E41: =+G41*I41 -> 18817.383 | F41: =+D41+E41 -> 57759.383 | G41: =(G9+G25)/2 -> 31268.5 | H41: =+H25*$I$57+H25 -> 1.3651427 | I41: =I62 -> 0.6018 | K41: =H41+I41 -> 1.9669427 | N41: therms now at 2 year average
B42: February | D42: 41112 | E42: =+G42*I42 -> 16899.447 | F42: =+D42+E42 -> 58011.447 | G42: =(G10+G26)/2 -> 28081.5 | H42: =+H26*$I$57+H26 -> 1.4348345 | I42: =I62 -> 0.6018 | K42: =H42+I42 -> 2.0366345 | M42: redo formula for 2026
B43: March | D43: =+G43*H43 -> 36514.746 | E43: =+G43*I43 -> 12020.052 | F43: =+D43+E43 -> 48534.799 | G43: =(G11+G27)/2 -> 19973.5 | H43: =+H27*$I$57+H27 -> 1.8281596 | I43: =I62 -> 0.6018 | K43: =H43+I43 -> 2.4299596
B44: April | D44: 19356 | E44: =+G44*I44 -> 9546.6543 | F44: =+D44+E44 -> 28902.654 | G44: =(G12+G28)/2 -> 15863.5 | H44: =+H28*$I$57+H28 -> 1.6007578 | I44: =I62 -> 0.6018 | K44: =H44+I44 -> 2.2025578
B45: May | D45: =+G45*H45 -> 20990.827 | E45: =+G45*I45 -> 6852.3957 | F45: =+D45+E45 -> 27843.222 | G45: =(G13+G29)/2 -> 11386.5 | H45: =+H29*$I$57+H29 -> 1.8434837 | I45: =I62 -> 0.6018 | K45: =H45+I45 -> 2.4452837
B46: June | D46: 24840 | E46: =+G46*I46 -> 12106.411 | F46: =+D46+E46 -> 36946.411 | G46: =(G14+G30)/2 -> 20117 | H46: =+H30*$I$57+H30 -> 1.4749242 | I46: =I62 -> 0.6018 | K46: =H46+I46 -> 2.0767242 | M46: change forula for 2026 july and august figures
B47: July | D47: 33213 | E47: =+G47*I47-1000 -> 20879.944 | F47: =+D47+E47 -> 54092.944 | G47: =(G15+G31)/2 -> 36357.5 | H47: =+H31*$I$57+H31 -> 1.5912171 | I47: =I62 -> 0.6018 | K47: =H47+I47 -> 2.1930171
B48: August | D48: =+G48*H48-5000 -> 43340.751 | E48: =+G48*I48-1000 -> 16859.619 | F48: =+D48+E48 -> 60200.37 | G48: =(G16+G32)/2 -> 29677 | H48: =+H32*$I$57+H32 -> 1.6288962 | I48: =I62 -> 0.6018 | K48: =H48+I48 -> 2.2306962
B49: September | D49: =+G49*H49 -> 46347.759 | E49: =+G49*I49 -> 16789.919 | F49: =+D49+E49 -> 63137.678 | G49: =(G17+G33)/2 -> 27899.5 | H49: =+H33*$I$57+H33 -> 1.6612398 | I49: =I62 -> 0.6018 | K49: =H49+I49 -> 2.2630398
B50: October | D50: =+G50*H50 -> 23931.233 | E50: =+G50*I50 -> 8816.9718 | F50: =+D50+E50 -> 32748.205 | G50: =(G18+G34)/2 -> 14651 | H50: =+H34*$I$57+H34 -> 1.6334198 | I50: =I62 -> 0.6018 | K50: =H50+I50 -> 2.2352198
B51: November | D51: =+G51*H51 -> 18466.304 | E51: =+G51*I51 -> 6780.932 | F51: =+D51+E51 -> 25247.236 | G51: =(G19+G35)/2 -> 11267.75 | H51: =+H35*$I$57+H35 -> 1.6388634 | I51: =I62 -> 0.6018 | K51: =H51+I51 -> 2.2406634
B52: December | D52: 44642 | E52: =+G52*I52 -> 17389.161 | F52: =+D52+E52 -> 62031.161 | G52: =(G20+G36)/2 -> 28895.25 | H52: =+H36*$I$57+H36 -> 1.6047601 | I52: =I62 -> 0.6018 | K52: =H52+I52 -> 2.2065601
B53: Total | D53: =SUM(D41:D52) -> 391696.62 | E53: =SUM(E41:E52) -> 163758.89 | F53: =SUM(F41:F52) -> 555455.51 | G53: =SUM(G41:G52) -> 275438.5 | H53: =D53/G53 -> 1.4220838 | I53: =E53/G53 -> 0.59453885 | K53: =+F53/G53 -> 2.0166226
B55: =Electric!B55 -> 2026 Budget Assumptions:
B56: ='Gas Cooking'!B56 -> 2026 Budget Gas Usage: Prio two year average consumption
B57: ='Gas Cooking'!B57 -> 2026 Con Ed Budget Price relects an increase over prior year costs @ | I57: 0.14
N58: New contract with Direct Energy for 2020 expires December
B59: ='Gas Cooking'!B59 -> 2025 August - December Gas Usage: Prior Period Two Year Average
B60: ='Gas Cooking'!B60 -> 2025 August - December Gas Price is at 2025 YTD Average $/Therm
B62: Contract Proce for ESCO: 07/01/2025-06/30/2027 | I62: 0.6018
F71: Page 10
D79: Con Ed #42-2039-0422-3701-4
B80: =Electric!B70 -> 2023 | D80: Con Ed | E80: Direct Energy | F80: Total | G80: Therms | H80: Con Ed Therms | I80: Direct Energy Therms | K80: $/Per Therm
B81: January | D81: 33893.31 | E81: 18833.04 | F81: 52726.35 | G81: 24975 | H81: 1.3570895 | I81: 0.75407568 | K81: 2.1111652
B82: February | D82: 36022.57 | E82: 18450.27 | F82: 54472.84 | G82: 27349 | H82: 1.317144 | I82: 0.6746232 | K82: 1.9917672
B83: March | D83: 25776.45 | E83: 13320.36 | F83: 39096.81 | G83: 22323 | H83: 1.1547037 | I83: 0.59671012 | K83: 1.7514138
B84: April | D84: 17334.05 | E84: 7281.09 | F84: 24615.14 | G84: 12817 | H84: 1.3524265 | I84: 0.56808067 | K84: 1.9205071
B85: May | D85: 19133.09 | E85: 10539.2 | F85: 29672.29 | G85: 18228 | H85: 1.0496538 | I85: 0.5781874 | K85: 1.6278412
B86: June | D86: 24808.13 | E86: 14542.3 | F86: 39350.43 | G86: 25070 | H86: 0.98955445 | I86: 0.58006781 | K86: 1.5696223
B87: July | D87: 34285.78 | E87: 16195.78 | F87: 50481.56 | G87: 34920 | H87: 0.98183792 | I87: 0.46379668 | K87: 1.4456346
B88: August | D88: 34449.36 | E88: 13632.86 | F88: 48082.22 | G88: 31270 | H88: 1.1016744 | I88: 0.4359725 | K88: 1.5376469
B89: September | D89: 37013.56 | E89: 14281.56 | F89: 51295.12 | G89: 32509 | H89: 1.1385635 | I89: 0.43931096 | K89: 1.5778744
B90: October | D90: 18089.9 | E90: 6622.99 | F90: 24712.89 | G90: 14411 | H90: 1.2552842 | I90: 0.45957879 | K90: 1.7259414
B91: November | D91: 17534.68 | E91: 7071.85 | F91: 24606.53 | G91: 14204 | H91: 1.2344889 | I91: 0.55504038 | K91: 1.7259414
B92: December | D92: 33781.61 | E92: 12459.61 | F92: 46241.22 | G92: 36543 | H92: 0.9244345 | I92: 0.3409575 | K92: 1.265392
B93: Total | D93: =SUM(D81:D92) -> 332122.49 | E93: =SUM(E81:E92) -> 153230.91 | F93: =SUM(F81:F92) -> 485353.4 | G93: =SUM(G81:G92) -> 294619 | H93: =D93/G93 -> 1.1272949 | I93: =E93/G93 -> 0.52009853 | K93: =+F93/G93 -> 1.6473934

Sheet Repairs & Supplies
B1: Schedule F | E1: =+yrlycomp!H1 -> 444 East 86th Street Owners Corp.
E2: Supplies,Repairs, & Maintenance
E3: =+yrlycomp!H3 -> For Year Ending 12/31/2026
D5: =+yrlycomp!H7 -> 2025 | E5: Accrual | F5: Unpaids | G5: =+D5 -> 2025 | H5: =+G5 -> 2025 | I5: =+H5 -> 2025 | J5: =+I5+1 -> 2026
D6: Jan - Aug | E6: Adjustments | F6: @08/31/25 | G6: Sep - Dec | H6: 12 Month | I6: Budget | J6: Budget | N6: =675000-J57 -> -0.2576
A7: GL Code | B7: Supplies | D7: Actual | G7: Est | H7: Forecast
A8: 5406-0000 | B8: Supplies & Hardware | D8: =SUMIF('VLookup Data'!$A:$A,A8,'VLookup Data'!$E:$E) -> 45896.47 | E8: =-1054.6-136.08-1884.28+90 -> -2984.96 | F8: =1355.55 -> 1355.55 | G8: =SUM(D8:F8)/8*4 -> 22133.53 | H8: =SUM(D8:G8) -> 66400.59 | I8: 90000 | J8: 90000
B9: Total Supplies | D9: =SUM(D8:D8) -> 45896.47 | E9: =SUM(E8:E8) -> -2984.96 | F9: =SUM(F8:F8) -> 1355.55 | G9: =SUM(G8:G8) -> 22133.53 | H9: =SUM(H8:H8) -> 66400.59 | I9: =SUM(I8) -> 90000 | J9: =SUM(J8:J8) -> 90000
B11: Repairs
A12: 5606-0000 | B12: Insurance Repairs | D12: =SUMIF('VLookup Data'!$A:$A,A12,'VLookup Data'!$E:$E) -> 0 | E12: 0 | F12: 0 | G12: =SUM(D12:F12)/8*4 -> 0 | H12: =SUM(D12:G12) -> 0 | I12: 0 | J12: 0
A13: 5609-0000 | B13: =_xlfn.XLOOKUP(A13,'VLookup Data'!A:A,'VLookup Data'!B:B) -> Appliance Repairs | D13: =SUMIF('VLookup Data'!$A:$A,A13,'VLookup Data'!$E:$E) -> 0 | E13: 0 | F13: 0 | G13: =SUM(D13:F13)/8*4 -> 0 | H13: =SUM(D13:G13) -> 0 | I13: 0 | J13: 0
A14: 5621-0000 | B14: Equipment Repairs | D14: =SUMIF('VLookup Data'!$A:$A,A14,'VLookup Data'!$E:$E) -> 0 | E14: 0 | F14: 0 | G14: =SUM(D14:F14)/8*4 -> 0 | H14: =SUM(D14:G14) -> 0 | I14: 2000 | J14: 2000
B15: Heating Repairs | D15: =SUMIF('VLookup Data'!$A:$A,A15,'VLookup Data'!$E:$E) -> 0 | E15: 0 | F15: 0 | G15: =SUM(D15:F15)/8*4 -> 0 | H15: =SUM(D15:G15) -> 0 | I15: 0 | J15: 0
A16: 5627-0000 | B16: Boiler/Burner Repairs | D16: =SUMIF('VLookup Data'!$A:$A,A16,'VLookup Data'!$E:$E) -> 2955.95 | E16: =-658.69-2297.26 -> -2955.95 | F16: =1350.05 -> 1350.05 | G16: =SUM(D16:F16)/8*4 -> 675.025 | H16: =SUM(D16:G16) -> 2025.075 | I16: 35000 | J16: 20000
A17: 5630-0000 | B17: Plumbing Repairs | D17: =SUMIF('VLookup Data'!$A:$A,A17,'VLookup Data'!$E:$E) -> 248790.47 | E17: =-1360.94-961-6858.52-1237.18-7603.83-1334.81-1001.65-3024.55-2882.67 -> -26265.15 | F17: =1627.68 -> 1627.68 | G17: =SUM(D17:F17)/8*4 -> 112076.5 | H17: =SUM(D17:G17) -> 336229.5 | I17: 200000 | J17: 330000
A18: 5630-0001 | B18: Pump/Motor Repair | D18: =SUMIF('VLookup Data'!$A:$A,A18,'VLookup Data'!$E:$E) -> 10038.28 | E18: 0 | F18: 0 | G18: 0 | H18: =SUM(D18:G18) -> 10038.28 | I18: 5000 | J18: 5000
A19: 5633-0000 | B19: Electrical Repairs | D19: =SUMIF('VLookup Data'!$A:$A,A19,'VLookup Data'!$E:$E) -> 3290.21 | E19: 0 | F19: 0 | G19: =SUM(D19:F19)/8*4 -> 1645.105 | H19: =SUM(D19:G19) -> 4935.315 | I19: 10000 | J19: 10000
A20: 5636-0000 | B20: Air Conditioning Repairs | D20: =SUMIF('VLookup Data'!$A:$A,A20,'VLookup Data'!$E:$E) -> 25933.16 | E20: 0 | F20: 0 | G20: 0 | H20: =SUM(D20:G20) -> 25933.16 | I20: 31000 | J20: 31000
A21: 5639-0000 | B21: Elevator Repairs | D21: =SUMIF('VLookup Data'!$A:$A,A21,'VLookup Data'!$E:$E) -> 11660.51 | E21: 0 | F21: 0 | G21: 0 | H21: =SUM(D21:G21) -> 11660.51 | I21: 0 | J21: 5000
A22: 5642-0000 | B22: Compactor / Incinerator Repairs | D22: =SUMIF('VLookup Data'!$A:$A,A22,'VLookup Data'!$E:$E) -> 0 | E22: 0 | F22: 0 | G22: =SUM(D22:F22)/8*4 -> 0 | H22: =SUM(D22:G22) -> 0 | I22: 0 | J22: 0
A23: 5645-0000 | B23: Window Repairs | D23: =SUMIF('VLookup Data'!$A:$A,A23,'VLookup Data'!$E:$E) -> 40490.67 | E23: -8296.28 | F23: 0 | G23: 0 | H23: =SUM(D23:G23) -> 32194.39 | I23: 10000 | J23: 11000
A24: 5648-0000 | B24: Floor / Carpet Repair | D24: =SUMIF('VLookup Data'!$A:$A,A24,'VLookup Data'!$E:$E) -> 0 | E24: 0 | F24: 0 | G24: =SUM(D24:F24)/8*4 -> 0 | H24: =SUM(D24:G24) -> 0 | I24: 5000 | J24: 2000
A25: 5657-0000 | B25: Lobby Repairs | D25: =SUMIF('VLookup Data'!$A:$A,A25,'VLookup Data'!$E:$E) -> 0 | E25: 0 | F25: 0 | G25: =SUM(D25:F25)/8*4 -> 0 | H25: =SUM(D25:G25) -> 0 | I25: 0 | J25: 0
A26: 5660-0000 | B26: Paint & Plaster Repairs | D26: =SUMIF('VLookup Data'!$A:$A,A26,'VLookup Data'!$E:$E) -> 29650 | E26: =-3000-1850-480 -> -5330 | F26: 0 | G26: =SUM(D26:F26)/8*4 -> 12160 | H26: =SUM(D26:G26) -> 36480 | I26: 35000 | J26: 35000
A27: 5666-0000 | B27: Door Repairs | D27: =SUMIF('VLookup Data'!$A:$A,A27,'VLookup Data'!$E:$E) -> 10109.97 | E27: -3995 | F27: 0 | G27: 0 | H27: =SUM(D27:G27) -> 6114.97 | I27: 2500 | J27: 2500
A28: 5670-0000 | B28: Intercom Repairs | D28: =SUMIF('VLookup Data'!$A:$A,A28,'VLookup Data'!$E:$E) -> 0 | E28: 0 | F28: 0 | G28: =SUM(D28:F28)/8*4 -> 0 | H28: =SUM(D28:G28) -> 0 | I28: 0 | J28: 0
A29: 5672-0000 | B29: Time Recorder Repairs | D29: =SUMIF('VLookup Data'!$A:$A,A29,'VLookup Data'!$E:$E) -> 0 | E29: 0 | F29: 0 | G29: =SUM(D29:F29)/8*4 -> 0 | H29: =SUM(D29:G29) -> 0 | I29: 0 | J29: 0
A30: 5674-0000 | B30: Façade / Waterproofing Repairs | D30: =SUMIF('VLookup Data'!$A:$A,A30,'VLookup Data'!$E:$E) -> 0 | E30: 0 | F30: 0 | G30: =SUM(D30:F30)/8*4 -> 0 | H30: =SUM(D30:G30) -> 0 | I30: 5000 | J30: 2000
A31: 5678-0000 | B31: Roof Tank / Water Tank Repairs | D31: =SUMIF('VLookup Data'!$A:$A,A31,'VLookup Data'!$E:$E) -> 1970.64 | E31: -1970.64 | F31: 0 | G31: =SUM(D31:F31)/8*4 -> 0 | H31: =SUM(D31:G31) -> 0 | I31: 3000 | J31: 3000 | K31: House tank cleaning
A32: 5680-0000 | B32: Roof Exhaust Repairs | D32: =SUMIF('VLookup Data'!$A:$A,A32,'VLookup Data'!$E:$E) -> 0 | E32: 0 | F32: 0 | G32: =SUM(D32:F32)/8*4 -> 0 | H32: =SUM(D32:G32) -> 0 | I32: 1500 | J32: 1000
A33: 5682-0000 | B33: Sprinkler System Repairs | D33: =SUMIF('VLookup Data'!$A:$A,A33,'VLookup Data'!$E:$E) -> 3775.79 | E33: 0 | F33: 0 | G33: =SUM(D33:F33)/8*4 -> 1887.895 | H33: =SUM(D33:G33) -> 5663.685 | I33: 10000 | J33: 10000 | K33: Backflow preventer testing, Rael Maint -FDNY pretest of 2 standpipes
A34: 5692-0000 | B34: Fitness Equipment Repair | D34: =SUMIF('VLookup Data'!$A:$A,A34,'VLookup Data'!$E:$E) -> 0 | E34: 0 | F34: 0 | G34: =SUM(D34:F34)/8*4 -> 0 | H34: =SUM(D34:G34) -> 0 | I34: 2000 | J34: 2000
A35: 5695-0000 | B35: Other Building Repairs | D35: =SUMIF('VLookup Data'!$A:$A,A35,'VLookup Data'!$E:$E) -> 7300 | E35: 0 | F35: 0 | G35: =SUM(D35:F35)/8*4 -> 3650 | H35: =SUM(D35:G35) -> 10950 | I35: 18500 | J35: 10000
B36: Total Repairs | D36: =SUM(D12:D34) -> 388665.65 | E36: =SUM(E12:E34) -> -48813.02 | F36: =SUM(F12:F34) -> 2977.73 | G36: =SUM(G12:G34) -> 128444.52 | H36: =SUM(H12:H34) -> 471274.89 | I36: =SUM(I12:I35) -> 375500 | J36: =SUM(J12:J35) -> 481500
B38: Maintenance
A39: 5803-0000 | B39: Cleaning & Maintenance | D39: =SUMIF('VLookup Data'!$A:$A,A39,'VLookup Data'!$E:$E) -> 0 | E39: 0 | F39: 0 | G39: =SUM(D39:F39)/8*4 -> 0 | H39: =SUM(D39:G39) -> 0 | I39: 0 | J39: 0 | K39: Building disinfecting for COVID-19 in 202
A40: 5810-0000 | B40: HVAC Maintenance | D40: =SUMIF('VLookup Data'!$A:$A,A40,'VLookup Data'!$E:$E) -> 14240.88 | E40: =-460.46-497.99 -> -958.45 | F40: 0 | G40: =1780.11*4 -> 7120.44 | H40: =SUM(D40:G40) -> 20402.87 | I40: 24800 | J40: =21400+3400 -> 24800 | K40: Matco Service $1780.11/mo
A41: 5812-0000 | B41: Elevator Maintenance | D41: =SUMIF('VLookup Data'!$A:$A,A41,'VLookup Data'!$E:$E)-2120 -> 27696.96 | E41: 0 | F41: 0 | G41: =3462.12*4 -> 13848.48 | H41: =SUM(D41:G41) -> 41545.44 | I41: 39567.091 | J41: =((3462.12*4%)+3462.12)*12 -> 43207.258 | K41: PS Marcato $3,462.12/mo
A42: 5815-0000 | B42: Floor/Carpet Cleaning | D42: =SUMIF('VLookup Data'!$A:$A,A42,'VLookup Data'!$E:$E) -> 0 | E42: 0 | F42: 0 | G42: =SUM(D42:F42)/8*4 -> 0 | H42: =SUM(D42:G42) -> 0 | I42: 0 | J42: 0
A43: 5818-0000 | B43: Window Cleaning | D43: =SUMIF('VLookup Data'!$A:$A,A43,'VLookup Data'!$E:$E) -> 0 | E43: 0 | F43: 0 | G43: =SUM(D43:F43)/8*4 -> 0 | H43: =SUM(D43:G43) -> 0 | I43: 0 | J43: 0
A44: 5821-0000 | B44: Fire Extinguisher Maintenance | D44: =SUMIF('VLookup Data'!$A:$A,A44,'VLookup Data'!$E:$E) -> 0 | E44: 0 | F44: =2307.56 -> 2307.56 | G44: =SUM(D44:F44)/8*4 -> 1153.78 | H44: =SUM(D44:G44) -> 3461.34 | I44: 3700 | J44: 3700 | K44: 2x per year $2,307.56
A45: 5825-0000 | B45: Uniform Cleaning & Maintenance | D45: =SUMIF('VLookup Data'!$A:$A,A45,'VLookup Data'!$E:$E) -> 23690.8 | E45: =-2478.5-400-400-400 -> -3678.5 | F45: 0 | G45: =SUM(D45:F45)/8*4 -> 10006.15 | H45: =SUM(D45:G45) -> 30018.45 | I45: 20000 | J45: 30000 | K45: David Leonick-Jerris Cleaners
A46: 5828-0000 | B46: Rubbish Removal | D46: =SUMIF('VLookup Data'!$A:$A,A46,'VLookup Data'!$E:$E) -> 0 | E46: 0 | F46: 0 | G46: =SUM(D46:F46)/8*4 -> 0 | H46: =SUM(D46:G46) -> 0 | I46: 0 | J46: 0
A47: 5831-0000 | B47: Exterminating | D47: =SUMIF('VLookup Data'!$A:$A,A47,'VLookup Data'!$E:$E) -> 12906.22 | E47: =-653.25-471.97-212.31 -> -1337.53 | F47: =481.41 -> 481.41 | G47: =SUM(D47:F47)/8*4 -> 6025.05 | H47: =SUM(D47:G47) -> 18075.15 | I47: 31000 | J47: 31000 | K47: Dial A Bug
A48: 5834-0000 | B48: Cooling Tower Maintenance | D48: =SUMIF('VLookup Data'!$A:$A,A48,'VLookup Data'!$E:$E) -> 5217.28 | E48: 0 | F48: 0 | G48: =SUM(D48:F48)/8*4 -> 2608.64 | H48: =SUM(D48:G48) -> 7825.92 | I48: 7933 | J48: 8293 | K48: Vitralogy Environmental for monitoring $652.16/mo
A49: 5837-0000 | B49: Alarm / Security System Maintenance | D49: =SUMIF('VLookup Data'!$A:$A,A49,'VLookup Data'!$E:$E) -> 3375.13 | E49: 0 | F49: 0 | G49: 0 | H49: =SUM(D49:G49) -> 3375.13 | I49: 2500 | J49: 2500 | K49: Academy Mailbox
A50: 5840-0000 | B50: Metal / Marble/ Wood Maintenance | D50: =SUMIF('VLookup Data'!$A:$A,A50,'VLookup Data'!$E:$E) -> 0 | E50: 0 | F50: 0 | G50: =SUM(D50:F50)/8*4 -> 0 | H50: =SUM(D50:G50) -> 0 | I50: 0 | J50: 0
A51: 5846-0000 | B51: Garage Maintenance | D51: =SUMIF('VLookup Data'!$A:$A,A51,'VLookup Data'!$E:$E) -> 0 | E51: 0 | F51: 0 | G51: =SUM(D51:F51)/8*4 -> 0 | H51: =SUM(D51:G51) -> 0 | I51: 0 | J51: 0
A52: 5852-0000 | B52: Water Treatment Maintenance | D52: =SUMIF('VLookup Data'!$A:$A,A52,'VLookup Data'!$E:$E) -> 9018.12 | E52: 0 | F52: 598.81 | G52: 0 | H52: =SUM(D52:G52) -> 9616.93 | I52: 10000 | J52: 10000 | K52: Cooling Tower water treatment - OCS Chemical
A53: 5856-0000 | B53: Equipment Maintenance - Software | D53: =SUMIF('VLookup Data'!$A:$A,A53,'VLookup Data'!$E:$E) -> 23605.32 | E53: 0 | F53: 0 | G53: 0 | H53: =SUM(D53:G53) -> 23605.32 | I53: 25000 | J53: 25000 | K53: Parity
A54: 5865-0000 | B54: Landscaping | D54: =SUMIF('VLookup Data'!$A:$A,A54,'VLookup Data'!$E:$E) -> 11411.79 | E54: -2084.96 | F54: 0 | G54: =SUM(D54:F54)/8*4 -> 4663.415 | H54: =SUM(D54:G54) -> 13990.245 | I54: 10000 | J54: 15000 | K54: Gabriel Landscaping - NYC Floral Decorators
D55: =SUM(D39:D54) -> 131162.5 | E55: =SUM(E39:E54) -> -8059.44 | F55: =SUM(F39:F54) -> 3387.78 | G55: =SUM(G39:G54) -> 45425.955 | H55: =SUM(H39:H54) -> 171916.79 | I55: =SUM(I39:I54) -> 174500.09 | J55: =SUM(J39:J54) -> 193500.26
B57: Total Repairs & Maintenance | D57: =+D36+D55 -> 519828.15 | E57: =+E36+E55 -> -56872.46 | F57: =+F36+F55 -> 6365.51 | G57: =+G36+G55 -> 173870.48 | H57: =+H36+H55 -> 643191.68 | I57: 461393.01 | J57: =+J36+J55 -> 675000.26
L58: 2025 note
L59: (A) Façade/Waterproofin repairs - Thomas Fenniman window reccomendations
F78: Page 11

Sheet Gen & Admin
B1: Schedule F-1 | E1: =+yrlycomp!H1 -> 444 East 86th Street Owners Corp.
E2: General & Administrative Expenses
E3: =+yrlycomp!H3 -> For Year Ending 12/31/2026
D7: =+yrlycomp!I7 -> 2025 | E7: Accrual | F7: Unpaids | G7: =+D7 -> 2025 | H7: =+G7 -> 2025 | I7: =+H7 -> 2025 | J7: =+I7+1 -> 2026
D8: Jan - Aug | E8: Adjustments | F8: ='Repairs & Supplies'!F6 -> @08/31/25 | G8: Sep - Dec | H8: 12 Month | I8: Budget | J8: Budget
A9: GL Code | D9: Actual | G9: Est | H9: Forecast
B11: Professional Fees
A12: 6505-0000 | B12: Engineering & Architectural Fees | D12: =SUMIF('VLookup Data'!$A:$A,A12,'VLookup Data'!$E:$E) -> 1500 | E12: 0 | F12: 750 | G12: =SUM(D12:F12)/8*4 -> 1125 | H12: =SUM(D12:G12) -> 3375 | I12: 5000 | J12: 5000
A13: 6510-0000 | B13: Management Fees | D13: =SUMIF('VLookup Data'!$A:$A,A13,'VLookup Data'!$E:$E) -> 93380.4 | E13: 0 | F13: 0 | G13: =11672.55*4 -> 46690.2 | H13: =SUM(D13:G13) -> 140070.6 | I13: 140070.63 | J13: =11993.55*12 -> 143922.6
A14: 6515-0000 | B14: Legal Fees | D14: =SUMIF('VLookup Data'!$A:$A,A14,'VLookup Data'!$E:$E) -> 1242.75 | E14: -395 | F14: 0 | G14: =SUM(D14:F14)/8*4 -> 423.875 | H14: =SUM(D14:G14) -> 1271.625 | I14: 10000 | J14: 10000
A15: 6520-0000 | B15: Real Estate Tax Certiorari Fees | D15: =SUMIF('VLookup Data'!$A:$A,A15,'VLookup Data'!$E:$E) -> 500 | E15: 0 | F15: 0 | G15: =SUM(D15:F15)/8*4 -> 250 | H15: =SUM(D15:G15) -> 750 | I15: 500 | J15: 500
A16: 6525-0000 | B16: Accounting Fees | D16: =SUMIF('VLookup Data'!$A:$A,A16,'VLookup Data'!$E:$E) -> 17000 | E16: 0 | F16: 0 | G16: 0 | H16: =SUM(D16:G16) -> 17000 | I16: 16750 | J16: 16750 | K16: Prager Metis
A17: 6590-0000 | B17: Other Professional Fees | D17: =SUMIF('VLookup Data'!$A:$A,A17,'VLookup Data'!$E:$E)-1905 -> 2600 | E17: 0 | F17: 0 | G17: 0 | H17: =SUM(D17:G17) -> 2600 | I17: 3500 | J17: 2600 | K17: Jack Jaffa
D18: =SUM(D12:D17) -> 116223.15 | E18: =SUM(E12:E17) -> -395 | F18: =SUM(F12:F17) -> 750 | G18: =SUM(G12:G17) -> 48489.075 | H18: =SUM(H12:H17) -> 165067.22 | I18: =SUM(I12:I17) -> 175820.63 | J18: =SUM(J12:J17) -> 178772.6
B20: Administrative & Other
A21: 6706-0020 | B21: Water Cooler Expense | D21: =SUMIF('VLookup Data'!$A:$A,A21,'VLookup Data'!$E:$E) -> 0 | E21: 0 | F21: 0 | G21: =SUM(D21:F21)/8*4 -> 0 | H21: =SUM(D21:G21) -> 0 | I21: 0 | J21: 0
A22: 6708-0000 | B22: Stationary & Printing | D22: =SUMIF('VLookup Data'!$A:$A,A22,'VLookup Data'!$E:$E) -> 0 | E22: 0 | F22: 0 | G22: =SUM(D22:F22)/8*4 -> 0 | H22: =SUM(D22:G22) -> 0 | I22: 0 | J22: 0
A23: 6710-0000 | B23: Postage Expense | D23: =SUMIF('VLookup Data'!$A:$A,A23,'VLookup Data'!$E:$E) -> 1447.55 | E23: 0 | F23: 0 | G23: =SUM(D23:F23)/8*4 -> 723.775 | H23: =SUM(D23:G23) -> 2171.325 | I23: 2400 | J23: 2400
A24: 6710-0015 | B24: Messenger Expense | D24: =SUMIF('VLookup Data'!$A:$A,A24,'VLookup Data'!$E:$E) -> 436.3 | E24: =-14.9-14.9 -> -29.8 | F24: 0 | G24: =SUM(D24:F24)/8*4 -> 203.25 | H24: =SUM(D24:G24) -> 609.75 | I24: 275 | J24: 275
A25: 6714-0000 | B25: Telephone Expense | D25: =SUMIF('VLookup Data'!$A:$A,A25,'VLookup Data'!$E:$E) -> 400 | E25: 0 | F25: 0 | G25: =SUM(D25:F25)/8*4 -> 200 | H25: =SUM(D25:G25) -> 600 | I25: 1000 | J25: 1000 | K25: 50/mo Payroll reimb
A26: 6716-0000 | B26: Cable TV Expense | D26: =SUMIF('VLookup Data'!$A:$A,A26,'VLookup Data'!$E:$E) -> 6353.92 | E26: -87.87 | F26: 0 | G26: =SUM(D26:F26)/8*4 -> 3133.025 | H26: =SUM(D26:G26) -> 9399.075 | I26: 8800 | J26: 9400 | K26: RCN increase to 736.81/mo & 79.39/mo
A27: 6718-0000 | B27: Photocopy Expense | D27: =SUMIF('VLookup Data'!$A:$A,A27,'VLookup Data'!$E:$E) -> 2014.3 | E27: 0 | F27: 0 | G27: =SUM(D27:F27)/8*4 -> 1007.15 | H27: =SUM(D27:G27) -> 3021.45 | I27: 4000 | J27: 3500
A28: 6720-0000 | B28: Dues & Subscriptions | D28: =SUMIF('VLookup Data'!$A:$A,A28,'VLookup Data'!$E:$E) -> 17328.56 | E28: 0 | F28: 0 | G28: =467.25*4 -> 1869 | H28: =SUM(D28:G28) -> 19197.56 | I28: 16000 | J28: 20000 | K28: Bldg Link & RAB-Rent Stabilization -SmartCon Solutions
A29: 6722-0000 | B29: Education & Seminars | D29: =SUMIF('VLookup Data'!$A:$A,A29,'VLookup Data'!$E:$E) -> 0 | E29: 0 | F29: 0 | G29: 1500 | H29: =SUM(D29:G29) -> 1500 | I29: 1500 | J29: 1500 | K29: Employee Sexual Harassment Training
A30: 6726-0000 | B30: Inspection Fees & Permits | D30: =SUMIF('VLookup Data'!$A:$A,A30,'VLookup Data'!$E:$E)+2120 -> 6359.1 | E30: 0 | F30: 0 | G30: 0 | H30: =SUM(D30:G30) -> 6359.1 | I30: 6000 | J30: 6000 | K30: benchmarking, rent stabilization, DOB-elevator, NYSDEC reg fee
A31: 6728-0000 | B31: Violations | D31: =SUMIF('VLookup Data'!$A:$A,A31,'VLookup Data'!$E:$E)+1905 -> 4965 | E31: 0 | F31: 0 | G31: 0 | H31: =SUM(D31:G31) -> 4965 | I31: 11125 | J31: 5000
A32: 6732-0000 | B32: Meter Reading Charges | D32: =SUMIF('VLookup Data'!$A:$A,A32,'VLookup Data'!$E:$E) -> 690 | E32: 0 | F32: 0 | G32: =SUM(D32:F32)/8*4 -> 345 | H32: =SUM(D32:G32) -> 1035 | I32: 1000 | J32: 1100 | K32: Vantage 230/qtr
A33: 6734-0000 | B33: Gratuities | D33: =SUMIF('VLookup Data'!$A:$A,A33,'VLookup Data'!$E:$E) -> 0 | E33: 0 | F33: 0 | G33: 1000 | H33: =SUM(D33:G33) -> 1000 | I33: 1000 | J33: 1000 | K33: garage attendants
A34: 6736-0000 | B34: Donations | D34: =SUMIF('VLookup Data'!$A:$A,A34,'VLookup Data'!$E:$E) -> 0 | E34: 0 | F34: 0 | G34: =SUM(D34:F34)/8*4 -> 0 | H34: =SUM(D34:G34) -> 0 | I34: 0 | J34: 0
A35: 6738-0000 | B35: Meals Reimbursement - Admin | D35: =SUMIF('VLookup Data'!$A:$A,A35,'VLookup Data'!$E:$E) -> 0 | E35: 0 | F35: 0 | G35: 1200 | H35: =SUM(D35:G35) -> 1200 | I35: 1200 | J35: 1200 | K35: staff dinner
A36: 6740-0000 | B36: Security Guards | D36: =SUMIF('VLookup Data'!$A:$A,A36,'VLookup Data'!$E:$E) -> 0 | E36: 0 | F36: 0 | G36: =SUM(D36:F36)/8*4 -> 0 | H36: =SUM(D36:G36) -> 0 | I36: 0 | J36: 0
A37: 6742-0000 | B37: Travel Expenses | D37: =SUMIF('VLookup Data'!$A:$A,A37,'VLookup Data'!$E:$E) -> 0 | E37: 0 | F37: 0 | G37: =SUM(D37:F37)/8*4 -> 0 | H37: =SUM(D37:G37) -> 0 | I37: 0 | J37: 0
A38: 6746-0000 | B38: Lobby & Hallway Decorations | D38: =SUMIF('VLookup Data'!$A:$A,A38,'VLookup Data'!$E:$E) -> 2585.9 | E38: =-408.3-326.64 -> -734.94 | F38: =435.52 -> 435.52 | G38: =SUM(D38:F38)/8*4 -> 1143.24 | H38: =SUM(D38:G38) -> 3429.72 | I38: 4500 | J38: 4500 | K38: NYC Floral Decorators roughly 350/mo in December they pay addt'l lobby flowers
A39: 6748-0000 | B39: Party Supplies | D39: =SUMIF('VLookup Data'!$A:$A,A39,'VLookup Data'!$E:$E) -> 0 | E39: 0 | F39: 0 | G39: =SUM(D39:F39)/8*4 -> 0 | H39: =SUM(D39:G39) -> 0 | I39: 500 | J39: 500
A40: 6754-0000 | B40: Credit Check | D40: =SUMIF('VLookup Data'!$A:$A,A40,'VLookup Data'!$E:$E) -> 0 | E40: 0 | F40: 0 | G40: =SUM(D40:F40)/8*4 -> 0 | H40: =SUM(D40:G40) -> 0 | I40: 500 | J40: 500
A41: 6762-0000 | B41: 1098 Fee's | D41: =SUMIF('VLookup Data'!$A:$A,A41,'VLookup Data'!$E:$E) -> 4965 | E41: 0 | F41: 0 | G41: 0 | H41: =SUM(D41:G41) -> 4965 | I41: 4965 | J41: 4965
A42: 6763-0000 | B42: Safety Notices | D42: =SUMIF('VLookup Data'!$A:$A,A42,'VLookup Data'!$E:$E) -> 7584 | E42: 0 | F42: 0 | G42: 0 | H42: =SUM(D42:G42) -> 7584 | I42: 7560 | J42: 7560
A43: 6764-0000 | B43: Abatement Processing | D43: =SUMIF('VLookup Data'!$A:$A,A43,'VLookup Data'!$E:$E) -> 1575 | E43: 0 | F43: 0 | G43: 0 | H43: =SUM(D43:G43) -> 1575 | I43: 1575 | J43: 1575
A44: 6768-0000 | B44: Secretary Services | D44: =SUMIF('VLookup Data'!$A:$A,A44,'VLookup Data'!$E:$E) -> 125 | E44: 0 | F44: 0 | G44: =SUM(D44:F44)/8*4 -> 62.5 | H44: =SUM(D44:G44) -> 187.5 | I44: 500 | J44: 500
A45: 6774-0000 | B45: Bank Charges | D45: =SUMIF('VLookup Data'!$A:$A,A45,'VLookup Data'!$E:$E) -> 880.83 | E45: 0 | F45: 0 | G45: =SUM(D45:F45)/8*4 -> 440.415 | H45: =SUM(D45:G45) -> 1321.245 | I45: 1300 | J45: 1300
A46: 6795-0000 | B46: Other Administrative | C46: (A) | D46: =SUMIF('VLookup Data'!$A:$A,A46,'VLookup Data'!$E:$E) -> 3547.09 | E46: -252.84 | F46: 0 | G46: =SUM(D46:F46)/8*4 -> 1647.125 | H46: =SUM(D46:G46) -> 4941.375 | I46: 1200 | J46: =1200+(315*40) -> 13800 | K46: Iron Mountain monthly shredding-Century data storage
D47: =SUM(D21:D46) -> 61257.55 | E47: =SUM(E21:E46) -> -1105.45 | F47: =SUM(F21:F46) -> 435.52 | G47: =SUM(G21:G46) -> 14474.48 | H47: =SUM(H21:H46) -> 75062.1 | I47: =SUM(I21:I46) -> 76900 | J47: =SUM(J21:J46) -> 87575 | K47: 315 apts
B49: Insurance
A50: 6105-0000 | B50: Package Policy | D50: =SUMIF('VLookup Data'!$A:$A,A50,'VLookup Data'!$E:$E) -> 466099.93 | E50: 0 | F50: 0 | G50: 0 | H50: =SUM(D50:G50) -> 466099.93 | I50: 425307.23 | J50: =+' Insurance-Sched(No PDF)'!G8 -> 536014.92
A51: 6110-0000 | B51: General Liability Insurance | D51: =SUMIF('VLookup Data'!$A:$A,A51,'VLookup Data'!$E:$E) -> 14362.32 | E51: 0 | F51: 0 | G51: 0 | H51: =SUM(D51:G51) -> 14362.32 | I51: 0 | J51: =' Insurance-Sched(No PDF)'!G29 -> 16516.668
A52: 6120-0000 | B52: Umbrella Insurance | D52: =SUMIF('VLookup Data'!$A:$A,A52,'VLookup Data'!$E:$E) -> 63148.82 | E52: 0 | F52: 0 | G52: 0 | H52: =SUM(D52:G52) -> 63148.82 | I52: 55059.2 | J52: =+' Insurance-Sched(No PDF)'!G10 -> 72621.143
A53: 6125-0000 | B53: D&O Insurance | D53: =SUMIF('VLookup Data'!$A:$A,A53,'VLookup Data'!$E:$E) -> 12812 | E53: 0 | F53: 0 | G53: 0 | H53: =SUM(D53:G53) -> 12812 | I53: 15752.8 | J53: =+' Insurance-Sched(No PDF)'!G11 -> 14733.8
A54: 6126-0000 | B54: Cyber Insurance | D54: =SUMIF('VLookup Data'!$A:$A,A54,'VLookup Data'!$E:$E) -> 1471 | E54: 0 | F54: 0 | G54: 0 | H54: =SUM(D54:G54) -> 1471 | I54: 1834 | J54: =+' Insurance-Sched(No PDF)'!G12 -> 1691.65
A55: 6135-0000 | B55: Crime / Fidelity Insurance | D55: =SUMIF('VLookup Data'!$A:$A,A55,'VLookup Data'!$E:$E) -> 0 | E55: 0 | F55: 0 | G55: =SUM(D55:F55)/8*4 -> 0 | H55: =SUM(D55:G55) -> 0 | I55: 273.056 | J55: =+' Insurance-Sched(No PDF)'!G13 -> 0
A56: 6195-0000 | B56: Other Insurance | D56: =SUMIF('VLookup Data'!$A:$A,A56,'VLookup Data'!$E:$E) -> 0 | E56: 0 | F56: 0 | G56: =SUM(D56:F56)/8*4 -> 0 | H56: =SUM(D56:G56) -> 0 | I56: 3000 | J56: =+' Insurance-Sched(No PDF)'!G14 -> 0
D57: =SUM(D50:D56) -> 557894.07 | E57: =SUM(E50:E56) -> 0 | F57: =SUM(F50:F56) -> 0 | G57: =SUM(G50:G56) -> 0 | H57: =SUM(H50:H56) -> 557894.07 | I57: =SUM(I50:I56) -> 501226.29 | J57: =SUM(J50:J56) -> 641578.18
B59: Corp Tax
A60: 6310-0000 | B60: Corporation Tax | D60: =SUMIF('VLookup Data'!$A:$A,A60,'VLookup Data'!$E:$E) -> 19550 | E60: 0 | F60: 0 | G60: =123+81+5460 -> 5664 | H60: =SUM(D60:G60) -> 25214 | I60: 27300 | J60: =20000+4500 -> 24500 | K60: per accountant Prager Metis 09/2025
D61: =SUM(D60) -> 19550 | E61: =SUM(E60) -> 0 | F61: =SUM(F60) -> 0 | G61: =SUM(G60) -> 5664 | H61: =SUM(H60) -> 25214 | I61: =SUM(I60) -> 27300 | J61: =SUM(J60) -> 24500
B63: Financial Expenses
A64: 6905-0000 | B64: Interest Expense | C64: (B) | D64: =SUMIF('VLookup Data'!$A:$A,A64,'VLookup Data'!$E:$E) -> 382336.38 | E64: 0 | F64: 0 | G64: =SUM(D64:F64)/8*4 -> 191168.19 | H64: =SUM(D64:G64) -> 573504.57 | I64: 572950.63 | J64: =SUM('Mortgage Info and Amort(NO PDF)'!G20:G31) -> 564717.03
A65: 2510-0000 | B65: Mortgage Amortization | C65: (B) | D65: =SUMIF('VLookup Data'!$A:$A,A65,'VLookup Data'!$E:$E) -> 135585.94 | E65: 0 | F65: 0 | G65: =SUM(D65:F65)/8*4 -> 67792.97 | H65: =SUM(D65:G65) -> 203378.91 | I65: 203932.85 | J65: =SUM('Mortgage Info and Amort(NO PDF)'!F20:F31) -> 212166.45
A66: 6995-0000 | B66: Mortgage Payable 2 | C66: (B) | D66: =SUMIF('VLookup Data'!$A:$A,A66,'VLookup Data'!$E:$E) -> 1250 | E66: 0 | F66: 0 | G66: =SUM(D66:F66)/8*4 -> 625 | H66: =SUM(D66:G66) -> 1875 | I66: 1250 | J66: 1250 | K66: for line of credit - Annual facility fee
A67: 6925-0000 | B67: Equipment Lease | C67: (C) | D67: =SUMIF('VLookup Data'!$A:$A,A67,'VLookup Data'!$E:$E) -> 74857.76 | E67: 0 | F67: 0 | G67: =9357.22*4 -> 37428.88 | H67: =SUM(D67:G67) -> 112286.64 | I67: 112286.64 | J67: =9357.22*12 -> 112286.64 | K67: Verdant monthly finance payment
D68: =SUM(D64:D67) -> 594030.08 | E68: =SUM(E64:E67) -> 0 | F68: =SUM(F64:F67) -> 0 | G68: =SUM(G64:G67) -> 297015.04 | H68: =SUM(H64:H67) -> 891045.12 | I68: =SUM(I64:I67) -> 890420.12 | J68: =SUM(J64:J67) -> 890420.12
A70: (A) Other Administrative - 2026 Budget includes a 32BJ Strike Prep Fee as the contract ends 04/2026. | K70: (A) Education & Seminars - 2025 Budget reflects a $25.00/employee increase for Sexual Harassment Training.
A71: (B) 1st Mortgage is for $15,700,000.00 at 3.91% maturing 5/01/2028. The 2nd Mortgage is a line of credit for $500,000.00. | K71: (B) 1098 Fees - 2025 Budget includes a $3.00/form increase
A72: (C) Verdant finance payment | K72: (C) 1st Mortgage is for $15,700,000.00 at 3.91% maturing 5/01/2028. The 2nd Mortgage is a line of credit for $500,000.00.
K73: (D) Verdant finance payment
F78: Page 12

Sheet Mortgage Info and Amort(NO PDF)
B2: Mortgage
B3: Princpal & Interest
B4: Bank: John Hancock Financial Services
B5: Original Balance: | E5: 15700000 | L5: NCB - New mortgage in 2018
B6: Interest Rate: | E6: 0.0391 | L6: does not escrow
B7: Maturity : | E7: 46874 | L7: 2nd Mtg - Line of Credit $500,000.00
B8: Fixed Monthly Payment: | E8: 64740.29
B11: Mortgage Amortization
E12: Monthly Payment | F12: Prinicpal | G12: Interest | H12: Balance
B13: 2024 | H13: 14410413 | I13: Take this amount from Statement
B14: September | E14: =+$E$8 -> 64740.29 | F14: =+E14-G14 -> 17786.36 | G14: =+($E$6*H13)/360*30 -> 46953.93 | H14: =+H13-F14 -> 14392627
B15: October | E15: =+$E$8 -> 64740.29 | F15: =+E15-G15 -> 17844.314 | G15: =+($E$6*H14)/360*30 -> 46895.976 | H15: =+H14-F15 -> 14374783
B16: November | E16: =+$E$8 -> 64740.29 | F16: =+E16-G16 -> 16281.115 | G16: =+($E$6*H14)/360*31 -> 48459.175 | H16: =+H14-F16 -> 14376346
B17: December | E17: =+$E$8 -> 64740.29 | F17: =+E17-G17 -> 17897.363 | G17: =+($E$6*H16)/360*30 -> 46842.927 | H17: 14342052
B19: 2025
B20: January | E20: =+$E$8 -> 64740.29 | F20: =+E20-G20 -> 16451.397 | G20: =+($E$6*H17)/360*31 -> 48288.893 | H20: =+H17-F20 -> 14325601
B21: February | E21: =+$E$8 -> 64740.29 | F21: =+E21-G21 -> 16506.788 | G21: =+($E$6*H20)/360*31 -> 48233.502 | H21: =+H20-F21 -> 14309094
B22: March | E22: =+$E$8 -> 64740.29 | F22: =+E22-G22 -> 21224.745 | G22: =+($E$6*H21)/360*28 -> 43515.545 | H22: =+H21-F22 -> 14287869
B23: April | E23: =+$E$8 -> 64740.29 | F23: =+E23-G23 -> 16633.828 | G23: =+($E$6*H22)/360*31 -> 48106.462 | H23: =+H22-F23 -> 14271236 | M23: February 2025 = 28 days
B24: May | E24: =+$E$8 -> 64740.29 | F24: =+E24-G24 -> 18239.847 | G24: =+($E$6*H23)/360*30 -> 46500.443 | H24: =+H23-F24 -> 14252996
B25: June | E25: =+$E$8 -> 64740.29 | F25: =+E25-G25 -> 16751.245 | G25: =+($E$6*H24)/360*31 -> 47989.045 | H25: =+H24-F25 -> 14236244
B26: July | E26: =+$E$8 -> 64740.29 | F26: =+E26-G26 -> 18353.86 | G26: =+($E$6*H25)/360*30 -> 46386.43 | H26: =+H25-F26 -> 14217891
B27: August | E27: =+$E$8 -> 64740.29 | F27: =+E27-G27 -> 16869.442 | G27: =+($E$6*H26)/360*31 -> 47870.848 | H27: =+H26-F27 -> 14201021
B28: September | E28: =+$E$8 -> 64740.29 | F28: =+E28-G28 -> 16926.241 | G28: =+($E$6*H27)/360*31 -> 47814.049 | H28: =+H27-F28 -> 14184095
B29: October | E29: =+$E$8 -> 64740.29 | F29: =+E29-G29 -> 18523.781 | G29: =+($E$6*H28)/360*30 -> 46216.509 | H29: =+H28-F29 -> 14165571
B30: November | E30: =+$E$8 -> 64740.29 | F30: =+E30-G30 -> 17045.599 | G30: =+($E$6*H29)/360*31 -> 47694.691 | H30: =+H29-F30 -> 14148526
B31: December | E31: =+$E$8 -> 64740.29 | F31: =+E31-G31 -> 18639.678 | G31: =+($E$6*H30)/360*30 -> 46100.612 | H31: =+H30-F31 -> 14129886
F32: =SUM(F20:F31) -> 212166.45 | G32: =SUM(G20:G31) -> 564717.03 | I32: =G32+F32 -> 776883.48

Sheet  Insurance-Sched(No PDF)
B1: Schedule F | D1: =+COV!C23 -> 444 East 86th Street Owners Corp.
D2: Insurance
D3: =yrlycomp!H3 -> For Year Ending 12/31/2026
B5: Insurance
A6: G/L | C6: Annual | G6: Budget (A)
B7: Policy | C7: ='Gen & Admin'!D7 -> 2025 | E7: Expires | G7: =C7+1 -> 2026
A8: 6105-0000 | B8: Package Policy | C8: =SUMIF('VLookup Data'!$A:$A,A8,'VLookup Data'!$E:$E) -> 466099.93 | E8: 12/31/23-12/31/24 | G8: =+C8*$G$19+C8 -> 536014.92
A9: 6110-0000 | B9: General Liability | C9: =SUMIF('VLookup Data'!$A:$A,A9,'VLookup Data'!$E:$E) -> 14362.32 | G9: =+C9*$G$19+C9 -> 16516.668
A10: 6120-0000 | B10: Umbrella Insurance | C10: =SUMIF('VLookup Data'!$A:$A,A10,'VLookup Data'!$E:$E) -> 63148.82 | E10: =E8 -> 12/31/23-12/31/24 | G10: =+C10*$G$19+C10 -> 72621.143
A11: 6125-0000 | B11: D&O Insurance | C11: =SUMIF('VLookup Data'!$A:$A,A11,'VLookup Data'!$E:$E) -> 12812 | E11: =E10 -> 12/31/23-12/31/24 | G11: =+C11*$G$19+C11 -> 14733.8
A12: 6126-0000 | B12: Cyber Insurance | C12: =SUMIF('VLookup Data'!$A:$A,A12,'VLookup Data'!$E:$E) -> 1471 | E12: =E11 -> 12/31/23-12/31/24 | G12: =+C12*$G$19+C12 -> 1691.65
A13: 6135-0000 | B13: Crime / Fidelity Insurance | C13: =SUMIF('VLookup Data'!$A:$A,A13,'VLookup Data'!$E:$E) -> 0 | E13: =E12 -> 12/31/23-12/31/24 | G13: =+C13*$G$19+C13 -> 0
A14: 6195-0000 | B14: Other Insurance | C14: =SUMIF('VLookup Data'!$A:$A,A14,'VLookup Data'!$E:$E) -> 0 | E14: =E13 -> 12/31/23-12/31/24 | G14: =C14 -> 0
B15: Accrual adjustment | C15: 0
B17: Total | C17: =SUM(C8:C16) -> 557894.07 | G17: =SUM(G8:G16) -> 641578.18
C19: (A) 2026 budget reflects an increase over 2025@ | G19: 0.15
A22: This Section Should be used for Financed Polices. If Policy expires 12/31/16 and has been paid in Full than remove the yellow section from Budget.
C24: =+yrlycomp!H7 -> 2025 | D24: =+C24 -> 2025 | E24: =+D24 -> 2025 | F24: =+E24 -> 2025 | G24: =+F24+1 -> 2026
C25: Jan - Aug | D25: Sep - Dec | E25: 12 Month | F25: Budget | G25: Budget (A)
C26: Actual | D26: Est (A) | E26: Forecast
B27: Insurance
A28: 6105-0000 | B28: Package Policy | C28: =SUMIF('VLookup Data'!$A:$A,A28,'VLookup Data'!$E:$E) -> 466099.93 | D28: 0 | E28: =SUM(C28:D28) -> 466099.93 | F28: 425307.23 | G28: =+G8 -> 536014.92
A29: 6110-0000 | B29: General Liability | C29: =SUMIF('VLookup Data'!$A:$A,A29,'VLookup Data'!$E:$E) -> 14362.32 | E29: =SUM(C29:D29) -> 14362.32 | F29: 0 | G29: =+G9 -> 16516.668
A30: 6120-0000 | B30: Umbrella Insurance | C30: =SUMIF('VLookup Data'!$A:$A,A30,'VLookup Data'!$E:$E) -> 63148.82 | D30: 0 | E30: =SUM(C30:D30) -> 63148.82 | F30: 55059.2 | G30: =+G10 -> 72621.143
A31: 6125-0000 | B31: D&O Insurance | C31: =SUMIF('VLookup Data'!$A:$A,A31,'VLookup Data'!$E:$E) -> 12812 | D31: 0 | E31: =SUM(C31:D31) -> 12812 | F31: 15752.8 | G31: =+G11 -> 14733.8
A32: 6126-0000 | B32: Cyber Insurance | C32: =SUMIF('VLookup Data'!$A:$A,A32,'VLookup Data'!$E:$E) -> 1471 | D32: 0 | E32: =SUM(C32:D32) -> 1471 | F32: 1834 | G32: =+G12 -> 1691.65 | K32: D&O/Crime combined in 2020 budget
A33: 6135-0000 | B33: Crime / Fidelity Insurance | C33: =SUMIF('VLookup Data'!$A:$A,A33,'VLookup Data'!$E:$E) -> 0 | D33: 0 | E33: =SUM(C33:D33) -> 0 | F33: 273.056 | G33: =+G13 -> 0 | K33: can break out for 2021 if you want
A34: 6195-0000 | B34: Other Insurance | C34: =SUMIF('VLookup Data'!$A:$A,A34,'VLookup Data'!$E:$E) -> 0 | D34: 0 | E34: =SUM(C34:D34) -> 0 | F34: 3000 | G34: =+G14 -> 0
C35: =SUM(C28:C34) -> 557894.07 | D35: =SUM(D28:D34) -> 0 | E35: =SUM(E28:E34) -> 557894.07 | F35: =SUM(F28:F34) -> 501226.29 | G35: =SUM(G28:G34) -> 641578.18
A42: i
A44: i
B53: Page 8

Sheet Water
E1: =' Insurance-Sched(No PDF)'!D1 -> 444 East 86th Street Owners Corp.
B2: Schedule G | E2: Water & Sewer | L2: **Only enter beginning, end date, and payment**
E3: =wtrswr!C3 -> For Year Ending 12/31/2026
L4: 45658
G5: ='Gen & Admin'!D7 -> 2025 | I5: =G5+1 -> 2026
B6: Water & Sewer | G6: Est./Actual | I6: Budget
B8: A/C#70001-37048-001
E9: # of days | L9: Days in Prior Year
B10: Beginning | C10: End Date | D10: Payment
B12: 45608 | C12: 45637 | D12: 15007.75 | E12: =C12-B12 -> 29 | F12: =D12/E12 -> 517.50862 | G12: =F12*(E12-29) -> 0 | L12: =E12 -> 29
B13: 45637 | C13: 45669 | D13: 19423.93 | E13: =C13-B13 -> 32 | F13: =D13/E13 -> 606.99781 | G13: =F13*(E13-L13) -> 6676.9759 | L13: =+L4-B13 -> 21
B14: 45669 | C14: 45699 | D14: 17232.4 | E14: =C14-B14 -> 30 | F14: =D14/E14 -> 574.41333 | G14: =+E14*F14 -> 17232.4
B15: 45699 | C15: 45728 | D15: 15562.74 | E15: =C15-B15 -> 29 | F15: =D15/E15 -> 536.64621 | G15: =+E15*F15 -> 15562.74
B16: 45728 | C16: 45757 | D16: 15335.7 | E16: =C16-B16 -> 29 | F16: =D16/E16 -> 528.81724 | G16: =+E16*F16 -> 15335.7
B17: 45757 | C17: 45788 | D17: 16623.97 | E17: =C17-B17 -> 31 | F17: =D17/E17 -> 536.2571 | G17: =+E17*F17 -> 16623.97
B18: 45788 | C18: 45817 | D18: 17381.03 | E18: =C18-B18 -> 29 | F18: =D18/E18 -> 599.34586 | G18: =+E18*F18 -> 17381.03
B19: 45817 | C19: 45847 | D19: 19713.38 | E19: =C19-B19 -> 30 | F19: =D19/E19 -> 657.11267 | G19: =+E19*F19 -> 19713.38
N20: changed average for 2019 est to not include 07/19
N21: change back next year
C23: 2025 | D23: Balance | E23: =365-SUM(E14:E19)-11 -> 176 | F23: =AVERAGE(F12:F19) -> 569.63736 | G23: =F23*E23 -> 100256.17
C30: Total Water & Sewer | G30: =SUM(G11:G29) -> 208782.37 | I30: =G30*G34+G30 -> 216507.32
C34: 2026 Budget Based on Rate Increase of | G34: 0.037
D36: =+yrlycomp!H7 -> 2025 | E36: Accrual | F36: =+D36 -> 2025 | G36: =+F36 -> 2025 | H36: =+G36 -> 2025 | I36: =+H36+1 -> 2026
D37: Jan - Aug | E37: Adjustments | F37: Sep - Dec | G37: 12 Month | H37: Budget | I37: Budget
B38: G/L | D38: Actual | F38: Est | G38: Forecast
B39: 6305-0000 | C39: Water & Sewer | D39: =SUMIF('VLookup Data'!$A:$A,B39,'VLookup Data'!$E:$E) -> 136280.9 | E39: =-F13*L13-L12*F12 -> -27754.704 | F39: =+G23 -> 100256.17 | G39: =SUM(D39:F39) -> 208782.37 | H39: 217796.61 | I39: =+I30 -> 216507.32
E64: Page 13
A81: A/C#70001-37048-001
D82: # of days
A83: Beginning | B83: End Date | C83: Payment
A85: 42328 | B85: 42356 | C85: 14049.91 | D85: 29 | E85: =C85/D85 -> 484.47966 | F85: =E85*(D85-29) -> 0
A86: 42357 | B86: 42389 | C86: 16344.1 | D86: 33 | E86: =C86/D86 -> 495.27576 | F86: =+E86*(D86-12) -> 10400.791
A87: 42390 | B87: 42419 | C87: 14833.16 | D87: 30 | E87: =C87/D87 -> 494.43867 | F87: =+E87*(D87) -> 14833.16
A88: 42420 | B88: 42450 | C88: 14521.05 | D88: 31 | E88: =C88/D88 -> 468.42097 | F88: =+E88*(D88) -> 14521.05
A89: 42451 | B89: 42480 | C89: 15967.97 | D89: 30 | E89: =C89/D89 -> 532.26567 | F89: =+E89*(D89) -> 15967.97
A90: 42481 | B90: 42510 | C90: 14673.12 | D90: 30 | E90: =C90/D90 -> 489.104 | F90: =+E90*(D90) -> 14673.12
A91: 42511 | B91: 42533 | C91: 17906.33 | D91: 31 | E91: =C91/D91 -> 577.62355 | F91: =+E91*(D91) -> 17906.33
A92: 42542 | B92: 42571 | C92: 17145.51 | D92: 30 | E92: =C92/D92 -> 571.517 | F92: =+E92*(D92) -> 17145.51
A93: 42572 | B93: 42600 | C93: 16431.77 | D93: 29 | E93: =C93/D93 -> 566.61276 | F93: =+E93*(D93) -> 16431.77
A94: 42601 | B94: 42632 | C94: 19393.67 | D94: 32 | E94: =C94/D94 -> 606.05219 | F94: =+E94*(D94) -> 19393.67
A95: 42625 | B95: 42656 | C95: 20571.05 | D95: 31 | E95: =C95/D95 -> 663.58226 | F95: =+E95*(D95) -> 20571.05
A97: A/C#70001-37048-001
D98: # of days
A99: Beginning | B99: End Date | C99: Payment
A101: 42687 | B101: 42717 | C101: 16302.3 | D101: 30 | E101: =C101/D101 -> 543.41 | F101: =+E101*(D101-30) -> 0
A102: 42717 | B102: 42747 | C102: 16633.09 | D102: 30 | E102: =C102/D102 -> 554.43633 | F102: =+E102*(D102-17) -> 7207.6723
A103: 42747 | B103: 42778 | C103: 17277.02 | D103: 31 | E103: =C103/D103 -> 557.32323 | F103: =+E103*(D103) -> 17277.02
A104: 42778 | B104: 42807 | C104: 15320.66 | D104: 29 | E104: =C104/D104 -> 528.29862 | F104: =+E104*(D104) -> 15320.66
A105: 42807 | B105: 42837 | C105: 15806.7 | D105: 30 | E105: =C105/D105 -> 526.89 | F105: =+E105*(D105) -> 15806.7
A106: 42837 | B106: 42865 | C106: 14220.97 | D106: 28 | E106: =C106/D106 -> 507.89179 | F106: =+E106*(D106) -> 14220.97
A107: 42865 | B107: 42898 | C107: 18556.57 | D107: 33 | E107: =C107/D107 -> 562.3203 | F107: =+E107*(D107) -> 18556.57
A108: 42898 | B108: 42934 | C108: 17561.37 | D108: 36 | E108: =C108/D108 -> 487.81583 | F108: =+E108*(D108) -> 17561.37
A109: 42929 | B109: 42957 | C109: 16107.86 | D109: 28 | E109: =C109/D109 -> 575.28071 | F109: =+E109*(D109) -> 16107.86
A110: 42957 | B110: 42991 | C110: 21052.14 | D110: 28 | E110: =C110/D110 -> 751.86214 | F110: =+E110*(D110) -> 21052.14
A111: 42998 | B111: 43027 | C111: 17714.11 | D111: 30 | E111: =C111/D111 -> 590.47033 | F111: =+E111*(D111) -> 17714.11
A112: 43028 | B112: 43059 | C112: 18639.88 | D112: 32 | E112: =C112/D112 -> 582.49625 | F112: =+E112*(D112) -> 18639.88
A113: 43060 | B113: 43088 | C113: 16369.17 | D113: 29 | E113: =C113/D113 -> 564.45414 | F113: =+E113*(D113-29) -> 0
A114: 43089 | B114: 43118 | C114: 17083.34 | D114: 30 | E114: =C114/D114 -> 569.44467 | F114: =+E114*(D114-12) -> 10250.004
A115: 43119 | B115: 43147 | C115: 16408.64 | D115: 29 | E115: =C115/D115 -> 565.81517 | F115: =+E115*(D115) -> 16408.64
A116: 43148 | B116: 43179 | C116: 14564.53 | D116: 32 | E116: =C116/D116 -> 455.14156 | F116: =+E116*(D116) -> 14564.53
A117: 43180 | B117: 43209 | C117: 13856.53 | D117: 30 | E117: =C117/D117 -> 461.88433 | F117: =+E117*(D117) -> 13856.53
A118: 43210 | B118: 43238 | C118: 14985.07 | D118: 29 | E118: =C118/D118 -> 516.72655 | F118: =+E118*(D118) -> 14985.07
A119: 43239 | B119: 43269 | C119: 15957.97 | D119: 31 | E119: =C119/D119 -> 514.77323 | F119: =+E119*(D119) -> 15957.97
A120: 43270 | B120: 43299 | C120: 19929.42 | D120: 30 | E120: =C120/D120 -> 664.314 | F120: =+E120*(D120) -> 19929.42
A121: 43300 | B121: 43324 | C121: 14163.94 | D121: 25 | E121: =C121/D121 -> 566.5576 | F121: =+E121*(D121) -> 14163.94
A122: 43324 | B122: 43356 | C122: 18899.78 | D122: 32 | E122: =C122/D122 -> 590.61812 | F122: =+E122*(D122) -> 18899.78
A123: 43356 | B123: 43387 | C123: 17481.7 | D123: 31 | E123: =C123/D123 -> 563.92581 | F123: =+E123*(D123) -> 17481.7
A124: 43387 | B124: 43418 | C124: 15284.06 | D124: 31 | E124: =C124/D124 -> 493.03419 | F124: =+E124*(D124) -> 15284.06
A125: 43418 | B125: 43446 | C125: 14401.88 | D125: 28 | E125: =C125/D125 -> 514.35286 | F125: =+E125*(D125-28) -> 0
A126: 43446 | B126: 43478 | C126: 15456.58 | D126: 32 | E126: =C126/D126 -> 483.01812 | F126: =+E126*(D126-12) -> 9660.3625
A127: 43478 | B127: 43508 | C127: 14706.55 | D127: 30 | E127: =C127/D127 -> 490.21833 | F127: =+E127*(D127) -> 14706.55
A128: 43508 | B128: 43537 | C128: 13776.05 | D128: 29 | E128: =C128/D128 -> 475.03621 | F128: =+E128*(D128) -> 13776.05
A129: 43537 | B129: 43566 | C129: 14169.99 | D129: 29 | E129: =C129/D129 -> 488.62034 | F129: =+E129*(D129) -> 14169.99
A130: 43566 | B130: 43597 | C130: 17627.6 | D130: 31 | E130: =C130/D130 -> 568.63226 | F130: =+E130*(D130) -> 17627.6
A131: 43597 | B131: 43633 | C131: 15525.67 | D131: 36 | E131: =C131/D131 -> 431.26861 | F131: =+E131*(D131) -> 15525.67
A132: 43633 | B132: 43677 | C132: 30559.03 | D132: 44 | E132: =C132/D132 -> 694.52341 | F132: =+E132*(D132) -> 30559.03
A133: 43677 | B133: 43689 | C133: 7790.86 | D133: 24 | E133: =C133/D133 -> 324.61917 | F133: =+E133*(D133) -> 7790.86
A134: 43689 | B134: 43720 | C134: 19637.3 | D134: 31 | E134: =C134/D134 -> 633.46129 | F134: =+E134*(D134) -> 19637.3
A135: 43720 | B135: 43752 | C135: 19648.93 | D135: 32 | E135: =C135/D135 -> 614.02906 | F135: =+E135*(D135) -> 19648.93
A136: 43752 | B136: 43783 | C136: 16529.6 | D136: 31 | E136: =C136/D136 -> 533.2129 | F136: =+E136*(D136) -> 16529.6
A137: 43783 | B137: 43811 | C137: 14992.71 | D137: 28 | E137: =C137/D137 -> 535.45393 | F137: =+E137*(D137-28) -> 0
A138: 43811 | B138: 43843 | C138: 15580.97 | D138: 32 | E138: =C138/D138 -> 486.90531 | F138: =+E138*(D138-21) -> 5355.9584
A139: 43843 | B139: 43873 | C139: 14417.85 | D139: 30 | E139: =C139/D139 -> 480.595 | F139: =+E139*(D139) -> 14417.85
A140: 43873 | B140: 43902 | C140: 14124.65 | D140: 29 | E140: =C140/D140 -> 487.0569 | F140: =+E140*(D140) -> 14124.65
A141: 43902 | B141: 43934 | C141: 14339.02 | D141: 32 | E141: =C141/D141 -> 448.09438 | F141: =+E141*(D141) -> 14339.02
A142: 43934 | B142: 43963 | C142: 12801.88 | D142: 29 | E142: =C142/D142 -> 441.44414 | F142: =+E142*(D142) -> 12801.88
A143: 43963 | B143: 43993 | C143: 14007.55 | D143: 30 | E143: =C143/D143 -> 466.91833 | F143: =+E143*(D143) -> 14007.55
A144: 43993 | B144: 44025 | C144: 24559.68 | D144: 33 | E144: =C144/D144 -> 744.23273 | F144: =+E144*(D144) -> 24559.68
A145: 44025 | B145: 44056 | C145: =28981.11+19.29 -> 29000.4 | D145: 31 | E145: =C145/D145 -> 935.49677 | F145: =+E145*(D145) -> 29000.4
A146: 44062 | B146: 44092 | C146: 22602.38 | D146: 31 | E146: =C146/D146 -> 729.10903 | F146: =+E146*(D146) -> 22602.38
A147: 44093 | B147: 44124 | C147: 16021.57 | D147: 32 | E147: =C147/D147 -> 500.67406 | F147: =+E147*(D147) -> 16021.57
A148: 44125 | B148: 44154 | C148: 14366.5 | D148: 30 | E148: =C148/D148 -> 478.88333 | F148: =+E148*(D148) -> 14366.5
A149: 44147 | B149: 44178 | C149: 16212.45 | D149: 31 | E149: =C149/D149 -> 522.98226 | F149: =+E149*(D149-31) -> 0
A150: 44178 | B150: 44208 | C150: 15318.48 | D150: 30 | E150: =C150/D150 -> 510.616 | F150: =+E150*(D150-19) -> 5616.776
A151: 44208 | B151: 44238 | C151: 15830.09 | D151: 30 | E151: =C151/D151 -> 527.66967 | F151: =+E151*(D151) -> 15830.09
A152: 44238 | B152: 44269 | C152: 16610.09 | D152: 31 | E152: =C152/D152 -> 535.80935 | F152: =+E152*(D152) -> 16610.09
A153: 44269 | B153: 44298 | C153: 16096.15 | D153: 29 | E153: =C153/D153 -> 555.03966 | F153: =+E153*(D153) -> 16096.15
A154: 44298 | B154: 44328 | C154: 15986.23 | D154: 30 | E154: =C154/D154 -> 532.87433 | F154: =+E154*(D154) -> 15986.23
A155: 44328 | B155: 44360 | C155: 18663.74 | D155: 32 | E155: =C155/D155 -> 583.24188 | F155: =+E155*(D155) -> 18663.74
A156: 44360 | B156: 44390 | C156: 17679.16 | D156: 30 | E156: =C156/D156 -> 589.30533 | F156: =+E156*(D156) -> 17679.16
...

Sheet RE Taxes
E1: =+yrlycomp!H1 -> 444 East 86th Street Owners Corp.
E2: Real Estate Taxes
B3: Schedule H | E3: =+yrlycomp!H3 -> For Year Ending 12/31/2026
B10: Real Estate Taxes (Manhattan: Blk 1565, Lot 29)
B11: 2025/2026 ASSESSED VALUATION-ACTUAL - July 2025 | G11: 39979620 | H11: First half | I11: =(+G11*G12)/2 -> 2474338.7
C12: TAX RATE - Est. | G12: 0.12378
C13: TAX RATE - Adjustment 1st & 2nd Qtr 2024/2025 | G13: 0 | I13: =+(G11*G13)/2 -> 0
B15: 2026/2027 ASSESSED VALUATION-ESTIMATED
B16: Trans AV | D16: 0.04316765 | E16: Estimated Increase * | G16: =G11*D16+G11 -> 41705446 | H16: Second half | I16: =(+G16*G17)/2 -> 2632656.3
B17: TAX RATE | D17: =G17-G12 -> 0.00247 | E17: Estimated Increase | G17: 0.12625
C18: Full Year Tax Liability(Gross) | I18: =SUM(I11:I17) -> 5106995
D24: Tax Benefits | F24: 2024/2025 | G24: 2025/2026 | H24: 2026/2027
D25: Veteran | F25: 21362.39 | G25: =+F25*1.02 -> 21789.638 | H25: =+G25*1.02 -> 22225.431
D26: Senior Citizen | F26: 19282.63 | G26: =+F26*1.02 -> 19668.283 | H26: =+G26*1.02 -> 20061.648
D27: Star | F27: 17369.25 | G27: =+F27*1.03 -> 17890.327 | H27: =+G27*1.02 -> 18248.134
D28: Co-op Abatment | F28: 750029.91 | G28: =+((I11*2)*17.5%)*89% -> 770756.5 | H28: =+G28*1.02 -> 786171.63 | J28: change formula
F29: =SUM(F25:F28) -> 808044.18 | G29: =SUM(G25:G28) -> 830104.75 | H29: =SUM(H25:H28) -> 846706.84
D35: =+yrlycomp!H7 -> 2025 | E35: =+D35 -> 2025 | F35: =+E35 -> 2025 | G35: =+F35 -> 2025 | H35: =+G35+1 -> 2026
D36: Jan - Aug | E36: Sep - Dec | F36: 12 Month | G36: Budget | H36: Budget
D37: Actual | E37: Est | F37: Forecast
A41: 6315-0000 | B41: Real Estate Tax | D41: =SUMIF('VLookup Data'!$A:$A,A41,'VLookup Data'!$E:$E) -> 3724147.8 | E41: 1249363.4 | F41: =SUM(D41:E41) -> 4973511.1 | G41: 5087406.1 | H41: =+I18 -> 5106995
A42: 6315-0010 | B42: Real Estate Tax Abatement | D42: =SUMIF('VLookup Data'!$A:$A,A42,'VLookup Data'!$E:$E) -> -561767.96 | E42: -186753 | F42: =SUM(D42:E42) -> -748520.96 | G42: -790273.68 | H42: =+G28/2*-1+H28/2*-1 -> -778464.06 | J42: To use Oct bill for est months
A43: 6315-0020 | B43: STAR Exemption | D43: =SUMIF('VLookup Data'!$A:$A,A43,'VLookup Data'!$E:$E) -> -12828.64 | E43: -4144 | F43: =SUM(D43:E43) -> -16972.64 | G43: -22667.816 | H43: =+G27*-0.5+H27/2*-1 -> -18069.231
A44: 6315-0025 | B44: Veteran Exemption | D44: =SUMIF('VLookup Data'!$A:$A,A44,'VLookup Data'!$E:$E) -> -16072.74 | E44: -5391.56 | F44: =SUM(D44:E44) -> -21464.3 | G44: -13857.967 | H44: =+G25/2*-1+H25/2*-1 -> -22007.534
A45: 6315-0035 | B45: SCHE Credit | D45: =SUMIF('VLookup Data'!$A:$A,A45,'VLookup Data'!$E:$E) -> -17613.51 | E45: -7972.19 | F45: =SUM(D45:E45) -> -25585.7 | G45: -19193.12 | H45: =+G26/2*-1+H26/2*-1 -> -19864.965
D46: =SUM(D41:D45) -> 3115864.9 | E46: =SUM(E41:E45) -> 1045102.6 | F46: =SUM(F41:F45) -> 4160967.5 | G46: =SUM(G41:G45) -> 4241413.5 | H46: =SUM(H41:H45) -> 4268589.2
A52: The 2025/2026 final and the estimated 2026/2027 assessed valuations have been confirmed by Tuchman Korngold Weiss Liebman & Gelles, LLP, the cooperatives
A53: tax certorari attorney. | J53: The 2023/2024 assessed valuation reflects reduction due to previous tax settlement accepted.
J55: (A) 2024/2025 final tax rate will be 12.50%. In January and April of 2025, the city will retroactively bill (Q1 & Q2) for the difference between
J56: new rate of 12509% and old rate of 12.502%. This results in a (0.020%) difference making the second half of the city's fiscal year 2024/2025
J57: effective tax rate of 12.50%
F71: Page 14

Sheet wtrswr
A1: Schedule G | C1: =+COV!C23 -> 444 East 86th Street Owners Corp.
C2: Water & Sewer
C3: =yrlycomp!H3 -> For Year Ending 12/31/2026
A6: Water Meter Charges:
B8: 2012 (A) | E8: 2012 (B) | F8: 2012 | G8: 2012 | H8: 2013 (C)
B9: 9 MONTH | C9: Unpaids | D9: Accrual | E9: 3 MONTH | F9: 12 MONTH | G9: BUDGET | H9: BUDGET
A10: A/C # 80009-80127-001 | B10: ACTUAL | C10: @ 9/30/12 | D10: Adjustment | E10: ESTIMATE | F10: FORECAST
A11: Meter # K13095158 | B11: =+C23 -> 17542.59 | C11: =+C38 -> 3167.31 | D11: =-C21 -> -8763.8174 | E11: =+C27*D35 -> 8988.2222 | F11: =SUM(B11:E11) -> 20934.305 | G11: 44943 | H11: =365*E45 -> 30897.982
A12: Actual vs Est Differential | B12: 0 | C12: 0 | D12: =+N47 -> 7804.46 | E12: 0 | F12: =SUM(B12:E12) -> 7804.46 | G12: 0 | H12: 0
A13: Rounding | B13: 0 | C13: 0 | D13: 0 | E13: 0 | F13: =+B13+E13 -> 0 | G13: 57 | H13: 4102
A14: TOTAL PAYMENT | B14: =SUM(B11:B13) -> 17542.59 | C14: =SUM(C11:C13) -> 3167.31 | D14: =SUM(D11:D13) -> -959.35737 | E14: =SUM(E11:E13) -> 8988.2222 | F14: =SUM(F11:F13) -> 28738.765 | G14: =SUM(G11:G13) -> 45000 | H14: =SUM(H11:H13) -> 34999.982
A17: (A) THE NINE MONTH ACTUAL INCLUDES PRIOR AND CURRENT STEAM CONDENSATE CHARGES
A18: AS FOLLOWS
C19: =+A10 -> A/C # 80009-80127-001
B21: PRIOR | C21: =+K40 -> 8763.8174
B22: CURRENT | C22: =+M40 -> 8778.7726
B23: TOTAL | C23: =SUM(C21:C22) -> 17542.59
A26: (B) THE THREE MONTH ESTIMATE REPRESENTS ESTIMATED CHARGES FOR BUILDING METER
A27: FOR YEAR END OF 12/31/ 2012 | C27: =30-6+31+30+31 -> 116 | D27: DAYS REMAINING AT CALCULATED
A28: AVERAGE RATE PER DAY AS FOLLOWS:
C30: CALCULATION: | J30: Work Area
K31: Prior | M31: Current
D32: AVERAGE
B33: DAYS | C33: AMOUNT | D33: $ PER DAY | E33: PERIOD COVERED
A34: =+A11 -> Meter # K13095158 | B34: 91 | C34: 9937.94 | D34: =+C34/B34 -> 109.20813 | E34: 06/08/10-09/07/10 | G34: Actual
A35: =+A34 -> Meter # K13095158 | B35: 92 | C35: 7128.59 | D35: =+C35/B35 -> 77.484674 | E35: 09/07/10-12/08/10 | G35: Actual | K35: =+C35 -> 7128.59
A36: =+A34 -> Meter # K13095158 | B36: 95 | C36: 6754.2 | D36: =+C36/B36 -> 71.096842 | E36: 12/08/10-03/13/11 | G36: Estimated | J36: 23 | K36: =+J36*D36 -> 1635.2274 | L36: =+B36-J36 -> 72 | M36: =+L36*D36 -> 5118.9726
A37: =+A36 -> Meter # K13095158 | B37: 90 | C37: 3659.8 | D37: =+C37/B37 -> 40.664444 | E37: 03/13/11-06/11/11 | G37: Estimated | M37: =+C37 -> 3659.8
A38: =+A34 -> Meter # K13095158 | B38: 91 | C38: 3167.31 | D38: =+C38/B38 -> 34.805604 | E38: 06/11/11-09/10/11 | G38: Estimated
A39: TOTAL | B39: =SUM(B34:B38) -> 459 | C39: =SUM(C34:C38) -> 30647.84 | D39: =+C39/B39 -> 66.770893
K40: =SUM(K35:K39) -> 8763.8174 | M40: =SUM(M35:M39) -> 8778.7726
A42: (C) THE 2013 BUDGET IS BASED ON AVE $ PER DAY INCREASED @ | F42: 0.0925 | J42: Estimated Adjustment
A43: CALCULATD AS FOLLOWS: | J43: Last Actual reading | K43: Est Reading | L43: differential | M43: Days | N43: Additional Chrg
B44: OLD | E44: NEW | J44: =+D35 -> 77.484674 | K44: =+D36 -> 71.096842 | L44: =+J44-K44 -> 6.3878318 | M44: =+B36 -> 95 | N44: =+L44*M44 -> 606.84402
A45: =+A34 -> Meter # K13095158 | B45: =+D35 -> 77.484674 | C45: PER DAY | E45: =+B45*F42+B45 -> 84.652006 | F45: PER DAY | J45: =+J44 -> 77.484674 | K45: =+D37 -> 40.664444 | L45: =+J45-K45 -> 36.820229 | M45: =+B37 -> 90 | N45: =+L45*M45 -> 3313.8207
C46: Last Actual Reading | J46: =+J45 -> 77.484674 | K46: =+D38 -> 34.805604 | L46: =+J46-K46 -> 42.67907 | M46: =+B38 -> 91 | N46: =+L46*M46 -> 3883.7953
N47: =SUM(N44:N46) -> 7804.46
C48: Page 9

Sheet CAP
E1: =+yrlycomp!H1 -> 444 East 86th Street Owners Corp.
E2: Capital Expenses
B3: Schedule I | E3: =+yrlycomp!H3 -> For Year Ending 12/31/2026
D7: =+yrlycomp!H7 -> 2025 | E7: Accrual | F7: Unpaids | G7: =+D7 -> 2025 | H7: =+G7 -> 2025 | I7: =+H7 -> 2025 | J7: =+I7+1 -> 2026
D8: Jan - Aug | E8: Adjustments | F8: ='Repairs & Supplies'!F6 -> @08/31/25 | G8: Sep - Dec | H8: 12 Month | I8: Budget | J8: Budget
D9: Actual | G9: Est | H9: Forecast
A10: G/L | B10: Capital Expense
A11: 7105-1411 | B11: Cap - Elevator | D11: =SUMIF('VLookup Data'!$A:$A,A11,'VLookup Data'!$E:$E) -> 0 | E11: 0 | F11: 0 | G11: 0 | H11: =SUM(D11:G11) -> 0 | I11: 0 | J11: 0
A12: 7110-1409 | B12: Cap - Boiler/Burner | D12: =SUMIF('VLookup Data'!$A:$A,A12,'VLookup Data'!$E:$E) -> 0 | E12: 0 | F12: 0 | G12: 0 | H12: =SUM(D12:G12) -> 0 | I12: 0 | J12: 0
A13: 7115-1409 | B13: Cap - HVAC | D13: =SUMIF('VLookup Data'!$A:$A,A13,'VLookup Data'!$E:$E) -> 0 | E13: 0 | F13: 0 | G13: 0 | H13: =SUM(D13:G13) -> 0 | I13: 0 | J13: 0
A14: 7120-1411 | B14: Cap - Pump & Motor | D14: =SUMIF('VLookup Data'!$A:$A,A14,'VLookup Data'!$E:$E) -> 8960.41 | E14: 0 | F14: 0 | G14: 0 | H14: =SUM(D14:G14) -> 8960.41 | I14: 0 | J14: 0
A15: 7125-1411 | B15: Cap - Appliances | D15: =SUMIF('VLookup Data'!$A:$A,A15,'VLookup Data'!$E:$E) -> 0 | E15: 0 | F15: 0 | G15: 0 | H15: =SUM(D15:G15) -> 0 | I15: 0 | J15: 0
A16: 7140-1419 | B16: Cap - Facade Waterproof | D16: =SUMIF('VLookup Data'!$A:$A,A16,'VLookup Data'!$E:$E) -> 43550 | E16: 0 | F16: 0 | G16: 0 | H16: =SUM(D16:G16) -> 43550 | I16: 0 | J16: 0
A17: 7145-1409 | B17: Cap - Plumbing | D17: =SUMIF('VLookup Data'!$A:$A,A17,'VLookup Data'!$E:$E) -> 33355.7 | E17: =-2613-10742.7 -> -13355.7 | F17: 0 | G17: 0 | H17: =SUM(D17:G17) -> 20000 | I17: 0 | J17: 0
A18: 7150-1409 | B18: Cap - Electrical | D18: =SUMIF('VLookup Data'!$A:$A,A18,'VLookup Data'!$E:$E) -> 3400 | E18: 0 | F18: 0 | G18: 0 | H18: =SUM(D18:G18) -> 3400 | I18: 0 | J18: 0
A19: 7155-1409 | B19: Cap - General Contractor | D19: =SUMIF('VLookup Data'!$A:$A,A19,'VLookup Data'!$E:$E) -> 67900 | E19: 0 | F19: 0 | G19: 0 | H19: =SUM(D19:G19) -> 67900 | I19: 0 | J19: 0
A20: 7165-1409 | B20: Cap - Engineering / Architectural | D20: =SUMIF('VLookup Data'!$A:$A,A20,'VLookup Data'!$E:$E) -> 15362.58 | E20: =-2006.67-3530-3475.91 -> -9012.58 | F20: 0 | G20: 0 | H20: =SUM(D20:G20) -> 6350 | I20: 0 | J20: 0
A21: 7190-1415 | B21: Cap - Hallways | D21: =SUMIF('VLookup Data'!$A:$A,A21,'VLookup Data'!$E:$E) -> 67694.31 | E21: -33140 | F21: 0 | G21: 0 | H21: =SUM(D21:G21) -> 34554.31 | I21: 0 | J21: 0
A22: 7195-1413 | B22: Cap - Lobby | D22: =SUMIF('VLookup Data'!$A:$A,A22,'VLookup Data'!$E:$E) -> 0 | F22: 0 | G22: 0 | H22: =SUM(D22:G22) -> 0 | I22: 0 | J22: 0
A23: 7205-1409 | B23: Cap - Storage | D23: =SUMIF('VLookup Data'!$A:$A,A23,'VLookup Data'!$E:$E) -> 0 | E23: 0 | F23: 0 | G23: 0 | H23: =SUM(D23:G23) -> 0 | I23: 0 | J23: 0
A24: 7235-1409 | B24: Cap - Doors | D24: =SUMIF('VLookup Data'!$A:$A,A24,'VLookup Data'!$E:$E) -> 0 | E24: 0 | F24: 0 | G24: 0 | H24: =SUM(D24:G24) -> 0 | I24: 0 | J24: 0
A25: 7265-1411 | B25: Cap - Security System | D25: =SUMIF('VLookup Data'!$A:$A,A25,'VLookup Data'!$E:$E) -> 0 | E25: 0 | F25: 0 | G25: 0 | H25: =SUM(D25:G25) -> 0 | I25: 0 | J25: 0
A26: 7273-1409 | B26: Cap - Insurance Repairs | D26: =SUMIF('VLookup Data'!$A:$A,A26,'VLookup Data'!$E:$E) -> 32095 | E26: =-4805-19230-2100-5960 -> -32095 | F26: 0 | G26: 0 | H26: =SUM(D26:G26) -> 0 | I26: 0 | J26: 0
A27: 7315-1421 | B27: Cap - Fitness Equipment | D27: =SUMIF('VLookup Data'!$A:$A,A27,'VLookup Data'!$E:$E) -> 0 | E27: 0 | F27: 0 | G27: 0 | H27: =SUM(D27:G27) -> 0 | I27: 0 | J27: 0
A28: 7360-1780 | B28: =_xlfn.XLOOKUP(A28,'VLookup Data'!A:A,'VLookup Data'!B:B) -> Cap - Professional | D28: =SUMIF('VLookup Data'!$A:$A,A28,'VLookup Data'!$E:$E) -> 15000 | E28: 0 | F28: 0 | G28: 0 | H28: =SUM(D28:G28) -> 15000 | I28: 0 | J28: 0
A29: 7385-1411 | B29: Cap - Building Equipment | D29: =SUMIF('VLookup Data'!$A:$A,A29,'VLookup Data'!$E:$E) -> 24896.43 | E29: 0 | F29: 0 | G29: 0 | H29: =SUM(D29:G29) -> 24896.43 | I29: 0 | J29: 0
A30: 7490-1409 | B30: Cap - Other | D30: =SUMIF('VLookup Data'!$A:$A,A30,'VLookup Data'!$E:$E) -> 27377.5 | E30: 0 | F30: 0 | G30: 0 | H30: =SUM(D30:G30) -> 27377.5 | I30: 0 | J30: 0 | K30: 435 East 85th St and Jonathan Stern
D31: =SUM(D11:D30) -> 339591.93 | E31: =SUM(E11:E30) -> -87603.28 | F31: =SUM(F11:F30) -> 0 | G31: =SUM(G11:G30) -> 0 | H31: =SUM(H11:H30) -> 251988.65 | I31: =SUM(I11:I30) -> 0 | J31: =SUM(J11:J30) -> 0
E68: Page 15

Sheet maint proof
A2: Maint Proof | I2: Maint Proof | Q2: Maint Proof
A4: Property | E4: Status | F4: Current | I4: Property | M4: Status | N4: Current | Q4: Property | U4: Status | V4: Current
A5: Charge Code | B5: maint | I5: Charge Code | J5: storage | Q5: Charge Code | R5: bike
A7: Property | B7: Unit Code | C7: %common/Share | D7: Status | E7: Charge Code | F7: Amount | G7: Unit | I7: Property | J7: Unit Code | K7: %common/Share | L7: Status | M7: Charge Code | N7: Amount | O7: Unit | Q7: Property | R7: Unit Code | S7: %common/Share | T7: Status | U7: Charge Code | V7: Amount | W7: Unit
B8: 03A | C8: 1286 | D8: Current | E8: maint | F8: 2354.81 | G8: 03A | J8: 03A | K8: 1286 | L8: Current | M8: storage | N8: 125 | O8: 03A | R8: 03G | S8: 2168 | T8: Current | U8: bike | V8: 15 | W8: 03G
B9: 03B | C9: 1286 | D9: Current | E9: maint | F9: 2354.82 | G9: 03B | J9: 04D | K9: 718 | L9: Current | M9: storage | N9: 100 | O9: 04D | R9: 04H | S9: 1368 | T9: Current | U9: bike | V9: 45 | W9: 04H
B10: 03C | C10: 716 | D10: Current | E10: maint | F10: 1311.09 | G10: 03C | J10: 04H | K10: 1368 | L10: Current | M10: storage | N10: 180 | O10: 04H | R10: 06J | S10: 1022 | T10: Current | U10: bike | V10: 15 | W10: 06J
B11: 03D | C11: 716 | D11: Current | E11: maint | F11: 1311.11 | G11: 03D | J11: 05G | K11: 2252 | L11: Current | M11: storage | N11: 75 | O11: 05G | R11: 07G | S11: 2255 | T11: Current | U11: bike | V11: 15 | W11: 07G
B12: 03E | C12: 1016 | D12: Current | E12: maint | F12: 1860.41 | G12: 03E | J12: 06C | K12: 722 | L12: Current | M12: storage | N12: 75 | O12: 06C | R12: 08A | S12: 1376 | T12: Current | U12: bike | V12: 15 | W12: 08A
B13: 03F | C13: 1286 | D13: Current | E13: maint | F13: 2354.81 | G13: 03F | J13: 06F | K13: 1292 | L13: Current | M13: storage | N13: 75 | O13: 06F | R13: 09E | S13: 1028 | T13: Current | U13: bike | V13: 15 | W13: 09E
B14: 03G | C14: 2168 | D14: Current | E14: maint | F14: 3969.84 | G14: 03G | J14: 07C | K14: 724 | L14: Current | M14: storage | N14: 75 | O14: 07C | R14: 15D | S14: 738 | T14: Current | U14: bike | V14: 15 | W14: 15D
B15: 03H | C15: 1286 | D15: Current | E15: maint | F15: 2354.81 | G15: 03H | J15: 07D | K15: 724 | L15: Current | M15: storage | N15: 100 | O15: 07D | R15: 17A | S15: 1392 | T15: Current | U15: bike | V15: 15 | W15: 17A
B16: 03J | C16: 1016 | D16: Current | E16: maint | F16: 1860.42 | G16: 03J | J16: 08A | K16: 1376 | L16: Current | M16: storage | N16: 75 | O16: 08A | R16: 19J | S16: 1046 | T16: Current | U16: bike | V16: 15 | W16: 19J
B17: 04A | C17: 1368 | D17: Current | E17: maint | F17: 2504.95 | G17: 04A | J17: 08F | K17: 1296 | L17: Current | M17: storage | N17: 125 | O17: 08F | R17: 21E | S17: 1050 | T17: Current | U17: bike | V17: 30 | W17: 21E
B18: 04B | C18: 1368 | D18: Current | E18: maint | F18: 2504.95 | G18: 04B | J18: 09E | K18: 1028 | L18: Current | M18: storage | N18: 100 | O18: 09E | R18: 21G | S18: 2280 | T18: Current | U18: bike | V18: 15 | W18: 21G
B19: 04C | C19: 718 | D19: Current | E19: maint | F19: 1314.74 | G19: 04C | J19: 09E | K19: 1028 | L19: Current | M19: storage | N19: 100 | O19: 09E | R19: 22E | S19: 1052 | T19: Current | U19: bike | V19: 15 | W19: 22E
... B29: 05D | C29: 720 | D29: Current | E29: maint | F29: 1318.41 | G29: 05D | J29: 21G | K29: 2280 | L29: Current | M29: storage | N29: 75 | O29: 21G | R29: 36H | S29: 1430 | T29: Current | U29: bike | V29: 15 | W29: 36H
B30: 05E | C30: 1020 | D30: Current | E30: maint | F30: 1867.71 | G30: 05E | J30: 21J | K30: 1050 | L30: Current | M30: storage | N30: 100 | O30: 21J | S30: =SUM(S8:S29) -> 31014 | V30: =SUM(V8:V29) -> 390
B31: 05F | C31: 1290 | D31: Current | E31: maint | F31: 2362.13 | G31: 05F | J31: 22C | K31: 752 | L31: Current | M31: storage | N31: 180 | O31: 22C
B32: 05G | C32: 2252 | D32: Current | E32: maint | F32: 4123.63 | G32: 05G | J32: 23J | K32: 1054 | L32: Current | M32: storage | N32: 125 | O32: 23J
B33: 05H | C33: 1370 | D33: Current | E33: maint | F33: 2508.63 | G33: 05H | J33: 24D | K33: 756 | L33: Current | M33: storage | N33: 125 | O33: 24D
B34: 05J | C34: 1020 | D34: Current | E34: maint | F34: 1867.71 | G34: 05J | J34: 26B | K34: 1410 | L34: Current | M34: storage | N34: 125 | O34: 26B
B35: 06A | C35: 1372 | D35: Current | E35: maint | F35: 2512.29 | G35: 06A | J35: 26G | K35: 2290 | L35: Current | M35: storage | N35: 100 | O35: 26G
B36: 06B | C36: 1372 | D36: Current | E36: maint | F36: 2512.29 | G36: 06B | J36: 28A | K36: 1414 | L36: Current | M36: storage | N36: 75 | O36: 28A
B37: 06C | C37: 722 | D37: Current | E37: maint | F37: 1322.05 | G37: 06C | J37: 28B | K37: 1414 | L37: Current | M37: storage | N37: 75 | O37: 28B
B38: 06D | C38: 722 | D38: Current | E38: maint | F38: 1322.06 | G38: 06D | J38: 28H | K38: 1414 | L38: Current | M38: storage | N38: 125 | O38: 28H
B39: 06E | C39: 1022 | D39: Current | E39: maint | F39: 1871.4 | G39: 06E | J39: 28J | K39: 1064 | L39: Current | M39: storage | N39: 75 | O39: 28J
B40: 06F | C40: 1292 | D40: Current | E40: maint | F40: 2365.8 | G40: 06F | J40: 29G | K40: 2295 | L40: Current | M40: storage | N40: 75 | O40: 29G
B41: 06G | C41: 2253 | D41: Current | E41: maint | F41: 4125.48 | G41: 06G | J41: 30D | K41: 768 | L41: Current | M41: storage | N41: 75 | O41: 30D
B42: 06H | C42: 1372 | D42: Current | E42: maint | F42: 2512.29 | G42: 06H | J42: 31B | K42: 1420 | L42: Current | M42: storage | N42: 125 | O42: 31B
... B51: 07H | C51: 1374 | D51: Current | E51: maint | F51: 2515.95 | G51: 07H | J51: PHE | K51: 1084 | L51: Current | M51: storage | N51: 125 | O51: PHE
B52: 07J | C52: 1024 | D52: Current | E52: maint | F52: 1875.05 | G52: 07J | K52: =SUM(K8:K51) -> 57185 | N52: =SUM(N8:N51) -> 4715
B53: 08A | C53: 1376 | D53: Current | E53: maint | F53: 2519.62 | G53: 08A
B54: 08B | C54: 1376 | D54: Current | E54: maint | F54: 2519.61 | G54: 08B
B55: 08C | C55: 726 | D55: Current | E55: maint | F55: 1329.4 | G55: 08C
B56: 08D | C56: 726 | D56: Current | E56: maint | F56: 1329.4 | G56: 08D
B57: 08E | C57: 1026 | D57: Current | E57: maint | F57: 1878.72 | G57: 08E
B58: 08F | C58: 1296 | D58: Current | E58: maint | F58: 2373.13 | G58: 08F
B59: 08G | C59: 2257 | D59: Current | E59: maint | F59: 4132.82 | G59: 08G
B60: 08H | C60: 1376 | D60: Current | E60: maint | F60: 2519.62 | G60: 08H
B61: 08J | C61: 1026 | D61: Current | E61: maint | F61: 1878.72 | G61: 08J
B62: 09A | C62: 1378 | D62: Current | E62: maint | F62: 2523.28 | G62: 09A
B63: 09B | C63: 1378 | D63: Current | E63: maint | F63: 2523.28 | G63: 09B
B64: 09C | C64: 728 | D64: Current | E64: maint | F64: 1333.04 | G64: 09C
... B322: PHJ | C322: 1084 | D322: Current | E322: maint | F322: 1984.93 | G322: PHJ
C323: =SUM(C8:C322) -> 398682 | F323: =SUM(F8:F322) -> 730031.64

Sheet Chart for Annual Meeting
A4: =+yrlycomp!H1 -> 444 East 86th Street Owners Corp.
A5: 2022 Budget
O10: Taxes | P10: =+yrlycomp!L31+yrlycomp!L32+yrlycomp!L33 -> 4293089.2 | Q10: =+P10/$P$19 -> 0.455045
O11: Payroll | P11: =+yrlycomp!L23 -> 1540644.7 | Q11: =+P11/$P$19 -> 0.16330028
O12: Financial | P12: =+yrlycomp!L36 -> 890420.12 | Q12: =+P12/$P$19 -> 0.094379876
O13: Utilities | P13: =+yrlycomp!L24+yrlycomp!L25+yrlycomp!L27 -> 1037347.7 | Q13: =+P13/$P$19 -> 0.10995343
O14: Insurance | P14: =+yrlycomp!L30 -> 641578.18 | Q14: =+P14/$P$19 -> 0.068003932
O15: Professional | P15: =+yrlycomp!L34 -> 178772.6 | Q15: =+P15/$P$19 -> 0.018948961
O16: Repairs & Maint | P16: =+'Repairs & Supplies'!J36+'Repairs & Supplies'!J55 -> 675000.26 | Q16: =+P16/$P$19 -> 0.071546497
O17: Supplies | P17: =+'Repairs & Supplies'!J9 -> 90000 | Q17: =+P17/$P$19 -> 0.0095395294
O18: Administrative | P18: =+'Gen & Admin'!J47 -> 87575 | Q18: =+P18/$P$19 -> 0.009282492
P19: =SUM(P10:P18) -> 9434427.7 | Q19: =SUM(Q10:Q18) -> 1
A29: NON-CONTROLLABLE EXPENSES: | F29: CONTROLLABLE EXPENSES:
A30: Taxes | C30: =+Q10 -> 0.455045 | D30: =P10 -> 4293089.2 | F30: Professional | H30: =+Q15 -> 0.018948961 | I30: =+P15 -> 178772.6
A31: Payroll | C31: =+Q11 -> 0.16330028 | D31: =P11 -> 1540644.7 | F31: Repairs & Maint. | H31: =+Q16 -> 0.071546497 | I31: =+P16 -> 675000.26
A32: Financial | C32: =+Q12 -> 0.094379876 | D32: =P12 -> 890420.12 | F32: Supplies | H32: =+Q17 -> 0.0095395294 | I32: =P17 -> 90000
A33: Utilities | C33: =+Q13 -> 0.10995343 | D33: =P13 -> 1037347.7 | F33: Administrative | H33: =+Q18 -> 0.009282492 | I33: =P18 -> 87575 | L33: =+C35+H34 -> 1
A34: Insurance | C34: =+Q14 -> 0.068003932 | D34: =P14 -> 641578.18 | H34: =SUM(H30:H33) -> 0.10931748 | I34: =SUM(I30:I33) -> 1031347.9
C35: =SUM(C30:C34) -> 0.89068252 | D35: =SUM(D30:D34) -> 8403079.8 | L35: =+D35+I34 -> 9434427.7 | M35: should equal total expenses for new budget on yearly comp
L36: =+yrlycomp!L37 -> 9434427.7

Sheet Pie Chart for Annual
B2: =yrlycomp!H1 -> 444 East 86th Street Owners Corp.
B3: 2017 Budget
T5: Matches to the Yrly Comp - change years
V7: Budget Year
S8: =yrlycomp!D7 -> 2021 | T8: =yrlycomp!E7 -> 2022 | U8: 2023 | V8: =yrlycomp!L7 -> 2026
R9: Taxes | S9: =yrlycomp!D31+yrlycomp!D32+yrlycomp!D33 -> 3837960 | T9: =yrlycomp!E31+yrlycomp!E32+yrlycomp!E33 -> 3979788 | U9: 3979788 | V9: =yrlycomp!L31+yrlycomp!L32+yrlycomp!L33 -> 4293089.2
R10: Payroll | S10: =yrlycomp!D23 -> 1273581 | T10: =yrlycomp!E23 -> 1321667 | U10: 1321667 | V10: =yrlycomp!L23 -> 1540644.7
R11: Financial | S11: =yrlycomp!D36 -> 755552 | T11: =yrlycomp!E36 -> 799714 | U11: 799714 | V11: =yrlycomp!L36 -> 890420.12
R12: Utilities | S12: =yrlycomp!D24+yrlycomp!D25+yrlycomp!D27 -> 829208 | T12: =yrlycomp!E24+yrlycomp!E25+yrlycomp!E27 -> 983989 | U12: 983989 | V12: =yrlycomp!L24+yrlycomp!L25++yrlycomp!L27 -> 1037347.7 | X12: Utilities include water
R13: Repairs & Maint | S13: =yrlycomp!D29 -> 527444 | T13: =yrlycomp!E29 -> 494781 | U13: 494781 | V13: =yrlycomp!L29 -> 675000.26
R14: Insurance | S14: =yrlycomp!D30 -> 249055 | T14: =yrlycomp!E30 -> 277481 | U14: 277481 | V14: =yrlycomp!L30 -> 641578.18
R15: Prof Fees | S15: =yrlycomp!D34 -> 208255 | T15: =yrlycomp!E34 -> 220126 | U15: 220126 | V15: =yrlycomp!L34 -> 178772.6
