Workbook

Sheet Cover Sheet
B4: CENTURY MANAGEMENT SERVICES
B6: OPERATING BUDGET
B9: Property Name: | C9: =Setup!B5
B10: Address: | C10: =Setup!B6
B11: Property Code: | C11: =Setup!B4
B12: Budget Year: | C12: =Setup!B7
B16: BUDGET SNAPSHOT
B18: Total Operating Income: | E18: ='Budget Summary'!E8
B19: Total Operating Expenses: | E19: ='Budget Summary'!E22
B20: Operating Surplus / (Deficit): | E20: ='Budget Summary'!E24
B22: Proposed Maintenance Increase: | E22: ='Budget Summary'!E26
B26: Status: | C26: =Setup!B10
B27: Prepared By: | C27: =Setup!B9

Sheet Setup
A1: BUDGET TEMPLATE — SETUP
A2: Enter property details below. All tabs reference these cells.
A4: Property Code: | C4: Yardi entity code
A5: Property Name: | C5: Full legal name
A6: Address: | C6: Street address
A7: Budget Year: | B7: 0 | C7: Year being budgeted
A8: YTD Through: | B8: Sep 20XX | C8: Period of Yardi data
A9: Prepared By: | C9: Initials
A10: YTD Months: | B10: 9 | C10: DRAFT or APPROVED
A11: Remaining Months: | B11: 3
A12: COLOR LEGEND
A13: Orange fill | B13: Yardi paste zone — paste data from Yardi report here
A14: Yellow fill + Blue text | B14: Manual input — team enters assumptions, adjustments
A15: No fill + Black text | B15: Formula — auto-calculates, do not overwrite
A16: Green text | B16: Cross-sheet link — pulls from another tab

Sheet Budget Summary
A1: =Setup!B5
A2: Budget Summary
A3: =Setup!B4 | D3: Status: | E3: =Setup!B10
B5: Category | C5: Prior Year Actual | D5: Current Year Budget | E5: Proposed Budget | F5: $ Variance vs Current | G5: % Change | H5: Source
A7: OPERATING INCOME
B8: Total Operating Income | C8: =Income!D77 | E8: =Income!M77 | F8: =E8-D8 | G8: =IFERROR(E8/D8-1,0) | H8: Income L77
A10: OPERATING EXPENSES
B11: Payroll & Related | C11: =Payroll!D105 | E11: =Payroll!M105 | F11: =E11-D11 | G11: =IFERROR(E11/D11-1,0) | H11: Payroll L105
B12: Energy (Gas + Electric) | C12: =Energy!D77 | E12: =Energy!M77 | F12: =E12-D12 | G12: =IFERROR(E12/D12-1,0) | H12: Energy L77
B13: Water & Sewer | C13: ='Water & Sewer'!D38 | E13: ='Water & Sewer'!M38 | F13: =E13-D13 | G13: =IFERROR(E13/D13-1,0) | H13: 'Water & Sewer' L38
B14: Repairs & Supplies | C14: ='Repairs & Supplies'!D71 | E14: ='Repairs & Supplies'!M71 | F14: =E14-D14 | G14: =IFERROR(E14/D14-1,0) | H14: 'Repairs & Supplies' L71
B15: Professional Fees | C15: ='Gen & Admin'!D17 | E15: ='Gen & Admin'!M17 | F15: =E15-D15 | G15: =IFERROR(E15/D15-1,0) | H15: 'Gen & Admin' L17
B16: Administrative & Other | C16: ='Gen & Admin'!D50 | E16: ='Gen & Admin'!M50 | F16: =E16-D16 | G16: =IFERROR(E16/D16-1,0) | H16: 'Gen & Admin' L50
B17: Insurance | C17: ='Insurance Schedule'!C21 | E17: ='Insurance Schedule'!L21 | F17: =E17-D17 | G17: =IFERROR(E17/D17-1,0) | H17: 'Insurance Schedule' K21
B18: Taxes (RE + Corp) | C18: ='Gen & Admin'!D79 | E18: ='Gen & Admin'!M79 | F18: =E18-D18 | G18: =IFERROR(E18/D18-1,0) | H18: 'Gen & Admin' L79
B19: Financial Expenses | C19: ='Gen & Admin'!D91 | E19: ='Gen & Admin'!M91 | F19: =E19-D19 | G19: =IFERROR(E19/D19-1,0) | H19: 'Gen & Admin' L91
B20: Capital Improvements | E20: 0 | F20: =E20-D20 | G20: =IFERROR(E20/D20-1,0) | H20: Manual input
B21: Reserve / Contingency | E21: 0 | F21: =E21-D21 | G21: =IFERROR(E21/D21-1,0) | H21: Manual input
B22: TOTAL OPERATING EXPENSES | C22: =SUM(C11:C21) | D22: =SUM(D11:D21) | E22: =SUM(E11:E21) | F22: =SUM(F11:F21) | G22: =IFERROR(E22/D22-1,0)
B24: OPERATING SURPLUS / (DEFICIT) | C24: =C8-C22 | D24: =D8-D22 | E24: =E8-E22 | F24: =F8-F22
B26: PROPOSED MAINTENANCE INCREASE: | E26: =IFERROR(IF(E24>=0,0,E24/D8*-1),0)

Sheet Income
A1: =Setup!B5
A2: Income — Budget Year
A3: =Setup!B4
A5: MAINTENANCE INCOME CALCULATION
A6: Total Shares | B6: 0 | C6: Prior Year $/Share/Mo | D6: 0
A7: Proposed Increase % | B7: 0 | C7: New $/Share/Mo | D7: =B6*(1+B7)
A8: Monthly Maintenance | B8: =B6*D7 | C8: Annual Maintenance | D8: =B8*12
A10: STORAGE ROOM INCOME CALCULATION
A11: Size | B11: # Units | C11: # Occupied | D11: $/Month | E11: Monthly Total | F11: Annual
A12: A (28-32 cf) | B12: 0 | C12: 0 | D12: 0 | E12: =C12*D12 | F12: =E12*12
A13: B (36 cf) | B13: 0 | C13: 0 | D13: 0 | E13: =C13*D13 | F13: =E13*12
A14: C (48 cf) | B14: 0 | C14: 0 | D14: 0 | E14: =C14*D14 | F14: =E14*12
A15: D | B15: 0 | C15: 0 | D15: 0 | E15: =C15*D15 | F15: =E15*12
A16: TOTAL STORAGE | B16: =SUM(B12:B15) | C16: =SUM(C12:C15) | E16: =SUM(E12:E15) | F16: =SUM(F12:F15)
A18: BICYCLE STORAGE
A19: # Racks | B19: 0 | C19: # Occupied | D19: 0 | E19: $/Month | F19: 0
A20: Annual Bicycle Income | F20: =D19*F19*12
A22: LAUNDRY / VENDING INCOME
A23: Contract/Description | C23: Monthly Amount | D23: 0
A24: Annual Laundry Income | D24: =D23*12
A26: GL Code | B26: Description | C26: Notes | D26: Prior Year Actual | E26: YTD Actual | F26: Accrual Adj | G26: Unpaid Bills | H26: YTD Budget | I26: Sep-Dec Estimate | J26: 12 Month Forecast | K26: Current Year Budget | L26: Increase % | M26: Proposed Budget | N26: $ Variance | O26: % Change
A27: Yardi | B27: Yardi | C27: Input | D27: Yardi | E27: Yardi | F27: Input | G27: Input | H27: Yardi | I27: Formula | J27: Formula | K27: Yardi | L27: Input | M27: Formula | N27: Formula | O27: Formula
A28: Recurring Income
A29: 4010-0000 | B29: Maintenance | F29: 0 | G29: 0 | I29: =IFERROR(IF((E29+F29+G29)>=D29,(E29+F29+G29)/Setup!$B$10*Setup!$B$11,D29-(E29+F29+G29)),0) | J29: =E29+F29+G29+I29 | L29: 0 | M29: =D8 | N29: =M29-D29 | O29: =IFERROR(M29/D29-1,0)
A30: 4010-0001 | B30: Maintenance - Commercial | F30: 0 | G30: 0 | I30: =IFERROR(IF((E30+F30+G30)>=D30,(E30+F30+G30)/Setup!$B$10*Setup!$B$11,D30-(E30+F30+G30)),0) | J30: =E30+F30+G30+I30 | L30: 0 | M30: =J30*(1+L30) | N30: =M30-D30 | O30: =IFERROR(M30/D30-1,0)
A31: 4040-0000 | B31: Commercial Rent | F31: 0 | G31: 0 | I31: =IFERROR(IF((E31+F31+G31)>=D31,(E31+F31+G31)/Setup!$B$10*Setup!$B$11,D31-(E31+F31+G31)),0) | J31: =E31+F31+G31+I31 | L31: 0 | M31: =J31*(1+L31) | N31: =M31-D31 | O31: =IFERROR(M31/D31-1,0)
A32: 4050-0000 | B32: Parking / Garage Income | F32: 0 | G32: 0 | I32: =IFERROR(IF((E32+F32+G32)>=D32,(E32+F32+G32)/Setup!$B$10*Setup!$B$11,D32-(E32+F32+G32)),0) | J32: =E32+F32+G32+I32 | L32: 0 | M32: =J32*(1+L32) | N32: =M32-D32 | O32: =IFERROR(M32/D32-1,0)
A33: 4060-0000 | B33: Storage Room Income | F33: 0 | G33: 0 | I33: =IFERROR(IF((E33+F33+G33)>=D33,(E33+F33+G33)/Setup!$B$10*Setup!$B$11,D33-(E33+F33+G33)),0) | J33: =E33+F33+G33+I33 | L33: 0 | M33: =J33*(1+L33) | N33: =M33-D33 | O33: =IFERROR(M33/D33-1,0)
A34: 4070-0000 | B34: Prepaid Income | F34: 0 | G34: 0 | I34: =IFERROR(IF((E34+F34+G34)>=D34,(E34+F34+G34)/Setup!$B$10*Setup!$B$11,D34-(E34+F34+G34)),0) | J34: =E34+F34+G34+I34 | L34: 0 | M34: =J34*(1+L34) | N34: =M34-D34 | O34: =IFERROR(M34/D34-1,0)
A35: 4105-0000 | B35: Real Estate Tax Abatement | F35: 0 | G35: 0 | I35: =IFERROR(IF((E35+F35+G35)>=D35,(E35+F35+G35)/Setup!$B$10*Setup!$B$11,D35-(E35+F35+G35)),0) | J35: =E35+F35+G35+I35 | L35: 0 | M35: =J35*(1+L35) | N35: =M35-D35 | O35: =IFERROR(M35/D35-1,0)
A36: 4110-0000 | B36: STAR Exemption | F36: 0 | G36: 0 | I36: =IFERROR(IF((E36+F36+G36)>=D36,(E36+F36+G36)/Setup!$B$10*Setup!$B$11,D36-(E36+F36+G36)),0) | J36: =E36+F36+G36+I36 | L36: 0 | M36: =J36*(1+L36) | N36: =M36-D36 | O36: =IFERROR(M36/D36-1,0)
A37: 4115-0000 | B37: Veterans Exemption | F37: 0 | G37: 0 | I37: =IFERROR(IF((E37+F37+G37)>=D37,(E37+F37+G37)/Setup!$B$10*Setup!$B$11,D37-(E37+F37+G37)),0) | J37: =E37+F37+G37+I37 | L37: 0 | M37: =J37*(1+L37) | N37: =M37-D37 | O37: =IFERROR(M37/D37-1,0)
A38: 4125-0000 | B38: SCHE | F38: 0 | G38: 0 | I38: =IFERROR(IF((E38+F38+G38)>=D38,(E38+F38+G38)/Setup!$B$10*Setup!$B$11,D38-(E38+F38+G38)),0) | J38: =E38+F38+G38+I38 | L38: 0 | M38: =J38*(1+L38) | N38: =M38-D38 | O38: =IFERROR(M38/D38-1,0)
A39: 4130-0010 | B39: Storage Room Rental | F39: 0 | G39: 0 | I39: =IFERROR(IF((E39+F39+G39)>=D39,(E39+F39+G39)/Setup!$B$10*Setup!$B$11,D39-(E39+F39+G39)),0) | J39: =E39+F39+G39+I39 | L39: 0 | M39: =F16 | N39: =M39-D39 | O39: =IFERROR(M39/D39-1,0)
A40: 4130-0015 | B40: Bicycle Charge | F40: 0 | G40: 0 | I40: =IFERROR(IF((E40+F40+G40)>=D40,(E40+F40+G40)/Setup!$B$10*Setup!$B$11,D40-(E40+F40+G40)),0) | J40: =E40+F40+G40+I40 | L40: 0 | M40: =F20 | N40: =M40-D40 | O40: =IFERROR(M40/D40-1,0)
A41: 4130-0030 | B41: Laundry | F41: 0 | G41: 0 | I41: =IFERROR(IF((E41+F41+G41)>=D41,(E41+F41+G41)/Setup!$B$10*Setup!$B$11,D41-(E41+F41+G41)),0) | J41: =E41+F41+G41+I41 | L41: 0 | M41: =D24 | N41: =M41-D41 | O41: =IFERROR(M41/D41-1,0)
A42: 4200-0000 | B42: Assessment - Operating | F42: 0 | G42: 0 | I42: =IFERROR(IF((E42+F42+G42)>=D42,(E42+F42+G42)/Setup!$B$10*Setup!$B$11,D42-(E42+F42+G42)),0) | J42: =E42+F42+G42+I42 | L42: 0 | M42: =J42*(1+L42) | N42: =M42-D42 | O42: =IFERROR(M42/D42-1,0)
A43: 4250-0010 | B43: Cable TV | F43: 0 | G43: 0 | I43: =IFERROR(IF((E43+F43+G43)>=D43,(E43+F43+G43)/Setup!$B$10*Setup!$B$11,D43-(E43+F43+G43)),0) | J43: =E43+F43+G43+I43 | L43: 0 | M43: =J43*(1+L43) | N43: =M43-D43 | O43: =IFERROR(M43/D43-1,0)
A44: 4250-0035 | B44: Dryer | F44: 0 | G44: 0 | I44: =IFERROR(IF((E44+F44+G44)>=D44,(E44+F44+G44)/Setup!$B$10*Setup!$B$11,D44-(E44+F44+G44)),0) | J44: =E44+F44+G44+I44 | L44: 0 | M44: =J44*(1+L44) | N44: =M44-D44 | O44: =IFERROR(M44/D44-1,0)
A45: 4135-0010 | B45: Garage | F45: 0 | G45: 0 | I45: =IFERROR(IF((E45+F45+G45)>=D45,(E45+F45+G45)/Setup!$B$10*Setup!$B$11,D45-(E45+F45+G45)),0) | J45: =E45+F45+G45+I45 | L45: 0 | M45: =J45*(1+L45) | N45: =M45-D45 | O45: =IFERROR(M45/D45-1,0)
A46: 4520-0000 | B46: Commercial Real Estate Tax | D46: 0 | E46: 0 | F46: 0 | G46: 0 | H46: 0 | I46: =IFERROR(D46-(E46+F46+G46),0) | J46: =E46+F46+G46+I46 | L46: 0 | M46: =J46*(1+L46) | N46: =M46-D46 | O46: =IFERROR(M46/D46-1,0)
A47: 4020-0000 | B47: Common Charges | D47: 0 | E47: 0 | F47: 0 | G47: 0 | H47: 0 | I47: =IFERROR(D47-(E47+F47+G47),0) | J47: =E47+F47+G47+I47 | L47: 0 | M47: =J47*(1+L47) | N47: =M47-D47 | O47: =IFERROR(M47/D47-1,0)
A48: 4250-0025 | B48: Electric
A49: 4250-0030 | B49: Washing Machine
B50: Total Recurring Income | D50: =SUM(D29:D47) | E50: =SUM(E29:E47) | F50: =SUM(F29:F47) | G50: =SUM(G29:G47) | H50: =SUM(H29:H47) | I50: =SUM(I29:I47) | J50: =SUM(J29:J47) | K50: =SUM(K29:K47) | M50: =SUM(M29:M47) | N50: =SUM(N29:N47) | O50: =IFERROR(M48/D48-1,0)
A52: Non-Recurring Income
A53: 4710-0000 | B53: Legal Fees | F53: 0 | G53: 0 | I53: =IFERROR(IF((E51+F51+G51)>=D51,(E51+F51+G51)/Setup!$B$10*Setup!$B$11,D51-(E51+F51+G51)),0) | J53: =E51+F51+G51+I51 | L53: 0 | M53: =J51*(1+L51) | N53: =M51-D51 | O53: =IFERROR(M51/D51-1,0)
A54: 4705-0000 | B54: Late Charges | F54: 0 | G54: 0 | I54: =IFERROR(IF((E52+F52+G52)>=D52,(E52+F52+G52)/Setup!$B$10*Setup!$B$11,D52-(E52+F52+G52)),0) | J54: =E52+F52+G52+I52 | L54: 0 | M54: =J52*(1+L52) | N54: =M52-D52 | O54: =IFERROR(M52/D52-1,0)
A55: 4715-0000 | B55: Bounce Check Fee | F55: 0 | G55: 0 | I55: =IFERROR(IF((E53+F53+G53)>=D53,(E53+F53+G53)/Setup!$B$10*Setup!$B$11,D53-(E53+F53+G53)),0) | J55: =E53+F53+G53+I53 | L55: 0 | M55: =J53*(1+L53) | N55: =M53-D53 | O55: =IFERROR(M53/D53-1,0)
A56: 4725-0025 | B56: Move-In Out Fees | F56: 0 | G56: 0 | I56: =IFERROR(IF((E54+F54+G54)>=D54,(E54+F54+G54)/Setup!$B$10*Setup!$B$11,D54-(E54+F54+G54)),0) | J56: =E54+F54+G54+I54 | L56: 0 | M56: =J54*(1+L54) | N56: =M54-D54 | O56: =IFERROR(M54/D54-1,0)
A57: 4725-0035 | B57: Sublet Fees | F57: 0 | G57: 0 | I57: =IFERROR(IF((E55+F55+G55)>=D55,(E55+F55+G55)/Setup!$B$10*Setup!$B$11,D55-(E55+F55+G55)),0) | J57: =E55+F55+G55+I55 | L57: 0 | M57: =J55*(1+L55) | N57: =M55-D55 | O57: =IFERROR(M55/D55-1,0)
A58: 4803-0000 | B58: Dividend Income | F58: 0 | G58: 0 | I58: =IFERROR(IF((E56+F56+G56)>=D56,(E56+F56+G56)/Setup!$B$10*Setup!$B$11,D56-(E56+F56+G56)),0) | J58: =E56+F56+G56+I56 | L58: 0 | M58: =J56*(1+L56) | N58: =M56-D56 | O58: =IFERROR(M56/D56-1,0)
A59: 4922-0000 | B59: Alteration Agreement Fees | F59: 0 | G59: 0 | I59: =IFERROR(IF((E57+F57+G57)>=D57,(E57+F57+G57)/Setup!$B$10*Setup!$B$11,D57-(E57+F57+G57)),0) | J59: =E57+F57+G57+I57 | L59: 0 | M59: =J57*(1+L57) | N59: =M57-D57 | O59: =IFERROR(M57/D57-1,0)
A60: 4932-0000 | B60: Application Fees | F60: 0 | G60: 0 | I60: =IFERROR(IF((E58+F58+G58)>=D58,(E58+F58+G58)/Setup!$B$10*Setup!$B$11,D58-(E58+F58+G58)),0) | J60: =E58+F58+G58+I58 | L60: 0 | M60: =J58*(1+L58) | N60: =M58-D58 | O60: =IFERROR(M58/D58-1,0)
A61: 4933-0000 | B61: Transfer Fees | F61: 0 | G61: 0 | I61: =IFERROR(IF((E59+F59+G59)>=D59,(E59+F59+G59)/Setup!$B$10*Setup!$B$11,D59-(E59+F59+G59)),0) | J61: =E59+F59+G59+I59 | L61: 0 | M61: =J59*(1+L59) | N61: =M59-D59 | O61: =IFERROR(M59/D59-1,0)
A62: 4935-0000 | B62: Flip Tax Income | F62: 0 | G62: 0 | I62: =IFERROR(IF((E60+F60+G60)>=D60,(E60+F60+G60)/Setup!$B$10*Setup!$B$11,D60-(E60+F60+G60)),0) | J62: =E60+F60+G60+I60 | L62: 0 | M62: =J60*(1+L60) | N62: =M60-D60 | O62: =IFERROR(M60/D60-1,0)
A63: 4990-0000 | B63: Other Non-Recurring Income | F63: 0 | G63: 0 | I63: =IFERROR(IF((E61+F61+G61)>=D61,(E61+F61+G61)/Setup!$B$10*Setup!$B$11,D61-(E61+F61+G61)),0) | J63: =E61+F61+G61+I61 | L63: 0 | M63: =J61*(1+L61) | N63: =M61-D61 | O63: =IFERROR(M61/D61-1,0)
A64: 4605-0000 | B64: Conference Room | F64: 0 | G64: 0 | I64: =IFERROR(IF((E62+F62+G62)>=D62,(E62+F62+G62)/Setup!$B$10*Setup!$B$11,D62-(E62+F62+G62)),0) | J64: =E62+F62+G62+I62 | L64: 0 | M64: =J62*(1+L62) | N64: =M62-D62 | O64: =IFERROR(M62/D62-1,0)
... A75: 4725-0030 | B75: Locks & Keys | F75: 0 | G75: 0 | I75: =IFERROR(IF((E73+F73+G73)>=D73,(E73+F73+G73)/Setup!$B$10*Setup!$B$11,D73-(E73+F73+G73)),0) | J75: =E73+F73+G73+I73 | L75: 0 | M75: =J73*(1+L73) | N75: =M73-D73 | O75: =IFERROR(M73/D73-1,0)
A76: 4809-0000 | B76: Real Estate Tax Refunds | D76: 0 | E76: 0 | F76: 0 | G76: 0 | H76: 0 | I76: =IFERROR(D74-(E74+F74+G74),0) | J76: =E74+F74+G74+I74 | L76: 0 | M76: =J74*(1+L74) | N76: =M74-D74 | O76: =IFERROR(M74/D74-1,0)
A77: 4812-0000 | B77: Corporation Tax Refunds
A78: 4830-0000 | B78: Water & Sewer Refunds
A79: 4925-0000 | B79: Pet Fees
B80: Total Non-Recurring Income | D80: =SUM(D51:D74) | E80: =SUM(E51:E74) | F80: =SUM(F51:F74) | G80: =SUM(G51:G74) | H80: =SUM(H51:H74) | I80: =SUM(I51:I74) | J80: =SUM(J51:J74) | K80: =SUM(K51:K74) | M80: =SUM(M51:M74) | N80: =SUM(N51:N74) | O80: =IFERROR(M75/D75-1,0)
B82: TOTAL OPERATING INCOME | D82: =D48+D75 | E82: =E48+E75 | F82: =F48+F75 | G82: =G48+G75 | H82: =H48+H75 | I82: =I48+I75 | J82: =J48+J75 | K82: =K48+K75 | M82: =M48+M75 | N82: =N48+N75 | O82: =IFERROR(M77/D77-1,0)
A84: NOTES
A85: Maintenance Income: set Shares, $/Share, Increase % in calculation area above. Override GL 4010-0000 Proposed Budget if needed.
A86: Storage/Bicycle/Laundry: set unit counts and rates in calculation areas above. Override GL lines if needed.
A87: Orange cells = paste from Yardi. Yellow/Blue = manual input. Black = formula (do not overwrite).

Sheet Payroll
A1: =Setup!B5
A2: Payroll — Budget Year
A3: =Setup!B4
A5: PAYROLL ASSUMPTIONS — Update rates here, all calculations auto-recalculate
A6: Payroll Tax Rates | F6: 32BJ Union Benefit Rates
A7: FICA | B7: 0 | C7: of gross wages | F7: Welfare | G7: $1,072.55/mo/man | H7: 0 | L7: Workers Comp % | M7: 0
A8: SUI | B8: 0 | C8: of first $12,000 | F8: Pension | G8: $82.75/wk/man | H8: 0 | L8: Union Increase % | M8: 0
A9: FUI | B9: 0 | C9: of first $7,000 | F9: Supp. Retirement | G9: $10.00/wk/man | H9: 0 | L9: Increase Effective | M9: Wk 16
A10: MTA | B10: 0 | C10: of gross wages | F10: Legal Fund | G10: $16.63/mo/man | H10: 0 | L10: Pre-increase Weeks | M10: 0
A11: NYS Disability | B11: 0 | C11: per employee/year | F11: Training Fund | G11: $14.13/mo/man | H11: 0 | L11: Post-increase Weeks | M11: 0
A12: Paid Family Leave | B12: 0 | C12: of gross wages | F12: Profit Sharing | G12: $130.00/qtr/man | H12: 0 | L12: Total Weeks | M12: 0
A14: EMPLOYEE ROSTER & WAGE CALCULATION
A15: Position | B15: # | C15: Hourly Rate | D15: Weekly Pay | E15: Pre-Incr Wks | F15: Pre-Incr Wages | G15: Post-Incr Rate | H15: Post-Incr Wks | I15: Post-Incr Wages | J15: Annual Base | L15: OT (0.2%) | M15: Vac/Sick/Hol
A16: Position | B16: Input | C16: Input | D16: Formula | E16: Assumption | F16: Formula | G16: Formula | H16: Assumption | I16: Formula | J16: Formula | L16: Formula | M16: Formula
A17: Resident Manager | B17: 0 | C17: 0 | D17: =C17*40 | E17: =$L$10 | F17: =D17*E17*B17 | G17: =C17*(1+$L$8) | H17: =$L$11 | I17: =(G17*40)*H17*B17 | J17: =F17+I17 | L17: =J17*0.002 | M17: =J17*0.1
A18: Handyman | B18: 0 | C18: 0 | D18: =C18*40 | E18: =$L$10 | F18: =D18*E18*B18 | G18: =C18*(1+$L$8) | H18: =$L$11 | I18: =(G18*40)*H18*B18 | J18: =F18+I18 | L18: =J18*0.002 | M18: =J18*0.1
A19: Porter / Doorman | B19: 0 | C19: 0 | D19: =C19*40 | E19: =$L$10 | F19: =D19*E19*B19 | G19: =C19*(1+$L$8) | H19: =$L$11 | I19: =(G19*40)*H19*B19 | J19: =F19+I19 | L19: =J19*0.002 | M19: =J19*0.1
A20: Porter (80%) | B20: 0 | C20: 0 | D20: =C20*40 | E20: =$L$10 | F20: =D20*E20*B20 | G20: =C20*(1+$L$8) | H20: =$L$11 | I20: =(G20*40)*H20*B20 | J20: =F20+I20 | L20: =J20*0.002 | M20: =J20*0.1
A21: Employee 5 | B21: 0 | C21: 0 | D21: =C21*40 | E21: =$L$10 | F21: =D21*E21*B21 | G21: =C21*(1+$L$8) | H21: =$L$11 | I21: =(G21*40)*H21*B21 | J21: =F21+I21 | L21: =J21*0.002 | M21: =J21*0.1
A22: Employee 6 | B22: 0 | C22: 0 | D22: =C22*40 | E22: =$L$10 | F22: =D22*E22*B22 | G22: =C22*(1+$L$8) | H22: =$L$11 | I22: =(G22*40)*H22*B22 | J22: =F22+I22 | L22: =J22*0.002 | M22: =J22*0.1
A23: Employee 7 | B23: 0 | C23: 0 | D23: =C23*40 | E23: =$L$10 | F23: =D23*E23*B23 | G23: =C23*(1+$L$8) | H23: =$L$11 | I23: =(G23*40)*H23*B23 | J23: =F23+I23 | L23: =J23*0.002 | M23: =J23*0.1
A24: Employee 8 | B24: 0 | C24: 0 | D24: =C24*40 | E24: =$L$10 | F24: =D24*E24*B24 | G24: =C24*(1+$L$8) | H24: =$L$11 | I24: =(G24*40)*H24*B24 | J24: =F24+I24 | L24: =J24*0.002 | M24: =J24*0.1
A25: TOTAL | B25: =SUM(B17:B24) | F25: =SUM(F17:F24) | I25: =SUM(I17:I24) | J25: =SUM(J17:J24) | L25: =SUM(K17:K24) | M25: =SUM(M17:M24)
A27: PAYROLL TAXES, WORKERS COMP & UNION BENEFITS
A28: Category | B28: Rate | C28: Basis | H28: Total
A29: FICA | B29: =$B$7 | C29: Gross × Rate | H29: =(J25+K25+L25)*B29
A30: SUI | B30: =$B$8 | C30: $12K × Rate × # Emp | H30: =12000*B30*B25
A31: FUI | B31: =$B$9 | C31: $7K × Rate × # Emp | H31: =7000*B31*B25
A32: MTA | B32: =$B$10 | C32: Gross × Rate | H32: =(J25+K25+L25)*B32
A33: NYS Disability | B33: =$B$11 | C33: $ per Employee | H33: =B33*B25
A34: Paid Family Leave | B34: =$B$12 | C34: Gross × Rate | H34: =(J25+K25+L25)*B34
A35: Total Payroll Taxes | H35: =SUM(H29:H34)
A37: Workers Compensation | B37: =$L$7 | C37: Gross × Rate | H37: =L7*(J25+K25+L25)
A39: UNION BENEFITS
A40: Benefit | B40: Annual/Man | C40: Basis | H40: Total
A41: Welfare | B41: =$H$7 | C41: $/mo × # emp × 12 | H41: =H7*B25
A42: Pension | B42: =$H$8 | C42: $/wk × # emp × 52 | H42: =H8*B25
A43: Supp. Retirement | B43: =$H$9 | C43: $/wk × # emp × 52 | H43: =H9*B25
A44: Legal Fund | B44: =$H$10 | C44: $/mo × # emp × 12 | H44: =H10*B25
A45: Training Fund | B45: =$H$11 | C45: $/mo × # emp × 12 | H45: =H11*B25
A46: Profit Sharing | B46: =$H$12 | C46: $/qtr × # emp × 4 | H46: =H12*B25
A47: Total Union Benefits | H47: =SUM(H41:H46)
A49: TOTAL LABOR & RELATED (from calculations above) | H49: =J25+K25+L25+H35+H37+H47
A52: GL Code | B52: Description | C52: Notes | D52: Prior Year Actual | E52: YTD Actual | F52: Accrual Adj | G52: Unpaid Bills | H52: YTD Budget | I52: Sep-Dec Estimate | J52: 12 Month Forecast | K52: Current Year Budget | L52: Increase % | M52: Proposed Budget | N52: $ Variance | O52: % Change
A53: Yardi | B53: Yardi | C53: Input | D53: Yardi | E53: Yardi | F53: Input | G53: Input | H53: Yardi | I53: Formula | J53: Formula | K53: Yardi | L53: Input | M53: Formula | N53: Formula | O53: Formula
A54: Wages
A55: 5105-0000 | B55: Gross Payroll | F55: 0 | G55: 0 | I55: =IFERROR(IF((E55+F55+G55)>=D55,(E55+F55+G55)/Setup!$B$10*Setup!$B$11,D55-(E55+F55+G55)),0) | J55: =E55+F55+G55+I55 | L55: =$L$8 | M55: =J55*(1+L55) | N55: =M55-D55 | O55: =IFERROR(M55/D55-1,0)
A56: 5105-0010 | B56: Overtime Pay | F56: 0 | G56: 0 | I56: =IFERROR(IF((E56+F56+G56)>=D56,(E56+F56+G56)/Setup!$B$10*Setup!$B$11,D56-(E56+F56+G56)),0) | J56: =E56+F56+G56+I56 | L56: =$L$8 | M56: =J56*(1+L56) | N56: =M56-D56 | O56: =IFERROR(M56/D56-1,0)
A57: 5105-0015 | B57: Vacation Pay | F57: 0 | G57: 0 | I57: =IFERROR(IF((E57+F57+G57)>=D57,(E57+F57+G57)/Setup!$B$10*Setup!$B$11,D57-(E57+F57+G57)),0) | J57: =E57+F57+G57+I57 | L57: =$L$8 | M57: =J57*(1+L57) | N57: =M57-D57 | O57: =IFERROR(M57/D57-1,0)
A58: 5105-0020 | B58: Holiday Pay | F58: 0 | G58: 0 | I58: =IFERROR(IF((E58+F58+G58)>=D58,(E58+F58+G58)/Setup!$B$10*Setup!$B$11,D58-(E58+F58+G58)),0) | J58: =E58+F58+G58+I58 | L58: =$L$8 | M58: =J58*(1+L58) | N58: =M58-D58 | O58: =IFERROR(M58/D58-1,0)
A59: 5105-0021 | B59: Holiday Premium Pay | F59: 0 | G59: 0 | I59: =IFERROR(IF((E59+F59+G59)>=D59,(E59+F59+G59)/Setup!$B$10*Setup!$B$11,D59-(E59+F59+G59)),0) | J59: =E59+F59+G59+I59 | L59: =$L$8 | M59: =J59*(1+L59) | N59: =M59-D59 | O59: =IFERROR(M59/D59-1,0)
A60: 5105-0025 | B60: Sick Pay | F60: 0 | G60: 0 | I60: =IFERROR(IF((E60+F60+G60)>=D60,(E60+F60+G60)/Setup!$B$10*Setup!$B$11,D60-(E60+F60+G60)),0) | J60: =E60+F60+G60+I60 | L60: =$L$8 | M60: =J60*(1+L60) | N60: =M60-D60 | O60: =IFERROR(M60/D60-1,0)
A61: 5105-0030 | B61: Miscellaneous Pay | F61: 0 | G61: 0 | I61: =IFERROR(IF((E61+F61+G61)>=D61,(E61+F61+G61)/Setup!$B$10*Setup!$B$11,D61-(E61+F61+G61)),0) | J61: =E61+F61+G61+I61 | L61: =$L$8 | M61: =J61*(1+L61) | N61: =M61-D61 | O61: =IFERROR(M61/D61-1,0)
A62: 5105-0035 | B62: Bonus | F62: 0 | G62: 0 | I62: =IFERROR(IF((E62+F62+G62)>=D62,(E62+F62+G62)/Setup!$B$10*Setup!$B$11,D62-(E62+F62+G62)),0) | J62: =E62+F62+G62+I62 | L62: =$L$8 | M62: =J62*(1+L62) | N62: =M62-D62 | O62: =IFERROR(M62/D62-1,0)
A63: 5105-0027 | B63: Meal Reimbursement - Payroll | F63: 0 | G63: 0 | I63: =IFERROR(IF((E63+F63+G63)>=D63,(E63+F63+G63)/Setup!$B$10*Setup!$B$11,D63-(E63+F63+G63)),0) | J63: =E63+F63+G63+I63 | L63: =$L$8 | M63: =J63*(1+L63) | N63: =M63-D63 | O63: =IFERROR(M63/D63-1,0)
D64: 0 | E64: 0 | F64: 0 | G64: 0 | H64: 0 | I64: =IFERROR(D64-(E64+F64+G64),0) | J64: =E64+F64+G64+I64 | L64: 0 | M64: =J64*(1+L64) | N64: =M64-D64 | O64: =IFERROR(M64/D64-1,0)
D65: 0 | E65: 0 | F65: 0 | G65: 0 | H65: 0 | I65: =IFERROR(D65-(E65+F65+G65),0) | J65: =E65+F65+G65+I65 | L65: 0 | M65: =J65*(1+L65) | N65: =M65-D65 | O65: =IFERROR(M65/D65-1,0)
B66: Total Wages | D66: =SUM(D55:D65) | E66: =SUM(E55:E65) | F66: =SUM(F55:F65) | G66: =SUM(G55:G65) | H66: =SUM(H55:H65) | I66: =SUM(I55:I65) | J66: =SUM(J55:J65) | K66: =SUM(K55:K65) | M66: =SUM(M55:M65) | N66: =SUM(N55:N65) | O66: =IFERROR(M66/D66-1,0)
A68: Payroll Taxes
A69: 5145-0000 | B69: Employer Payroll Taxes | F69: 0 | G69: 0 | I69: =IFERROR(IF((E69+F69+G69)>=D69,(E69+F69+G69)/Setup!$B$10*Setup!$B$11,D69-(E69+F69+G69)),0) | J69: =E69+F69+G69+I69 | L69: =$L$8 | M69: =J69*(1+L69) | N69: =M69-D69 | O69: =IFERROR(M69/D69-1,0)
A70: 5140-0015 | B70: Federal withholding Taxes | F70: 0 | G70: 0 | I70: =IFERROR(IF((E70+F70+G70)>=D70,(E70+F70+G70)/Setup!$B$10*Setup!$B$11,D70-(E70+F70+G70)),0) | J70: =E70+F70+G70+I70 | L70: =$L$8 | M70: =J70*(1+L70) | N70: =M70-D70 | O70: =IFERROR(M70/D70-1,0)
A71: 5140-0020 | B71: NYS withholding Taxes | F71: 0 | G71: 0 | I71: =IFERROR(IF((E71+F71+G71)>=D71,(E71+F71+G71)/Setup!$B$10*Setup!$B$11,D71-(E71+F71+G71)),0) | J71: =E71+F71+G71+I71 | L71: =$L$8 | M71: =J71*(1+L71) | N71: =M71-D71 | O71: =IFERROR(M71/D71-1,0)
A72: 5140-0025 | B72: NYC withholding Taxes | F72: 0 | G72: 0 | I72: =IFERROR(IF((E72+F72+G72)>=D72,(E72+F72+G72)/Setup!$B$10*Setup!$B$11,D72-(E72+F72+G72)),0) | J72: =E72+F72+G72+I72 | L72: =$L$8 | M72: =J72*(1+L72) | N72: =M72-D72 | O72: =IFERROR(M72/D72-1,0)
A73: 5145-0015 | B73: SUI - State Unemployment Insurance | D73: 0 | E73: 0 | F73: 0 | G73: 0 | H73: 0 | I73: =IFERROR(D73-(E73+F73+G73),0) | J73: =E73+F73+G73+I73 | L73: 0 | M73: =J73*(1+L73) | N73: =M73-D73 | O73: =IFERROR(M73/D73-1,0)
D74: 0 | E74: 0 | F74: 0 | G74: 0 | H74: 0 | I74: =IFERROR(D74-(E74+F74+G74),0) | J74: =E74+F74+G74+I74 | L74: 0 | M74: =J74*(1+L74) | N74: =M74-D74 | O74: =IFERROR(M74/D74-1,0)
D75: 0 | E75: 0 | F75: 0 | G75: 0 | H75: 0 | I75: =IFERROR(D75-(E75+F75+G75),0) | J75: =E75+F75+G75+I75 | L75: 0 | M75: =J75*(1+L75) | N75: =M75-D75 | O75: =IFERROR(M75/D75-1,0)
B76: Total Payroll Taxes | D76: =SUM(D69:D75) | E76: =SUM(E69:E75) | F76: =SUM(F69:F75) | G76: =SUM(G69:G75) | H76: =SUM(H69:H75) | I76: =SUM(I69:I75) | J76: =SUM(J69:J75) | K76: =SUM(K69:K75) | M76: =SUM(M69:M75) | N76: =SUM(N69:N75) | O76: =IFERROR(M76/D76-1,0)
A78: Benefits
A79: 5155-0015 | B79: Health Insurance | F79: 0 | G79: 0 | I79: =IFERROR(IF((E79+F79+G79)>=D79,(E79+F79+G79)/Setup!$B$10*Setup!$B$11,D79-(E79+F79+G79)),0) | J79: =E79+F79+G79+I79 | L79: =$L$8 | M79: =J79*(1+L79) | N79: =M79-D79 | O79: =IFERROR(M79/D79-1,0)
A80: 5160-0010 | B80: Pension Fund | F80: 0 | G80: 0 | I80: =IFERROR(IF((E80+F80+G80)>=D80,(E80+F80+G80)/Setup!$B$10*Setup!$B$11,D80-(E80+F80+G80)),0) | J80: =E80+F80+G80+I80 | L80: =$L$8 | M80: =J80*(1+L80) | N80: =M80-D80 | O80: =IFERROR(M80/D80-1,0)
A81: 5160-0015 | B81: Health Fund | F81: 0 | G81: 0 | I81: =IFERROR(IF((E81+F81+G81)>=D81,(E81+F81+G81)/Setup!$B$10*Setup!$B$11,D81-(E81+F81+G81)),0) | J81: =E81+F81+G81+I81 | L81: =$L$8 | M81: =J81*(1+L81) | N81: =M81-D81 | O81: =IFERROR(M81/D81-1,0)
A82: 5160-0020 | B82: Annuity Fund | F82: 0 | G82: 0 | I82: =IFERROR(IF((E82+F82+G82)>=D82,(E82+F82+G82)/Setup!$B$10*Setup!$B$11,D82-(E82+F82+G82)),0) | J82: =E82+F82+G82+I82 | L82: =$L$8 | M82: =J82*(1+L82) | N82: =M82-D82 | O82: =IFERROR(M82/D82-1,0)
A83: 5160-0025 | B83: Legal Fund | F83: 0 | G83: 0 | I83: =IFERROR(IF((E83+F83+G83)>=D83,(E83+F83+G83)/Setup!$B$10*Setup!$B$11,D83-(E83+F83+G83)),0) | J83: =E83+F83+G83+I83 | L83: =$L$8 | M83: =J83*(1+L83) | N83: =M83-D83 | O83: =IFERROR(M83/D83-1,0)
A84: 5160-0030 | B84: Training Fund | F84: 0 | G84: 0 | I84: =IFERROR(IF((E84+F84+G84)>=D84,(E84+F84+G84)/Setup!$B$10*Setup!$B$11,D84-(E84+F84+G84)),0) | J84: =E84+F84+G84+I84 | L84: =$L$8 | M84: =J84*(1+L84) | N84: =M84-D84 | O84: =IFERROR(M84/D84-1,0)
A85: 5160-0035 | B85: Profit Sharing | F85: 0 | G85: 0 | I85: =IFERROR(IF((E85+F85+G85)>=D85,(E85+F85+G85)/Setup!$B$10*Setup!$B$11,D85-(E85+F85+G85)),0) | J85: =E85+F85+G85+I85 | L85: =$L$8 | M85: =J85*(1+L85) | N85: =M85-D85 | O85: =IFERROR(M85/D85-1,0)
A86: 5150-0000 | B86: 401K | F86: 0 | G86: 0 | I86: =IFERROR(IF((E86+F86+G86)>=D86,(E86+F86+G86)/Setup!$B$10*Setup!$B$11,D86-(E86+F86+G86)),0) | J86: =E86+F86+G86+I86 | L86: =$L$8 | M86: =J86*(1+L86) | N86: =M86-D86 | O86: =IFERROR(M86/D86-1,0)
A87: 5160-0000 | B87: Union Benefit Funds | F87: 0 | G87: 0 | I87: =IFERROR(IF((E87+F87+G87)>=D87,(E87+F87+G87)/Setup!$B$10*Setup!$B$11,D87-(E87+F87+G87)),0) | J87: =E87+F87+G87+I87 | L87: =$L$8 | M87: =J87*(1+L87) | N87: =M87-D87 | O87: =IFERROR(M87/D87-1,0)
A88: 5155-0010 | B88: Union Dues | D88: 0 | E88: 0 | F88: 0 | G88: 0 | H88: 0 | I88: =IFERROR(D88-(E88+F88+G88),0) | J88: =E88+F88+G88+I88 | L88: 0 | M88: =J88*(1+L88) | N88: =M88-D88 | O88: =IFERROR(M88/D88-1,0)
D89: 0 | E89: 0 | F89: 0 | G89: 0 | H89: 0 | I89: =IFERROR(D89-(E89+F89+G89),0) | J89: =E89+F89+G89+I89 | L89: 0 | M89: =J89*(1+L89) | N89: =M89-D89 | O89: =IFERROR(M89/D89-1,0)
D90: 0 | E90: 0 | F90: 0 | G90: 0 | H90: 0 | I90: =IFERROR(D90-(E90+F90+G90),0) | J90: =E90+F90+G90+I90 | L90: 0 | M90: =J90*(1+L90) | N90: =M90-D90 | O90: =IFERROR(M90/D90-1,0)
B91: Total Benefits | D91: =SUM(D79:D90) | E91: =SUM(E79:E90) | F91: =SUM(F79:F90) | G91: =SUM(G79:G90) | H91: =SUM(H79:H90) | I91: =SUM(I79:I90) | J91: =SUM(J79:J90) | K91: =SUM(K79:K90) | M91: =SUM(M79:M90) | N91: =SUM(N79:N90) | O91: =IFERROR(M91/D91-1,0)
A93: Other Payroll
A94: 5162-0000 | B94: Workers Compensation | F94: 0 | G94: 0 | I94: =IFERROR(IF((E94+F94+G94)>=D94,(E94+F94+G94)/Setup!$B$10*Setup!$B$11,D94-(E94+F94+G94)),0) | J94: =E94+F94+G94+I94 | L94: =$L$8 | M94: =J94*(1+L94) | N94: =M94-D94 | O94: =IFERROR(M94/D94-1,0)
A95: 5165-0000 | B95: Workers Compensation Insurance | F95: 0 | G95: 0 | I95: =IFERROR(IF((E95+F95+G95)>=D95,(E95+F95+G95)/Setup!$B$10*Setup!$B$11,D95-(E95+F95+G95)),0) | J95: =E95+F95+G95+I95 | L95: =$L$8 | M95: =J95*(1+L95) | N95: =M95-D95 | O95: =IFERROR(M95/D95-1,0)
A96: 5166-0000 | B96: Disability Insurance | F96: 0 | G96: 0 | I96: =IFERROR(IF((E96+F96+G96)>=D96,(E96+F96+G96)/Setup!$B$10*Setup!$B$11,D96-(E96+F96+G96)),0) | J96: =E96+F96+G96+I96 | L96: =$L$8 | M96: =J96*(1+L96) | N96: =M96-D96 | O96: =IFERROR(M96/D96-1,0)
A97: 5168-0000 | B97: Paid Family Leave | F97: 0 | G97: 0 | I97: =IFERROR(IF((E97+F97+G97)>=D97,(E97+F97+G97)/Setup!$B$10*Setup!$B$11,D97-(E97+F97+G97)),0) | J97: =E97+F97+G97+I97 | L97: =$L$8 | M97: =J97*(1+L97) | N97: =M97-D97 | O97: =IFERROR(M97/D97-1,0)
A98: 5172-0000 | B98: Payroll Processing | F98: 0 | G98: 0 | I98: =IFERROR(IF((E98+F98+G98)>=D98,(E98+F98+G98)/Setup!$B$10*Setup!$B$11,D98-(E98+F98+G98)),0) | J98: =E98+F98+G98+I98 | L98: =$L$8 | M98: =J98*(1+L98) | N98: =M98-D98 | O98: =IFERROR(M98/D98-1,0)
A99: 5165-0050 | B99: Workers Comp Audit / Dividend | F99: 0 | G99: 0 | I99: =IFERROR(IF((E99+F99+G99)>=D99,(E99+F99+G99)/Setup!$B$10*Setup!$B$11,D99-(E99+F99+G99)),0) | J99: =E99+F99+G99+I99 | L99: =$L$8 | M99: =J99*(1+L99) | N99: =M99-D99 | O99: =IFERROR(M99/D99-1,0)
D100: 0 | E100: 0 | F100: 0 | G100: 0 | H100: 0 | I100: =IFERROR(D100-(E100+F100+G100),0) | J100: =E100+F100+G100+I100 | L100: 0 | M100: =J100*(1+L100) | N100: =M100-D100 | O100: =IFERROR(M100/D100-1,0)
D101: 0 | E101: 0 | F101: 0 | G101: 0 | H101: 0 | I101: =IFERROR(D101-(E101+F101+G101),0) | J101: =E101+F101+G101+I101 | L101: 0 | M101: =J101*(1+L101) | N101: =M101-D101 | O101: =IFERROR(M101/D101-1,0)
D102: 0 | E102: 0 | F102: 0 | G102: 0 | H102: 0 | I102: =IFERROR(D102-(E102+F102+G102),0) | J102: =E102+F102+G102+I102 | L102: 0 | M102: =J102*(1+L102) | N102: =M102-D102 | O102: =IFERROR(M102/D102-1,0)
B103: Total Other Payroll | D103: =SUM(D94:D102) | E103: =SUM(E94:E102) | F103: =SUM(F94:F102) | G103: =SUM(G94:G102) | H103: =SUM(H94:H102) | I103: =SUM(I94:I102) | J103: =SUM(J94:J102) | K103: =SUM(K94:K102) | M103: =SUM(M94:M102) | N103: =SUM(N94:N102) | O103: =IFERROR(M103/D103-1,0)
B105: TOTAL PAYROLL | D105: =D66+D76+D91+D103 | E105: =E66+E76+E91+E103 | F105: =F66+F76+F91+F103 | G105: =G66+G76+G91+G103 | H105: =H66+H76+H91+H103 | I105: =I66+I76+I91+I103 | J105: =J66+J76+J91+J103 | K105: =K66+K76+K91+K103 | M105: =M66+M76+M91+M103 | N105: =N66+N76+N91+N103 | O105: =IFERROR(M105/D105-1,0)
A107: NOTES
A108: Payroll Assumptions: update tax rates, union rates, and increase % at top of tab.
A109: Employee Roster: enter position count and hourly rate. Wages auto-calculate with split-year increase.
A110: GL detail section: Yardi YTD data + formulas for Sep-Dec estimate and Proposed Budget.
A111: Total Labor (H above) is the calculated budget. GL TOTAL PAYROLL (below) ties to Yardi format.

Sheet Energy
A1: =Setup!B5
A2: Energy — Budget Year
A3: =Setup!B4
A5: ENERGY ASSUMPTIONS
A6: Gas ESCO Contract $/Therm | B6: 0 | C6: Contract price if applicable
A7: Electric ESCO Contract $/KWH | B7: 0 | C7: Contract price if applicable
A8: Gas Rate Increase % | B8: 0 | C8: Budget year increase
A9: Electric Rate Increase % | B9: 0 | C9: Budget year increase
A10: Consumption Basis | B10: 2-Year Average | C10: Method: 2-Year Average, Prior Year, or Custom
A11: Water/Sewer Rate Increase % | B11: 0 | C11: Applied to prior year forecast
A13: UTILITY ACCOUNTS
A14: Utility Type | B14: GL Code | C14: Account # | D14: Supplier(s) | E14: Unit
A15: Gas - Heating | B15: 5252-0000 | E15: Therms
A16: Electric - Main | B16: 5255-0000 | E16: KWH
A17: Electric - Super | B17: 5255-0010 | E17: KWH
A18: Steam | B18: 5265-0000 | E18: MLB
A20: SECTION A: GAS / HEATING — Monthly Consumption Detail
A21: Month | B21: Prior Yr Therms | C21: Current Yr Therms | D21: 2-Yr Avg Therms | E21: ConEd $/Therm | F21: ESCO $/Therm | G21: ConEd Amount | H21: ESCO Amount | I21: Total Budget
A22: January | B22: 0 | C22: 0 | D22: =(B22+C22)/2 | E22: 0 | F22: =$B$6 | G22: =D22*E22 | H22: =D22*F22 | I22: =G22+H22
A23: February | B23: 0 | C23: 0 | D23: =(B23+C23)/2 | E23: 0 | F23: =$B$6 | G23: =D23*E23 | H23: =D23*F23 | I23: =G23+H23
A24: March | B24: 0 | C24: 0 | D24: =(B24+C24)/2 | E24: 0 | F24: =$B$6 | G24: =D24*E24 | H24: =D24*F24 | I24: =G24+H24
A25: April | B25: 0 | C25: 0 | D25: =(B25+C25)/2 | E25: 0 | F25: =$B$6 | G25: =D25*E25 | H25: =D25*F25 | I25: =G25+H25
A26: May | B26: 0 | C26: 0 | D26: =(B26+C26)/2 | E26: 0 | F26: =$B$6 | G26: =D26*E26 | H26: =D26*F26 | I26: =G26+H26
A27: June | B27: 0 | C27: 0 | D27: =(B27+C27)/2 | E27: 0 | F27: =$B$6 | G27: =D27*E27 | H27: =D27*F27 | I27: =G27+H27
A28: July | B28: 0 | C28: 0 | D28: =(B28+C28)/2 | E28: 0 | F28: =$B$6 | G28: =D28*E28 | H28: =D28*F28 | I28: =G28+H28
A29: August | B29: 0 | C29: 0 | D29: =(B29+C29)/2 | E29: 0 | F29: =$B$6 | G29: =D29*E29 | H29: =D29*F29 | I29: =G29+H29
A30: September | B30: 0 | C30: 0 | D30: =(B30+C30)/2 | E30: 0 | F30: =$B$6 | G30: =D30*E30 | H30: =D30*F30 | I30: =G30+H30
A31: October | B31: 0 | C31: 0 | D31: =(B31+C31)/2 | E31: 0 | F31: =$B$6 | G31: =D31*E31 | H31: =D31*F31 | I31: =G31+H31
A32: November | B32: 0 | C32: 0 | D32: =(B32+C32)/2 | E32: 0 | F32: =$B$6 | G32: =D32*E32 | H32: =D32*F32 | I32: =G32+H32
A33: December | B33: 0 | C33: 0 | D33: =(B33+C33)/2 | E33: 0 | F33: =$B$6 | G33: =D33*E33 | H33: =D33*F33 | I33: =G33+H33
A34: TOTAL GAS | B34: =SUM(B22:B33) | C34: =SUM(C22:C33) | D34: =SUM(D22:D33) | E34: =IF(D34=0,0,G34/D34) | F34: =IF(D34=0,0,H34/D34) | G34: =SUM(G22:G33) | H34: =SUM(H22:H33) | I34: =SUM(I22:I33) | K34: =SUM(K22:K33)
A36: SECTION B: ELECTRIC — Monthly Consumption Detail
A37: Month | B37: Prior Yr KWH | C37: Current Yr KWH | D37: 2-Yr Avg KWH | E37: ConEd $/KWH | F37: ESCO $/KWH | G37: ConEd Amount | H37: ESCO Amount | I37: Total Budget
A38: January | B38: 0 | C38: 0 | D38: =(B38+C38)/2 | E38: 0 | F38: =$B$7 | G38: =D38*E38 | H38: =D38*F38 | I38: =G38+H38
A39: February | B39: 0 | C39: 0 | D39: =(B39+C39)/2 | E39: 0 | F39: =$B$7 | G39: =D39*E39 | H39: =D39*F39 | I39: =G39+H39
A40: March | B40: 0 | C40: 0 | D40: =(B40+C40)/2 | E40: 0 | F40: =$B$7 | G40: =D40*E40 | H40: =D40*F40 | I40: =G40+H40
A41: April | B41: 0 | C41: 0 | D41: =(B41+C41)/2 | E41: 0 | F41: =$B$7 | G41: =D41*E41 | H41: =D41*F41 | I41: =G41+H41
A42: May | B42: 0 | C42: 0 | D42: =(B42+C42)/2 | E42: 0 | F42: =$B$7 | G42: =D42*E42 | H42: =D42*F42 | I42: =G42+H42
A43: June | B43: 0 | C43: 0 | D43: =(B43+C43)/2 | E43: 0 | F43: =$B$7 | G43: =D43*E43 | H43: =D43*F43 | I43: =G43+H43
A44: July | B44: 0 | C44: 0 | D44: =(B44+C44)/2 | E44: 0 | F44: =$B$7 | G44: =D44*E44 | H44: =D44*F44 | I44: =G44+H44
A45: August | B45: 0 | C45: 0 | D45: =(B45+C45)/2 | E45: 0 | F45: =$B$7 | G45: =D45*E45 | H45: =D45*F45 | I45: =G45+H45
A46: September | B46: 0 | C46: 0 | D46: =(B46+C46)/2 | E46: 0 | F46: =$B$7 | G46: =D46*E46 | H46: =D46*F46 | I46: =G46+H46
A47: October | B47: 0 | C47: 0 | D47: =(B47+C47)/2 | E47: 0 | F47: =$B$7 | G47: =D47*E47 | H47: =D47*F47 | I47: =G47+H47
A48: November | B48: 0 | C48: 0 | D48: =(B48+C48)/2 | E48: 0 | F48: =$B$7 | G48: =D48*E48 | H48: =D48*F48 | I48: =G48+H48
A49: December | B49: 0 | C49: 0 | D49: =(B49+C49)/2 | E49: 0 | F49: =$B$7 | G49: =D49*E49 | H49: =D49*F49 | I49: =G49+H49
A50: TOTAL ELECTRIC | B50: =SUM(B38:B49) | C50: =SUM(C38:C49) | D50: =SUM(D38:D49) | E50: =IF(D50=0,0,G50/D50) | F50: =IF(D50=0,0,H50/D50) | G50: =SUM(G38:G49) | H50: =SUM(H38:H49) | I50: =SUM(I38:I49) | K50: =SUM(K38:K49)
A53: GL Code | B53: Description | C53: Notes | D53: Prior Year Actual | E53: YTD Actual | F53: Accrual Adj | G53: Unpaid Bills | H53: YTD Budget | I53: Sep-Dec Estimate | J53: 12 Month Forecast | K53: Current Year Budget | L53: Increase % | M53: Proposed Budget | N53: $ Variance | O53: % Change
A54: Yardi | B54: Yardi | C54: Input | D54: Yardi | E54: Yardi | F54: Input | G54: Input | H54: Yardi | I54: Formula | J54: Formula | K54: Yardi | L54: Input | M54: Formula | N54: Formula | O54: Formula
A55: Gas / Heating
A56: 5252-0000 | B56: Gas - Heating | F56: 0 | G56: 0 | I56: =IFERROR(IF((E56+F56+G56)>=D56,(E56+F56+G56)/Setup!$B$10*Setup!$B$11,D56-(E56+F56+G56)),0) | J56: =E56+F56+G56+I56 | L56: =$B$8 | M56: =J56*(1+L56) | N56: =M56-D56 | O56: =IFERROR(M56/D56-1,0)
A57: 5252-0001 | B57: Gas - Cooking | F57: 0 | G57: 0 | I57: =IFERROR(IF((E57+F57+G57)>=D57,(E57+F57+G57)/Setup!$B$10*Setup!$B$11,D57-(E57+F57+G57)),0) | J57: =E57+F57+G57+I57 | L57: =$B$8 | M57: =J57*(1+L57) | N57: =M57-D57 | O57: =IFERROR(M57/D57-1,0)
A58: 5252-0010 | B58: Gas - Common Area | F58: 0 | G58: 0 | I58: =IFERROR(IF((E58+F58+G58)>=D58,(E58+F58+G58)/Setup!$B$10*Setup!$B$11,D58-(E58+F58+G58)),0) | J58: =E58+F58+G58+I58 | L58: =$B$8 | M58: =J58*(1+L58) | N58: =M58-D58 | O58: =IFERROR(M58/D58-1,0)
A59: 5253-0000 | B59: Oil / Fuel | F59: 0 | G59: 0 | I59: =IFERROR(IF((E59+F59+G59)>=D59,(E59+F59+G59)/Setup!$B$10*Setup!$B$11,D59-(E59+F59+G59)),0) | J59: =E59+F59+G59+I59 | L59: =$B$8 | M59: =J59*(1+L59) | N59: =M59-D59 | O59: =IFERROR(M59/D59-1,0)
A60: 5250-0000 | B60: Gas | F60: 0 | G60: 0 | I60: =IFERROR(IF((E60+F60+G60)>=D60,(E60+F60+G60)/Setup!$B$10*Setup!$B$11,D60-(E60+F60+G60)),0) | J60: =E60+F60+G60+I60 | L60: =$B$8 | M60: =J60*(1+L60) | N60: =M60-D60 | O60: =IFERROR(M60/D60-1,0)
D61: 0 | E61: 0 | F61: 0 | G61: 0 | H61: 0 | I61: =IFERROR(D61-(E61+F61+G61),0) | J61: =E61+F61+G61+I61 | L61: 0 | M61: =J61*(1+L61) | N61: =M61-D61 | O61: =IFERROR(M61/D61-1,0)
D62: 0 | E62: 0 | F62: 0 | G62: 0 | H62: 0 | I62: =IFERROR(D62-(E62+F62+G62),0) | J62: =E62+F62+G62+I62 | L62: 0 | M62: =J62*(1+L62) | N62: =M62-D62 | O62: =IFERROR(M62/D62-1,0)
A63: 5260-0000 | B63: Fuel | D63: 0 | E63: 0 | F63: 0 | G63: 0 | H63: 0 | I63: =IFERROR(D63-(E63+F63+G63),0) | J63: =E63+F63+G63+I63 | L63: 0 | M63: =J63*(1+L63) | N63: =M63-D63 | O63: =IFERROR(M63/D63-1,0)
B64: Total Gas / Heating | D64: =SUM(D56:D63) | E64: =SUM(E56:E63) | F64: =SUM(F56:F63) | G64: =SUM(G56:G63) | H64: =SUM(H56:H63) | I64: =SUM(I56:I63) | J64: =SUM(J56:J63) | K64: =SUM(K56:K63) | M64: =SUM(M56:M63) | N64: =SUM(N56:N63) | O64: =IFERROR(M64/D64-1,0)
A66: Electric
A67: 5255-0000 | B67: Electricity | F67: 0 | G67: 0 | I67: =IFERROR(IF((E67+F67+G67)>=D67,(E67+F67+G67)/Setup!$B$10*Setup!$B$11,D67-(E67+F67+G67)),0) | J67: =E67+F67+G67+I67 | L67: =$B$9 | M67: =J67*(1+L67) | N67: =M67-D67 | O67: =IFERROR(M67/D67-1,0)
A68: 5255-0010 | B68: Electricity - Common Area / Super | F68: 0 | G68: 0 | I68: =IFERROR(IF((E68+F68+G68)>=D68,(E68+F68+G68)/Setup!$B$10*Setup!$B$11,D68-(E68+F68+G68)),0) | J68: =E68+F68+G68+I68 | L68: =$B$9 | M68: =J68*(1+L68) | N68: =M68-D68 | O68: =IFERROR(M68/D68-1,0)
A69: 5255-0020 | B69: Electricity - Garage | F69: 0 | G69: 0 | I69: =IFERROR(IF((E69+F69+G69)>=D69,(E69+F69+G69)/Setup!$B$10*Setup!$B$11,D69-(E69+F69+G69)),0) | J69: =E69+F69+G69+I69 | L69: =$B$9 | M69: =J69*(1+L69) | N69: =M69-D69 | O69: =IFERROR(M69/D69-1,0)
A70: 5256-0000 | B70: Steam | F70: 0 | G70: 0 | I70: =IFERROR(IF((E70+F70+G70)>=D70,(E70+F70+G70)/Setup!$B$10*Setup!$B$11,D70-(E70+F70+G70)),0) | J70: =E70+F70+G70+I70 | L70: =$B$9 | M70: =J70*(1+L70) | N70: =M70-D70 | O70: =IFERROR(M70/D70-1,0)
A71: 5265-0000 | B71: Steam | F71: 0 | G71: 0 | I71: =IFERROR(IF((E71+F71+G71)>=D71,(E71+F71+G71)/Setup!$B$10*Setup!$B$11,D71-(E71+F71+G71)),0) | J71: =E71+F71+G71+I71 | L71: =$B$9 | M71: =J71*(1+L71) | N71: =M71-D71 | O71: =IFERROR(M71/D71-1,0)
D72: 0 | E72: 0 | F72: 0 | G72: 0 | H72: 0 | I72: =IFERROR(D72-(E72+F72+G72),0) | J72: =E72+F72+G72+I72 | L72: 0 | M72: =J72*(1+L72) | N72: =M72-D72 | O72: =IFERROR(M72/D72-1,0)
D73: 0 | E73: 0 | F73: 0 | G73: 0 | H73: 0 | I73: =IFERROR(D73-(E73+F73+G73),0) | J73: =E73+F73+G73+I73 | L73: 0 | M73: =J73*(1+L73) | N73: =M73-D73 | O73: =IFERROR(M73/D73-1,0)
D74: 0 | E74: 0 | F74: 0 | G74: 0 | H74: 0 | I74: =IFERROR(D74-(E74+F74+G74),0) | J74: =E74+F74+G74+I74 | L74: 0 | M74: =J74*(1+L74) | N74: =M74-D74 | O74: =IFERROR(M74/D74-1,0)
B75: Total Electric | D75: =SUM(D67:D74) | E75: =SUM(E67:E74) | F75: =SUM(F67:F74) | G75: =SUM(G67:G74) | H75: =SUM(H67:H74) | I75: =SUM(I67:I74) | J75: =SUM(J67:J74) | K75: =SUM(K67:K74) | M75: =SUM(M67:M74) | N75: =SUM(N67:N74) | O75: =IFERROR(M75/D75-1,0)
B77: TOTAL ENERGY | D77: =D64+D75 | E77: =E64+E75 | F77: =F64+F75 | G77: =G64+G75 | H77: =H64+H75 | I77: =I64+I75 | J77: =J64+J75 | K77: =K64+K75 | M77: =M64+M75 | N77: =N64+N75 | O77: =IFERROR(M77/D77-1,0)
A79: NOTES
A80: Monthly consumption sections above: enter prior yr and current yr therms/KWH. 2-yr average auto-calculates.
A81: Gas total from monthly detail = I34. Electric total = I50. Override GL Proposed Budget if needed.
A82: ESCO rates reference assumptions at top. ConEd rates are per-month inputs for actual bill detail.

Sheet Water & Sewer
A1: =Setup!B5
A2: Water & Sewer — Budget Year
A3: =Setup!B4
A5: WATER & SEWER ASSUMPTIONS
A6: Rate Increase % | B6: 0 | C6: Applied to prior year forecast
A7: Water Account # | C7: GL Code | D7: 6305-0000
A9: BILLING PERIOD TRACKER
A10: Begin Date | B10: End Date | C10: Payment Amount | D10: # of Days | E10: Avg $/Day | F10: Days in Budget Yr | G10: Allocated to Year
D11: =IFERROR(B11-A11,"") | E11: =IFERROR(C11/D11,"") | G11: =IFERROR(E11*F11,"")
D12: =IFERROR(B12-A12,"") | E12: =IFERROR(C12/D12,"") | G12: =IFERROR(E12*F12,"")
D13: =IFERROR(B13-A13,"") | E13: =IFERROR(C13/D13,"") | G13: =IFERROR(E13*F13,"")
D14: =IFERROR(B14-A14,"") | E14: =IFERROR(C14/D14,"") | G14: =IFERROR(E14*F14,"")
D15: =IFERROR(B15-A15,"") | E15: =IFERROR(C15/D15,"") | G15: =IFERROR(E15*F15,"")
D16: =IFERROR(B16-A16,"") | E16: =IFERROR(C16/D16,"") | G16: =IFERROR(E16*F16,"")
D17: =IFERROR(B17-A17,"") | E17: =IFERROR(C17/D17,"") | G17: =IFERROR(E17*F17,"")
D18: =IFERROR(B18-A18,"") | E18: =IFERROR(C18/D18,"") | G18: =IFERROR(E18*F18,"")
D19: =IFERROR(B19-A19,"") | E19: =IFERROR(C19/D19,"") | G19: =IFERROR(E19*F19,"")
D20: =IFERROR(B20-A20,"") | E20: =IFERROR(C20/D20,"") | G20: =IFERROR(E20*F20,"")
D21: =IFERROR(B21-A21,"") | E21: =IFERROR(C21/D21,"") | G21: =IFERROR(E21*F21,"")
D22: =IFERROR(B22-A22,"") | E22: =IFERROR(C22/D22,"") | G22: =IFERROR(E22*F22,"")
A23: Remaining Balance Est. | E23: 0 | F23: 0 | G23: =E23*F23
A24: TOTAL WATER FORECAST | G24: =SUM(G11:G23)
K26: Current Year Budget
A27: GL Code | B27: Description | C27: Notes | D27: Prior Year Actual | E27: YTD Actual | F27: Accrual Adj | G27: Unpaid Bills | H27: YTD Budget | I27: Sep-Dec Estimate | J27: 12 Month Forecast | K27: Yardi | L27: Increase % | M27: Proposed Budget | N27: $ Variance | O27: % Change
A28: Yardi | B28: Yardi | C28: Input | D28: Yardi | E28: Yardi | F28: Input | G28: Input | H28: Yardi | I28: Formula | J28: Formula | L28: Input | M28: Formula | N28: Formula | O28: Formula
A29: Water & Sewer
A30: 6305-0000 | B30: Water/Sewer | F30: 0 | G30: 0 | I30: =IFERROR(IF((E30+F30+G30)>=D30,(E30+F30+G30)/Setup!$B$10*Setup!$B$11,D30-(E30+F30+G30)),0) | J30: =E30+F30+G30+I30 | L30: =$B$6 | M30: =J30*(1+L30) | N30: =M30-D30 | O30: =IFERROR(M30/D30-1,0)
A31: 6305-0010 | B31: Water - Common Area | F31: 0 | G31: 0 | I31: =IFERROR(IF((E31+F31+G31)>=D31,(E31+F31+G31)/Setup!$B$10*Setup!$B$11,D31-(E31+F31+G31)),0) | J31: =E31+F31+G31+I31 | L31: =$B$6 | M31: =J31*(1+L31) | N31: =M31-D31 | O31: =IFERROR(M31/D31-1,0)
A32: 6305-0020 | B32: Sewer Charges | F32: 0 | G32: 0 | I32: =IFERROR(IF((E32+F32+G32)>=D32,(E32+F32+G32)/Setup!$B$10*Setup!$B$11,D32-(E32+F32+G32)),0) | J32: =E32+F32+G32+I32 | L32: =$B$6 | M32: =J32*(1+L32) | N32: =M32-D32 | O32: =IFERROR(M32/D32-1,0)
D33: 0 | E33: 0 | F33: 0 | G33: 0 | H33: 0 | I33: =IFERROR(D33-(E33+F33+G33),0) | J33: =E33+F33+G33+I33 | L33: 0 | M33: =J33*(1+L33) | N33: =M33-D33 | O33: =IFERROR(M33/D33-1,0)
D34: 0 | E34: 0 | F34: 0 | G34: 0 | H34: 0 | I34: =IFERROR(D34-(E34+F34+G34),0) | J34: =E34+F34+G34+I34 | L34: 0 | M34: =J34*(1+L34) | N34: =M34-D34 | O34: =IFERROR(M34/D34-1,0)
D35: 0 | E35: 0 | F35: 0 | G35: 0 | H35: 0 | I35: =IFERROR(D35-(E35+F35+G35),0) | J35: =E35+F35+G35+I35 | L35: 0 | M35: =J35*(1+L35) | N35: =M35-D35 | O35: =IFERROR(M35/D35-1,0)
B36: Total Water & Sewer | D36: =SUM(D30:D35) | E36: =SUM(E30:E35) | F36: =SUM(F30:F35) | G36: =SUM(G30:G35) | H36: =SUM(H30:H35) | I36: =SUM(I30:I35) | J36: =SUM(J30:J35) | K36: =SUM(K30:K35) | M36: =SUM(M30:M35) | N36: =SUM(N30:N35) | O36: =IFERROR(M36/D36-1,0)
B38: TOTAL WATER & SEWER | D38: =D36 | E38: =E36 | F38: =F36 | G38: =G36 | H38: =H36 | I38: =I36 | J38: =J36 | M38: =M36 | N38: =N36 | O38: =IFERROR(M38/D38-1,0)

Sheet Repairs & Supplies
A1: =Setup!B5
A2: Repairs & Supplies — Budget Year
A3: =Setup!B4
K4: Current Year Budget
A5: GL Code | B5: Description | C5: Notes | D5: Prior Year Actual | E5: YTD Actual | F5: Accrual Adj | G5: Unpaid Bills | H5: YTD Budget | I5: Sep-Dec Estimate | J5: 12 Month Forecast | K5: Yardi | L5: Increase % | M5: Proposed Budget | N5: $ Variance | O5: % Change
A6: Yardi | B6: Yardi | C6: Input | D6: Yardi | E6: Yardi | F6: Input | G6: Input | H6: Yardi | I6: Formula | J6: Formula | L6: Input | M6: Formula | N6: Formula | O6: Formula
A7: Supplies
A8: 5406-0000 | B8: Supplies & Hardware | F8: 0 | G8: 0 | I8: =IFERROR(IF((E8+F8+G8)>=D8,(E8+F8+G8)/Setup!$B$10*Setup!$B$11,D8-(E8+F8+G8)),0) | J8: =E8+F8+G8+I8 | L8: 0 | M8: =J8*(1+L8) | N8: =M8-D8 | O8: =IFERROR(M8/D8-1,0)
D9: 0 | E9: 0 | F9: 0 | G9: 0 | H9: 0 | I9: =IFERROR(D9-(E9+F9+G9),0) | J9: =E9+F9+G9+I9 | L9: 0 | M9: =J9*(1+L9) | N9: =M9-D9 | O9: =IFERROR(M9/D9-1,0)
D10: 0 | E10: 0 | F10: 0 | G10: 0 | H10: 0 | I10: =IFERROR(D10-(E10+F10+G10),0) | J10: =E10+F10+G10+I10 | L10: 0 | M10: =J10*(1+L10) | N10: =M10-D10 | O10: =IFERROR(M10/D10-1,0)
D11: 0 | E11: 0 | F11: 0 | G11: 0 | H11: 0 | I11: =IFERROR(D11-(E11+F11+G11),0) | J11: =E11+F11+G11+I11 | L11: 0 | M11: =J11*(1+L11) | N11: =M11-D11 | O11: =IFERROR(M11/D11-1,0)
B12: Total Supplies | D12: =SUM(D8:D11) | E12: =SUM(E8:E11) | F12: =SUM(F8:F11) | G12: =SUM(G8:G11) | H12: =SUM(H8:H11) | I12: =SUM(I8:I11) | J12: =SUM(J8:J11) | K12: =SUM(K8:K11) | M12: =SUM(M8:M11) | N12: =SUM(N8:N11) | O12: =IFERROR(M12/D12-1,0)
A13: 5445-0000 | B13: Uniforms Purchased
A14: Repairs
A15: 5606-0000 | B15: Insurance Repairs | F15: 0 | G15: 0 | I15: =IFERROR(IF((E15+F15+G15)>=D15,(E15+F15+G15)/Setup!$B$10*Setup!$B$11,D15-(E15+F15+G15)),0) | J15: =E15+F15+G15+I15 | L15: 0 | M15: =J15*(1+L15) | N15: =M15-D15 | O15: =IFERROR(M15/D15-1,0)
A16: 5609-0000 | B16: Appliance Repairs | F16: 0 | G16: 0 | I16: =IFERROR(IF((E16+F16+G16)>=D16,(E16+F16+G16)/Setup!$B$10*Setup!$B$11,D16-(E16+F16+G16)),0) | J16: =E16+F16+G16+I16 | L16: 0 | M16: =J16*(1+L16) | N16: =M16-D16 | O16: =IFERROR(M16/D16-1,0)
A17: 5621-0000 | B17: Equipment Repairs | F17: 0 | G17: 0 | I17: =IFERROR(IF((E17+F17+G17)>=D17,(E17+F17+G17)/Setup!$B$10*Setup!$B$11,D17-(E17+F17+G17)),0) | J17: =E17+F17+G17+I17 | L17: 0 | M17: =J17*(1+L17) | N17: =M17-D17 | O17: =IFERROR(M17/D17-1,0)
A18: 5622-0000 | B18: HVAC Repairs | F18: 0 | G18: 0 | I18: =IFERROR(IF((E18+F18+G18)>=D18,(E18+F18+G18)/Setup!$B$10*Setup!$B$11,D18-(E18+F18+G18)),0) | J18: =E18+F18+G18+I18 | L18: 0 | M18: =J18*(1+L18) | N18: =M18-D18 | O18: =IFERROR(M18/D18-1,0)
A19: 5624-0000 | B19: Heating Repairs | F19: 0 | G19: 0 | I19: =IFERROR(IF((E19+F19+G19)>=D19,(E19+F19+G19)/Setup!$B$10*Setup!$B$11,D19-(E19+F19+G19)),0) | J19: =E19+F19+G19+I19 | L19: 0 | M19: =J19*(1+L19) | N19: =M19-D19 | O19: =IFERROR(M19/D19-1,0)
A20: 5627-0000 | B20: Boiler/Burner Repairs | F20: 0 | G20: 0 | I20: =IFERROR(IF((E20+F20+G20)>=D20,(E20+F20+G20)/Setup!$B$10*Setup!$B$11,D20-(E20+F20+G20)),0) | J20: =E20+F20+G20+I20 | L20: 0 | M20: =J20*(1+L20) | N20: =M20-D20 | O20: =IFERROR(M20/D20-1,0)
A21: 5630-0000 | B21: Plumbing Repairs | F21: 0 | G21: 0 | I21: =IFERROR(IF((E21+F21+G21)>=D21,(E21+F21+G21)/Setup!$B$10*Setup!$B$11,D21-(E21+F21+G21)),0) | J21: =E21+F21+G21+I21 | L21: 0 | M21: =J21*(1+L21) | N21: =M21-D21 | O21: =IFERROR(M21/D21-1,0)
A22: 5630-0001 | B22: Pump/Motor Repair | F22: 0 | G22: 0 | I22: =IFERROR(IF((E22+F22+G22)>=D22,(E22+F22+G22)/Setup!$B$10*Setup!$B$11,D22-(E22+F22+G22)),0) | J22: =E22+F22+G22+I22 | L22: 0 | M22: =J22*(1+L22) | N22: =M22-D22 | O22: =IFERROR(M22/D22-1,0)
A23: 5633-0000 | B23: Electrical Repairs | F23: 0 | G23: 0 | I23: =IFERROR(IF((E23+F23+G23)>=D23,(E23+F23+G23)/Setup!$B$10*Setup!$B$11,D23-(E23+F23+G23)),0) | J23: =E23+F23+G23+I23 | L23: 0 | M23: =J23*(1+L23) | N23: =M23-D23 | O23: =IFERROR(M23/D23-1,0)
A24: 5636-0000 | B24: Air Conditioning Repairs | F24: 0 | G24: 0 | I24: =IFERROR(IF((E24+F24+G24)>=D24,(E24+F24+G24)/Setup!$B$10*Setup!$B$11,D24-(E24+F24+G24)),0) | J24: =E24+F24+G24+I24 | L24: 0 | M24: =J24*(1+L24) | N24: =M24-D24 | O24: =IFERROR(M24/D24-1,0)
A25: 5639-0000 | B25: Elevator Repairs | F25: 0 | G25: 0 | I25: =IFERROR(IF((E25+F25+G25)>=D25,(E25+F25+G25)/Setup!$B$10*Setup!$B$11,D25-(E25+F25+G25)),0) | J25: =E25+F25+G25+I25 | L25: 0 | M25: =J25*(1+L25) | N25: =M25-D25 | O25: =IFERROR(M25/D25-1,0)
A26: 5642-0000 | B26: Compactor / Incinerator Repairs | F26: 0 | G26: 0 | I26: =IFERROR(IF((E26+F26+G26)>=D26,(E26+F26+G26)/Setup!$B$10*Setup!$B$11,D26-(E26+F26+G26)),0) | J26: =E26+F26+G26+I26 | L26: 0 | M26: =J26*(1+L26) | N26: =M26-D26 | O26: =IFERROR(M26/D26-1,0)
... A40: 5603-0000 | B40: Apartment Repairs | F40: 0 | G40: 0 | I40: =IFERROR(IF((E40+F40+G40)>=D40,(E40+F40+G40)/Setup!$B$10*Setup!$B$11,D40-(E40+F40+G40)),0) | J40: =E40+F40+G40+I40 | L40: 0 | M40: =J40*(1+L40) | N40: =M40-D40 | O40: =IFERROR(M40/D40-1,0)
A41: 5668-0000 | B41: Canopy Repairs | D41: 0 | E41: 0 | F41: 0 | G41: 0 | H41: 0 | I41: =IFERROR(D41-(E41+F41+G41),0) | J41: =E41+F41+G41+I41 | L41: 0 | M41: =J41*(1+L41) | N41: =M41-D41 | O41: =IFERROR(M41/D41-1,0)
A42: 5684-0000 | B42: Sidewalk Concrete Repairs | D42: 0 | E42: 0 | F42: 0 | G42: 0 | H42: 0 | I42: =IFERROR(D42-(E42+F42+G42),0) | J42: =E42+F42+G42+I42 | L42: 0 | M42: =J42*(1+L42) | N42: =M42-D42 | O42: =IFERROR(M42/D42-1,0)
B43: Total Repairs | D43: =SUM(D15:D42) | E43: =SUM(E15:E42) | F43: =SUM(F15:F42) | G43: =SUM(G15:G42) | H43: =SUM(H15:H42) | I43: =SUM(I15:I42) | J43: =SUM(J15:J42) | K43: =SUM(K15:K42) | M43: =SUM(M15:M42) | N43: =SUM(N15:N42) | O43: =IFERROR(M43/D43-1,0)
A45: Maintenance Contracts
A46: 5803-0000 | B46: Cleaning & Maintenance | F46: 0 | G46: 0 | I46: =IFERROR(IF((E46+F46+G46)>=D46,(E46+F46+G46)/Setup!$B$10*Setup!$B$11,D46-(E46+F46+G46)),0) | J46: =E46+F46+G46+I46 | L46: 0 | M46: =J46*(1+L46) | N46: =M46-D46 | O46: =IFERROR(M46/D46-1,0)
A47: 5806-0000 | B47: Air Conditioning Maintenance | F47: 0 | G47: 0 | I47: =IFERROR(IF((E47+F47+G47)>=D47,(E47+F47+G47)/Setup!$B$10*Setup!$B$11,D47-(E47+F47+G47)),0) | J47: =E47+F47+G47+I47 | L47: 0 | M47: =J47*(1+L47) | N47: =M47-D47 | O47: =IFERROR(M47/D47-1,0)
A48: 5810-0000 | B48: HVAC Maintenance | F48: 0 | G48: 0 | I48: =IFERROR(IF((E48+F48+G48)>=D48,(E48+F48+G48)/Setup!$B$10*Setup!$B$11,D48-(E48+F48+G48)),0) | J48: =E48+F48+G48+I48 | L48: 0 | M48: =J48*(1+L48) | N48: =M48-D48 | O48: =IFERROR(M48/D48-1,0)
A49: 5812-0000 | B49: Elevator Maintenance | F49: 0 | G49: 0 | I49: =IFERROR(IF((E49+F49+G49)>=D49,(E49+F49+G49)/Setup!$B$10*Setup!$B$11,D49-(E49+F49+G49)),0) | J49: =E49+F49+G49+I49 | L49: 0 | M49: =J49*(1+L49) | N49: =M49-D49 | O49: =IFERROR(M49/D49-1,0)
A50: 5815-0000 | B50: Floor/Carpet Cleaning | F50: 0 | G50: 0 | I50: =IFERROR(IF((E50+F50+G50)>=D50,(E50+F50+G50)/Setup!$B$10*Setup!$B$11,D50-(E50+F50+G50)),0) | J50: =E50+F50+G50+I50 | L50: 0 | M50: =J50*(1+L50) | N50: =M50-D50 | O50: =IFERROR(M50/D50-1,0)
A51: 5818-0000 | B51: Window Cleaning | F51: 0 | G51: 0 | I51: =IFERROR(IF((E51+F51+G51)>=D51,(E51+F51+G51)/Setup!$B$10*Setup!$B$11,D51-(E51+F51+G51)),0) | J51: =E51+F51+G51+I51 | L51: 0 | M51: =J51*(1+L51) | N51: =M51-D51 | O51: =IFERROR(M51/D51-1,0)
A52: 5821-0000 | B52: Fire Extinguisher Maintenance | F52: 0 | G52: 0 | I52: =IFERROR(IF((E52+F52+G52)>=D52,(E52+F52+G52)/Setup!$B$10*Setup!$B$11,D52-(E52+F52+G52)),0) | J52: =E52+F52+G52+I52 | L52: 0 | M52: =J52*(1+L52) | N52: =M52-D52 | O52: =IFERROR(M52/D52-1,0)
A53: 5825-0000 | B53: Uniform Cleaning & Maintenance | F53: 0 | G53: 0 | I53: =IFERROR(IF((E53+F53+G53)>=D53,(E53+F53+G53)/Setup!$B$10*Setup!$B$11,D53-(E53+F53+G53)),0) | J53: =E53+F53+G53+I53 | L53: 0 | M53: =J53*(1+L53) | N53: =M53-D53 | O53: =IFERROR(M53/D53-1,0)
A54: 5828-0000 | B54: Rubbish Removal | F54: 0 | G54: 0 | I54: =IFERROR(IF((E54+F54+G54)>=D54,(E54+F54+G54)/Setup!$B$10*Setup!$B$11,D54-(E54+F54+G54)),0) | J54: =E54+F54+G54+I54 | L54: 0 | M54: =J54*(1+L54) | N54: =M54-D54 | O54: =IFERROR(M54/D54-1,0)
A55: 5831-0000 | B55: Exterminating | F55: 0 | G55: 0 | I55: =IFERROR(IF((E55+F55+G55)>=D55,(E55+F55+G55)/Setup!$B$10*Setup!$B$11,D55-(E55+F55+G55)),0) | J55: =E55+F55+G55+I55 | L55: 0 | M55: =J55*(1+L55) | N55: =M55-D55 | O55: =IFERROR(M55/D55-1,0)
A56: 5834-0000 | B56: Cooling Tower Maint | F56: 0 | G56: 0 | I56: =IFERROR(IF((E56+F56+G56)>=D56,(E56+F56+G56)/Setup!$B$10*Setup!$B$11,D56-(E56+F56+G56)),0) | J56: =E56+F56+G56+I56 | L56: 0 | M56: =J56*(1+L56) | N56: =M56-D56 | O56: =IFERROR(M56/D56-1,0)
A57: 5837-0000 | B57: Alarm / Security System Maintenance | F57: 0 | G57: 0 | I57: =IFERROR(IF((E57+F57+G57)>=D57,(E57+F57+G57)/Setup!$B$10*Setup!$B$11,D57-(E57+F57+G57)),0) | J57: =E57+F57+G57+I57 | L57: 0 | M57: =J57*(1+L57) | N57: =M57-D57 | O57: =IFERROR(M57/D57-1,0)
... A65: 5874-0000 | B65: Other Maintenance | F65: 0 | G65: 0 | I65: =IFERROR(IF((E65+F65+G65)>=D65,(E65+F65+G65)/Setup!$B$10*Setup!$B$11,D65-(E65+F65+G65)),0) | J65: =E65+F65+G65+I65 | L65: 0 | M65: =J65*(1+L65) | N65: =M65-D65 | O65: =IFERROR(M65/D65-1,0)
A66: 5809-0016 | B66: Sprinkler Maintenance | D66: 0 | E66: 0 | F66: 0 | G66: 0 | H66: 0 | I66: =IFERROR(D66-(E66+F66+G66),0) | J66: =E66+F66+G66+I66 | L66: 0 | M66: =J66*(1+L66) | N66: =M66-D66 | O66: =IFERROR(M66/D66-1,0)
D67: 0 | E67: 0 | F67: 0 | G67: 0 | H67: 0 | I67: =IFERROR(D67-(E67+F67+G67),0) | J67: =E67+F67+G67+I67 | L67: 0 | M67: =J67*(1+L67) | N67: =M67-D67 | O67: =IFERROR(M67/D67-1,0)
D68: 0 | E68: 0 | F68: 0 | G68: 0 | H68: 0 | I68: =IFERROR(D68-(E68+F68+G68),0) | J68: =E68+F68+G68+I68 | L68: 0 | M68: =J68*(1+L68) | N68: =M68-D68 | O68: =IFERROR(M68/D68-1,0)
B69: Total Maintenance Contracts | D69: =SUM(D46:D68) | E69: =SUM(E46:E68) | F69: =SUM(F46:F68) | G69: =SUM(G46:G68) | H69: =SUM(H46:H68) | I69: =SUM(I46:I68) | J69: =SUM(J46:J68) | K69: =SUM(K46:K68) | M69: =SUM(M46:M68) | N69: =SUM(N46:N68) | O69: =IFERROR(M69/D69-1,0)
B71: TOTAL REPAIRS & SUPPLIES | D71: =D12+D43+D69 | E71: =E12+E43+E69 | F71: =F12+F43+F69 | G71: =G12+G43+G69 | H71: =H12+H43+H69 | I71: =I12+I43+I69 | J71: =J12+J43+J69 | K71: =K12+K43+K69 | M71: =M12+M43+M69 | N71: =N12+N43+N69 | O71: =IFERROR(M71/D71-1,0)

Sheet Gen & Admin
A1: =Setup!B5
A2: Gen & Admin — Budget Year
A3: =Setup!B4
A5: GL Code | B5: Description | C5: Notes | D5: Prior Year Actual | E5: YTD Actual | F5: Accrual Adj | G5: Unpaid Bills | H5: YTD Budget | I5: Sep-Dec Estimate | J5: 12 Month Forecast | K5: Current Year Budget | L5: Increase % | M5: Proposed Budget | N5: $ Variance | O5: % Change
A6: Yardi | B6: Yardi | C6: Input | D6: Yardi | E6: Yardi | F6: Input | G6: Input | H6: Yardi | I6: Formula | J6: Formula | K6: Yardi | L6: Input | M6: Formula | N6: Formula | O6: Formula
A7: Professional Fees
A8: 6505-0000 | B8: Engineering & Architectural Fees | F8: 0 | G8: 0 | I8: =IFERROR(IF((E8+F8+G8)>=D8,(E8+F8+G8)/Setup!$B$10*Setup!$B$11,D8-(E8+F8+G8)),0) | J8: =E8+F8+G8+I8 | L8: 0 | M8: =J8*(1+L8) | N8: =M8-D8 | O8: =IFERROR(M8/D8-1,0)
A9: 6510-0000 | B9: Management Fees | F9: 0 | G9: 0 | I9: =IFERROR(IF((E9+F9+G9)>=D9,(E9+F9+G9)/Setup!$B$10*Setup!$B$11,D9-(E9+F9+G9)),0) | J9: =E9+F9+G9+I9 | L9: 0 | M9: =J9*(1+L9) | N9: =M9-D9 | O9: =IFERROR(M9/D9-1,0)
A10: 6515-0000 | B10: Legal Fees | F10: 0 | G10: 0 | I10: =IFERROR(IF((E10+F10+G10)>=D10,(E10+F10+G10)/Setup!$B$10*Setup!$B$11,D10-(E10+F10+G10)),0) | J10: =E10+F10+G10+I10 | L10: 0 | M10: =J10*(1+L10) | N10: =M10-D10 | O10: =IFERROR(M10/D10-1,0)
A11: 6520-0000 | B11: Real Estate Tax Certiorari Fees | F11: 0 | G11: 0 | I11: =IFERROR(IF((E11+F11+G11)>=D11,(E11+F11+G11)/Setup!$B$10*Setup!$B$11,D11-(E11+F11+G11)),0) | J11: =E11+F11+G11+I11 | L11: 0 | M11: =J11*(1+L11) | N11: =M11-D11 | O11: =IFERROR(M11/D11-1,0)
A12: 6525-0000 | B12: Accounting Fees | F12: 0 | G12: 0 | I12: =IFERROR(IF((E12+F12+G12)>=D12,(E12+F12+G12)/Setup!$B$10*Setup!$B$11,D12-(E12+F12+G12)),0) | J12: =E12+F12+G12+I12 | L12: 0 | M12: =J12*(1+L12) | N12: =M12-D12 | O12: =IFERROR(M12/D12-1,0)
A13: 6590-0000 | B13: Other Professional Fees | F13: 0 | G13: 0 | I13: =IFERROR(IF((E13+F13+G13)>=D13,(E13+F13+G13)/Setup!$B$10*Setup!$B$11,D13-(E13+F13+G13)),0) | J13: =E13+F13+G13+I13 | L13: 0 | M13: =J13*(1+L13) | N13: =M13-D13 | O13: =IFERROR(M13/D13-1,0)
D14: 0 | E14: 0 | F14: 0 | G14: 0 | H14: 0 | I14: =IFERROR(D14-(E14+F14+G14),0) | J14: =E14+F14+G14+I14 | L14: 0 | M14: =J14*(1+L14) | N14: =M14-D14 | O14: =IFERROR(M14/D14-1,0)
D15: 0 | E15: 0 | F15: 0 | G15: 0 | H15: 0 | I15: =IFERROR(D15-(E15+F15+G15),0) | J15: =E15+F15+G15+I15 | L15: 0 | M15: =J15*(1+L15) | N15: =M15-D15 | O15: =IFERROR(M15/D15-1,0)
D16: 0 | E16: 0 | F16: 0 | G16: 0 | H16: 0 | I16: =IFERROR(D16-(E16+F16+G16),0) | J16: =E16+F16+G16+I16 | L16: 0 | M16: =J16*(1+L16) | N16: =M16-D16 | O16: =IFERROR(M16/D16-1,0)
B17: Total Professional Fees | D17: =SUM(D8:D16) | E17: =SUM(E8:E16) | F17: =SUM(F8:F16) | G17: =SUM(G8:G16) | H17: =SUM(H8:H16) | I17: =SUM(I8:I16) | J17: =SUM(J8:J16) | K17: =SUM(K8:K16) | M17: =SUM(M8:M16) | N17: =SUM(N8:N16) | O17: =IFERROR(M17/D17-1,0)
A19: Administrative & Other
A20: 6706-0020 | B20: Water Cooler Expense | F20: 0 | G20: 0 | I20: =IFERROR(IF((E20+F20+G20)>=D20,(E20+F20+G20)/Setup!$B$10*Setup!$B$11,D20-(E20+F20+G20)),0) | J20: =E20+F20+G20+I20 | L20: 0 | M20: =J20*(1+L20) | N20: =M20-D20 | O20: =IFERROR(M20/D20-1,0)
A21: 6708-0000 | B21: Stationery & Printing | F21: 0 | G21: 0 | I21: =IFERROR(IF((E21+F21+G21)>=D21,(E21+F21+G21)/Setup!$B$10*Setup!$B$11,D21-(E21+F21+G21)),0) | J21: =E21+F21+G21+I21 | L21: 0 | M21: =J21*(1+L21) | N21: =M21-D21 | O21: =IFERROR(M21/D21-1,0)
A22: 6710-0000 | B22: Postage Expense | F22: 0 | G22: 0 | I22: =IFERROR(IF((E22+F22+G22)>=D22,(E22+F22+G22)/Setup!$B$10*Setup!$B$11,D22-(E22+F22+G22)),0) | J22: =E22+F22+G22+I22 | L22: 0 | M22: =J22*(1+L22) | N22: =M22-D22 | O22: =IFERROR(M22/D22-1,0)
A23: 6710-0015 | B23: Messenger Expense | F23: 0 | G23: 0 | I23: =IFERROR(IF((E23+F23+G23)>=D23,(E23+F23+G23)/Setup!$B$10*Setup!$B$11,D23-(E23+F23+G23)),0) | J23: =E23+F23+G23+I23 | L23: 0 | M23: =J23*(1+L23) | N23: =M23-D23 | O23: =IFERROR(M23/D23-1,0)
A24: 6712-0000 | B24: Computer Software | F24: 0 | G24: 0 | I24: =IFERROR(IF((E24+F24+G24)>=D24,(E24+F24+G24)/Setup!$B$10*Setup!$B$11,D24-(E24+F24+G24)),0) | J24: =E24+F24+G24+I24 | L24: 0 | M24: =J24*(1+L24) | N24: =M24-D24 | O24: =IFERROR(M24/D24-1,0)
A25: 6714-0000 | B25: Telephone Expense | F25: 0 | G25: 0 | I25: =IFERROR(IF((E25+F25+G25)>=D25,(E25+F25+G25)/Setup!$B$10*Setup!$B$11,D25-(E25+F25+G25)),0) | J25: =E25+F25+G25+I25 | L25: 0 | M25: =J25*(1+L25) | N25: =M25-D25 | O25: =IFERROR(M25/D25-1,0)
A26: 6716-0000 | B26: Cable TV Expense | F26: 0 | G26: 0 | I26: =IFERROR(IF((E26+F26+G26)>=D26,(E26+F26+G26)/Setup!$B$10*Setup!$B$11,D26-(E26+F26+G26)),0) | J26: =E26+F26+G26+I26 | L26: 0 | M26: =J26*(1+L26) | N26: =M26-D26 | O26: =IFERROR(M26/D26-1,0)
A27: 6718-0000 | B27: Photocopy Expense | F27: 0 | G27: 0 | I27: =IFERROR(IF((E27+F27+G27)>=D27,(E27+F27+G27)/Setup!$B$10*Setup!$B$11,D27-(E27+F27+G27)),0) | J27: =E27+F27+G27+I27 | L27: 0 | M27: =J27*(1+L27) | N27: =M27-D27 | O27: =IFERROR(M27/D27-1,0)
A28: 6720-0000 | B28: Dues & Subscriptions | F28: 0 | G28: 0 | I28: =IFERROR(IF((E28+F28+G28)>=D28,(E28+F28+G28)/Setup!$B$10*Setup!$B$11,D28-(E28+F28+G28)),0) | J28: =E28+F28+G28+I28 | L28: 0 | M28: =J28*(1+L28) | N28: =M28-D28 | O28: =IFERROR(M28/D28-1,0)
A29: 6722-0000 | B29: Education & Seminars | F29: 0 | G29: 0 | I29: =IFERROR(IF((E29+F29+G29)>=D29,(E29+F29+G29)/Setup!$B$10*Setup!$B$11,D29-(E29+F29+G29)),0) | J29: =E29+F29+G29+I29 | L29: 0 | M29: =J29*(1+L29) | N29: =M29-D29 | O29: =IFERROR(M29/D29-1,0)
A30: 6726-0000 | B30: Inspection Fees & Permits | F30: 0 | G30: 0 | I30: =IFERROR(IF((E30+F30+G30)>=D30,(E30+F30+G30)/Setup!$B$10*Setup!$B$11,D30-(E30+F30+G30)),0) | J30: =E30+F30+G30+I30 | L30: 0 | M30: =J30*(1+L30) | N30: =M30-D30 | O30: =IFERROR(M30/D30-1,0)
A31: 6728-0000 | B31: Violations | F31: 0 | G31: 0 | I31: =IFERROR(IF((E31+F31+G31)>=D31,(E31+F31+G31)/Setup!$B$10*Setup!$B$11,D31-(E31+F31+G31)),0) | J31: =E31+F31+G31+I31 | L31: 0 | M31: =J31*(1+L31) | N31: =M31-D31 | O31: =IFERROR(M31/D31-1,0)
... A46: 6795-0000 | B46: Other Administrative | F46: 0 | G46: 0 | I46: =IFERROR(IF((E46+F46+G46)>=D46,(E46+F46+G46)/Setup!$B$10*Setup!$B$11,D46-(E46+F46+G46)),0) | J46: =E46+F46+G46+I46 | L46: 0 | M46: =J46*(1+L46) | N46: =M46-D46 | O46: =IFERROR(M46/D46-1,0)
D47: 0 | E47: 0 | F47: 0 | G47: 0 | H47: 0 | I47: =IFERROR(D47-(E47+F47+G47),0) | J47: =E47+F47+G47+I47 | L47: 0 | M47: =J47*(1+L47) | N47: =M47-D47 | O47: =IFERROR(M47/D47-1,0)
D48: 0 | E48: 0 | F48: 0 | G48: 0 | H48: 0 | I48: =IFERROR(D48-(E48+F48+G48),0) | J48: =E48+F48+G48+I48 | L48: 0 | M48: =J48*(1+L48) | N48: =M48-D48 | O48: =IFERROR(M48/D48-1,0)
D49: 0 | E49: 0 | F49: 0 | G49: 0 | H49: 0 | I49: =IFERROR(D49-(E49+F49+G49),0) | J49: =E49+F49+G49+I49 | L49: 0 | M49: =J49*(1+L49) | N49: =M49-D49 | O49: =IFERROR(M49/D49-1,0)
B50: Total Administrative & Other | D50: =SUM(D20:D49) | E50: =SUM(E20:E49) | F50: =SUM(F20:F49) | G50: =SUM(G20:G49) | H50: =SUM(H20:H49) | I50: =SUM(I20:I49) | J50: =SUM(J20:J49) | K50: =SUM(K20:K49) | M50: =SUM(M20:M49) | N50: =SUM(N20:N49) | O50: =IFERROR(M50/D50-1,0)
A52: Insurance
A53: 6105-0000 | B53: Package Policy | F53: 0 | G53: 0 | I53: =IFERROR(IF((E53+F53+G53)>=D53,(E53+F53+G53)/Setup!$B$10*Setup!$B$11,D53-(E53+F53+G53)),0) | J53: =E53+F53+G53+I53 | L53: 0 | M53: ='Insurance Schedule'!L12 | N53: =M53-D53 | O53: =IFERROR(M53/D53-1,0)
A54: 6110-0000 | B54: General Liability | F54: 0 | G54: 0 | I54: =IFERROR(IF((E54+F54+G54)>=D54,(E54+F54+G54)/Setup!$B$10*Setup!$B$11,D54-(E54+F54+G54)),0) | J54: =E54+F54+G54+I54 | L54: 0 | M54: ='Insurance Schedule'!L13 | N54: =M54-D54 | O54: =IFERROR(M54/D54-1,0)
A55: 6115-0000 | B55: Umbrella Insurance | F55: 0 | G55: 0 | I55: =IFERROR(IF((E55+F55+G55)>=D55,(E55+F55+G55)/Setup!$B$10*Setup!$B$11,D55-(E55+F55+G55)),0) | J55: =E55+F55+G55+I55 | L55: 0 | M55: ='Insurance Schedule'!L14 | N55: =M55-D55 | O55: =IFERROR(M55/D55-1,0)
A56: 6120-0000 | B56: Umbrella Insurance | F56: 0 | G56: 0 | I56: =IFERROR(IF((E56+F56+G56)>=D56,(E56+F56+G56)/Setup!$B$10*Setup!$B$11,D56-(E56+F56+G56)),0) | J56: =E56+F56+G56+I56 | L56: 0 | M56: ='Insurance Schedule'!L19 | N56: =M56-D56 | O56: =IFERROR(M56/D56-1,0)
A57: 6125-0000 | B57: D&O Insurance | F57: 0 | G57: 0 | I57: =IFERROR(IF((E57+F57+G57)>=D57,(E57+F57+G57)/Setup!$B$10*Setup!$B$11,D57-(E57+F57+G57)),0) | J57: =E57+F57+G57+I57 | L57: 0 | M57: ='Insurance Schedule'!L15 | N57: =M57-D57 | O57: =IFERROR(M57/D57-1,0)
A58: 6126-0000 | B58: Cyber Insurance | F58: 0 | G58: 0 | I58: =IFERROR(IF((E58+F58+G58)>=D58,(E58+F58+G58)/Setup!$B$10*Setup!$B$11,D58-(E58+F58+G58)),0) | J58: =E58+F58+G58+I58 | L58: 0 | M58: ='Insurance Schedule'!L16 | N58: =M58-D58 | O58: =IFERROR(M58/D58-1,0)
A59: 6135-0000 | B59: Crime/Fidelity | F59: 0 | G59: 0 | I59: =IFERROR(IF((E59+F59+G59)>=D59,(E59+F59+G59)/Setup!$B$10*Setup!$B$11,D59-(E59+F59+G59)),0) | J59: =E59+F59+G59+I59 | L59: 0 | M59: ='Insurance Schedule'!L17 | N59: =M59-D59 | O59: =IFERROR(M59/D59-1,0)
A60: 6180-0000 | B60: D&O (alt GL) | F60: 0 | G60: 0 | I60: =IFERROR(IF((E60+F60+G60)>=D60,(E60+F60+G60)/Setup!$B$10*Setup!$B$11,D60-(E60+F60+G60)),0) | J60: =E60+F60+G60+I60 | L60: 0 | M60: ='Insurance Schedule'!L20 | N60: =M60-D60 | O60: =IFERROR(M60/D60-1,0)
A61: 6195-0000 | B61: Other Insurance | F61: 0 | G61: 0 | I61: =IFERROR(IF((E61+F61+G61)>=D61,(E61+F61+G61)/Setup!$B$10*Setup!$B$11,D61-(E61+F61+G61)),0) | J61: =E61+F61+G61+I61 | L61: 0 | M61: ='Insurance Schedule'!L18 | N61: =M61-D61 | O61: =IFERROR(M61/D61-1,0)
D62: 0 | E62: 0 | F62: 0 | G62: 0 | H62: 0 | I62: =IFERROR(D62-(E62+F62+G62),0) | J62: =E62+F62+G62+I62 | L62: 0 | M62: =J62*(1+L62) | N62: =M62-D62 | O62: =IFERROR(M62/D62-1,0)
D63: 0 | E63: 0 | F63: 0 | G63: 0 | H63: 0 | I63: =IFERROR(D63-(E63+F63+G63),0) | J63: =E63+F63+G63+I63 | L63: 0 | M63: =J63*(1+L63) | N63: =M63-D63 | O63: =IFERROR(M63/D63-1,0)
D64: 0 | E64: 0 | F64: 0 | G64: 0 | H64: 0 | I64: =IFERROR(D64-(E64+F64+G64),0) | J64: =E64+F64+G64+I64 | L64: 0 | M64: =J64*(1+L64) | N64: =M64-D64 | O64: =IFERROR(M64/D64-1,0)
B65: Total Insurance | D65: =SUM(D53:D64) | E65: =SUM(E53:E64) | F65: =SUM(F53:F64) | G65: =SUM(G53:G64) | H65: =SUM(H53:H64) | I65: =SUM(I53:I64) | J65: =SUM(J53:J64) | K65: =SUM(K53:K64) | M65: =SUM(M53:M64) | N65: =SUM(N53:N64) | O65: =IFERROR(M65/D65-1,0)
A67: Taxes
A68: 6310-0000 | B68: Corporation Tax | F68: 0 | G68: 0 | I68: =IFERROR(IF((E68+F68+G68)>=D68,(E68+F68+G68)/Setup!$B$10*Setup!$B$11,D68-(E68+F68+G68)),0) | J68: =E68+F68+G68+I68 | L68: 0 | M68: =J68*(1+L68) | N68: =M68-D68 | O68: =IFERROR(M68/D68-1,0)
A69: 6315-0000 | B69: Real Estate Tax | C69: Gross Tax from RE Taxes calc | F69: 0 | G69: 0 | I69: =IFERROR(IF((E69+F69+G69)>=D69,(E69+F69+G69)/Setup!$B$10*Setup!$B$11,D69-(E69+F69+G69)),0) | J69: =E69+F69+G69+I69 | L69: 0 | M69: ='RE Taxes'!B15 | N69: =M69-D69 | O69: =IFERROR(M69/D69-1,0)
A70: 6315-0010 | B70: Real Estate Tax Abatement | C70: Co-op Abatement (negated) | F70: 0 | G70: 0 | I70: =IFERROR(IF((E70+F70+G70)>=D70,(E70+F70+G70)/Setup!$B$10*Setup!$B$11,D70-(E70+F70+G70)),0) | J70: =E70+F70+G70+I70 | L70: 0 | M70: =-'RE Taxes'!D22 | N70: =M70-D70 | O70: =IFERROR(M70/D70-1,0)
A71: 6315-0020 | B71: STAR Exemption | C71: STAR Exemption (negated) | F71: 0 | G71: 0 | I71: =IFERROR(IF((E71+F71+G71)>=D71,(E71+F71+G71)/Setup!$B$10*Setup!$B$11,D71-(E71+F71+G71)),0) | J71: =E71+F71+G71+I71 | L71: 0 | M71: =-'RE Taxes'!D21 | N71: =M71-D71 | O71: =IFERROR(M71/D71-1,0)
A72: 6315-0025 | B72: Veteran Exemption | C72: Veteran Exemption (negated) | F72: 0 | G72: 0 | I72: =IFERROR(IF((E72+F72+G72)>=D72,(E72+F72+G72)/Setup!$B$10*Setup!$B$11,D72-(E72+F72+G72)),0) | J72: =E72+F72+G72+I72 | L72: 0 | M72: =-'RE Taxes'!D19 | N72: =M72-D72 | O72: =IFERROR(M72/D72-1,0)
A73: 6315-0035 | B73: SCHE Credit | C73: SCHE Credit (negated) | F73: 0 | G73: 0 | I73: =IFERROR(IF((E73+F73+G73)>=D73,(E73+F73+G73)/Setup!$B$10*Setup!$B$11,D73-(E73+F73+G73)),0) | J73: =E73+F73+G73+I73 | L73: 0 | M73: =-'RE Taxes'!D20 | N73: =M73-D73 | O73: =IFERROR(M73/D73-1,0)
A74: 6320-0000 | B74: Commercial RE Tax | F74: 0 | G74: 0 | I74: =IFERROR(IF((E74+F74+G74)>=D74,(E74+F74+G74)/Setup!$B$10*Setup!$B$11,D74-(E74+F74+G74)),0) | J74: =E74+F74+G74+I74 | L74: 0 | M74: =J74*(1+L74) | N74: =M74-D74 | O74: =IFERROR(M74/D74-1,0)
A75: 6325-0000 | B75: Other Taxes | F75: 0 | G75: 0 | I75: =IFERROR(IF((E75+F75+G75)>=D75,(E75+F75+G75)/Setup!$B$10*Setup!$B$11,D75-(E75+F75+G75)),0) | J75: =E75+F75+G75+I75 | L75: 0 | M75: =J75*(1+L75) | N75: =M75-D75 | O75: =IFERROR(M75/D75-1,0)
A76: 6335-0000 | B76: BID Tax | D76: 0 | E76: 0 | F76: 0 | G76: 0 | H76: 0 | I76: =IFERROR(D76-(E76+F76+G76),0) | J76: =E76+F76+G76+I76 | L76: 0 | M76: =J76*(1+L76) | N76: =M76-D76 | O76: =IFERROR(M76/D76-1,0)
D77: 0 | E77: 0 | F77: 0 | G77: 0 | H77: 0 | I77: =IFERROR(D77-(E77+F77+G77),0) | J77: =E77+F77+G77+I77 | L77: 0 | M77: =J77*(1+L77) | N77: =M77-D77 | O77: =IFERROR(M77/D77-1,0)
D78: 0 | E78: 0 | F78: 0 | G78: 0 | H78: 0 | I78: =IFERROR(D78-(E78+F78+G78),0) | J78: =E78+F78+G78+I78 | L78: 0 | M78: =J78*(1+L78) | N78: =M78-D78 | O78: =IFERROR(M78/D78-1,0)
B79: Total Taxes | D79: =SUM(D68:D78) | E79: =SUM(E68:E78) | F79: =SUM(F68:F78) | G79: =SUM(G68:G78) | H79: =SUM(H68:H78) | I79: =SUM(I68:I78) | J79: =SUM(J68:J78) | K79: =SUM(K68:K78) | M79: =SUM(M68:M78) | N79: =SUM(N68:N78) | O79: =IFERROR(M79/D79-1,0)
A81: Financial Expenses
A82: 6905-0000 | B82: Interest Expense | F82: 0 | G82: 0 | I82: =IFERROR(IF((E82+F82+G82)>=D82,(E82+F82+G82)/Setup!$B$10*Setup!$B$11,D82-(E82+F82+G82)),0) | J82: =E82+F82+G82+I82 | L82: 0 | M82: =J82*(1+L82) | N82: =M82-D82 | O82: =IFERROR(M82/D82-1,0)
A84: 6925-0000 | B84: Equipment Lease | F84: 0 | G84: 0 | I84: =IFERROR(IF((E84+F84+G84)>=D84,(E84+F84+G84)/Setup!$B$10*Setup!$B$11,D84-(E84+F84+G84)),0) | J84: =E84+F84+G84+I84 | L84: 0 | M84: =J84*(1+L84) | N84: =M84-D84 | O84: =IFERROR(M84/D84-1,0)
A85: 6995-0000 | B85: Other Financial Expense | F85: 0 | G85: 0 | I85: =IFERROR(IF((E85+F85+G85)>=D85,(E85+F85+G85)/Setup!$B$10*Setup!$B$11,D85-(E85+F85+G85)),0) | J85: =E85+F85+G85+I85 | L85: 0 | M85: =J85*(1+L85) | N85: =M85-D85 | O85: =IFERROR(M85/D85-1,0)
A86: 6996-0000 | B86: Other Financial | F86: 0 | G86: 0 | I86: =IFERROR(IF((E86+F86+G86)>=D86,(E86+F86+G86)/Setup!$B$10*Setup!$B$11,D86-(E86+F86+G86)),0) | J86: =E86+F86+G86+I86 | L86: 0 | M86: =J86*(1+L86) | N86: =M86-D86 | O86: =IFERROR(M86/D86-1,0)
A87: 6920-0000 | B87: Financing Fees | F87: 0 | G87: 0 | I87: =IFERROR(IF((E87+F87+G87)>=D87,(E87+F87+G87)/Setup!$B$10*Setup!$B$11,D87-(E87+F87+G87)),0) | J87: =E87+F87+G87+I87 | L87: 0 | M87: =J87*(1+L87) | N87: =M87-D87 | O87: =IFERROR(M87/D87-1,0)
A88: 2510-0000 | B88: Mortgage Amortization | D88: 0 | E88: 0 | F88: 0 | G88: 0 | H88: 0 | I88: =IFERROR(D88-(E88+F88+G88),0) | J88: =E88+F88+G88+I88 | L88: 0 | M88: =J88*(1+L88) | N88: =M88-D88 | O88: =IFERROR(M88/D88-1,0)
D89: 0 | E89: 0 | F89: 0 | G89: 0 | H89: 0 | I89: =IFERROR(D89-(E89+F89+G89),0) | J89: =E89+F89+G89+I89 | L89: 0 | M89: =J89*(1+L89) | N89: =M89-D89 | O89: =IFERROR(M89/D89-1,0)
D90: 0 | E90: 0 | F90: 0 | G90: 0 | H90: 0 | I90: =IFERROR(D90-(E90+F90+G90),0) | J90: =E90+F90+G90+I90 | L90: 0 | M90: =J90*(1+L90) | N90: =M90-D90 | O90: =IFERROR(M90/D90-1,0)
B91: Total Financial Expenses | D91: =SUM(D82:D90) | E91: =SUM(E82:E90) | F91: =SUM(F82:F90) | G91: =SUM(G82:G90) | H91: =SUM(H82:H90) | I91: =SUM(I82:I90) | J91: =SUM(J82:J90) | K91: =SUM(K82:K90) | M91: =SUM(M82:M90) | N91: =SUM(N82:N90) | O91: =IFERROR(M91/D91-1,0)
B93: TOTAL GEN & ADMIN | D93: =D17+D50+D65+D79+D91 | E93: =E17+E50+E65+E79+E91 | F93: =F17+F50+F65+F79+F91 | G93: =G17+G50+G65+G79+G91 | H93: =H17+H50+H65+H79+H91 | I93: =I17+I50+I65+I79+I91 | J93: =J17+J50+J65+J79+J91 | K93: =K17+K50+K65+K79+K91 | M93: =M17+M50+M65+M79+M91 | N93: =N17+N50+N65+N79+N91 | O93: =IFERROR(M93/D93-1,0)

Sheet RE Taxes
A1: =Setup!B5
A2: Real Estate Tax Calculation — Budget Year
A3: =Setup!B4
A5: TAX CALCULATION — Update assessed valuation and rates each budget cycle
A6: 1st Half — Current City Fiscal Year (Jul-Dec)
A7: Assessed Valuation (Actual) | B7: 0 | C7: From DOF Notice of Property Value
A8: Tax Rate (Actual) | B8: 0 | C8: Published rate for current city FY | D8: =B7*B8/2 | E8: ← 1st Half Tax
A10: 2nd Half — Next City Fiscal Year (Jan-Jun)
A11: Transitional AV Increase % | B11: 0 | C11: Estimated increase in assessed valuation
A12: Estimated Assessed Valuation | B12: =B7*(1+B11) | C12: AV × (1 + increase %)
A13: Estimated Tax Rate | B13: 0 | C13: Estimated rate for next city FY | D13: =B12*B13/2 | E13: ← 2nd Half Tax
A15: GROSS TAX LIABILITY (Full Year) | B15: =D8+D13 | C15: 1st Half + 2nd Half
A17: TAX EXEMPTIONS & ABATEMENTS
A18: Exemption Type | B18: Growth % | C18: Current Year | D18: Budget Year | E18: Notes
A19: Veteran Exemption | B19: 0 | C19: 0 | D19: =C19*(1+B19) | E19: GL 6315-0025
A20: Senior Citizen (SCHE) | B20: 0 | C20: 0 | D20: =C20*(1+B20) | E20: GL 6315-0035
A21: STAR Exemption | B21: 0 | C21: 0 | D21: =C21*(1+B21) | E21: GL 6315-0020
A22: Co-op Abatement | B22: 0 | C22: 0 | D22: =C22*(1+B22) | E22: GL 6315-0010
A23: TOTAL EXEMPTIONS | C23: =SUM(C19:C22) | D23: =SUM(D19:D22)
A25: NET TAX LIABILITY (Proposed Budget) | B25: =B15-D23 | C25: Gross Tax - Total Exemptions

Sheet Insurance Schedule
A1: =Setup!B5
A2: Insurance Schedule — Budget Year
A3: =Setup!B4
A5: RENEWAL ASSUMPTIONS
A6: Expected Renewal Increase % | C6: 0
A7: Renewal Effective Date | C7: Mar 2027
A8: Pre-Renewal Months | C8: 0
A9: Post-Renewal Months | C9: 0
A11: GL Code | B11: Policy Type | C11: Current Annual Premium | D11: Current Year Budget | E11: Expires | F11: YTD Actual | G11: Accrual Adj | H11: Unpaid Bills | I11: Sep-Dec Estimate | J11: 12 Mo Forecast | K11: Renewal Increase % | L11: Proposed Budget | M11: $ Variance
A12: 6105-0000 | B12: Package Policy | F12: ='Gen & Admin'!E53 | G12: ='Gen & Admin'!F53 | H12: ='Gen & Admin'!G53 | I12: =C12-F12-G12-H12 | J12: =F12+G12+H12+I12 | K12: =$C$6 | L12: =C12/12*$C$8+(C12/12*(1+K12))*$C$9 | M12: =L12-C12
A13: 6110-0000 | B13: General Liability | F13: ='Gen & Admin'!E54 | G13: ='Gen & Admin'!F54 | H13: ='Gen & Admin'!G54 | I13: =C13-F13-G13-H13 | J13: =F13+G13+H13+I13 | K13: =$C$6 | L13: =C13/12*$C$8+(C13/12*(1+K13))*$C$9 | M13: =L13-C13
A14: 6115-0000 | B14: Umbrella Insurance | F14: ='Gen & Admin'!E55 | G14: ='Gen & Admin'!F55 | H14: ='Gen & Admin'!G55 | I14: =C14-F14-G14-H14 | J14: =F14+G14+H14+I14 | K14: =$C$6 | L14: =C14/12*$C$8+(C14/12*(1+K14))*$C$9 | M14: =L14-C14
A15: 6125-0000 | B15: D&O Insurance | F15: ='Gen & Admin'!E57 | G15: ='Gen & Admin'!F57 | H15: ='Gen & Admin'!G57 | I15: =C15-F15-G15-H15 | J15: =F15+G15+H15+I15 | K15: =$C$6 | L15: =C15/12*$C$8+(C15/12*(1+K15))*$C$9 | M15: =L15-C15
A16: 6126-0000 | B16: Cyber Insurance | F16: ='Gen & Admin'!E58 | G16: ='Gen & Admin'!F58 | H16: ='Gen & Admin'!G58 | I16: =C16-F16-G16-H16 | J16: =F16+G16+H16+I16 | K16: =$C$6 | L16: =C16/12*$C$8+(C16/12*(1+K16))*$C$9 | M16: =L16-C16
A17: 6135-0000 | B17: Crime/Fidelity | F17: ='Gen & Admin'!E59 | G17: ='Gen & Admin'!F59 | H17: ='Gen & Admin'!G59 | I17: =C17-F17-G17-H17 | J17: =F17+G17+H17+I17 | K17: =$C$6 | L17: =C17/12*$C$8+(C17/12*(1+K17))*$C$9 | M17: =L17-C17
A18: 6195-0000 | B18: Other Insurance | F18: ='Gen & Admin'!E61 | G18: ='Gen & Admin'!F61 | H18: ='Gen & Admin'!G61 | I18: =C18-F18-G18-H18 | J18: =F18+G18+H18+I18 | K18: =$C$6 | L18: =C18/12*$C$8+(C18/12*(1+K18))*$C$9 | M18: =L18-C18
A19: 6120-0000 | B19: Umbrella Insurance (alt) | F19: ='Gen & Admin'!E56 | G19: ='Gen & Admin'!F56 | H19: ='Gen & Admin'!G56 | I19: =C19-F19-G19-H19 | J19: =F19+G19+H19+I19 | K19: =$C$6 | L19: =C19/12*$C$8+(C19/12*(1+K19))*$C$9 | M19: =L19-C19
A20: 6180-0000 | B20: D&O Insurance (alt) | F20: ='Gen & Admin'!E60 | G20: ='Gen & Admin'!F60 | H20: ='Gen & Admin'!G60 | I20: =C20-F20-G20-H20 | J20: =F20+G20+H20+I20 | K20: =$C$6 | L20: =C20/12*$C$8+(C20/12*(1+K20))*$C$9 | M20: =L20-C20
B21: TOTAL INSURANCE | C21: =SUM(C12:C20) | D21: =SUM(D12:D20) | F21: =SUM(F12:F20) | G21: =SUM(G12:G20) | H21: =SUM(H12:H20) | I21: =SUM(I12:I20) | J21: =SUM(J12:J20) | L21: =SUM(L12:L20) | M21: =SUM(M12:M20)
